Workbook

Sheet 2.1meta
A1: CUADRO DE EJECUCION Y PROYECCIÓN DE GASTOS DE LA GG 2.1
A2: UE: 003 G.A AREQUIPA
A4: Meta | B4: E.G. | C4: Descripción Específica Gasto | D4: PIM (1) | E4: Certificado | F4: Compromiso Anual | G4: Ejecución Devengado UE | Q4: Saldo Presupuestal | U4: Proyeccion de plazas vacantes | W4: PAGO FACTURAS EPS | X4: BENEFICIOS | Y4: TOTAL PROYECCIÓN | Z4: TOTAL EJECUCION +PROYECCION (2) | AA4: Saldo disponible ( 1-2)
G5: Enero | H5: Febrero | I5: Marzo | J5: Abril | K5: Mayo | L5: Junio | M5: Julio | N5: Agosto | O5: Setiembre | P5: TOTAL EJECUCION | R5: Octubre | S5: Noviembre | T5: Diciembre | U5: 276 | V5: 728
A6: 0001 | D6: =SUBTOTAL(9,D7:D22) -> 0 | E6: =SUBTOTAL(9,E7:E22) -> 0 | F6: =SUBTOTAL(9,F7:F22) -> 0 | G6: =SUBTOTAL(9,G7:G22) -> 0 | H6: =SUBTOTAL(9,H7:H22) -> 0 | I6: =SUBTOTAL(9,I7:I22) -> 0 | J6: =SUBTOTAL(9,J7:J22) -> 0 | K6: =SUBTOTAL(9,K7:K22) -> 0 | ... O6: =SUBTOTAL(9,O7:O22) -> 0 | P6: =SUM(G6:O6) -> 0 | Q6: =D6-P6 -> 0 | R6: =SUBTOTAL(9,R7:R22) -> 0 | S6: =SUBTOTAL(9,S7:S22) -> 0 | T6: =SUBTOTAL(9,T7:T22) -> 0 | U6: =SUBTOTAL(9,U7:U22) -> 0 | V6: =SUBTOTAL(9,V7:V22) -> 0 | W6: =SUBTOTAL(9,W7:W22) -> 0 | X6: =SUBTOTAL(9,X7:X22) -> 0 | Y6: =SUM(R6:X6) -> 0 | Z6: =+P6+Y6 -> 0 | AA6: =+D6-Z6 -> 0
A7: 0001 | B7: 2.1.1.1.1.2 | C7: PERSONAL ADMINISTRATIVO NOMBRADO (REGIMEN PUBLICO) | P7: =SUM(G7:O7) -> 0 | Q7: =D7-P7 -> 0 | U7: 0 | V7: 0 | Y7: =SUM(R7:X7) -> 0 | Z7: =+P7+Y7 -> 0 | AA7: =+D7-Z7 -> 0
A8: 0001 | B8: 2.1.1.1.1.4 | C8: PERSONAL CON CONTRATO A PLAZO INDETERMINADO (REGIMEN | P8: =SUM(G8:O8) -> 0 | Q8: =D8-P8 -> 0 | U8: 0 | V8: 0 | Y8: =SUM(R8:X8) -> 0 | Z8: =+P8+Y8 -> 0 | AA8: =+D8-Z8 -> 0
A9: 0001 | B9: 2.1.1.1.1.5 | C9: PERSONAL CON CONTRATO A PLAZO FIJO (REGIMEN LABORAL | P9: =SUM(G9:O9) -> 0 | Q9: =D9-P9 -> 0 | U9: 0 | V9: 0 | Y9: =SUM(R9:X9) -> 0 | Z9: =+P9+Y9 -> 0 | AA9: =+D9-Z9 -> 0
A10: 0001 | B10: 2.1.1.1.2.1 | C10: ASIGNACION A FONDOS PARA PERSONAL | P10: =SUM(G10:O10) -> 0 | Q10: =D10-P10 -> 0 | U10: 0 | V10: 0 | Y10: =SUM(R10:X10) -> 0 | Z10: =+P10+Y10 -> 0 | AA10: =+D10-Z10 -> 0
A11: 0001 | B11: 2.1.1.4.1.1 | C11: PERSONAL NOMBRADO | P11: =SUM(G11:O11) -> 0 | Q11: =D11-P11 -> 0 | U11: 0 | V11: 0 | Y11: =SUM(R11:X11) -> 0 | Z11: =+P11+Y11 -> 0 | AA11: =+D11-Z11 -> 0
A12: 0001 | B12: 2.1.1.4.2.1 | C12: BONO POR FUNCION JURISDICCIONAL Y FISCAL | P12: =SUM(G12:O12) -> 0 | Q12: =D12-P12 -> 0 | U12: 0 | V12: 0 | Y12: =SUM(R12:X12) -> 0 | Z12: =+P12+Y12 -> 0 | AA12: =+D12-Z12 -> 0
A13: 0001 | B13: 2.1.1.4.2.2 | C13: ASIGNACION POR GASTOS OPERATIVOS | P13: =SUM(G13:O13) -> 0 | Q13: =D13-P13 -> 0 | U13: 0 | V13: 0 | Y13: =SUM(R13:X13) -> 0 | Z13: =+P13+Y13 -> 0 | AA13: =+D13-Z13 -> 0
A14: 0001 | B14: 2.1.1.9.1.1 | C14: GRATIFICACIONES | P14: =SUM(G14:O14) -> 0 | Q14: =D14-P14 -> 0 | U14: 0 | V14: 0 | Y14: =SUM(R14:X14) -> 0 | Z14: =+P14+Y14 -> 0 | AA14: =+D14-Z14 -> 0
A15: 0001 | B15: 2.1.1.9.1.2 | C15: AGUINALDOS | P15: =SUM(G15:O15) -> 0 | Q15: =D15-P15 -> 0 | U15: 0 | V15: 0 | Y15: =SUM(R15:X15) -> 0 | Z15: =+P15+Y15 -> 0 | AA15: =+D15-Z15 -> 0
A16: 0001 | B16: 2.1.1.9.1.3 | C16: BONIFICACION POR ESCOLARIDAD | P16: =SUM(G16:O16) -> 0 | Q16: =D16-P16 -> 0 | U16: 0 | V16: 0 | Y16: =SUM(R16:X16) -> 0 | Z16: =+P16+Y16 -> 0 | AA16: =+D16-Z16 -> 0
A17: 0001 | B17: 2.1.1.9.2.1 | C17: COMPENSACION POR TIEMPO DE SERVICIOS (CTS) | P17: =SUM(G17:O17) -> 0 | Q17: =D17-P17 -> 0 | U17: 0 | V17: 0 | Y17: =SUM(R17:X17) -> 0 | Z17: =+P17+Y17 -> 0 | AA17: =+D17-Z17 -> 0
A18: 0001 | B18: 2.1.1.9.3.3 | C18: COMPENSACION VACACIONAL (VACACIONES TRUNCAS) | P18: =SUM(G18:O18) -> 0 | Q18: =D18-P18 -> 0 | U18: 0 | V18: 0 | Y18: =SUM(R18:X18) -> 0 | Z18: =+P18+Y18 -> 0 | AA18: =+D18-Z18 -> 0
... A22: 0001 | B22: 2.1.3.1.1.5 | C22: CONTRIBUCIONES A ESSALUD | P22: =SUM(G22:O22) -> 0 | Q22: =D22-P22 -> 0 | U22: 0 | V22: 0 | Y22: =SUM(R22:X22) -> 0 | Z22: =+P22+Y22 -> 0 | AA22: =+D22-Z22 -> 0
A23: 0002 | D23: =SUBTOTAL(9,D24:D39) -> 0 | E23: =SUBTOTAL(9,E24:E39) -> 0 | F23: =SUBTOTAL(9,F24:F39) -> 0 | G23: =SUBTOTAL(9,G24:G39) -> 0 | H23: =SUBTOTAL(9,H24:H39) -> 0 | I23: =SUBTOTAL(9,I24:I39) -> 0 | J23: =SUBTOTAL(9,J24:J39) -> 0 | K23: =SUBTOTAL(9,K24:K39) -> 0 | ... O23: =SUBTOTAL(9,O24:O39) -> 0 | P23: =SUM(G23:O23) -> 0 | Q23: =D23-P23 -> 0 | R23: =SUBTOTAL(9,R24:R39) -> 0 | S23: =SUBTOTAL(9,S24:S39) -> 0 | T23: =SUBTOTAL(9,T24:T39) -> 0 | U23: =SUBTOTAL(9,U24:U39) -> 0 | V23: =SUBTOTAL(9,V24:V39) -> 0 | W23: =SUBTOTAL(9,W24:W39) -> 0 | X23: =SUBTOTAL(9,X24:X39) -> 0 | Y23: =SUM(R23:X23) -> 0 | Z23: =+P23+Y23 -> 0 | AA23: =+D23-Z23 -> 0
A24: 0002 | B24: 2.1.1.1.1.2 | C24: PERSONAL ADMINISTRATIVO NOMBRADO (REGIMEN PUBLICO) | P24: =SUM(G24:O24) -> 0 | Q24: =D24-P24 -> 0 | U24: 0 | V24: 0 | Y24: =SUM(R24:X24) -> 0 | Z24: =+P24+Y24 -> 0 | AA24: =+D24-Z24 -> 0
A25: 0002 | B25: 2.1.1.1.1.4 | C25: PERSONAL CON CONTRATO A PLAZO INDETERMINADO (REGIMEN | P25: =SUM(G25:O25) -> 0 | Q25: =D25-P25 -> 0 | U25: 0 | V25: 0 | Y25: =SUM(R25:X25) -> 0 | Z25: =+P25+Y25 -> 0 | AA25: =+D25-Z25 -> 0
A26: 0002 | B26: 2.1.1.1.1.5 | C26: PERSONAL CON CONTRATO A PLAZO FIJO (REGIMEN LABORAL | P26: =SUM(G26:O26) -> 0 | Q26: =D26-P26 -> 0 | U26: 0 | V26: 0 | Y26: =SUM(R26:X26) -> 0 | Z26: =+P26+Y26 -> 0 | AA26: =+D26-Z26 -> 0
A27: 0002 | B27: 2.1.1.1.2.1 | C27: ASIGNACION A FONDOS PARA PERSONAL | P27: =SUM(G27:O27) -> 0 | Q27: =D27-P27 -> 0 | U27: 0 | V27: 0 | Y27: =SUM(R27:X27) -> 0 | Z27: =+P27+Y27 -> 0 | AA27: =+D27-Z27 -> 0
A28: 0002 | B28: 2.1.1.4.1.1 | C28: PERSONAL NOMBRADO | P28: =SUM(G28:O28) -> 0 | Q28: =D28-P28 -> 0 | U28: 0 | V28: 0 | Y28: =SUM(R28:X28) -> 0 | Z28: =+P28+Y28 -> 0 | AA28: =+D28-Z28 -> 0
A29: 0002 | B29: 2.1.1.4.2.1 | C29: BONO POR FUNCION JURISDICCIONAL Y FISCAL | P29: =SUM(G29:O29) -> 0 | Q29: =D29-P29 -> 0 | U29: 0 | V29: 0 | Y29: =SUM(R29:X29) -> 0 | Z29: =+P29+Y29 -> 0 | AA29: =+D29-Z29 -> 0
A30: 0002 | B30: 2.1.1.4.2.2 | C30: ASIGNACION POR GASTOS OPERATIVOS | P30: =SUM(G30:O30) -> 0 | Q30: =D30-P30 -> 0 | U30: 0 | V30: 0 | Y30: =SUM(R30:X30) -> 0 | Z30: =+P30+Y30 -> 0 | AA30: =+D30-Z30 -> 0
A31: 0002 | B31: 2.1.1.9.1.1 | C31: GRATIFICACIONES | P31: =SUM(G31:O31) -> 0 | Q31: =D31-P31 -> 0 | U31: 0 | V31: 0 | Y31: =SUM(R31:X31) -> 0 | Z31: =+P31+Y31 -> 0 | AA31: =+D31-Z31 -> 0
A32: 0002 | B32: 2.1.1.9.1.2 | C32: AGUINALDOS | P32: =SUM(G32:O32) -> 0 | Q32: =D32-P32 -> 0 | U32: 0 | V32: 0 | Y32: =SUM(R32:X32) -> 0 | Z32: =+P32+Y32 -> 0 | AA32: =+D32-Z32 -> 0
A33: 0002 | B33: 2.1.1.9.1.3 | C33: BONIFICACION POR ESCOLARIDAD | P33: =SUM(G33:O33) -> 0 | Q33: =D33-P33 -> 0 | U33: 0 | V33: 0 | Y33: =SUM(R33:X33) -> 0 | Z33: =+P33+Y33 -> 0 | AA33: =+D33-Z33 -> 0
A34: 0002 | B34: 2.1.1.9.2.1 | C34: COMPENSACION POR TIEMPO DE SERVICIOS (CTS) | P34: =SUM(G34:O34) -> 0 | Q34: =D34-P34 -> 0 | U34: 0 | V34: 0 | Y34: =SUM(R34:X34) -> 0 | Z34: =+P34+Y34 -> 0 | AA34: =+D34-Z34 -> 0
A35: 0002 | B35: 2.1.1.9.3.3 | C35: COMPENSACION VACACIONAL (VACACIONES TRUNCAS) | P35: =SUM(G35:O35) -> 0 | Q35: =D35-P35 -> 0 | U35: 0 | V35: 0 | Y35: =SUM(R35:X35) -> 0 | Z35: =+P35+Y35 -> 0 | AA35: =+D35-Z35 -> 0
... A39: 0002 | B39: 2.1.3.1.1.5 | C39: CONTRIBUCIONES A ESSALUD | P39: =SUM(G39:O39) -> 0 | Q39: =D39-P39 -> 0 | U39: 0 | V39: 0 | Y39: =SUM(R39:X39) -> 0 | Z39: =+P39+Y39 -> 0 | AA39: =+D39-Z39 -> 0
A40: 0003 | D40: =SUBTOTAL(9,D41:D56) -> 0 | E40: =SUBTOTAL(9,E41:E56) -> 0 | F40: =SUBTOTAL(9,F41:F56) -> 0 | G40: =SUBTOTAL(9,G41:G56) -> 0 | H40: =SUBTOTAL(9,H41:H56) -> 0 | I40: =SUBTOTAL(9,I41:I56) -> 0 | J40: =SUBTOTAL(9,J41:J56) -> 0 | K40: =SUBTOTAL(9,K41:K56) -> 0 | ... O40: =SUBTOTAL(9,O41:O56) -> 0 | P40: =SUM(G40:O40) -> 0 | Q40: =D40-P40 -> 0 | R40: =SUBTOTAL(9,R41:R56) -> 0 | S40: =SUBTOTAL(9,S41:S56) -> 0 | T40: =SUBTOTAL(9,T41:T56) -> 0 | U40: =SUBTOTAL(9,U41:U56) -> 0 | V40: =SUBTOTAL(9,V41:V56) -> 0 | W40: =SUBTOTAL(9,W41:W56) -> 0 | X40: =SUBTOTAL(9,X41:X56) -> 0 | Y40: =SUM(R40:X40) -> 0 | Z40: =+P40+Y40 -> 0 | AA40: =+D40-Z40 -> 0
A41: 0003 | B41: 2.1.1.1.1.2 | C41: PERSONAL ADMINISTRATIVO NOMBRADO (REGIMEN PUBLICO) | P41: =SUM(G41:O41) -> 0 | Q41: =D41-P41 -> 0 | U41: 0 | V41: 0 | Y41: =SUM(R41:X41) -> 0 | Z41: =+P41+Y41 -> 0 | AA41: =+D41-Z41 -> 0
A42: 0003 | B42: 2.1.1.1.1.4 | C42: PERSONAL CON CONTRATO A PLAZO INDETERMINADO (REGIMEN | P42: =SUM(G42:O42) -> 0 | Q42: =D42-P42 -> 0 | U42: 0 | V42: 0 | Y42: =SUM(R42:X42) -> 0 | Z42: =+P42+Y42 -> 0 | AA42: =+D42-Z42 -> 0
A43: 0003 | B43: 2.1.1.1.1.5 | C43: PERSONAL CON CONTRATO A PLAZO FIJO (REGIMEN LABORAL | P43: =SUM(G43:O43) -> 0 | Q43: =D43-P43 -> 0 | U43: 0 | V43: 0 | Y43: =SUM(R43:X43) -> 0 | Z43: =+P43+Y43 -> 0 | AA43: =+D43-Z43 -> 0
A44: 0003 | B44: 2.1.1.1.2.1 | C44: ASIGNACION A FONDOS PARA PERSONAL | P44: =SUM(G44:O44) -> 0 | Q44: =D44-P44 -> 0 | U44: 0 | V44: 0 | Y44: =SUM(R44:X44) -> 0 | Z44: =+P44+Y44 -> 0 | AA44: =+D44-Z44 -> 0
A45: 0003 | B45: 2.1.1.4.1.1 | C45: PERSONAL NOMBRADO | P45: =SUM(G45:O45) -> 0 | Q45: =D45-P45 -> 0 | U45: 0 | V45: 0 | Y45: =SUM(R45:X45) -> 0 | Z45: =+P45+Y45 -> 0 | AA45: =+D45-Z45 -> 0
A46: 0003 | B46: 2.1.1.4.2.1 | C46: BONO POR FUNCION JURISDICCIONAL Y FISCAL | P46: =SUM(G46:O46) -> 0 | Q46: =D46-P46 -> 0 | U46: 0 | V46: 0 | Y46: =SUM(R46:X46) -> 0 | Z46: =+P46+Y46 -> 0 | AA46: =+D46-Z46 -> 0
A47: 0003 | B47: 2.1.1.4.2.2 | C47: ASIGNACION POR GASTOS OPERATIVOS | P47: =SUM(G47:O47) -> 0 | Q47: =D47-P47 -> 0 | U47: 0 | V47: 0 | Y47: =SUM(R47:X47) -> 0 | Z47: =+P47+Y47 -> 0 | AA47: =+D47-Z47 -> 0
A48: 0003 | B48: 2.1.1.9.1.1 | C48: GRATIFICACIONES | P48: =SUM(G48:O48) -> 0 | Q48: =D48-P48 -> 0 | U48: 0 | V48: 0 | Y48: =SUM(R48:X48) -> 0 | Z48: =+P48+Y48 -> 0 | AA48: =+D48-Z48 -> 0
A49: 0003 | B49: 2.1.1.9.1.2 | C49: AGUINALDOS | P49: =SUM(G49:O49) -> 0 | Q49: =D49-P49 -> 0 | U49: 0 | V49: 0 | Y49: =SUM(R49:X49) -> 0 | Z49: =+P49+Y49 -> 0 | AA49: =+D49-Z49 -> 0
A50: 0003 | B50: 2.1.1.9.1.3 | C50: BONIFICACION POR ESCOLARIDAD | P50: =SUM(G50:O50) -> 0 | Q50: =D50-P50 -> 0 | U50: 0 | V50: 0 | Y50: =SUM(R50:X50) -> 0 | Z50: =+P50+Y50 -> 0 | AA50: =+D50-Z50 -> 0
A51: 0003 | B51: 2.1.1.9.2.1 | C51: COMPENSACION POR TIEMPO DE SERVICIOS (CTS) | P51: =SUM(G51:O51) -> 0 | Q51: =D51-P51 -> 0 | U51: 0 | V51: 0 | Y51: =SUM(R51:X51) -> 0 | Z51: =+P51+Y51 -> 0 | AA51: =+D51-Z51 -> 0
A52: 0003 | B52: 2.1.1.9.3.3 | C52: COMPENSACION VACACIONAL (VACACIONES TRUNCAS) | P52: =SUM(G52:O52) -> 0 | Q52: =D52-P52 -> 0 | U52: 0 | V52: 0 | Y52: =SUM(R52:X52) -> 0 | Z52: =+P52+Y52 -> 0 | AA52: =+D52-Z52 -> 0
... A56: 0003 | B56: 2.1.3.1.1.5 | C56: CONTRIBUCIONES A ESSALUD | P56: =SUM(G56:O56) -> 0 | Q56: =D56-P56 -> 0 | U56: 0 | V56: 0 | Y56: =SUM(R56:X56) -> 0 | Z56: =+P56+Y56 -> 0 | AA56: =+D56-Z56 -> 0
A57: 0004 | D57: =SUBTOTAL(9,D58:D74) -> 0 | E57: =SUBTOTAL(9,E58:E74) -> 0 | F57: =SUBTOTAL(9,F58:F74) -> 0 | G57: =SUBTOTAL(9,G58:G74) -> 0 | H57: =SUBTOTAL(9,H58:H74) -> 0 | I57: =SUBTOTAL(9,I58:I74) -> 0 | J57: =SUBTOTAL(9,J58:J74) -> 0 | K57: =SUBTOTAL(9,K58:K74) -> 0 | ... O57: =SUBTOTAL(9,O58:O74) -> 0 | P57: =SUM(G57:O57) -> 0 | Q57: =D57-P57 -> 0 | R57: =SUBTOTAL(9,R58:R74) -> 0 | S57: =SUBTOTAL(9,S58:S74) -> 0 | T57: =SUBTOTAL(9,T58:T74) -> 0 | U57: =SUBTOTAL(9,U58:U74) -> 0 | V57: =SUBTOTAL(9,V58:V74) -> 0 | W57: =SUBTOTAL(9,W58:W74) -> 0 | X57: =SUBTOTAL(9,X58:X74) -> 0 | Y57: =SUM(R57:X57) -> 0 | Z57: =+P57+Y57 -> 0 | AA57: =+D57-Z57 -> 0
A58: 0004 | B58: 2.1.1.1.1.2 | C58: PERSONAL ADMINISTRATIVO NOMBRADO (REGIMEN PUBLICO) | P58: =SUM(G58:O58) -> 0 | Q58: =D58-P58 -> 0 | U58: 0 | V58: 0 | Y58: =SUM(R58:X58) -> 0 | Z58: =+P58+Y58 -> 0 | AA58: =+D58-Z58 -> 0
A59: 0004 | B59: 2.1.1.1.1.4 | C59: PERSONAL CON CONTRATO A PLAZO INDETERMINADO (REGIMEN | P59: =SUM(G59:O59) -> 0 | Q59: =D59-P59 -> 0 | U59: 0 | V59: 0 | Y59: =SUM(R59:X59) -> 0 | Z59: =+P59+Y59 -> 0 | AA59: =+D59-Z59 -> 0
A60: 0004 | B60: 2.1.1.1.1.5 | C60: PERSONAL CON CONTRATO A PLAZO FIJO (REGIMEN LABORAL | P60: =SUM(G60:O60) -> 0 | Q60: =D60-P60 -> 0 | U60: 0 | V60: 0 | Y60: =SUM(R60:X60) -> 0 | Z60: =+P60+Y60 -> 0 | AA60: =+D60-Z60 -> 0
A61: 0004 | B61: 2.1.1.1.2.1 | C61: ASIGNACION A FONDOS PARA PERSONAL | P61: =SUM(G61:O61) -> 0 | Q61: =D61-P61 -> 0 | U61: 0 | V61: 0 | Y61: =SUM(R61:X61) -> 0 | Z61: =+P61+Y61 -> 0 | AA61: =+D61-Z61 -> 0
A62: 0004 | B62: 2.1.1.3.1.2 | C62: PERSONAL CONTRATADO | P62: =SUM(G62:O62) -> 0 | Q62: =D62-P62 -> 0 | U62: 0 | V62: 0 | Y62: =SUM(R62:X62) -> 0 | Z62: =+P62+Y62 -> 0 | AA62: =+D62-Z62 -> 0
A63: 0004 | B63: 2.1.1.4.1.1 | C63: PERSONAL NOMBRADO | P63: =SUM(G63:O63) -> 0 | Q63: =D63-P63 -> 0 | U63: 0 | V63: 0 | Y63: =SUM(R63:X63) -> 0 | Z63: =+P63+Y63 -> 0 | AA63: =+D63-Z63 -> 0
A64: 0004 | B64: 2.1.1.4.2.1 | C64: BONO POR FUNCION JURISDICCIONAL Y FISCAL | P64: =SUM(G64:O64) -> 0 | Q64: =D64-P64 -> 0 | U64: 0 | V64: 0 | Y64: =SUM(R64:X64) -> 0 | Z64: =+P64+Y64 -> 0 | AA64: =+D64-Z64 -> 0
A65: 0004 | B65: 2.1.1.4.2.2 | C65: ASIGNACION POR GASTOS OPERATIVOS | P65: =SUM(G65:O65) -> 0 | Q65: =D65-P65 -> 0 | U65: 0 | V65: 0 | Y65: =SUM(R65:X65) -> 0 | Z65: =+P65+Y65 -> 0 | AA65: =+D65-Z65 -> 0
A66: 0004 | B66: 2.1.1.9.1.1 | C66: GRATIFICACIONES | P66: =SUM(G66:O66) -> 0 | Q66: =D66-P66 -> 0 | U66: 0 | V66: 0 | Y66: =SUM(R66:X66) -> 0 | Z66: =+P66+Y66 -> 0 | AA66: =+D66-Z66 -> 0
A67: 0004 | B67: 2.1.1.9.1.2 | C67: AGUINALDOS | P67: =SUM(G67:O67) -> 0 | Q67: =D67-P67 -> 0 | U67: 0 | V67: 0 | Y67: =SUM(R67:X67) -> 0 | Z67: =+P67+Y67 -> 0 | AA67: =+D67-Z67 -> 0
A68: 0004 | B68: 2.1.1.9.1.3 | C68: BONIFICACION POR ESCOLARIDAD | P68: =SUM(G68:O68) -> 0 | Q68: =D68-P68 -> 0 | U68: 0 | V68: 0 | Y68: =SUM(R68:X68) -> 0 | Z68: =+P68+Y68 -> 0 | AA68: =+D68-Z68 -> 0
A69: 0004 | B69: 2.1.1.9.2.1 | C69: COMPENSACION POR TIEMPO DE SERVICIOS (CTS) | P69: =SUM(G69:O69) -> 0 | Q69: =D69-P69 -> 0 | U69: 0 | V69: 0 | Y69: =SUM(R69:X69) -> 0 | Z69: =+P69+Y69 -> 0 | AA69: =+D69-Z69 -> 0
... A74: 0004 | B74: 2.1.3.1.1.5 | C74: CONTRIBUCIONES A ESSALUD | P74: =SUM(G74:O74) -> 0 | Q74: =D74-P74 -> 0 | U74: 0 | V74: 0 | Y74: =SUM(R74:X74) -> 0 | Z74: =+P74+Y74 -> 0 | AA74: =+D74-Z74 -> 0
A75: 0005 | D75: =SUBTOTAL(9,D76:D91) -> 0 | E75: =SUBTOTAL(9,E76:E91) -> 0 | F75: =SUBTOTAL(9,F76:F91) -> 0 | G75: =SUBTOTAL(9,G76:G91) -> 0 | H75: =SUBTOTAL(9,H76:H91) -> 0 | I75: =SUBTOTAL(9,I76:I91) -> 0 | J75: =SUBTOTAL(9,J76:J91) -> 0 | K75: =SUBTOTAL(9,K76:K91) -> 0 | ... O75: =SUBTOTAL(9,O76:O91) -> 0 | P75: =SUM(G75:O75) -> 0 | Q75: =D75-P75 -> 0 | R75: =SUBTOTAL(9,R76:R91) -> 0 | S75: =SUBTOTAL(9,S76:S91) -> 0 | T75: =SUBTOTAL(9,T76:T91) -> 0 | U75: =SUBTOTAL(9,U76:U91) -> 0 | V75: =SUBTOTAL(9,V76:V91) -> 0 | W75: =SUBTOTAL(9,W76:W91) -> 0 | X75: =SUBTOTAL(9,X76:X91) -> 0 | Y75: =SUM(R75:X75) -> 0 | Z75: =+P75+Y75 -> 0 | AA75: =+D75-Z75 -> 0
A76: 0005 | B76: 2.1.1.1.1.2 | C76: PERSONAL ADMINISTRATIVO NOMBRADO (REGIMEN PUBLICO) | P76: =SUM(G76:O76) -> 0 | Q76: =D76-P76 -> 0 | U76: 0 | V76: 0 | Y76: =SUM(R76:X76) -> 0 | Z76: =+P76+Y76 -> 0 | AA76: =+D76-Z76 -> 0
A77: 0005 | B77: 2.1.1.1.1.4 | C77: PERSONAL CON CONTRATO A PLAZO INDETERMINADO (REGIMEN | P77: =SUM(G77:O77) -> 0 | Q77: =D77-P77 -> 0 | U77: 0 | V77: 0 | Y77: =SUM(R77:X77) -> 0 | Z77: =+P77+Y77 -> 0 | AA77: =+D77-Z77 -> 0
A78: 0005 | B78: 2.1.1.1.1.5 | C78: PERSONAL CON CONTRATO A PLAZO FIJO (REGIMEN LABORAL | P78: =SUM(G78:O78) -> 0 | Q78: =D78-P78 -> 0 | U78: 0 | V78: 0 | Y78: =SUM(R78:X78) -> 0 | Z78: =+P78+Y78 -> 0 | AA78: =+D78-Z78 -> 0
A79: 0005 | B79: 2.1.1.1.2.1 | C79: ASIGNACION A FONDOS PARA PERSONAL | P79: =SUM(G79:O79) -> 0 | Q79: =D79-P79 -> 0 | U79: 0 | V79: 0 | Y79: =SUM(R79:X79) -> 0 | Z79: =+P79+Y79 -> 0 | AA79: =+D79-Z79 -> 0
A80: 0005 | B80: 2.1.1.4.1.1 | C80: PERSONAL NOMBRADO | P80: =SUM(G80:O80) -> 0 | Q80: =D80-P80 -> 0 | U80: 0 | V80: 0 | Y80: =SUM(R80:X80) -> 0 | Z80: =+P80+Y80 -> 0 | AA80: =+D80-Z80 -> 0
A81: 0005 | B81: 2.1.1.4.2.1 | C81: BONO POR FUNCION JURISDICCIONAL Y FISCAL | P81: =SUM(G81:O81) -> 0 | Q81: =D81-P81 -> 0 | U81: 0 | V81: 0 | Y81: =SUM(R81:X81) -> 0 | Z81: =+P81+Y81 -> 0 | AA81: =+D81-Z81 -> 0
A82: 0005 | B82: 2.1.1.4.2.2 | C82: ASIGNACION POR GASTOS OPERATIVOS | P82: =SUM(G82:O82) -> 0 | Q82: =D82-P82 -> 0 | U82: 0 | V82: 0 | Y82: =SUM(R82:X82) -> 0 | Z82: =+P82+Y82 -> 0 | AA82: =+D82-Z82 -> 0
A83: 0005 | B83: 2.1.1.9.1.1 | C83: GRATIFICACIONES | P83: =SUM(G83:O83) -> 0 | Q83: =D83-P83 -> 0 | U83: 0 | V83: 0 | Y83: =SUM(R83:X83) -> 0 | Z83: =+P83+Y83 -> 0 | AA83: =+D83-Z83 -> 0
A84: 0005 | B84: 2.1.1.9.1.2 | C84: AGUINALDOS | P84: =SUM(G84:O84) -> 0 | Q84: =D84-P84 -> 0 | U84: 0 | V84: 0 | Y84: =SUM(R84:X84) -> 0 | Z84: =+P84+Y84 -> 0 | AA84: =+D84-Z84 -> 0
A85: 0005 | B85: 2.1.1.9.1.3 | C85: BONIFICACION POR ESCOLARIDAD | P85: =SUM(G85:O85) -> 0 | Q85: =D85-P85 -> 0 | U85: 0 | V85: 0 | Y85: =SUM(R85:X85) -> 0 | Z85: =+P85+Y85 -> 0 | AA85: =+D85-Z85 -> 0
A86: 0005 | B86: 2.1.1.9.2.1 | C86: COMPENSACION POR TIEMPO DE SERVICIOS (CTS) | P86: =SUM(G86:O86) -> 0 | Q86: =D86-P86 -> 0 | U86: 0 | V86: 0 | Y86: =SUM(R86:X86) -> 0 | Z86: =+P86+Y86 -> 0 | AA86: =+D86-Z86 -> 0
A87: 0005 | B87: 2.1.1.9.3.3 | C87: COMPENSACION VACACIONAL (VACACIONES TRUNCAS) | P87: =SUM(G87:O87) -> 0 | Q87: =D87-P87 -> 0 | U87: 0 | V87: 0 | Y87: =SUM(R87:X87) -> 0 | Z87: =+P87+Y87 -> 0 | AA87: =+D87-Z87 -> 0
... A91: 0005 | B91: 2.1.3.1.1.5 | C91: CONTRIBUCIONES A ESSALUD | P91: =SUM(G91:O91) -> 0 | Q91: =D91-P91 -> 0 | U91: 0 | V91: 0 | Y91: =SUM(R91:X91) -> 0 | Z91: =+P91+Y91 -> 0 | AA91: =+D91-Z91 -> 0
A92: 0006 | D92: =SUBTOTAL(9,D93:D108) -> 0 | E92: =SUBTOTAL(9,E93:E108) -> 0 | F92: =SUBTOTAL(9,F93:F108) -> 0 | G92: =SUBTOTAL(9,G93:G108) -> 0 | H92: =SUBTOTAL(9,H93:H108) -> 0 | I92: =SUBTOTAL(9,I93:I108) -> 0 | J92: =SUBTOTAL(9,J93:J108) -> 0 | K92: =SUBTOTAL(9,K93:K108) -> 0 | ... O92: =SUBTOTAL(9,O93:O108) -> 0 | P92: =SUM(G92:O92) -> 0 | Q92: =D92-P92 -> 0 | R92: =SUBTOTAL(9,R93:R108) -> 0 | S92: =SUBTOTAL(9,S93:S108) -> 0 | T92: =SUBTOTAL(9,T93:T108) -> 0 | U92: =SUBTOTAL(9,U93:U108) -> 0 | V92: =SUBTOTAL(9,V93:V108) -> 0 | W92: =SUBTOTAL(9,W93:W108) -> 0 | X92: =SUBTOTAL(9,X93:X108) -> 0 | Y92: =SUM(R92:X92) -> 0 | Z92: =+P92+Y92 -> 0 | AA92: =+D92-Z92 -> 0
A93: 0006 | B93: 2.1.1.1.1.2 | C93: PERSONAL ADMINISTRATIVO NOMBRADO (REGIMEN PUBLICO) | P93: =SUM(G93:O93) -> 0 | Q93: =D93-P93 -> 0 | U93: 0 | V93: 0 | Y93: =SUM(R93:X93) -> 0 | Z93: =+P93+Y93 -> 0 | AA93: =+D93-Z93 -> 0
A94: 0006 | B94: 2.1.1.1.1.4 | C94: PERSONAL CON CONTRATO A PLAZO INDETERMINADO (REGIMEN | P94: =SUM(G94:O94) -> 0 | Q94: =D94-P94 -> 0 | U94: 0 | V94: 0 | Y94: =SUM(R94:X94) -> 0 | Z94: =+P94+Y94 -> 0 | AA94: =+D94-Z94 -> 0
A95: 0006 | B95: 2.1.1.1.1.5 | C95: PERSONAL CON CONTRATO A PLAZO FIJO (REGIMEN LABORAL | P95: =SUM(G95:O95) -> 0 | Q95: =D95-P95 -> 0 | U95: 0 | V95: 0 | Y95: =SUM(R95:X95) -> 0 | Z95: =+P95+Y95 -> 0 | AA95: =+D95-Z95 -> 0
A96: 0006 | B96: 2.1.1.1.2.1 | C96: ASIGNACION A FONDOS PARA PERSONAL | P96: =SUM(G96:O96) -> 0 | Q96: =D96-P96 -> 0 | U96: 0 | V96: 0 | Y96: =SUM(R96:X96) -> 0 | Z96: =+P96+Y96 -> 0 | AA96: =+D96-Z96 -> 0
A97: 0006 | B97: 2.1.1.4.1.1 | C97: PERSONAL NOMBRADO | P97: =SUM(G97:O97) -> 0 | Q97: =D97-P97 -> 0 | U97: 0 | V97: 0 | Y97: =SUM(R97:X97) -> 0 | Z97: =+P97+Y97 -> 0 | AA97: =+D97-Z97 -> 0
A98: 0006 | B98: 2.1.1.4.2.1 | C98: BONO POR FUNCION JURISDICCIONAL Y FISCAL | P98: =SUM(G98:O98) -> 0 | Q98: =D98-P98 -> 0 | U98: 0 | V98: 0 | Y98: =SUM(R98:X98) -> 0 | Z98: =+P98+Y98 -> 0 | AA98: =+D98-Z98 -> 0
A99: 0006 | B99: 2.1.1.4.2.2 | C99: ASIGNACION POR GASTOS OPERATIVOS | P99: =SUM(G99:O99) -> 0 | Q99: =D99-P99 -> 0 | U99: 0 | V99: 0 | Y99: =SUM(R99:X99) -> 0 | Z99: =+P99+Y99 -> 0 | AA99: =+D99-Z99 -> 0
A100: 0006 | B100: 2.1.1.9.1.1 | C100: GRATIFICACIONES | P100: =SUM(G100:O100) -> 0 | Q100: =D100-P100 -> 0 | U100: 0 | V100: 0 | Y100: =SUM(R100:X100) -> 0 | Z100: =+P100+Y100 -> 0 | AA100: =+D100-Z100 -> 0
A101: 0006 | B101: 2.1.1.9.1.2 | C101: AGUINALDOS | P101: =SUM(G101:O101) -> 0 | Q101: =D101-P101 -> 0 | U101: 0 | V101: 0 | Y101: =SUM(R101:X101) -> 0 | Z101: =+P101+Y101 -> 0 | AA101: =+D101-Z101 -> 0
A102: 0006 | B102: 2.1.1.9.1.3 | C102: BONIFICACION POR ESCOLARIDAD | P102: =SUM(G102:O102) -> 0 | Q102: =D102-P102 -> 0 | U102: 0 | V102: 0 | Y102: =SUM(R102:X102) -> 0 | Z102: =+P102+Y102 -> 0 | AA102: =+D102-Z102 -> 0
A103: 0006 | B103: 2.1.1.9.2.1 | C103: COMPENSACION POR TIEMPO DE SERVICIOS (CTS) | P103: =SUM(G103:O103) -> 0 | Q103: =D103-P103 -> 0 | U103: 0 | V103: 0 | Y103: =SUM(R103:X103) -> 0 | Z103: =+P103+Y103 -> 0 | AA103: =+D103-Z103 -> 0
A104: 0006 | B104: 2.1.1.9.3.3 | C104: COMPENSACION VACACIONAL (VACACIONES TRUNCAS) | P104: =SUM(G104:O104) -> 0 | Q104: =D104-P104 -> 0 | U104: 0 | V104: 0 | Y104: =SUM(R104:X104) -> 0 | Z104: =+P104+Y104 -> 0 | AA104: =+D104-Z104 -> 0
... A108: 0006 | B108: 2.1.3.1.1.5 | C108: CONTRIBUCIONES A ESSALUD | P108: =SUM(G108:O108) -> 0 | Q108: =D108-P108 -> 0 | U108: 0 | V108: 0 | Y108: =SUM(R108:X108) -> 0 | Z108: =+P108+Y108 -> 0 | AA108: =+D108-Z108 -> 0
A109: 0007 | D109: =SUBTOTAL(9,D110:D125) -> 0 | E109: =SUBTOTAL(9,E110:E125) -> 0 | F109: =SUBTOTAL(9,F110:F125) -> 0 | G109: =SUBTOTAL(9,G110:G125) -> 0 | H109: =SUBTOTAL(9,H110:H125) -> 0 | I109: =SUBTOTAL(9,I110:I125) -> 0 | J109: =SUBTOTAL(9,J110:J125) -> 0 | K109: =SUBTOTAL(9,K110:K125) -> 0 | ... O109: =SUBTOTAL(9,O110:O125) -> 0 | P109: =SUM(G109:O109) -> 0 | Q109: =D109-P109 -> 0 | R109: =SUBTOTAL(9,R110:R125) -> 0 | S109: =SUBTOTAL(9,S110:S125) -> 0 | T109: =SUBTOTAL(9,T110:T125) -> 0 | U109: =SUBTOTAL(9,U110:U125) -> 0 | V109: =SUBTOTAL(9,V110:V125) -> 0 | W109: =SUBTOTAL(9,W110:W125) -> 0 | X109: =SUBTOTAL(9,X110:X125) -> 0 | Y109: =SUM(R109:X109) -> 0 | Z109: =+P109+Y109 -> 0 | AA109: =+D109-Z109 -> 0
A110: 0007 | B110: 2.1.1.1.1.2 | C110: PERSONAL ADMINISTRATIVO NOMBRADO (REGIMEN PUBLICO) | P110: =SUM(G110:O110) -> 0 | Q110: =D110-P110 -> 0 | U110: 0 | V110: 0 | Y110: =SUM(R110:X110) -> 0 | Z110: =+P110+Y110 -> 0 | AA110: =+D110-Z110 -> 0
A111: 0007 | B111: 2.1.1.1.1.4 | C111: PERSONAL CON CONTRATO A PLAZO INDETERMINADO (REGIMEN | P111: =SUM(G111:O111) -> 0 | Q111: =D111-P111 -> 0 | U111: 0 | V111: 0 | Y111: =SUM(R111:X111) -> 0 | Z111: =+P111+Y111 -> 0 | AA111: =+D111-Z111 -> 0
A112: 0007 | B112: 2.1.1.1.1.5 | C112: PERSONAL CON CONTRATO A PLAZO FIJO (REGIMEN LABORAL | P112: =SUM(G112:O112) -> 0 | Q112: =D112-P112 -> 0 | U112: 0 | V112: 0 | Y112: =SUM(R112:X112) -> 0 | Z112: =+P112+Y112 -> 0 | AA112: =+D112-Z112 -> 0
A113: 0007 | B113: 2.1.1.1.2.1 | C113: ASIGNACION A FONDOS PARA PERSONAL | P113: =SUM(G113:O113) -> 0 | Q113: =D113-P113 -> 0 | U113: 0 | V113: 0 | Y113: =SUM(R113:X113) -> 0 | Z113: =+P113+Y113 -> 0 | AA113: =+D113-Z113 -> 0
A114: 0007 | B114: 2.1.1.4.1.1 | C114: PERSONAL NOMBRADO | P114: =SUM(G114:O114) -> 0 | Q114: =D114-P114 -> 0 | U114: 0 | V114: 0 | Y114: =SUM(R114:X114) -> 0 | Z114: =+P114+Y114 -> 0 | AA114: =+D114-Z114 -> 0
A115: 0007 | B115: 2.1.1.4.2.1 | C115: BONO POR FUNCION JURISDICCIONAL Y FISCAL | P115: =SUM(G115:O115) -> 0 | Q115: =D115-P115 -> 0 | U115: 0 | V115: 0 | Y115: =SUM(R115:X115) -> 0 | Z115: =+P115+Y115 -> 0 | AA115: =+D115-Z115 -> 0
A116: 0007 | B116: 2.1.1.4.2.2 | C116: ASIGNACION POR GASTOS OPERATIVOS | P116: =SUM(G116:O116) -> 0 | Q116: =D116-P116 -> 0 | U116: 0 | V116: 0 | Y116: =SUM(R116:X116) -> 0 | Z116: =+P116+Y116 -> 0 | AA116: =+D116-Z116 -> 0
A117: 0007 | B117: 2.1.1.9.1.1 | C117: GRATIFICACIONES | P117: =SUM(G117:O117) -> 0 | Q117: =D117-P117 -> 0 | U117: 0 | V117: 0 | Y117: =SUM(R117:X117) -> 0 | Z117: =+P117+Y117 -> 0 | AA117: =+D117-Z117 -> 0
A118: 0007 | B118: 2.1.1.9.1.2 | C118: AGUINALDOS | P118: =SUM(G118:O118) -> 0 | Q118: =D118-P118 -> 0 | U118: 0 | V118: 0 | Y118: =SUM(R118:X118) -> 0 | Z118: =+P118+Y118 -> 0 | AA118: =+D118-Z118 -> 0
A119: 0007 | B119: 2.1.1.9.1.3 | C119: BONIFICACION POR ESCOLARIDAD | P119: =SUM(G119:O119) -> 0 | Q119: =D119-P119 -> 0 | U119: 0 | V119: 0 | Y119: =SUM(R119:X119) -> 0 | Z119: =+P119+Y119 -> 0 | AA119: =+D119-Z119 -> 0
A120: 0007 | B120: 2.1.1.9.2.1 | C120: COMPENSACION POR TIEMPO DE SERVICIOS (CTS) | P120: =SUM(G120:O120) -> 0 | Q120: =D120-P120 -> 0 | U120: 0 | V120: 0 | Y120: =SUM(R120:X120) -> 0 | Z120: =+P120+Y120 -> 0 | AA120: =+D120-Z120 -> 0
...

Sheet CATEGORIA PRESUPUESTAL
A1: EJECUTORA: 0003 MINISTERIO PUBLICO - GERENCIA ADMINISTRATIVA DE AREQUIPA (1419)
A3: Cat pptal/ Detalle Específica de Gasto | C3: PIM | D3: Certificado | E3: Compromiso Anual | F3: Ejecución Devengado UE | O3: T O T A L | P3: Saldo Presupuestal al 17.09.2021 | T3: Proyeccion de plazas vacantes | V3: PAGO FACTURAS EPS | W3: BENEFICIOS | X3: TOTAL PROYECCION | Y3: TOTAL EJECUCION +PROYECCION | Z3: SALDO DISPONIBLE
F4: 01 ENERO | G4: 02 FEBRERO | H4: 03 MARZO | I4: 04 ABRIL | J4: 05 MAYO | K4: 06 JUNIO | L4: 07 JULIO | M4: 08 AGOSTO | N4: 09 SETIEMBRE | Q4: 10 OCTUBRE | R4: 11 NOVIEMBRE | S4: 12 DICIEMBRE | T4: 276 | U4: 728
A5: 0086 MEJORA DE LOS SERVICIOS DEL SISTEMA DE JUSTICIA PENAL | C5: =SUBTOTAL(9,C6:C22) -> 0 | D5: =SUBTOTAL(9,D6:D22) -> 0 | E5: =SUBTOTAL(9,E6:E22) -> 0 | F5: =SUBTOTAL(9,F6:F22) -> 0 | G5: =SUBTOTAL(9,G6:G22) -> 0 | H5: =SUBTOTAL(9,H6:H22) -> 0 | I5: =SUBTOTAL(9,I6:I22) -> 0 | J5: =SUBTOTAL(9,J6:J22) -> 0 | ... O5: =SUBTOTAL(9,O6:O22) -> 0 | P5: =C5-O5 -> 0 | Q5: =SUBTOTAL(9,Q6:Q22) -> 0 | R5: =SUBTOTAL(9,R6:R22) -> 0 | S5: =SUBTOTAL(9,S6:S22) -> 0 | T5: =SUBTOTAL(9,T6:T22) -> 0 | U5: =SUBTOTAL(9,U6:U22) -> 0 | V5: =SUBTOTAL(9,V6:V22) -> 0 | W5: =SUBTOTAL(9,W6:W22) -> 0 | X5: =SUBTOTAL(9,X6:X22) -> 0 | ... Z5: =SUBTOTAL(9,Z6:Z22) -> 0
A6: 2.1.1.1.1.2 | B6: PERSONAL ADMINISTRATIVO NOMBRADO (REGIMEN PUBLICO) | C6: ='2.1meta'!D7+'2.1meta'!D24+'2.1meta'!D41+'2.1meta'!D58+'2.1meta'!D76+'2.1meta'!D93+'2.1meta'!D110+'2.1meta'!D127+'2.1meta'!D144+'2.1meta'!D161+'2.1meta'!D178+'2.1meta'!D288+'2.1meta'!D305+'2.1meta'!D322 -> 0 | D6: ='2.1meta'!E7+'2.1meta'!E24+'2.1meta'!E41+'2.1meta'!E58+'2.1meta'!E76+'2.1meta'!E93+'2.1meta'!E110+'2.1meta'!E127+'2.1meta'!E144+'2.1meta'!E161+'2.1meta'!E178+'2.1meta'!E288+'2.1meta'!E305+'2.1meta'!E322 -> 0 | E6: ='2.1meta'!F7+'2.1meta'!F24+'2.1meta'!F41+'2.1meta'!F58+'2.1meta'!F76+'2.1meta'!F93+'2.1meta'!F110+'2.1meta'!F127+'2.1meta'!F144+'2.1meta'!F161+'2.1meta'!F178+'2.1meta'!F288+'2.1meta'!F305+'2.1meta'!F322 -> 0 | F6: ='2.1meta'!G7+'2.1meta'!G24+'2.1meta'!G41+'2.1meta'!G58+'2.1meta'!G76+'2.1meta'!G93+'2.1meta'!G110+'2.1meta'!G127+'2.1meta'!G144+'2.1meta'!G161+'2.1meta'!G178+'2.1meta'!G288+'2.1meta'!G305+'2.1meta'!G322 -> 0 | G6: ='2.1meta'!H7+'2.1meta'!H24+'2.1meta'!H41+'2.1meta'!H58+'2.1meta'!H76+'2.1meta'!H93+'2.1meta'!H110+'2.1meta'!H127+'2.1meta'!H144+'2.1meta'!H161+'2.1meta'!H178+'2.1meta'!H288+'2.1meta'!H305+'2.1meta'!H322 -> 0 | H6: ='2.1meta'!I7+'2.1meta'!I24+'2.1meta'!I41+'2.1meta'!I58+'2.1meta'!I76+'2.1meta'!I93+'2.1meta'!I110+'2.1meta'!I127+'2.1meta'!I144+'2.1meta'!I161+'2.1meta'!I178+'2.1meta'!I288+'2.1meta'!I305+'2.1meta'!I322 -> 0 | I6: ='2.1meta'!J7+'2.1meta'!J24+'2.1meta'!J41+'2.1meta'!J58+'2.1meta'!J76+'2.1meta'!J93+'2.1meta'!J110+'2.1meta'!J127+'2.1meta'!J144+'2.1meta'!J161+'2.1meta'!J178+'2.1meta'!J288+'2.1meta'!J305+'2.1meta'!J322 -> 0 | J6: ='2.1meta'!K7+'2.1meta'!K24+'2.1meta'!K41+'2.1meta'!K58+'2.1meta'!K76+'2.1meta'!K93+'2.1meta'!K110+'2.1meta'!K127+'2.1meta'!K144+'2.1meta'!K161+'2.1meta'!K178+'2.1meta'!K288+'2.1meta'!K305+'2.1meta'!K322 -> 0 | ... N6: ='2.1meta'!O7+'2.1meta'!O24+'2.1meta'!O41+'2.1meta'!O58+'2.1meta'!O76+'2.1meta'!O93+'2.1meta'!O110+'2.1meta'!O127+'2.1meta'!O144+'2.1meta'!O161+'2.1meta'!O178+'2.1meta'!O288+'2.1meta'!O305+'2.1meta'!O322 -> 0 | O6: =SUM(F6:N6) -> 0 | P6: =C6-O6 -> 0 | Q6: ='2.1meta'!R7+'2.1meta'!R24+'2.1meta'!R41+'2.1meta'!R58+'2.1meta'!R76+'2.1meta'!R93+'2.1meta'!R110+'2.1meta'!R127+'2.1meta'!R144+'2.1meta'!R161+'2.1meta'!R178+'2.1meta'!R288+'2.1meta'!R305+'2.1meta'!R322 -> 0 | R6: ='2.1meta'!S7+'2.1meta'!S24+'2.1meta'!S41+'2.1meta'!S58+'2.1meta'!S76+'2.1meta'!S93+'2.1meta'!S110+'2.1meta'!S127+'2.1meta'!S144+'2.1meta'!S161+'2.1meta'!S178+'2.1meta'!S288+'2.1meta'!S305+'2.1meta'!S322 -> 0 | S6: ='2.1meta'!T7+'2.1meta'!T24+'2.1meta'!T41+'2.1meta'!T58+'2.1meta'!T76+'2.1meta'!T93+'2.1meta'!T110+'2.1meta'!T127+'2.1meta'!T144+'2.1meta'!T161+'2.1meta'!T178+'2.1meta'!T288+'2.1meta'!T305+'2.1meta'!T322 -> 0 | T6: ='2.1meta'!U7+'2.1meta'!U24+'2.1meta'!U41+'2.1meta'!U58+'2.1meta'!U76+'2.1meta'!U93+'2.1meta'!U110+'2.1meta'!U127+'2.1meta'!U144+'2.1meta'!U161+'2.1meta'!U178+'2.1meta'!U288+'2.1meta'!U305+'2.1meta'!U322 -> 0 | U6: ='2.1meta'!V7+'2.1meta'!V24+'2.1meta'!V41+'2.1meta'!V58+'2.1meta'!V76+'2.1meta'!V93+'2.1meta'!V110+'2.1meta'!V127+'2.1meta'!V144+'2.1meta'!V161+'2.1meta'!V178+'2.1meta'!V288+'2.1meta'!V305+'2.1meta'!V322 -> 0 | V6: ='2.1meta'!W7+'2.1meta'!W24+'2.1meta'!W41+'2.1meta'!W58+'2.1meta'!W76+'2.1meta'!W93+'2.1meta'!W110+'2.1meta'!W127+'2.1meta'!W144+'2.1meta'!W161+'2.1meta'!W178+'2.1meta'!W288+'2.1meta'!W305+'2.1meta'!W322 -> 0 | W6: ='2.1meta'!X7+'2.1meta'!X24+'2.1meta'!X41+'2.1meta'!X58+'2.1meta'!X76+'2.1meta'!X93+'2.1meta'!X110+'2.1meta'!X127+'2.1meta'!X144+'2.1meta'!X161+'2.1meta'!X178+'2.1meta'!X288+'2.1meta'!X305+'2.1meta'!X322 -> 0 | X6: =SUM(Q6:W6) -> 0 | Y6: =O6+X6 -> 0 | Z6: =C6-Y6 -> 0
A7: 2.1.1.1.1.4 | B7: PERSONAL CON CONTRATO A PLAZO INDETERMINADO (REGIMEN LABORAL PRIVADO) | C7: ='2.1meta'!D8+'2.1meta'!D25+'2.1meta'!D42+'2.1meta'!D59+'2.1meta'!D77+'2.1meta'!D94+'2.1meta'!D111+'2.1meta'!D128+'2.1meta'!D145+'2.1meta'!D162+'2.1meta'!D179+'2.1meta'!D289+'2.1meta'!D306+'2.1meta'!D323 -> 0 | D7: ='2.1meta'!E8+'2.1meta'!E25+'2.1meta'!E42+'2.1meta'!E59+'2.1meta'!E77+'2.1meta'!E94+'2.1meta'!E111+'2.1meta'!E128+'2.1meta'!E145+'2.1meta'!E162+'2.1meta'!E179+'2.1meta'!E289+'2.1meta'!E306+'2.1meta'!E323 -> 0 | E7: ='2.1meta'!F8+'2.1meta'!F25+'2.1meta'!F42+'2.1meta'!F59+'2.1meta'!F77+'2.1meta'!F94+'2.1meta'!F111+'2.1meta'!F128+'2.1meta'!F145+'2.1meta'!F162+'2.1meta'!F179+'2.1meta'!F289+'2.1meta'!F306+'2.1meta'!F323 -> 0 | F7: ='2.1meta'!G8+'2.1meta'!G25+'2.1meta'!G42+'2.1meta'!G59+'2.1meta'!G77+'2.1meta'!G94+'2.1meta'!G111+'2.1meta'!G128+'2.1meta'!G145+'2.1meta'!G162+'2.1meta'!G179+'2.1meta'!G289+'2.1meta'!G306+'2.1meta'!G323 -> 0 | G7: ='2.1meta'!H8+'2.1meta'!H25+'2.1meta'!H42+'2.1meta'!H59+'2.1meta'!H77+'2.1meta'!H94+'2.1meta'!H111+'2.1meta'!H128+'2.1meta'!H145+'2.1meta'!H162+'2.1meta'!H179+'2.1meta'!H289+'2.1meta'!H306+'2.1meta'!H323 -> 0 | H7: ='2.1meta'!I8+'2.1meta'!I25+'2.1meta'!I42+'2.1meta'!I59+'2.1meta'!I77+'2.1meta'!I94+'2.1meta'!I111+'2.1meta'!I128+'2.1meta'!I145+'2.1meta'!I162+'2.1meta'!I179+'2.1meta'!I289+'2.1meta'!I306+'2.1meta'!I323 -> 0 | I7: ='2.1meta'!J8+'2.1meta'!J25+'2.1meta'!J42+'2.1meta'!J59+'2.1meta'!J77+'2.1meta'!J94+'2.1meta'!J111+'2.1meta'!J128+'2.1meta'!J145+'2.1meta'!J162+'2.1meta'!J179+'2.1meta'!J289+'2.1meta'!J306+'2.1meta'!J323 -> 0 | J7: ='2.1meta'!K8+'2.1meta'!K25+'2.1meta'!K42+'2.1meta'!K59+'2.1meta'!K77+'2.1meta'!K94+'2.1meta'!K111+'2.1meta'!K128+'2.1meta'!K145+'2.1meta'!K162+'2.1meta'!K179+'2.1meta'!K289+'2.1meta'!K306+'2.1meta'!K323 -> 0 | ... N7: ='2.1meta'!O8+'2.1meta'!O25+'2.1meta'!O42+'2.1meta'!O59+'2.1meta'!O77+'2.1meta'!O94+'2.1meta'!O111+'2.1meta'!O128+'2.1meta'!O145+'2.1meta'!O162+'2.1meta'!O179+'2.1meta'!O289+'2.1meta'!O306+'2.1meta'!O323 -> 0 | O7: =SUM(F7:N7) -> 0 | P7: =C7-O7 -> 0 | Q7: ='2.1meta'!R8+'2.1meta'!R25+'2.1meta'!R42+'2.1meta'!R59+'2.1meta'!R77+'2.1meta'!R94+'2.1meta'!R111+'2.1meta'!R128+'2.1meta'!R145+'2.1meta'!R162+'2.1meta'!R179+'2.1meta'!R289+'2.1meta'!R306+'2.1meta'!R323 -> 0 | R7: ='2.1meta'!S8+'2.1meta'!S25+'2.1meta'!S42+'2.1meta'!S59+'2.1meta'!S77+'2.1meta'!S94+'2.1meta'!S111+'2.1meta'!S128+'2.1meta'!S145+'2.1meta'!S162+'2.1meta'!S179+'2.1meta'!S289+'2.1meta'!S306+'2.1meta'!S323 -> 0 | S7: ='2.1meta'!T8+'2.1meta'!T25+'2.1meta'!T42+'2.1meta'!T59+'2.1meta'!T77+'2.1meta'!T94+'2.1meta'!T111+'2.1meta'!T128+'2.1meta'!T145+'2.1meta'!T162+'2.1meta'!T179+'2.1meta'!T289+'2.1meta'!T306+'2.1meta'!T323 -> 0 | T7: ='2.1meta'!U8+'2.1meta'!U25+'2.1meta'!U42+'2.1meta'!U59+'2.1meta'!U77+'2.1meta'!U94+'2.1meta'!U111+'2.1meta'!U128+'2.1meta'!U145+'2.1meta'!U162+'2.1meta'!U179+'2.1meta'!U289+'2.1meta'!U306+'2.1meta'!U323 -> 0 | U7: ='2.1meta'!V8+'2.1meta'!V25+'2.1meta'!V42+'2.1meta'!V59+'2.1meta'!V77+'2.1meta'!V94+'2.1meta'!V111+'2.1meta'!V128+'2.1meta'!V145+'2.1meta'!V162+'2.1meta'!V179+'2.1meta'!V289+'2.1meta'!V306+'2.1meta'!V323 -> 0 | V7: ='2.1meta'!W8+'2.1meta'!W25+'2.1meta'!W42+'2.1meta'!W59+'2.1meta'!W77+'2.1meta'!W94+'2.1meta'!W111+'2.1meta'!W128+'2.1meta'!W145+'2.1meta'!W162+'2.1meta'!W179+'2.1meta'!W289+'2.1meta'!W306+'2.1meta'!W323 -> 0 | W7: ='2.1meta'!X8+'2.1meta'!X25+'2.1meta'!X42+'2.1meta'!X59+'2.1meta'!X77+'2.1meta'!X94+'2.1meta'!X111+'2.1meta'!X128+'2.1meta'!X145+'2.1meta'!X162+'2.1meta'!X179+'2.1meta'!X289+'2.1meta'!X306+'2.1meta'!X323 -> 0 | X7: =SUM(Q7:W7) -> 0 | Y7: =O7+X7 -> 0 | Z7: =C7-Y7 -> 0
A8: 2.1.1.1.1.5 | B8: PERSONAL CON CONTRATO A PLAZO FIJO (REGIMEN LABORAL PRIVADO) | C8: ='2.1meta'!D9+'2.1meta'!D26+'2.1meta'!D43+'2.1meta'!D60+'2.1meta'!D78+'2.1meta'!D95+'2.1meta'!D112+'2.1meta'!D129+'2.1meta'!D146+'2.1meta'!D163+'2.1meta'!D180+'2.1meta'!D290+'2.1meta'!D307+'2.1meta'!D324 -> 0 | D8: ='2.1meta'!E8+'2.1meta'!E25+'2.1meta'!E42+'2.1meta'!E60+'2.1meta'!E77+'2.1meta'!E94+'2.1meta'!E111+'2.1meta'!E128+'2.1meta'!E145+'2.1meta'!E162+'2.1meta'!E179+'2.1meta'!E289+'2.1meta'!E306+'2.1meta'!E323 -> 0 | E8: ='2.1meta'!F8+'2.1meta'!F25+'2.1meta'!F42+'2.1meta'!F60+'2.1meta'!F77+'2.1meta'!F94+'2.1meta'!F111+'2.1meta'!F128+'2.1meta'!F145+'2.1meta'!F162+'2.1meta'!F179+'2.1meta'!F289+'2.1meta'!F306+'2.1meta'!F323 -> 0 | F8: ='2.1meta'!G9+'2.1meta'!G26+'2.1meta'!G43+'2.1meta'!G60+'2.1meta'!G78+'2.1meta'!G95+'2.1meta'!G112+'2.1meta'!G129+'2.1meta'!G146+'2.1meta'!G163+'2.1meta'!G180+'2.1meta'!G290+'2.1meta'!G307+'2.1meta'!G324 -> 0 | G8: ='2.1meta'!H9+'2.1meta'!H26+'2.1meta'!H43+'2.1meta'!H60+'2.1meta'!H78+'2.1meta'!H95+'2.1meta'!H112+'2.1meta'!H129+'2.1meta'!H146+'2.1meta'!H163+'2.1meta'!H180+'2.1meta'!H290+'2.1meta'!H307+'2.1meta'!H324 -> 0 | H8: ='2.1meta'!I9+'2.1meta'!I26+'2.1meta'!I43+'2.1meta'!I60+'2.1meta'!I78+'2.1meta'!I95+'2.1meta'!I112+'2.1meta'!I129+'2.1meta'!I146+'2.1meta'!I163+'2.1meta'!I180+'2.1meta'!I290+'2.1meta'!I307+'2.1meta'!I324 -> 0 | I8: ='2.1meta'!J9+'2.1meta'!J26+'2.1meta'!J43+'2.1meta'!J60+'2.1meta'!J78+'2.1meta'!J95+'2.1meta'!J112+'2.1meta'!J129+'2.1meta'!J146+'2.1meta'!J163+'2.1meta'!J180+'2.1meta'!J290+'2.1meta'!J307+'2.1meta'!J324 -> 0 | J8: ='2.1meta'!K9+'2.1meta'!K26+'2.1meta'!K43+'2.1meta'!K60+'2.1meta'!K78+'2.1meta'!K95+'2.1meta'!K112+'2.1meta'!K129+'2.1meta'!K146+'2.1meta'!K163+'2.1meta'!K180+'2.1meta'!K290+'2.1meta'!K307+'2.1meta'!K324 -> 0 | K8: ='2.1meta'!L9+'2.1meta'!L26+'2.1meta'!L43+'2.1meta'!L60+'2.1meta'!L78+'2.1meta'!L95+'2.1meta'!L112+'2.1meta'!L129+'2.1meta'!L146+'2.1meta'!L163+'2.1meta'!L180+'2.1meta'!L290+'2.1meta'!L307+'2.1meta'!L324 -> 0 | L8: ='2.1meta'!M9+'2.1meta'!M26+'2.1meta'!M43+'2.1meta'!M60+'2.1meta'!M78+'2.1meta'!M95+'2.1meta'!M112+'2.1meta'!M129+'2.1meta'!M146+'2.1meta'!M163+'2.1meta'!M180+'2.1meta'!M290+'2.1meta'!M307+'2.1meta'!M324 -> 0 | M8: ='2.1meta'!N9+'2.1meta'!N26+'2.1meta'!N43+'2.1meta'!N60+'2.1meta'!N78+'2.1meta'!N95+'2.1meta'!N112+'2.1meta'!N129+'2.1meta'!N146+'2.1meta'!N163+'2.1meta'!N180+'2.1meta'!N290+'2.1meta'!N307+'2.1meta'!N324 -> 0 | N8: ='2.1meta'!O9+'2.1meta'!O26+'2.1meta'!O43+'2.1meta'!O60+'2.1meta'!O78+'2.1meta'!O95+'2.1meta'!O112+'2.1meta'!O129+'2.1meta'!O146+'2.1meta'!O163+'2.1meta'!O180+'2.1meta'!O290+'2.1meta'!O307+'2.1meta'!O324 -> 0 | O8: =SUM(F8:N8) -> 0 | P8: =C8-O8 -> 0 | Q8: ='2.1meta'!R9+'2.1meta'!R26+'2.1meta'!R43+'2.1meta'!R60+'2.1meta'!R78+'2.1meta'!R95+'2.1meta'!R112+'2.1meta'!R129+'2.1meta'!R146+'2.1meta'!R163+'2.1meta'!R180+'2.1meta'!R290+'2.1meta'!R307+'2.1meta'!R324 -> 0 | R8: ='2.1meta'!S9+'2.1meta'!S26+'2.1meta'!S43+'2.1meta'!S60+'2.1meta'!S78+'2.1meta'!S95+'2.1meta'!S112+'2.1meta'!S129+'2.1meta'!S146+'2.1meta'!S163+'2.1meta'!S180+'2.1meta'!S290+'2.1meta'!S307+'2.1meta'!S324 -> 0 | S8: ='2.1meta'!T9+'2.1meta'!T26+'2.1meta'!T43+'2.1meta'!T60+'2.1meta'!T78+'2.1meta'!T95+'2.1meta'!T112+'2.1meta'!T129+'2.1meta'!T146+'2.1meta'!T163+'2.1meta'!T180+'2.1meta'!T290+'2.1meta'!T307+'2.1meta'!T324 -> 0 | T8: ='2.1meta'!U9+'2.1meta'!U26+'2.1meta'!U43+'2.1meta'!U60+'2.1meta'!U78+'2.1meta'!U95+'2.1meta'!U112+'2.1meta'!U129+'2.1meta'!U146+'2.1meta'!U163+'2.1meta'!U180+'2.1meta'!U290+'2.1meta'!U307+'2.1meta'!U324 -> 0 | U8: ='2.1meta'!V9+'2.1meta'!V26+'2.1meta'!V43+'2.1meta'!V60+'2.1meta'!V78+'2.1meta'!V95+'2.1meta'!V112+'2.1meta'!V129+'2.1meta'!V146+'2.1meta'!V163+'2.1meta'!V180+'2.1meta'!V290+'2.1meta'!V307+'2.1meta'!V324 -> 0 | V8: ='2.1meta'!W9+'2.1meta'!W26+'2.1meta'!W43+'2.1meta'!W60+'2.1meta'!W78+'2.1meta'!W95+'2.1meta'!W112+'2.1meta'!W129+'2.1meta'!W146+'2.1meta'!W163+'2.1meta'!W180+'2.1meta'!W290+'2.1meta'!W307+'2.1meta'!W324 -> 0 | W8: ='2.1meta'!X9+'2.1meta'!X26+'2.1meta'!X43+'2.1meta'!X60+'2.1meta'!X78+'2.1meta'!X95+'2.1meta'!X112+'2.1meta'!X129+'2.1meta'!X146+'2.1meta'!X163+'2.1meta'!X180+'2.1meta'!X290+'2.1meta'!X307+'2.1meta'!X324 -> 0 | X8: =SUM(Q8:W8) -> 0 | Y8: =O8+X8 -> 0 | Z8: =C8-Y8 -> 0
A9: 2.1.1.1.2.1 | B9: ASIGNACION A FONDOS PARA PERSONAL | C9: ='2.1meta'!D10+'2.1meta'!D27+'2.1meta'!D44+'2.1meta'!D61+'2.1meta'!D79+'2.1meta'!D96+'2.1meta'!D113+'2.1meta'!D130+'2.1meta'!D147+'2.1meta'!D164+'2.1meta'!D181+'2.1meta'!D291+'2.1meta'!D308+'2.1meta'!D325 -> 0 | D9: ='2.1meta'!E9+'2.1meta'!E26+'2.1meta'!E43+'2.1meta'!E61+'2.1meta'!E78+'2.1meta'!E95+'2.1meta'!E112+'2.1meta'!E129+'2.1meta'!E146+'2.1meta'!E163+'2.1meta'!E180+'2.1meta'!E290+'2.1meta'!E307+'2.1meta'!E324 -> 0 | E9: ='2.1meta'!F9+'2.1meta'!F26+'2.1meta'!F43+'2.1meta'!F61+'2.1meta'!F78+'2.1meta'!F95+'2.1meta'!F112+'2.1meta'!F129+'2.1meta'!F146+'2.1meta'!F163+'2.1meta'!F180+'2.1meta'!F290+'2.1meta'!F307+'2.1meta'!F324 -> 0 | F9: ='2.1meta'!G10+'2.1meta'!G27+'2.1meta'!G44+'2.1meta'!G61+'2.1meta'!G79+'2.1meta'!G96+'2.1meta'!G113+'2.1meta'!G130+'2.1meta'!G147+'2.1meta'!G164+'2.1meta'!G181+'2.1meta'!G291+'2.1meta'!G308+'2.1meta'!G325 -> 0 | G9: ='2.1meta'!H10+'2.1meta'!H27+'2.1meta'!H44+'2.1meta'!H61+'2.1meta'!H79+'2.1meta'!H96+'2.1meta'!H113+'2.1meta'!H130+'2.1meta'!H147+'2.1meta'!H164+'2.1meta'!H181+'2.1meta'!H291+'2.1meta'!H308+'2.1meta'!H325 -> 0 | H9: ='2.1meta'!I10+'2.1meta'!I27+'2.1meta'!I44+'2.1meta'!I61+'2.1meta'!I79+'2.1meta'!I96+'2.1meta'!I113+'2.1meta'!I130+'2.1meta'!I147+'2.1meta'!I164+'2.1meta'!I181+'2.1meta'!I291+'2.1meta'!I308+'2.1meta'!I325 -> 0 | I9: ='2.1meta'!J10+'2.1meta'!J27+'2.1meta'!J44+'2.1meta'!J61+'2.1meta'!J79+'2.1meta'!J96+'2.1meta'!J113+'2.1meta'!J130+'2.1meta'!J147+'2.1meta'!J164+'2.1meta'!J181+'2.1meta'!J291+'2.1meta'!J308+'2.1meta'!J325 -> 0 | J9: ='2.1meta'!K10+'2.1meta'!K27+'2.1meta'!K44+'2.1meta'!K61+'2.1meta'!K79+'2.1meta'!K96+'2.1meta'!K113+'2.1meta'!K130+'2.1meta'!K147+'2.1meta'!K164+'2.1meta'!K181+'2.1meta'!K291+'2.1meta'!K308+'2.1meta'!K325 -> 0 | K9: ='2.1meta'!L10+'2.1meta'!L27+'2.1meta'!L44+'2.1meta'!L61+'2.1meta'!L79+'2.1meta'!L96+'2.1meta'!L113+'2.1meta'!L130+'2.1meta'!L147+'2.1meta'!L164+'2.1meta'!L181+'2.1meta'!L291+'2.1meta'!L308+'2.1meta'!L325 -> 0 | L9: ='2.1meta'!M10+'2.1meta'!M27+'2.1meta'!M44+'2.1meta'!M61+'2.1meta'!M79+'2.1meta'!M96+'2.1meta'!M113+'2.1meta'!M130+'2.1meta'!M147+'2.1meta'!M164+'2.1meta'!M181+'2.1meta'!M291+'2.1meta'!M308+'2.1meta'!M325 -> 0 | M9: ='2.1meta'!N10+'2.1meta'!N27+'2.1meta'!N44+'2.1meta'!N61+'2.1meta'!N79+'2.1meta'!N96+'2.1meta'!N113+'2.1meta'!N130+'2.1meta'!N147+'2.1meta'!N164+'2.1meta'!N181+'2.1meta'!N291+'2.1meta'!N308+'2.1meta'!N325 -> 0 | N9: ='2.1meta'!O10+'2.1meta'!O27+'2.1meta'!O44+'2.1meta'!O61+'2.1meta'!O79+'2.1meta'!O96+'2.1meta'!O113+'2.1meta'!O130+'2.1meta'!O147+'2.1meta'!O164+'2.1meta'!O181+'2.1meta'!O291+'2.1meta'!O308+'2.1meta'!O325 -> 0 | O9: =SUM(F9:N9) -> 0 | P9: =C9-O9 -> 0 | Q9: ='2.1meta'!R10+'2.1meta'!R27+'2.1meta'!R44+'2.1meta'!R61+'2.1meta'!R79+'2.1meta'!R96+'2.1meta'!R113+'2.1meta'!R130+'2.1meta'!R147+'2.1meta'!R164+'2.1meta'!R181+'2.1meta'!R291+'2.1meta'!R308+'2.1meta'!R325 -> 0 | R9: ='2.1meta'!S10+'2.1meta'!S27+'2.1meta'!S44+'2.1meta'!S61+'2.1meta'!S79+'2.1meta'!S96+'2.1meta'!S113+'2.1meta'!S130+'2.1meta'!S147+'2.1meta'!S164+'2.1meta'!S181+'2.1meta'!S291+'2.1meta'!S308+'2.1meta'!S325 -> 0 | S9: ='2.1meta'!T10+'2.1meta'!T27+'2.1meta'!T44+'2.1meta'!T61+'2.1meta'!T79+'2.1meta'!T96+'2.1meta'!T113+'2.1meta'!T130+'2.1meta'!T147+'2.1meta'!T164+'2.1meta'!T181+'2.1meta'!T291+'2.1meta'!T308+'2.1meta'!T325 -> 0 | T9: ='2.1meta'!U10+'2.1meta'!U27+'2.1meta'!U44+'2.1meta'!U61+'2.1meta'!U79+'2.1meta'!U96+'2.1meta'!U113+'2.1meta'!U130+'2.1meta'!U147+'2.1meta'!U164+'2.1meta'!U181+'2.1meta'!U291+'2.1meta'!U308+'2.1meta'!U325 -> 0 | U9: ='2.1meta'!V10+'2.1meta'!V27+'2.1meta'!V44+'2.1meta'!V61+'2.1meta'!V79+'2.1meta'!V96+'2.1meta'!V113+'2.1meta'!V130+'2.1meta'!V147+'2.1meta'!V164+'2.1meta'!V181+'2.1meta'!V291+'2.1meta'!V308+'2.1meta'!V325 -> 0 | V9: ='2.1meta'!W10+'2.1meta'!W27+'2.1meta'!W44+'2.1meta'!W61+'2.1meta'!W79+'2.1meta'!W96+'2.1meta'!W113+'2.1meta'!W130+'2.1meta'!W147+'2.1meta'!W164+'2.1meta'!W181+'2.1meta'!W291+'2.1meta'!W308+'2.1meta'!W325 -> 0 | W9: ='2.1meta'!X10+'2.1meta'!X27+'2.1meta'!X44+'2.1meta'!X61+'2.1meta'!X79+'2.1meta'!X96+'2.1meta'!X113+'2.1meta'!X130+'2.1meta'!X147+'2.1meta'!X164+'2.1meta'!X181+'2.1meta'!X291+'2.1meta'!X308+'2.1meta'!X325 -> 0 | X9: =SUM(Q9:W9) -> 0 | Y9: =O9+X9 -> 0 | Z9: =C9-Y9 -> 0
A10: 2.1.1.3.1.2 | B10: PERSONAL CONTRATADO | C10: ='2.1meta'!D62 -> 0 | D10: ='2.1meta'!E10+'2.1meta'!E27+'2.1meta'!E44+'2.1meta'!E62+'2.1meta'!E79+'2.1meta'!E96+'2.1meta'!E113+'2.1meta'!E130+'2.1meta'!E147+'2.1meta'!E164+'2.1meta'!E181+'2.1meta'!E291+'2.1meta'!E308+'2.1meta'!E325 -> 0 | E10: ='2.1meta'!F10+'2.1meta'!F27+'2.1meta'!F44+'2.1meta'!F62+'2.1meta'!F79+'2.1meta'!F96+'2.1meta'!F113+'2.1meta'!F130+'2.1meta'!F147+'2.1meta'!F164+'2.1meta'!F181+'2.1meta'!F291+'2.1meta'!F308+'2.1meta'!F325 -> 0 | F10: ='2.1meta'!G62 -> 0 | G10: ='2.1meta'!H62 -> 0 | H10: ='2.1meta'!I62 -> 0 | I10: ='2.1meta'!J62 -> 0 | J10: ='2.1meta'!K62 -> 0 | K10: ='2.1meta'!L62 -> 0 | L10: ='2.1meta'!M62 -> 0 | M10: ='2.1meta'!N62 -> 0 | N10: ='2.1meta'!O62 -> 0 | O10: =SUM(F10:N10) -> 0 | P10: =C10-O10 -> 0 | Q10: ='2.1meta'!R62 -> 0 | R10: ='2.1meta'!S62 -> 0 | S10: ='2.1meta'!T62 -> 0 | T10: ='2.1meta'!U62 -> 0 | U10: ='2.1meta'!V62 -> 0 | V10: ='2.1meta'!W62 -> 0 | W10: ='2.1meta'!X62 -> 0 | X10: =SUM(Q10:W10) -> 0 | Y10: =O10+X10 -> 0 | Z10: =C10-Y10 -> 0
A11: 2.1.1.4.1.1 | B11: PERSONAL NOMBRADO | C11: ='2.1meta'!D11+'2.1meta'!D28+'2.1meta'!D45+'2.1meta'!D63+'2.1meta'!D80+'2.1meta'!D97+'2.1meta'!D114+'2.1meta'!D131+'2.1meta'!D148+'2.1meta'!D165+'2.1meta'!D182+'2.1meta'!D292+'2.1meta'!D309+'2.1meta'!D326 -> 0 | D11: ='2.1meta'!E11+'2.1meta'!E28+'2.1meta'!E45+'2.1meta'!E63+'2.1meta'!E80+'2.1meta'!E97+'2.1meta'!E114+'2.1meta'!E131+'2.1meta'!E148+'2.1meta'!E165+'2.1meta'!E182+'2.1meta'!E292+'2.1meta'!E309+'2.1meta'!E326 -> 0 | E11: ='2.1meta'!F11+'2.1meta'!F28+'2.1meta'!F45+'2.1meta'!F63+'2.1meta'!F80+'2.1meta'!F97+'2.1meta'!F114+'2.1meta'!F131+'2.1meta'!F148+'2.1meta'!F165+'2.1meta'!F182+'2.1meta'!F292+'2.1meta'!F309+'2.1meta'!F326 -> 0 | F11: ='2.1meta'!G11+'2.1meta'!G28+'2.1meta'!G45+'2.1meta'!G63+'2.1meta'!G80+'2.1meta'!G97+'2.1meta'!G114+'2.1meta'!G131+'2.1meta'!G148+'2.1meta'!G165+'2.1meta'!G182+'2.1meta'!G292+'2.1meta'!G309+'2.1meta'!G326 -> 0 | G11: ='2.1meta'!H11+'2.1meta'!H28+'2.1meta'!H45+'2.1meta'!H63+'2.1meta'!H80+'2.1meta'!H97+'2.1meta'!H114+'2.1meta'!H131+'2.1meta'!H148+'2.1meta'!H165+'2.1meta'!H182+'2.1meta'!H292+'2.1meta'!H309+'2.1meta'!H326 -> 0 | H11: ='2.1meta'!I11+'2.1meta'!I28+'2.1meta'!I45+'2.1meta'!I63+'2.1meta'!I80+'2.1meta'!I97+'2.1meta'!I114+'2.1meta'!I131+'2.1meta'!I148+'2.1meta'!I165+'2.1meta'!I182+'2.1meta'!I292+'2.1meta'!I309+'2.1meta'!I326 -> 0 | I11: ='2.1meta'!J11+'2.1meta'!J28+'2.1meta'!J45+'2.1meta'!J63+'2.1meta'!J80+'2.1meta'!J97+'2.1meta'!J114+'2.1meta'!J131+'2.1meta'!J148+'2.1meta'!J165+'2.1meta'!J182+'2.1meta'!J292+'2.1meta'!J309+'2.1meta'!J326 -> 0 | J11: ='2.1meta'!K11+'2.1meta'!K28+'2.1meta'!K45+'2.1meta'!K63+'2.1meta'!K80+'2.1meta'!K97+'2.1meta'!K114+'2.1meta'!K131+'2.1meta'!K148+'2.1meta'!K165+'2.1meta'!K182+'2.1meta'!K292+'2.1meta'!K309+'2.1meta'!K326 -> 0 | ... N11: ='2.1meta'!O11+'2.1meta'!O28+'2.1meta'!O45+'2.1meta'!O63+'2.1meta'!O80+'2.1meta'!O97+'2.1meta'!O114+'2.1meta'!O131+'2.1meta'!O148+'2.1meta'!O165+'2.1meta'!O182+'2.1meta'!O292+'2.1meta'!O309+'2.1meta'!O326 -> 0 | O11: =SUM(F11:N11) -> 0 | P11: =C11-O11 -> 0 | Q11: ='2.1meta'!R11+'2.1meta'!R28+'2.1meta'!R45+'2.1meta'!R63+'2.1meta'!R80+'2.1meta'!R97+'2.1meta'!R114+'2.1meta'!R131+'2.1meta'!R148+'2.1meta'!R165+'2.1meta'!R182+'2.1meta'!R292+'2.1meta'!R309+'2.1meta'!R326 -> 0 | R11: ='2.1meta'!S11+'2.1meta'!S28+'2.1meta'!S45+'2.1meta'!S63+'2.1meta'!S80+'2.1meta'!S97+'2.1meta'!S114+'2.1meta'!S131+'2.1meta'!S148+'2.1meta'!S165+'2.1meta'!S182+'2.1meta'!S292+'2.1meta'!S309+'2.1meta'!S326 -> 0 | S11: ='2.1meta'!T11+'2.1meta'!T28+'2.1meta'!T45+'2.1meta'!T63+'2.1meta'!T80+'2.1meta'!T97+'2.1meta'!T114+'2.1meta'!T131+'2.1meta'!T148+'2.1meta'!T165+'2.1meta'!T182+'2.1meta'!T292+'2.1meta'!T309+'2.1meta'!T326 -> 0 | T11: ='2.1meta'!U11+'2.1meta'!U28+'2.1meta'!U45+'2.1meta'!U63+'2.1meta'!U80+'2.1meta'!U97+'2.1meta'!U114+'2.1meta'!U131+'2.1meta'!U148+'2.1meta'!U165+'2.1meta'!U182+'2.1meta'!U292+'2.1meta'!U309+'2.1meta'!U326 -> 0 | U11: ='2.1meta'!V11+'2.1meta'!V28+'2.1meta'!V45+'2.1meta'!V63+'2.1meta'!V80+'2.1meta'!V97+'2.1meta'!V114+'2.1meta'!V131+'2.1meta'!V148+'2.1meta'!V165+'2.1meta'!V182+'2.1meta'!V292+'2.1meta'!V309+'2.1meta'!V326 -> 0 | V11: ='2.1meta'!W11+'2.1meta'!W28+'2.1meta'!W45+'2.1meta'!W63+'2.1meta'!W80+'2.1meta'!W97+'2.1meta'!W114+'2.1meta'!W131+'2.1meta'!W148+'2.1meta'!W165+'2.1meta'!W182+'2.1meta'!W292+'2.1meta'!W309+'2.1meta'!W326 -> 0 | W11: ='2.1meta'!X11+'2.1meta'!X28+'2.1meta'!X45+'2.1meta'!X63+'2.1meta'!X80+'2.1meta'!X97+'2.1meta'!X114+'2.1meta'!X131+'2.1meta'!X148+'2.1meta'!X165+'2.1meta'!X182+'2.1meta'!X292+'2.1meta'!X309+'2.1meta'!X326 -> 0 | X11: =SUM(Q11:W11) -> 0 | Y11: =O11+X11 -> 0 | Z11: =C11-Y11 -> 0
A12: 2.1.1.4.2.1 | B12: BONO POR FUNCION JURISDICCIONAL Y FISCAL | C12: ='2.1meta'!D12+'2.1meta'!D29+'2.1meta'!D46+'2.1meta'!D64+'2.1meta'!D81+'2.1meta'!D98+'2.1meta'!D115+'2.1meta'!D132+'2.1meta'!D149+'2.1meta'!D166+'2.1meta'!D183+'2.1meta'!D293+'2.1meta'!D310+'2.1meta'!D327 -> 0 | D12: ='2.1meta'!E12+'2.1meta'!E29+'2.1meta'!E46+'2.1meta'!E64+'2.1meta'!E81+'2.1meta'!E98+'2.1meta'!E115+'2.1meta'!E132+'2.1meta'!E149+'2.1meta'!E166+'2.1meta'!E183+'2.1meta'!E293+'2.1meta'!E310+'2.1meta'!E327 -> 0 | E12: ='2.1meta'!F12+'2.1meta'!F29+'2.1meta'!F46+'2.1meta'!F64+'2.1meta'!F81+'2.1meta'!F98+'2.1meta'!F115+'2.1meta'!F132+'2.1meta'!F149+'2.1meta'!F166+'2.1meta'!F183+'2.1meta'!F293+'2.1meta'!F310+'2.1meta'!F327 -> 0 | F12: ='2.1meta'!G12+'2.1meta'!G29+'2.1meta'!G46+'2.1meta'!G64+'2.1meta'!G81+'2.1meta'!G98+'2.1meta'!G115+'2.1meta'!G132+'2.1meta'!G149+'2.1meta'!G166+'2.1meta'!G183+'2.1meta'!G293+'2.1meta'!G310+'2.1meta'!G327 -> 0 | G12: ='2.1meta'!H12+'2.1meta'!H29+'2.1meta'!H46+'2.1meta'!H64+'2.1meta'!H81+'2.1meta'!H98+'2.1meta'!H115+'2.1meta'!H132+'2.1meta'!H149+'2.1meta'!H166+'2.1meta'!H183+'2.1meta'!H293+'2.1meta'!H310+'2.1meta'!H327 -> 0 | H12: ='2.1meta'!I12+'2.1meta'!I29+'2.1meta'!I46+'2.1meta'!I64+'2.1meta'!I81+'2.1meta'!I98+'2.1meta'!I115+'2.1meta'!I132+'2.1meta'!I149+'2.1meta'!I166+'2.1meta'!I183+'2.1meta'!I293+'2.1meta'!I310+'2.1meta'!I327 -> 0 | I12: ='2.1meta'!J12+'2.1meta'!J29+'2.1meta'!J46+'2.1meta'!J64+'2.1meta'!J81+'2.1meta'!J98+'2.1meta'!J115+'2.1meta'!J132+'2.1meta'!J149+'2.1meta'!J166+'2.1meta'!J183+'2.1meta'!J293+'2.1meta'!J310+'2.1meta'!J327 -> 0 | J12: ='2.1meta'!K12+'2.1meta'!K29+'2.1meta'!K46+'2.1meta'!K64+'2.1meta'!K81+'2.1meta'!K98+'2.1meta'!K115+'2.1meta'!K132+'2.1meta'!K149+'2.1meta'!K166+'2.1meta'!K183+'2.1meta'!K293+'2.1meta'!K310+'2.1meta'!K327 -> 0 | ... N12: ='2.1meta'!O12+'2.1meta'!O29+'2.1meta'!O46+'2.1meta'!O64+'2.1meta'!O81+'2.1meta'!O98+'2.1meta'!O115+'2.1meta'!O132+'2.1meta'!O149+'2.1meta'!O166+'2.1meta'!O183+'2.1meta'!O293+'2.1meta'!O310+'2.1meta'!O327 -> 0 | O12: =SUM(F12:N12) -> 0 | P12: =C12-O12 -> 0 | Q12: ='2.1meta'!R12+'2.1meta'!R29+'2.1meta'!R46+'2.1meta'!R64+'2.1meta'!R81+'2.1meta'!R98+'2.1meta'!R115+'2.1meta'!R132+'2.1meta'!R149+'2.1meta'!R166+'2.1meta'!R183+'2.1meta'!R293+'2.1meta'!R310+'2.1meta'!R327 -> 0 | R12: ='2.1meta'!S12+'2.1meta'!S29+'2.1meta'!S46+'2.1meta'!S64+'2.1meta'!S81+'2.1meta'!S98+'2.1meta'!S115+'2.1meta'!S132+'2.1meta'!S149+'2.1meta'!S166+'2.1meta'!S183+'2.1meta'!S293+'2.1meta'!S310+'2.1meta'!S327 -> 0 | S12: ='2.1meta'!T12+'2.1meta'!T29+'2.1meta'!T46+'2.1meta'!T64+'2.1meta'!T81+'2.1meta'!T98+'2.1meta'!T115+'2.1meta'!T132+'2.1meta'!T149+'2.1meta'!T166+'2.1meta'!T183+'2.1meta'!T293+'2.1meta'!T310+'2.1meta'!T327 -> 0 | T12: ='2.1meta'!U12+'2.1meta'!U29+'2.1meta'!U46+'2.1meta'!U64+'2.1meta'!U81+'2.1meta'!U98+'2.1meta'!U115+'2.1meta'!U132+'2.1meta'!U149+'2.1meta'!U166+'2.1meta'!U183+'2.1meta'!U293+'2.1meta'!U310+'2.1meta'!U327 -> 0 | U12: ='2.1meta'!V12+'2.1meta'!V29+'2.1meta'!V46+'2.1meta'!V64+'2.1meta'!V81+'2.1meta'!V98+'2.1meta'!V115+'2.1meta'!V132+'2.1meta'!V149+'2.1meta'!V166+'2.1meta'!V183+'2.1meta'!V293+'2.1meta'!V310+'2.1meta'!V327 -> 0 | V12: ='2.1meta'!W12+'2.1meta'!W29+'2.1meta'!W46+'2.1meta'!W64+'2.1meta'!W81+'2.1meta'!W98+'2.1meta'!W115+'2.1meta'!W132+'2.1meta'!W149+'2.1meta'!W166+'2.1meta'!W183+'2.1meta'!W293+'2.1meta'!W310+'2.1meta'!W327 -> 0 | W12: ='2.1meta'!X13+'2.1meta'!X30+'2.1meta'!X47+'2.1meta'!X64+'2.1meta'!X82+'2.1meta'!X99+'2.1meta'!X116+'2.1meta'!X133+'2.1meta'!X150+'2.1meta'!X167+'2.1meta'!X184+'2.1meta'!X294+'2.1meta'!X311+'2.1meta'!X328 -> 0 | X12: =SUM(Q12:W12) -> 0 | Y12: =O12+X12 -> 0 | Z12: =C12-Y12 -> 0
A13: 2.1.1.4.2.2 | B13: ASIGNACION POR GASTOS OPERATIVOS | C13: ='2.1meta'!D13+'2.1meta'!D30+'2.1meta'!D47+'2.1meta'!D65+'2.1meta'!D82+'2.1meta'!D99+'2.1meta'!D116+'2.1meta'!D133+'2.1meta'!D150+'2.1meta'!D167+'2.1meta'!D184+'2.1meta'!D294+'2.1meta'!D311+'2.1meta'!D328 -> 0 | D13: ='2.1meta'!E13+'2.1meta'!E30+'2.1meta'!E47+'2.1meta'!E65+'2.1meta'!E82+'2.1meta'!E99+'2.1meta'!E116+'2.1meta'!E133+'2.1meta'!E150+'2.1meta'!E167+'2.1meta'!E184+'2.1meta'!E294+'2.1meta'!E311+'2.1meta'!E328 -> 0 | E13: ='2.1meta'!F13+'2.1meta'!F30+'2.1meta'!F47+'2.1meta'!F65+'2.1meta'!F82+'2.1meta'!F99+'2.1meta'!F116+'2.1meta'!F133+'2.1meta'!F150+'2.1meta'!F167+'2.1meta'!F184+'2.1meta'!F294+'2.1meta'!F311+'2.1meta'!F328 -> 0 | F13: ='2.1meta'!G13+'2.1meta'!G30+'2.1meta'!G47+'2.1meta'!G65+'2.1meta'!G82+'2.1meta'!G99+'2.1meta'!G116+'2.1meta'!G133+'2.1meta'!G150+'2.1meta'!G167+'2.1meta'!G184+'2.1meta'!G294+'2.1meta'!G311+'2.1meta'!G328 -> 0 | G13: ='2.1meta'!H13+'2.1meta'!H30+'2.1meta'!H47+'2.1meta'!H65+'2.1meta'!H82+'2.1meta'!H99+'2.1meta'!H116+'2.1meta'!H133+'2.1meta'!H150+'2.1meta'!H167+'2.1meta'!H184+'2.1meta'!H294+'2.1meta'!H311+'2.1meta'!H328 -> 0 | H13: ='2.1meta'!I13+'2.1meta'!I30+'2.1meta'!I47+'2.1meta'!I65+'2.1meta'!I82+'2.1meta'!I99+'2.1meta'!I116+'2.1meta'!I133+'2.1meta'!I150+'2.1meta'!I167+'2.1meta'!I184+'2.1meta'!I294+'2.1meta'!I311+'2.1meta'!I328 -> 0 | I13: ='2.1meta'!J13+'2.1meta'!J30+'2.1meta'!J47+'2.1meta'!J65+'2.1meta'!J82+'2.1meta'!J99+'2.1meta'!J116+'2.1meta'!J133+'2.1meta'!J150+'2.1meta'!J167+'2.1meta'!J184+'2.1meta'!J294+'2.1meta'!J311+'2.1meta'!J328 -> 0 | J13: ='2.1meta'!K13+'2.1meta'!K30+'2.1meta'!K47+'2.1meta'!K65+'2.1meta'!K82+'2.1meta'!K99+'2.1meta'!K116+'2.1meta'!K133+'2.1meta'!K150+'2.1meta'!K167+'2.1meta'!K184+'2.1meta'!K294+'2.1meta'!K311+'2.1meta'!K328 -> 0 | ... N13: ='2.1meta'!O13+'2.1meta'!O30+'2.1meta'!O47+'2.1meta'!O65+'2.1meta'!O82+'2.1meta'!O99+'2.1meta'!O116+'2.1meta'!O133+'2.1meta'!O150+'2.1meta'!O167+'2.1meta'!O184+'2.1meta'!O294+'2.1meta'!O311+'2.1meta'!O328 -> 0 | O13: =SUM(F13:N13) -> 0 | P13: =C13-O13 -> 0 | Q13: ='2.1meta'!R13+'2.1meta'!R30+'2.1meta'!R47+'2.1meta'!R65+'2.1meta'!R82+'2.1meta'!R99+'2.1meta'!R116+'2.1meta'!R133+'2.1meta'!R150+'2.1meta'!R167+'2.1meta'!R184+'2.1meta'!R294+'2.1meta'!R311+'2.1meta'!R328 -> 0 | R13: ='2.1meta'!S13+'2.1meta'!S30+'2.1meta'!S47+'2.1meta'!S65+'2.1meta'!S82+'2.1meta'!S99+'2.1meta'!S116+'2.1meta'!S133+'2.1meta'!S150+'2.1meta'!S167+'2.1meta'!S184+'2.1meta'!S294+'2.1meta'!S311+'2.1meta'!S328 -> 0 | S13: ='2.1meta'!T13+'2.1meta'!T30+'2.1meta'!T47+'2.1meta'!T65+'2.1meta'!T82+'2.1meta'!T99+'2.1meta'!T116+'2.1meta'!T133+'2.1meta'!T150+'2.1meta'!T167+'2.1meta'!T184+'2.1meta'!T294+'2.1meta'!T311+'2.1meta'!T328 -> 0 | T13: ='2.1meta'!U13+'2.1meta'!U30+'2.1meta'!U47+'2.1meta'!U65+'2.1meta'!U82+'2.1meta'!U99+'2.1meta'!U116+'2.1meta'!U133+'2.1meta'!U150+'2.1meta'!U167+'2.1meta'!U184+'2.1meta'!U294+'2.1meta'!U311+'2.1meta'!U328 -> 0 | U13: ='2.1meta'!V13+'2.1meta'!V30+'2.1meta'!V47+'2.1meta'!V65+'2.1meta'!V82+'2.1meta'!V99+'2.1meta'!V116+'2.1meta'!V133+'2.1meta'!V150+'2.1meta'!V167+'2.1meta'!V184+'2.1meta'!V294+'2.1meta'!V311+'2.1meta'!V328 -> 0 | V13: ='2.1meta'!W13+'2.1meta'!W30+'2.1meta'!W47+'2.1meta'!W65+'2.1meta'!W82+'2.1meta'!W99+'2.1meta'!W116+'2.1meta'!W133+'2.1meta'!W150+'2.1meta'!W167+'2.1meta'!W184+'2.1meta'!W294+'2.1meta'!W311+'2.1meta'!W328 -> 0 | W13: ='2.1meta'!X13+'2.1meta'!X30+'2.1meta'!X47+'2.1meta'!X65+'2.1meta'!X82+'2.1meta'!X99+'2.1meta'!X116+'2.1meta'!X133+'2.1meta'!X150+'2.1meta'!X167+'2.1meta'!X184+'2.1meta'!X294+'2.1meta'!X311+'2.1meta'!X328 -> 0 | X13: =SUM(Q13:W13) -> 0 | Y13: =O13+X13 -> 0 | Z13: =C13-Y13 -> 0
A14: 2.1.1.9.1.1 | B14: GRATIFICACIONES | C14: ='2.1meta'!D14+'2.1meta'!D31+'2.1meta'!D48+'2.1meta'!D66+'2.1meta'!D83+'2.1meta'!D100+'2.1meta'!D117+'2.1meta'!D134+'2.1meta'!D151+'2.1meta'!D168+'2.1meta'!D185+'2.1meta'!D295+'2.1meta'!D312+'2.1meta'!D329 -> 0 | D14: ='2.1meta'!E14+'2.1meta'!E31+'2.1meta'!E48+'2.1meta'!E66+'2.1meta'!E83+'2.1meta'!E100+'2.1meta'!E117+'2.1meta'!E134+'2.1meta'!E151+'2.1meta'!E168+'2.1meta'!E185+'2.1meta'!E295+'2.1meta'!E312+'2.1meta'!E329 -> 0 | E14: ='2.1meta'!F14+'2.1meta'!F31+'2.1meta'!F48+'2.1meta'!F66+'2.1meta'!F83+'2.1meta'!F100+'2.1meta'!F117+'2.1meta'!F134+'2.1meta'!F151+'2.1meta'!F168+'2.1meta'!F185+'2.1meta'!F295+'2.1meta'!F312+'2.1meta'!F329 -> 0 | F14: ='2.1meta'!G14+'2.1meta'!G31+'2.1meta'!G48+'2.1meta'!G66+'2.1meta'!G83+'2.1meta'!G100+'2.1meta'!G117+'2.1meta'!G134+'2.1meta'!G151+'2.1meta'!G168+'2.1meta'!G185+'2.1meta'!G295+'2.1meta'!G312+'2.1meta'!G329 -> 0 | G14: ='2.1meta'!H14+'2.1meta'!H31+'2.1meta'!H48+'2.1meta'!H66+'2.1meta'!H83+'2.1meta'!H100+'2.1meta'!H117+'2.1meta'!H134+'2.1meta'!H151+'2.1meta'!H168+'2.1meta'!H185+'2.1meta'!H295+'2.1meta'!H312+'2.1meta'!H329 -> 0 | H14: ='2.1meta'!I14+'2.1meta'!I31+'2.1meta'!I48+'2.1meta'!I66+'2.1meta'!I83+'2.1meta'!I100+'2.1meta'!I117+'2.1meta'!I134+'2.1meta'!I151+'2.1meta'!I168+'2.1meta'!I185+'2.1meta'!I295+'2.1meta'!I312+'2.1meta'!I329 -> 0 | I14: ='2.1meta'!J14+'2.1meta'!J31+'2.1meta'!J48+'2.1meta'!J66+'2.1meta'!J83+'2.1meta'!J100+'2.1meta'!J117+'2.1meta'!J134+'2.1meta'!J151+'2.1meta'!J168+'2.1meta'!J185+'2.1meta'!J295+'2.1meta'!J312+'2.1meta'!J329 -> 0 | J14: ='2.1meta'!K14+'2.1meta'!K31+'2.1meta'!K48+'2.1meta'!K66+'2.1meta'!K83+'2.1meta'!K100+'2.1meta'!K117+'2.1meta'!K134+'2.1meta'!K151+'2.1meta'!K168+'2.1meta'!K185+'2.1meta'!K295+'2.1meta'!K312+'2.1meta'!K329 -> 0 | ... N14: ='2.1meta'!O14+'2.1meta'!O31+'2.1meta'!O48+'2.1meta'!O66+'2.1meta'!O83+'2.1meta'!O100+'2.1meta'!O117+'2.1meta'!O134+'2.1meta'!O151+'2.1meta'!O168+'2.1meta'!O185+'2.1meta'!O295+'2.1meta'!O312+'2.1meta'!O329 -> 0 | O14: =SUM(F14:N14) -> 0 | P14: =C14-O14 -> 0 | Q14: ='2.1meta'!R14+'2.1meta'!R31+'2.1meta'!R48+'2.1meta'!R66+'2.1meta'!R83+'2.1meta'!R100+'2.1meta'!R117+'2.1meta'!R134+'2.1meta'!R151+'2.1meta'!R168+'2.1meta'!R185+'2.1meta'!R295+'2.1meta'!R312+'2.1meta'!R329 -> 0 | R14: ='2.1meta'!S14+'2.1meta'!S31+'2.1meta'!S48+'2.1meta'!S66+'2.1meta'!S83+'2.1meta'!S100+'2.1meta'!S117+'2.1meta'!S134+'2.1meta'!S151+'2.1meta'!S168+'2.1meta'!S185+'2.1meta'!S295+'2.1meta'!S312+'2.1meta'!S329 -> 0 | S14: ='2.1meta'!T14+'2.1meta'!T31+'2.1meta'!T48+'2.1meta'!T66+'2.1meta'!T83+'2.1meta'!T100+'2.1meta'!T117+'2.1meta'!T134+'2.1meta'!T151+'2.1meta'!T168+'2.1meta'!T185+'2.1meta'!T295+'2.1meta'!T312+'2.1meta'!T329 -> 0 | T14: ='2.1meta'!U14+'2.1meta'!U31+'2.1meta'!U48+'2.1meta'!U66+'2.1meta'!U83+'2.1meta'!U100+'2.1meta'!U117+'2.1meta'!U134+'2.1meta'!U151+'2.1meta'!U168+'2.1meta'!U185+'2.1meta'!U295+'2.1meta'!U312+'2.1meta'!U329 -> 0 | U14: ='2.1meta'!V14+'2.1meta'!V31+'2.1meta'!V48+'2.1meta'!V66+'2.1meta'!V83+'2.1meta'!V100+'2.1meta'!V117+'2.1meta'!V134+'2.1meta'!V151+'2.1meta'!V168+'2.1meta'!V185+'2.1meta'!V295+'2.1meta'!V312+'2.1meta'!V329 -> 0 | V14: ='2.1meta'!W14+'2.1meta'!W31+'2.1meta'!W48+'2.1meta'!W66+'2.1meta'!W83+'2.1meta'!W100+'2.1meta'!W117+'2.1meta'!W134+'2.1meta'!W151+'2.1meta'!W168+'2.1meta'!W185+'2.1meta'!W295+'2.1meta'!W312+'2.1meta'!W329 -> 0 | W14: ='2.1meta'!X14+'2.1meta'!X31+'2.1meta'!X48+'2.1meta'!X66+'2.1meta'!X83+'2.1meta'!X100+'2.1meta'!X117+'2.1meta'!X134+'2.1meta'!X151+'2.1meta'!X168+'2.1meta'!X185+'2.1meta'!X295+'2.1meta'!X312+'2.1meta'!X329 -> 0 | X14: =SUM(Q14:W14) -> 0 | Y14: =O14+X14 -> 0 | Z14: =C14-Y14 -> 0
A15: 2.1.1.9.1.2 | B15: AGUINALDOS | C15: ='2.1meta'!D15+'2.1meta'!D32+'2.1meta'!D49+'2.1meta'!D67+'2.1meta'!D84+'2.1meta'!D101+'2.1meta'!D118+'2.1meta'!D135+'2.1meta'!D152+'2.1meta'!D169+'2.1meta'!D186+'2.1meta'!D296+'2.1meta'!D313+'2.1meta'!D330 -> 0 | D15: ='2.1meta'!E15+'2.1meta'!E32+'2.1meta'!E49+'2.1meta'!E66+'2.1meta'!E84+'2.1meta'!E101+'2.1meta'!E118+'2.1meta'!E135+'2.1meta'!E152+'2.1meta'!E169+'2.1meta'!E186+'2.1meta'!E296+'2.1meta'!E313+'2.1meta'!E330 -> 0 | E15: ='2.1meta'!F15+'2.1meta'!F32+'2.1meta'!F49+'2.1meta'!F66+'2.1meta'!F84+'2.1meta'!F101+'2.1meta'!F118+'2.1meta'!F135+'2.1meta'!F152+'2.1meta'!F169+'2.1meta'!F186+'2.1meta'!F296+'2.1meta'!F313+'2.1meta'!F330 -> 0 | F15: ='2.1meta'!G15+'2.1meta'!G32+'2.1meta'!G49+'2.1meta'!G67+'2.1meta'!G84+'2.1meta'!G101+'2.1meta'!G118+'2.1meta'!G135+'2.1meta'!G152+'2.1meta'!G169+'2.1meta'!G186+'2.1meta'!G296+'2.1meta'!G313+'2.1meta'!G330 -> 0 | G15: ='2.1meta'!H15+'2.1meta'!H32+'2.1meta'!H49+'2.1meta'!H67+'2.1meta'!H84+'2.1meta'!H101+'2.1meta'!H118+'2.1meta'!H135+'2.1meta'!H152+'2.1meta'!H169+'2.1meta'!H186+'2.1meta'!H296+'2.1meta'!H313+'2.1meta'!H330 -> 0 | H15: ='2.1meta'!I15+'2.1meta'!I32+'2.1meta'!I49+'2.1meta'!I67+'2.1meta'!I84+'2.1meta'!I101+'2.1meta'!I118+'2.1meta'!I135+'2.1meta'!I152+'2.1meta'!I169+'2.1meta'!I186+'2.1meta'!I296+'2.1meta'!I313+'2.1meta'!I330 -> 0 | I15: ='2.1meta'!J15+'2.1meta'!J32+'2.1meta'!J49+'2.1meta'!J67+'2.1meta'!J84+'2.1meta'!J101+'2.1meta'!J118+'2.1meta'!J135+'2.1meta'!J152+'2.1meta'!J169+'2.1meta'!J186+'2.1meta'!J296+'2.1meta'!J313+'2.1meta'!J330 -> 0 | J15: ='2.1meta'!K15+'2.1meta'!K32+'2.1meta'!K49+'2.1meta'!K67+'2.1meta'!K84+'2.1meta'!K101+'2.1meta'!K118+'2.1meta'!K135+'2.1meta'!K152+'2.1meta'!K169+'2.1meta'!K186+'2.1meta'!K296+'2.1meta'!K313+'2.1meta'!K330 -> 0 | K15: ='2.1meta'!L15+'2.1meta'!L32+'2.1meta'!L49+'2.1meta'!L67+'2.1meta'!L84+'2.1meta'!L101+'2.1meta'!L118+'2.1meta'!L135+'2.1meta'!L152+'2.1meta'!L169+'2.1meta'!L186+'2.1meta'!L296+'2.1meta'!L313+'2.1meta'!L330 -> 0 | L15: ='2.1meta'!M15+'2.1meta'!M32+'2.1meta'!M49+'2.1meta'!M67+'2.1meta'!M84+'2.1meta'!M101+'2.1meta'!M118+'2.1meta'!M135+'2.1meta'!M152+'2.1meta'!M169+'2.1meta'!M186+'2.1meta'!M296+'2.1meta'!M313+'2.1meta'!M330 -> 0 | M15: ='2.1meta'!N15+'2.1meta'!N32+'2.1meta'!N49+'2.1meta'!N67+'2.1meta'!N84+'2.1meta'!N101+'2.1meta'!N118+'2.1meta'!N135+'2.1meta'!N152+'2.1meta'!N169+'2.1meta'!N186+'2.1meta'!N296+'2.1meta'!N313+'2.1meta'!N330 -> 0 | N15: ='2.1meta'!O15+'2.1meta'!O32+'2.1meta'!O49+'2.1meta'!O67+'2.1meta'!O84+'2.1meta'!O101+'2.1meta'!O118+'2.1meta'!O135+'2.1meta'!O152+'2.1meta'!O169+'2.1meta'!O186+'2.1meta'!O296+'2.1meta'!O313+'2.1meta'!O330 -> 0 | O15: =SUM(F15:N15) -> 0 | P15: =C15-O15 -> 0 | Q15: ='2.1meta'!R15+'2.1meta'!R32+'2.1meta'!R49+'2.1meta'!R67+'2.1meta'!R84+'2.1meta'!R101+'2.1meta'!R118+'2.1meta'!R135+'2.1meta'!R152+'2.1meta'!R169+'2.1meta'!R186+'2.1meta'!R296+'2.1meta'!R313+'2.1meta'!R330 -> 0 | R15: ='2.1meta'!S15+'2.1meta'!S32+'2.1meta'!S49+'2.1meta'!S67+'2.1meta'!S84+'2.1meta'!S101+'2.1meta'!S118+'2.1meta'!S135+'2.1meta'!S152+'2.1meta'!S169+'2.1meta'!S186+'2.1meta'!S296+'2.1meta'!S313+'2.1meta'!S330 -> 0 | S15: ='2.1meta'!T15+'2.1meta'!T32+'2.1meta'!T49+'2.1meta'!T67+'2.1meta'!T84+'2.1meta'!T101+'2.1meta'!T118+'2.1meta'!T135+'2.1meta'!T152+'2.1meta'!T169+'2.1meta'!T186+'2.1meta'!T296+'2.1meta'!T313+'2.1meta'!T330 -> 0 | T15: ='2.1meta'!U15+'2.1meta'!U32+'2.1meta'!U49+'2.1meta'!U67+'2.1meta'!U84+'2.1meta'!U101+'2.1meta'!U118+'2.1meta'!U135+'2.1meta'!U152+'2.1meta'!U169+'2.1meta'!U186+'2.1meta'!U296+'2.1meta'!U313+'2.1meta'!U330 -> 0 | U15: ='2.1meta'!V15+'2.1meta'!V32+'2.1meta'!V49+'2.1meta'!V67+'2.1meta'!V84+'2.1meta'!V101+'2.1meta'!V118+'2.1meta'!V135+'2.1meta'!V152+'2.1meta'!V169+'2.1meta'!V186+'2.1meta'!V296+'2.1meta'!V313+'2.1meta'!V330 -> 0 | V15: ='2.1meta'!W15+'2.1meta'!W32+'2.1meta'!W49+'2.1meta'!W67+'2.1meta'!W84+'2.1meta'!W101+'2.1meta'!W118+'2.1meta'!W135+'2.1meta'!W152+'2.1meta'!W169+'2.1meta'!W186+'2.1meta'!W296+'2.1meta'!W313+'2.1meta'!W330 -> 0 | W15: ='2.1meta'!X15+'2.1meta'!X32+'2.1meta'!X49+'2.1meta'!X67+'2.1meta'!X84+'2.1meta'!X101+'2.1meta'!X118+'2.1meta'!X135+'2.1meta'!X152+'2.1meta'!X169+'2.1meta'!X186+'2.1meta'!X296+'2.1meta'!X313+'2.1meta'!X330 -> 0 | X15: =SUM(Q15:W15) -> 0 | Y15: =O15+X15 -> 0 | Z15: =C15-Y15 -> 0
A16: 2.1.1.9.1.3 | B16: BONIFICACION POR ESCOLARIDAD | C16: ='2.1meta'!D16+'2.1meta'!D33+'2.1meta'!D50+'2.1meta'!D68+'2.1meta'!D85+'2.1meta'!D102+'2.1meta'!D119+'2.1meta'!D136+'2.1meta'!D153+'2.1meta'!D170+'2.1meta'!D187+'2.1meta'!D297+'2.1meta'!D314+'2.1meta'!D331 -> 0 | D16: ='2.1meta'!E16+'2.1meta'!E33+'2.1meta'!E50+'2.1meta'!E68+'2.1meta'!E85+'2.1meta'!E102+'2.1meta'!E119+'2.1meta'!E136+'2.1meta'!E153+'2.1meta'!E170+'2.1meta'!E187+'2.1meta'!E297+'2.1meta'!E314+'2.1meta'!E331 -> 0 | E16: ='2.1meta'!F16+'2.1meta'!F33+'2.1meta'!F50+'2.1meta'!F68+'2.1meta'!F85+'2.1meta'!F102+'2.1meta'!F119+'2.1meta'!F136+'2.1meta'!F153+'2.1meta'!F170+'2.1meta'!F187+'2.1meta'!F297+'2.1meta'!F314+'2.1meta'!F331 -> 0 | F16: ='2.1meta'!G16+'2.1meta'!G33+'2.1meta'!G50+'2.1meta'!G68+'2.1meta'!G85+'2.1meta'!G102+'2.1meta'!G119+'2.1meta'!G136+'2.1meta'!G153+'2.1meta'!G170+'2.1meta'!G187+'2.1meta'!G297+'2.1meta'!G314+'2.1meta'!G331 -> 0 | G16: ='2.1meta'!H16+'2.1meta'!H33+'2.1meta'!H50+'2.1meta'!H68+'2.1meta'!H85+'2.1meta'!H102+'2.1meta'!H119+'2.1meta'!H136+'2.1meta'!H153+'2.1meta'!H170+'2.1meta'!H187+'2.1meta'!H297+'2.1meta'!H314+'2.1meta'!H331 -> 0 | H16: ='2.1meta'!I16+'2.1meta'!I33+'2.1meta'!I50+'2.1meta'!I68+'2.1meta'!I85+'2.1meta'!I102+'2.1meta'!I119+'2.1meta'!I136+'2.1meta'!I153+'2.1meta'!I170+'2.1meta'!I187+'2.1meta'!I297+'2.1meta'!I314+'2.1meta'!I331 -> 0 | I16: ='2.1meta'!J16+'2.1meta'!J33+'2.1meta'!J50+'2.1meta'!J68+'2.1meta'!J85+'2.1meta'!J102+'2.1meta'!J119+'2.1meta'!J136+'2.1meta'!J153+'2.1meta'!J170+'2.1meta'!J187+'2.1meta'!J297+'2.1meta'!J314+'2.1meta'!J331 -> 0 | J16: ='2.1meta'!K16+'2.1meta'!K33+'2.1meta'!K50+'2.1meta'!K68+'2.1meta'!K85+'2.1meta'!K102+'2.1meta'!K119+'2.1meta'!K136+'2.1meta'!K153+'2.1meta'!K170+'2.1meta'!K187+'2.1meta'!K297+'2.1meta'!K314+'2.1meta'!K331 -> 0 | ... N16: ='2.1meta'!O16+'2.1meta'!O33+'2.1meta'!O50+'2.1meta'!O68+'2.1meta'!O85+'2.1meta'!O102+'2.1meta'!O119+'2.1meta'!O136+'2.1meta'!O153+'2.1meta'!O170+'2.1meta'!O187+'2.1meta'!O297+'2.1meta'!O314+'2.1meta'!O331 -> 0 | O16: =SUM(F16:N16) -> 0 | P16: =C16-O16 -> 0 | Q16: ='2.1meta'!R16+'2.1meta'!R33+'2.1meta'!R50+'2.1meta'!R68+'2.1meta'!R85+'2.1meta'!R102+'2.1meta'!R119+'2.1meta'!R136+'2.1meta'!R153+'2.1meta'!R170+'2.1meta'!R187+'2.1meta'!R297+'2.1meta'!R314+'2.1meta'!R331 -> 0 | R16: ='2.1meta'!S16+'2.1meta'!S33+'2.1meta'!S50+'2.1meta'!S68+'2.1meta'!S85+'2.1meta'!S102+'2.1meta'!S119+'2.1meta'!S136+'2.1meta'!S153+'2.1meta'!S170+'2.1meta'!S187+'2.1meta'!S297+'2.1meta'!S314+'2.1meta'!S331 -> 0 | S16: ='2.1meta'!T16+'2.1meta'!T33+'2.1meta'!T50+'2.1meta'!T68+'2.1meta'!T85+'2.1meta'!T102+'2.1meta'!T119+'2.1meta'!T136+'2.1meta'!T153+'2.1meta'!T170+'2.1meta'!T187+'2.1meta'!T297+'2.1meta'!T314+'2.1meta'!T331 -> 0 | T16: ='2.1meta'!U16+'2.1meta'!U33+'2.1meta'!U50+'2.1meta'!U68+'2.1meta'!U85+'2.1meta'!U102+'2.1meta'!U119+'2.1meta'!U136+'2.1meta'!U153+'2.1meta'!U170+'2.1meta'!U187+'2.1meta'!U297+'2.1meta'!U314+'2.1meta'!U331 -> 0 | U16: ='2.1meta'!V16+'2.1meta'!V33+'2.1meta'!V50+'2.1meta'!V68+'2.1meta'!V85+'2.1meta'!V102+'2.1meta'!V119+'2.1meta'!V136+'2.1meta'!V153+'2.1meta'!V170+'2.1meta'!V187+'2.1meta'!V297+'2.1meta'!V314+'2.1meta'!V331 -> 0 | V16: ='2.1meta'!W16+'2.1meta'!W33+'2.1meta'!W50+'2.1meta'!W68+'2.1meta'!W85+'2.1meta'!W102+'2.1meta'!W119+'2.1meta'!W136+'2.1meta'!W153+'2.1meta'!W170+'2.1meta'!W187+'2.1meta'!W297+'2.1meta'!W314+'2.1meta'!W331 -> 0 | W16: ='2.1meta'!X16+'2.1meta'!X33+'2.1meta'!X50+'2.1meta'!X68+'2.1meta'!X85+'2.1meta'!X102+'2.1meta'!X119+'2.1meta'!X136+'2.1meta'!X153+'2.1meta'!X170+'2.1meta'!X187+'2.1meta'!X297+'2.1meta'!X314+'2.1meta'!X331 -> 0 | X16: =SUM(Q16:W16) -> 0 | Y16: =O16+X16 -> 0 | Z16: =C16-Y16 -> 0
A17: 2.1.1.9.2.1 | B17: COMPENSACION POR TIEMPO DE SERVICIOS (CTS) | C17: ='2.1meta'!D17+'2.1meta'!D34+'2.1meta'!D51+'2.1meta'!D69+'2.1meta'!D86+'2.1meta'!D103+'2.1meta'!D120+'2.1meta'!D137+'2.1meta'!D154+'2.1meta'!D171+'2.1meta'!D188+'2.1meta'!D298+'2.1meta'!D315+'2.1meta'!D332 -> 0 | D17: ='2.1meta'!E17+'2.1meta'!E34+'2.1meta'!E51+'2.1meta'!E69+'2.1meta'!E86+'2.1meta'!E103+'2.1meta'!E120+'2.1meta'!E137+'2.1meta'!E154+'2.1meta'!E171+'2.1meta'!E188+'2.1meta'!E298+'2.1meta'!E315+'2.1meta'!E332 -> 0 | E17: ='2.1meta'!F17+'2.1meta'!F34+'2.1meta'!F51+'2.1meta'!F69+'2.1meta'!F86+'2.1meta'!F103+'2.1meta'!F120+'2.1meta'!F137+'2.1meta'!F154+'2.1meta'!F171+'2.1meta'!F188+'2.1meta'!F298+'2.1meta'!F315+'2.1meta'!F332 -> 0 | F17: ='2.1meta'!G17+'2.1meta'!G34+'2.1meta'!G51+'2.1meta'!G69+'2.1meta'!G86+'2.1meta'!G103+'2.1meta'!G120+'2.1meta'!G137+'2.1meta'!G154+'2.1meta'!G171+'2.1meta'!G188+'2.1meta'!G298+'2.1meta'!G315+'2.1meta'!G332 -> 0 | G17: ='2.1meta'!H17+'2.1meta'!H34+'2.1meta'!H51+'2.1meta'!H69+'2.1meta'!H86+'2.1meta'!H103+'2.1meta'!H120+'2.1meta'!H137+'2.1meta'!H154+'2.1meta'!H171+'2.1meta'!H188+'2.1meta'!H298+'2.1meta'!H315+'2.1meta'!H332 -> 0 | H17: ='2.1meta'!I17+'2.1meta'!I34+'2.1meta'!I51+'2.1meta'!I69+'2.1meta'!I86+'2.1meta'!I103+'2.1meta'!I120+'2.1meta'!I137+'2.1meta'!I154+'2.1meta'!I171+'2.1meta'!I188+'2.1meta'!I298+'2.1meta'!I315+'2.1meta'!I332 -> 0 | I17: ='2.1meta'!J17+'2.1meta'!J34+'2.1meta'!J51+'2.1meta'!J69+'2.1meta'!J86+'2.1meta'!J103+'2.1meta'!J120+'2.1meta'!J137+'2.1meta'!J154+'2.1meta'!J171+'2.1meta'!J188+'2.1meta'!J298+'2.1meta'!J315+'2.1meta'!J332 -> 0 | J17: ='2.1meta'!K17+'2.1meta'!K34+'2.1meta'!K51+'2.1meta'!K69+'2.1meta'!K86+'2.1meta'!K103+'2.1meta'!K120+'2.1meta'!K137+'2.1meta'!K154+'2.1meta'!K171+'2.1meta'!K188+'2.1meta'!K298+'2.1meta'!K315+'2.1meta'!K332 -> 0 | ... N17: ='2.1meta'!O17+'2.1meta'!O34+'2.1meta'!O51+'2.1meta'!O69+'2.1meta'!O86+'2.1meta'!O103+'2.1meta'!O120+'2.1meta'!O137+'2.1meta'!O154+'2.1meta'!O171+'2.1meta'!O188+'2.1meta'!O298+'2.1meta'!O315+'2.1meta'!O332 -> 0 | O17: =SUM(F17:N17) -> 0 | P17: =C17-O17 -> 0 | Q17: ='2.1meta'!R17+'2.1meta'!R34+'2.1meta'!R51+'2.1meta'!R69+'2.1meta'!R86+'2.1meta'!R103+'2.1meta'!R120+'2.1meta'!R137+'2.1meta'!R154+'2.1meta'!R171+'2.1meta'!R188+'2.1meta'!R298+'2.1meta'!R315+'2.1meta'!R332 -> 0 | R17: ='2.1meta'!S17+'2.1meta'!S34+'2.1meta'!S51+'2.1meta'!S69+'2.1meta'!S86+'2.1meta'!S103+'2.1meta'!S120+'2.1meta'!S137+'2.1meta'!S154+'2.1meta'!S171+'2.1meta'!S188+'2.1meta'!S298+'2.1meta'!S315+'2.1meta'!S332 -> 0 | S17: ='2.1meta'!T17+'2.1meta'!T34+'2.1meta'!T51+'2.1meta'!T69+'2.1meta'!T86+'2.1meta'!T103+'2.1meta'!T120+'2.1meta'!T137+'2.1meta'!T154+'2.1meta'!T171+'2.1meta'!T188+'2.1meta'!T298+'2.1meta'!T315+'2.1meta'!T332 -> 0 | T17: ='2.1meta'!U17+'2.1meta'!U34+'2.1meta'!U51+'2.1meta'!U69+'2.1meta'!U86+'2.1meta'!U103+'2.1meta'!U120+'2.1meta'!U137+'2.1meta'!U154+'2.1meta'!U171+'2.1meta'!U188+'2.1meta'!U298+'2.1meta'!U315+'2.1meta'!U332 -> 0 | U17: ='2.1meta'!V17+'2.1meta'!V34+'2.1meta'!V51+'2.1meta'!V69+'2.1meta'!V86+'2.1meta'!V103+'2.1meta'!V120+'2.1meta'!V137+'2.1meta'!V154+'2.1meta'!V171+'2.1meta'!V188+'2.1meta'!V298+'2.1meta'!V315+'2.1meta'!V332 -> 0 | V17: ='2.1meta'!W17+'2.1meta'!W34+'2.1meta'!W51+'2.1meta'!W69+'2.1meta'!W86+'2.1meta'!W103+'2.1meta'!W120+'2.1meta'!W137+'2.1meta'!W154+'2.1meta'!W171+'2.1meta'!W188+'2.1meta'!W298+'2.1meta'!W315+'2.1meta'!W332 -> 0 | W17: ='2.1meta'!X17+'2.1meta'!X34+'2.1meta'!X51+'2.1meta'!X69+'2.1meta'!X86+'2.1meta'!X103+'2.1meta'!X120+'2.1meta'!X137+'2.1meta'!X154+'2.1meta'!X171+'2.1meta'!X188+'2.1meta'!X298+'2.1meta'!X315+'2.1meta'!X332 -> 0 | X17: =SUM(Q17:W17) -> 0 | Y17: =O17+X17 -> 0 | Z17: =C17-Y17 -> 0
A18: 2.1.1.9.3.3 | B18: COMPENSACION VACACIONAL (VACACIONES TRUNCAS) | C18: ='2.1meta'!D18+'2.1meta'!D35+'2.1meta'!D52+'2.1meta'!D70+'2.1meta'!D87+'2.1meta'!D104+'2.1meta'!D121+'2.1meta'!D138+'2.1meta'!D155+'2.1meta'!D172+'2.1meta'!D189+'2.1meta'!D299+'2.1meta'!D316+'2.1meta'!D333 -> 0 | D18: ='2.1meta'!E18+'2.1meta'!E35+'2.1meta'!E52+'2.1meta'!E70+'2.1meta'!E87+'2.1meta'!E104+'2.1meta'!E121+'2.1meta'!E138+'2.1meta'!E155+'2.1meta'!E172+'2.1meta'!E189+'2.1meta'!E299+'2.1meta'!E316+'2.1meta'!E333 -> 0 | E18: ='2.1meta'!F18+'2.1meta'!F35+'2.1meta'!F52+'2.1meta'!F70+'2.1meta'!F87+'2.1meta'!F104+'2.1meta'!F121+'2.1meta'!F138+'2.1meta'!F155+'2.1meta'!F172+'2.1meta'!F189+'2.1meta'!F299+'2.1meta'!F316+'2.1meta'!F333 -> 0 | F18: ='2.1meta'!G18+'2.1meta'!G35+'2.1meta'!G52+'2.1meta'!G70+'2.1meta'!G87+'2.1meta'!G104+'2.1meta'!G121+'2.1meta'!G138+'2.1meta'!G155+'2.1meta'!G172+'2.1meta'!G189+'2.1meta'!G299+'2.1meta'!G316+'2.1meta'!G333 -> 0 | G18: ='2.1meta'!H18+'2.1meta'!H35+'2.1meta'!H52+'2.1meta'!H70+'2.1meta'!H87+'2.1meta'!H104+'2.1meta'!H121+'2.1meta'!H138+'2.1meta'!H155+'2.1meta'!H172+'2.1meta'!H189+'2.1meta'!H299+'2.1meta'!H316+'2.1meta'!H333 -> 0 | H18: ='2.1meta'!I18+'2.1meta'!I35+'2.1meta'!I52+'2.1meta'!I70+'2.1meta'!I87+'2.1meta'!I104+'2.1meta'!I121+'2.1meta'!I138+'2.1meta'!I155+'2.1meta'!I172+'2.1meta'!I189+'2.1meta'!I299+'2.1meta'!I316+'2.1meta'!I333 -> 0 | I18: ='2.1meta'!J18+'2.1meta'!J35+'2.1meta'!J52+'2.1meta'!J70+'2.1meta'!J87+'2.1meta'!J104+'2.1meta'!J121+'2.1meta'!J138+'2.1meta'!J155+'2.1meta'!J172+'2.1meta'!J189+'2.1meta'!J299+'2.1meta'!J316+'2.1meta'!J333 -> 0 | J18: ='2.1meta'!K18+'2.1meta'!K35+'2.1meta'!K52+'2.1meta'!K70+'2.1meta'!K87+'2.1meta'!K104+'2.1meta'!K121+'2.1meta'!K138+'2.1meta'!K155+'2.1meta'!K172+'2.1meta'!K189+'2.1meta'!K299+'2.1meta'!K316+'2.1meta'!K333 -> 0 | ... N18: ='2.1meta'!O18+'2.1meta'!O35+'2.1meta'!O52+'2.1meta'!O70+'2.1meta'!O87+'2.1meta'!O104+'2.1meta'!O121+'2.1meta'!O138+'2.1meta'!O155+'2.1meta'!O172+'2.1meta'!O189+'2.1meta'!O299+'2.1meta'!O316+'2.1meta'!O333 -> 0 | O18: =SUM(F18:N18) -> 0 | P18: =C18-O18 -> 0 | Q18: ='2.1meta'!R18+'2.1meta'!R35+'2.1meta'!R52+'2.1meta'!R70+'2.1meta'!R87+'2.1meta'!R104+'2.1meta'!R121+'2.1meta'!R138+'2.1meta'!R155+'2.1meta'!R172+'2.1meta'!R189+'2.1meta'!R299+'2.1meta'!R316+'2.1meta'!R333 -> 0 | R18: ='2.1meta'!S18+'2.1meta'!S35+'2.1meta'!S52+'2.1meta'!S70+'2.1meta'!S87+'2.1meta'!S104+'2.1meta'!S121+'2.1meta'!S138+'2.1meta'!S155+'2.1meta'!S172+'2.1meta'!S189+'2.1meta'!S299+'2.1meta'!S316+'2.1meta'!S333 -> 0 | S18: ='2.1meta'!T18+'2.1meta'!T35+'2.1meta'!T52+'2.1meta'!T70+'2.1meta'!T87+'2.1meta'!T104+'2.1meta'!T121+'2.1meta'!T138+'2.1meta'!T155+'2.1meta'!T172+'2.1meta'!T189+'2.1meta'!T299+'2.1meta'!T316+'2.1meta'!T333 -> 0 | T18: ='2.1meta'!U18+'2.1meta'!U35+'2.1meta'!U52+'2.1meta'!U70+'2.1meta'!U87+'2.1meta'!U104+'2.1meta'!U121+'2.1meta'!U138+'2.1meta'!U155+'2.1meta'!U172+'2.1meta'!U189+'2.1meta'!U299+'2.1meta'!U316+'2.1meta'!U333 -> 0 | U18: ='2.1meta'!V18+'2.1meta'!V35+'2.1meta'!V52+'2.1meta'!V70+'2.1meta'!V87+'2.1meta'!V104+'2.1meta'!V121+'2.1meta'!V138+'2.1meta'!V155+'2.1meta'!V172+'2.1meta'!V189+'2.1meta'!V299+'2.1meta'!V316+'2.1meta'!V333 -> 0 | V18: ='2.1meta'!W18+'2.1meta'!W35+'2.1meta'!W52+'2.1meta'!W70+'2.1meta'!W87+'2.1meta'!W104+'2.1meta'!W121+'2.1meta'!W138+'2.1meta'!W155+'2.1meta'!W172+'2.1meta'!W189+'2.1meta'!W299+'2.1meta'!W316+'2.1meta'!W333 -> 0 | W18: ='2.1meta'!X18+'2.1meta'!X35+'2.1meta'!X52+'2.1meta'!X70+'2.1meta'!X87+'2.1meta'!X104+'2.1meta'!X121+'2.1meta'!X138+'2.1meta'!X155+'2.1meta'!X172+'2.1meta'!X189+'2.1meta'!X299+'2.1meta'!X316+'2.1meta'!X333 -> 0 | X18: =SUM(Q18:W18) -> 0 | Y18: =O18+X18 -> 0 | Z18: =C18-Y18 -> 0
A19: 2.1.1.9.3.99 | B19: OTRAS OCASIONALES | C19: ='2.1meta'!D19+'2.1meta'!D36+'2.1meta'!D53+'2.1meta'!D71+'2.1meta'!D88+'2.1meta'!D105+'2.1meta'!D122+'2.1meta'!D139+'2.1meta'!D156+'2.1meta'!D173+'2.1meta'!D190+'2.1meta'!D300+'2.1meta'!D317+'2.1meta'!D334 -> 0 | D19: ='2.1meta'!E19+'2.1meta'!E36+'2.1meta'!E53+'2.1meta'!E71+'2.1meta'!E88+'2.1meta'!E105+'2.1meta'!E122+'2.1meta'!E139+'2.1meta'!E156+'2.1meta'!E173+'2.1meta'!E190+'2.1meta'!E300+'2.1meta'!E317+'2.1meta'!E334 -> 0 | E19: ='2.1meta'!F19+'2.1meta'!F36+'2.1meta'!F53+'2.1meta'!F71+'2.1meta'!F88+'2.1meta'!F105+'2.1meta'!F122+'2.1meta'!F139+'2.1meta'!F156+'2.1meta'!F173+'2.1meta'!F190+'2.1meta'!F300+'2.1meta'!F317+'2.1meta'!F334 -> 0 | F19: ='2.1meta'!G19+'2.1meta'!G36+'2.1meta'!G53+'2.1meta'!G71+'2.1meta'!G88+'2.1meta'!G105+'2.1meta'!G122+'2.1meta'!G139+'2.1meta'!G156+'2.1meta'!G173+'2.1meta'!G190+'2.1meta'!G300+'2.1meta'!G317+'2.1meta'!G334 -> 0 | G19: ='2.1meta'!H19+'2.1meta'!H36+'2.1meta'!H53+'2.1meta'!H71+'2.1meta'!H88+'2.1meta'!H105+'2.1meta'!H122+'2.1meta'!H139+'2.1meta'!H156+'2.1meta'!H173+'2.1meta'!H190+'2.1meta'!H300+'2.1meta'!H317+'2.1meta'!H334 -> 0 | H19: ='2.1meta'!I19+'2.1meta'!I36+'2.1meta'!I53+'2.1meta'!I71+'2.1meta'!I88+'2.1meta'!I105+'2.1meta'!I122+'2.1meta'!I139+'2.1meta'!I156+'2.1meta'!I173+'2.1meta'!I190+'2.1meta'!I300+'2.1meta'!I317+'2.1meta'!I334 -> 0 | I19: ='2.1meta'!J19+'2.1meta'!J36+'2.1meta'!J53+'2.1meta'!J71+'2.1meta'!J88+'2.1meta'!J105+'2.1meta'!J122+'2.1meta'!J139+'2.1meta'!J156+'2.1meta'!J173+'2.1meta'!J190+'2.1meta'!J300+'2.1meta'!J317+'2.1meta'!J334 -> 0 | J19: ='2.1meta'!K19+'2.1meta'!K36+'2.1meta'!K53+'2.1meta'!K71+'2.1meta'!K88+'2.1meta'!K105+'2.1meta'!K122+'2.1meta'!K139+'2.1meta'!K156+'2.1meta'!K173+'2.1meta'!K190+'2.1meta'!K300+'2.1meta'!K317+'2.1meta'!K334 -> 0 | ... N19: ='2.1meta'!O19+'2.1meta'!O36+'2.1meta'!O53+'2.1meta'!O71+'2.1meta'!O88+'2.1meta'!O105+'2.1meta'!O122+'2.1meta'!O139+'2.1meta'!O156+'2.1meta'!O173+'2.1meta'!O190+'2.1meta'!O300+'2.1meta'!O317+'2.1meta'!O334 -> 0 | O19: =SUM(F19:N19) -> 0 | P19: =C19-O19 -> 0 | Q19: ='2.1meta'!R19+'2.1meta'!R36+'2.1meta'!R53+'2.1meta'!R71+'2.1meta'!R88+'2.1meta'!R105+'2.1meta'!R122+'2.1meta'!R139+'2.1meta'!R156+'2.1meta'!R173+'2.1meta'!R190+'2.1meta'!R300+'2.1meta'!R317+'2.1meta'!R334 -> 0 | R19: ='2.1meta'!S19+'2.1meta'!S36+'2.1meta'!S53+'2.1meta'!S71+'2.1meta'!S88+'2.1meta'!S105+'2.1meta'!S122+'2.1meta'!S139+'2.1meta'!S156+'2.1meta'!S173+'2.1meta'!S190+'2.1meta'!S300+'2.1meta'!S317+'2.1meta'!S334 -> 0 | S19: ='2.1meta'!T19+'2.1meta'!T36+'2.1meta'!T53+'2.1meta'!T71+'2.1meta'!T88+'2.1meta'!T105+'2.1meta'!T122+'2.1meta'!T139+'2.1meta'!T156+'2.1meta'!T173+'2.1meta'!T190+'2.1meta'!T300+'2.1meta'!T317+'2.1meta'!T334 -> 0 | T19: ='2.1meta'!U19+'2.1meta'!U36+'2.1meta'!U53+'2.1meta'!U71+'2.1meta'!U88+'2.1meta'!U105+'2.1meta'!U122+'2.1meta'!U139+'2.1meta'!U156+'2.1meta'!U173+'2.1meta'!U190+'2.1meta'!U300+'2.1meta'!U317+'2.1meta'!U334 -> 0 | U19: ='2.1meta'!V19+'2.1meta'!V36+'2.1meta'!V53+'2.1meta'!V71+'2.1meta'!V88+'2.1meta'!V105+'2.1meta'!V122+'2.1meta'!V139+'2.1meta'!V156+'2.1meta'!V173+'2.1meta'!V190+'2.1meta'!V300+'2.1meta'!V317+'2.1meta'!V334 -> 0 | V19: ='2.1meta'!W19+'2.1meta'!W36+'2.1meta'!W53+'2.1meta'!W71+'2.1meta'!W88+'2.1meta'!W105+'2.1meta'!W122+'2.1meta'!W139+'2.1meta'!W156+'2.1meta'!W173+'2.1meta'!W190+'2.1meta'!W300+'2.1meta'!W317+'2.1meta'!W334 -> 0 | W19: ='2.1meta'!X19+'2.1meta'!X36+'2.1meta'!X53+'2.1meta'!X71+'2.1meta'!X88+'2.1meta'!X105+'2.1meta'!X122+'2.1meta'!X139+'2.1meta'!X156+'2.1meta'!X173+'2.1meta'!X190+'2.1meta'!X300+'2.1meta'!X317+'2.1meta'!X334 -> 0 | X19: =SUM(Q19:W19) -> 0 | Y19: =O19+X19 -> 0 | Z19: =C19-Y19 -> 0
A20: 2.1.3.1.1.1 | B20: APORTES A LOS FONDOS DE SALUD | C20: ='2.1meta'!D20+'2.1meta'!D37+'2.1meta'!D54+'2.1meta'!D72+'2.1meta'!D89+'2.1meta'!D106+'2.1meta'!D123+'2.1meta'!D140+'2.1meta'!D157+'2.1meta'!D174+'2.1meta'!D191+'2.1meta'!D301+'2.1meta'!D318+'2.1meta'!D335 -> 0 | D20: ='2.1meta'!E20+'2.1meta'!E37+'2.1meta'!E54+'2.1meta'!E72+'2.1meta'!E89+'2.1meta'!E106+'2.1meta'!E123+'2.1meta'!E140+'2.1meta'!E157+'2.1meta'!E174+'2.1meta'!E191+'2.1meta'!E301+'2.1meta'!E318+'2.1meta'!E335 -> 0 | E20: ='2.1meta'!F20+'2.1meta'!F37+'2.1meta'!F54+'2.1meta'!F72+'2.1meta'!F89+'2.1meta'!F106+'2.1meta'!F123+'2.1meta'!F140+'2.1meta'!F157+'2.1meta'!F174+'2.1meta'!F191+'2.1meta'!F301+'2.1meta'!F318+'2.1meta'!F335 -> 0 | F20: ='2.1meta'!G20+'2.1meta'!G37+'2.1meta'!G54+'2.1meta'!G72+'2.1meta'!G89+'2.1meta'!G106+'2.1meta'!G123+'2.1meta'!G140+'2.1meta'!G157+'2.1meta'!G174+'2.1meta'!G191+'2.1meta'!G301+'2.1meta'!G318+'2.1meta'!G335 -> 0 | G20: ='2.1meta'!H20+'2.1meta'!H37+'2.1meta'!H54+'2.1meta'!H72+'2.1meta'!H89+'2.1meta'!H106+'2.1meta'!H123+'2.1meta'!H140+'2.1meta'!H157+'2.1meta'!H174+'2.1meta'!H191+'2.1meta'!H301+'2.1meta'!H318+'2.1meta'!H335 -> 0 | H20: ='2.1meta'!I20+'2.1meta'!I37+'2.1meta'!I54+'2.1meta'!I72+'2.1meta'!I89+'2.1meta'!I106+'2.1meta'!I123+'2.1meta'!I140+'2.1meta'!I157+'2.1meta'!I174+'2.1meta'!I191+'2.1meta'!I301+'2.1meta'!I318+'2.1meta'!I335 -> 0 | I20: ='2.1meta'!J20+'2.1meta'!J37+'2.1meta'!J54+'2.1meta'!J72+'2.1meta'!J89+'2.1meta'!J106+'2.1meta'!J123+'2.1meta'!J140+'2.1meta'!J157+'2.1meta'!J174+'2.1meta'!J191+'2.1meta'!J301+'2.1meta'!J318+'2.1meta'!J335 -> 0 | J20: ='2.1meta'!K20+'2.1meta'!K37+'2.1meta'!K54+'2.1meta'!K72+'2.1meta'!K89+'2.1meta'!K106+'2.1meta'!K123+'2.1meta'!K140+'2.1meta'!K157+'2.1meta'!K174+'2.1meta'!K191+'2.1meta'!K301+'2.1meta'!K318+'2.1meta'!K335 -> 0 | ... N20: ='2.1meta'!O20+'2.1meta'!O37+'2.1meta'!O54+'2.1meta'!O72+'2.1meta'!O89+'2.1meta'!O106+'2.1meta'!O123+'2.1meta'!O140+'2.1meta'!O157+'2.1meta'!O174+'2.1meta'!O191+'2.1meta'!O301+'2.1meta'!O318+'2.1meta'!O335 -> 0 | O20: =SUM(F20:N20) -> 0 | P20: =C20-O20 -> 0 | Q20: ='2.1meta'!R20+'2.1meta'!R37+'2.1meta'!R54+'2.1meta'!R72+'2.1meta'!R89+'2.1meta'!R106+'2.1meta'!R123+'2.1meta'!R140+'2.1meta'!R157+'2.1meta'!R174+'2.1meta'!R191+'2.1meta'!R301+'2.1meta'!R318+'2.1meta'!R335 -> 0 | R20: ='2.1meta'!S20+'2.1meta'!S37+'2.1meta'!S54+'2.1meta'!S72+'2.1meta'!S89+'2.1meta'!S106+'2.1meta'!S123+'2.1meta'!S140+'2.1meta'!S157+'2.1meta'!S174+'2.1meta'!S191+'2.1meta'!S301+'2.1meta'!S318+'2.1meta'!S335 -> 0 | S20: ='2.1meta'!T20+'2.1meta'!T37+'2.1meta'!T54+'2.1meta'!T72+'2.1meta'!T89+'2.1meta'!T106+'2.1meta'!T123+'2.1meta'!T140+'2.1meta'!T157+'2.1meta'!T174+'2.1meta'!T191+'2.1meta'!T301+'2.1meta'!T318+'2.1meta'!T335 -> 0 | T20: ='2.1meta'!U20+'2.1meta'!U37+'2.1meta'!U54+'2.1meta'!U72+'2.1meta'!U89+'2.1meta'!U106+'2.1meta'!U123+'2.1meta'!U140+'2.1meta'!U157+'2.1meta'!U174+'2.1meta'!U191+'2.1meta'!U301+'2.1meta'!U318+'2.1meta'!U335 -> 0 | U20: ='2.1meta'!V20+'2.1meta'!V37+'2.1meta'!V54+'2.1meta'!V72+'2.1meta'!V89+'2.1meta'!V106+'2.1meta'!V123+'2.1meta'!V140+'2.1meta'!V157+'2.1meta'!V174+'2.1meta'!V191+'2.1meta'!V301+'2.1meta'!V318+'2.1meta'!V335 -> 0 | V20: ='2.1meta'!W20+'2.1meta'!W37+'2.1meta'!W54+'2.1meta'!W72+'2.1meta'!W89+'2.1meta'!W106+'2.1meta'!W123+'2.1meta'!W140+'2.1meta'!W157+'2.1meta'!W174+'2.1meta'!W191+'2.1meta'!W301+'2.1meta'!W318+'2.1meta'!W335 -> 0 | W20: ='2.1meta'!X20+'2.1meta'!X37+'2.1meta'!X54+'2.1meta'!X72+'2.1meta'!X89+'2.1meta'!X106+'2.1meta'!X123+'2.1meta'!X140+'2.1meta'!X157+'2.1meta'!X174+'2.1meta'!X191+'2.1meta'!X301+'2.1meta'!X318+'2.1meta'!X335 -> 0 | X20: =SUM(Q20:W20) -> 0 | Y20: =O20+X20 -> 0 | Z20: =C20-Y20 -> 0
A21: 2.1.3.1.1.3 | B21: APORTES A LOS FONDOS DE PENSIONES | C21: ='2.1meta'!D21+'2.1meta'!D38+'2.1meta'!D55+'2.1meta'!D73+'2.1meta'!D90+'2.1meta'!D107+'2.1meta'!D124+'2.1meta'!D141+'2.1meta'!D158+'2.1meta'!D175+'2.1meta'!D192+'2.1meta'!D302+'2.1meta'!D319+'2.1meta'!D336 -> 0 | D21: ='2.1meta'!E21+'2.1meta'!E38+'2.1meta'!E55+'2.1meta'!E73+'2.1meta'!E90+'2.1meta'!E107+'2.1meta'!E124+'2.1meta'!E141+'2.1meta'!E158+'2.1meta'!E175+'2.1meta'!E192+'2.1meta'!E302+'2.1meta'!E319+'2.1meta'!E336 -> 0 | E21: ='2.1meta'!F21+'2.1meta'!F38+'2.1meta'!F55+'2.1meta'!F73+'2.1meta'!F90+'2.1meta'!F107+'2.1meta'!F124+'2.1meta'!F141+'2.1meta'!F158+'2.1meta'!F175+'2.1meta'!F192+'2.1meta'!F302+'2.1meta'!F319+'2.1meta'!F336 -> 0 | F21: ='2.1meta'!G21+'2.1meta'!G38+'2.1meta'!G55+'2.1meta'!G73+'2.1meta'!G90+'2.1meta'!G107+'2.1meta'!G124+'2.1meta'!G141+'2.1meta'!G158+'2.1meta'!G175+'2.1meta'!G192+'2.1meta'!G302+'2.1meta'!G319+'2.1meta'!G336 -> 0 | G21: ='2.1meta'!H21+'2.1meta'!H38+'2.1meta'!H55+'2.1meta'!H73+'2.1meta'!H90+'2.1meta'!H107+'2.1meta'!H124+'2.1meta'!H141+'2.1meta'!H158+'2.1meta'!H175+'2.1meta'!H192+'2.1meta'!H302+'2.1meta'!H319+'2.1meta'!H336 -> 0 | H21: ='2.1meta'!I21+'2.1meta'!I38+'2.1meta'!I55+'2.1meta'!I73+'2.1meta'!I90+'2.1meta'!I107+'2.1meta'!I124+'2.1meta'!I141+'2.1meta'!I158+'2.1meta'!I175+'2.1meta'!I192+'2.1meta'!I302+'2.1meta'!I319+'2.1meta'!I336 -> 0 | I21: ='2.1meta'!J21+'2.1meta'!J38+'2.1meta'!J55+'2.1meta'!J73+'2.1meta'!J90+'2.1meta'!J107+'2.1meta'!J124+'2.1meta'!J141+'2.1meta'!J158+'2.1meta'!J175+'2.1meta'!J192+'2.1meta'!J302+'2.1meta'!J319+'2.1meta'!J336 -> 0 | J21: ='2.1meta'!K21+'2.1meta'!K38+'2.1meta'!K55+'2.1meta'!K73+'2.1meta'!K90+'2.1meta'!K107+'2.1meta'!K124+'2.1meta'!K141+'2.1meta'!K158+'2.1meta'!K175+'2.1meta'!K192+'2.1meta'!K302+'2.1meta'!K319+'2.1meta'!K336 -> 0 | ... N21: ='2.1meta'!O21+'2.1meta'!O38+'2.1meta'!O55+'2.1meta'!O73+'2.1meta'!O90+'2.1meta'!O107+'2.1meta'!O124+'2.1meta'!O141+'2.1meta'!O158+'2.1meta'!O175+'2.1meta'!O192+'2.1meta'!O302+'2.1meta'!O319+'2.1meta'!O336 -> 0 | O21: =SUM(F21:N21) -> 0 | P21: =C21-O21 -> 0 | Q21: ='2.1meta'!R21+'2.1meta'!R38+'2.1meta'!R55+'2.1meta'!R73+'2.1meta'!R90+'2.1meta'!R107+'2.1meta'!R124+'2.1meta'!R141+'2.1meta'!R158+'2.1meta'!R175+'2.1meta'!R192+'2.1meta'!R302+'2.1meta'!R319+'2.1meta'!R336 -> 0 | R21: ='2.1meta'!S21+'2.1meta'!S38+'2.1meta'!S55+'2.1meta'!S73+'2.1meta'!S90+'2.1meta'!S107+'2.1meta'!S124+'2.1meta'!S141+'2.1meta'!S158+'2.1meta'!S175+'2.1meta'!S192+'2.1meta'!S302+'2.1meta'!S319+'2.1meta'!S336 -> 0 | S21: ='2.1meta'!T21+'2.1meta'!T38+'2.1meta'!T55+'2.1meta'!T73+'2.1meta'!T90+'2.1meta'!T107+'2.1meta'!T124+'2.1meta'!T141+'2.1meta'!T158+'2.1meta'!T175+'2.1meta'!T192+'2.1meta'!T302+'2.1meta'!T319+'2.1meta'!T336 -> 0 | T21: ='2.1meta'!U21+'2.1meta'!U38+'2.1meta'!U55+'2.1meta'!U73+'2.1meta'!U90+'2.1meta'!U107+'2.1meta'!U124+'2.1meta'!U141+'2.1meta'!U158+'2.1meta'!U175+'2.1meta'!U192+'2.1meta'!U302+'2.1meta'!U319+'2.1meta'!U336 -> 0 | U21: ='2.1meta'!V21+'2.1meta'!V38+'2.1meta'!V55+'2.1meta'!V73+'2.1meta'!V90+'2.1meta'!V107+'2.1meta'!V124+'2.1meta'!V141+'2.1meta'!V158+'2.1meta'!V175+'2.1meta'!V192+'2.1meta'!V302+'2.1meta'!V319+'2.1meta'!V336 -> 0 | V21: ='2.1meta'!W21+'2.1meta'!W38+'2.1meta'!W55+'2.1meta'!W73+'2.1meta'!W90+'2.1meta'!W107+'2.1meta'!W124+'2.1meta'!W141+'2.1meta'!W158+'2.1meta'!W175+'2.1meta'!W192+'2.1meta'!W302+'2.1meta'!W319+'2.1meta'!W336 -> 0 | W21: ='2.1meta'!X21+'2.1meta'!X38+'2.1meta'!X55+'2.1meta'!X73+'2.1meta'!X90+'2.1meta'!X107+'2.1meta'!X124+'2.1meta'!X141+'2.1meta'!X158+'2.1meta'!X175+'2.1meta'!X192+'2.1meta'!X302+'2.1meta'!X319+'2.1meta'!X336 -> 0 | X21: =SUM(Q21:W21) -> 0 | Y21: =O21+X21 -> 0 | Z21: =C21-Y21 -> 0
A22: 2.1.3.1.1.5 | B22: CONTRIBUCIONES A ESSALUD | C22: ='2.1meta'!D22+'2.1meta'!D39+'2.1meta'!D56+'2.1meta'!D74+'2.1meta'!D91+'2.1meta'!D108+'2.1meta'!D125+'2.1meta'!D142+'2.1meta'!D159+'2.1meta'!D176+'2.1meta'!D193+'2.1meta'!D303+'2.1meta'!D320+'2.1meta'!D337 -> 0 | D22: ='2.1meta'!E22+'2.1meta'!E39+'2.1meta'!E56+'2.1meta'!E74+'2.1meta'!E92+'2.1meta'!E108+'2.1meta'!E125+'2.1meta'!E142+'2.1meta'!E159+'2.1meta'!E176+'2.1meta'!E193+'2.1meta'!E303+'2.1meta'!E320+'2.1meta'!E337 -> 0 | E22: ='2.1meta'!F22+'2.1meta'!F39+'2.1meta'!F56+'2.1meta'!F74+'2.1meta'!F92+'2.1meta'!F108+'2.1meta'!F125+'2.1meta'!F142+'2.1meta'!F159+'2.1meta'!F176+'2.1meta'!F193+'2.1meta'!F303+'2.1meta'!F320+'2.1meta'!F337 -> 0 | F22: ='2.1meta'!G22+'2.1meta'!G39+'2.1meta'!G56+'2.1meta'!G74+'2.1meta'!G91+'2.1meta'!G108+'2.1meta'!G125+'2.1meta'!G142+'2.1meta'!G159+'2.1meta'!G176+'2.1meta'!G193+'2.1meta'!G303+'2.1meta'!G320+'2.1meta'!G337 -> 0 | G22: ='2.1meta'!H22+'2.1meta'!H39+'2.1meta'!H56+'2.1meta'!H74+'2.1meta'!H91+'2.1meta'!H108+'2.1meta'!H125+'2.1meta'!H142+'2.1meta'!H159+'2.1meta'!H176+'2.1meta'!H193+'2.1meta'!H303+'2.1meta'!H320+'2.1meta'!H337 -> 0 | H22: ='2.1meta'!I22+'2.1meta'!I39+'2.1meta'!I56+'2.1meta'!I74+'2.1meta'!I91+'2.1meta'!I108+'2.1meta'!I125+'2.1meta'!I142+'2.1meta'!I159+'2.1meta'!I176+'2.1meta'!I193+'2.1meta'!I303+'2.1meta'!I320+'2.1meta'!I337 -> 0 | I22: ='2.1meta'!J22+'2.1meta'!J39+'2.1meta'!J56+'2.1meta'!J74+'2.1meta'!J91+'2.1meta'!J108+'2.1meta'!J125+'2.1meta'!J142+'2.1meta'!J159+'2.1meta'!J176+'2.1meta'!J193+'2.1meta'!J303+'2.1meta'!J320+'2.1meta'!J337 -> 0 | J22: ='2.1meta'!K22+'2.1meta'!K39+'2.1meta'!K56+'2.1meta'!K74+'2.1meta'!K91+'2.1meta'!K108+'2.1meta'!K125+'2.1meta'!K142+'2.1meta'!K159+'2.1meta'!K176+'2.1meta'!K193+'2.1meta'!K303+'2.1meta'!K320+'2.1meta'!K337 -> 0 | K22: ='2.1meta'!L22+'2.1meta'!L39+'2.1meta'!L56+'2.1meta'!L74+'2.1meta'!L91+'2.1meta'!L108+'2.1meta'!L125+'2.1meta'!L142+'2.1meta'!L159+'2.1meta'!L176+'2.1meta'!L193+'2.1meta'!L303+'2.1meta'!L320+'2.1meta'!L337 -> 0 | L22: ='2.1meta'!M22+'2.1meta'!M39+'2.1meta'!M56+'2.1meta'!M74+'2.1meta'!M91+'2.1meta'!M108+'2.1meta'!M125+'2.1meta'!M142+'2.1meta'!M159+'2.1meta'!M176+'2.1meta'!M193+'2.1meta'!M303+'2.1meta'!M320+'2.1meta'!M337 -> 0 | M22: ='2.1meta'!N22+'2.1meta'!N39+'2.1meta'!N56+'2.1meta'!N74+'2.1meta'!N91+'2.1meta'!N108+'2.1meta'!N125+'2.1meta'!N142+'2.1meta'!N159+'2.1meta'!N176+'2.1meta'!N193+'2.1meta'!N303+'2.1meta'!N320+'2.1meta'!N337 -> 0 | N22: ='2.1meta'!O22+'2.1meta'!O39+'2.1meta'!O56+'2.1meta'!O74+'2.1meta'!O91+'2.1meta'!O108+'2.1meta'!O125+'2.1meta'!O142+'2.1meta'!O159+'2.1meta'!O176+'2.1meta'!O193+'2.1meta'!O303+'2.1meta'!O320+'2.1meta'!O337 -> 0 | O22: =SUM(F22:N22) -> 0 | P22: =C22-O22 -> 0 | Q22: ='2.1meta'!R22+'2.1meta'!R39+'2.1meta'!R56+'2.1meta'!R74+'2.1meta'!R91+'2.1meta'!R108+'2.1meta'!R125+'2.1meta'!R142+'2.1meta'!R159+'2.1meta'!R176+'2.1meta'!R193+'2.1meta'!R303+'2.1meta'!R320+'2.1meta'!R337 -> 0 | R22: ='2.1meta'!S22+'2.1meta'!S39+'2.1meta'!S56+'2.1meta'!S74+'2.1meta'!S91+'2.1meta'!S108+'2.1meta'!S125+'2.1meta'!S142+'2.1meta'!S159+'2.1meta'!S176+'2.1meta'!S193+'2.1meta'!S303+'2.1meta'!S320+'2.1meta'!S337 -> 0 | S22: ='2.1meta'!T22+'2.1meta'!T39+'2.1meta'!T56+'2.1meta'!T74+'2.1meta'!T91+'2.1meta'!T108+'2.1meta'!T125+'2.1meta'!T142+'2.1meta'!T159+'2.1meta'!T176+'2.1meta'!T193+'2.1meta'!T303+'2.1meta'!T320+'2.1meta'!T337 -> 0 | T22: ='2.1meta'!U22+'2.1meta'!U39+'2.1meta'!U56+'2.1meta'!U74+'2.1meta'!U91+'2.1meta'!U108+'2.1meta'!U125+'2.1meta'!U142+'2.1meta'!U159+'2.1meta'!U176+'2.1meta'!U193+'2.1meta'!U303+'2.1meta'!U320+'2.1meta'!U337 -> 0 | U22: ='2.1meta'!V22+'2.1meta'!V39+'2.1meta'!V56+'2.1meta'!V74+'2.1meta'!V91+'2.1meta'!V108+'2.1meta'!V125+'2.1meta'!V142+'2.1meta'!V159+'2.1meta'!V176+'2.1meta'!V193+'2.1meta'!V303+'2.1meta'!V320+'2.1meta'!V337 -> 0 | V22: ='2.1meta'!W22+'2.1meta'!W39+'2.1meta'!W56+'2.1meta'!W74+'2.1meta'!W91+'2.1meta'!W108+'2.1meta'!W125+'2.1meta'!W142+'2.1meta'!W159+'2.1meta'!W176+'2.1meta'!W193+'2.1meta'!W303+'2.1meta'!W320+'2.1meta'!W337 -> 0 | W22: ='2.1meta'!X22+'2.1meta'!X39+'2.1meta'!X56+'2.1meta'!X74+'2.1meta'!X91+'2.1meta'!X108+'2.1meta'!X125+'2.1meta'!X142+'2.1meta'!X159+'2.1meta'!X176+'2.1meta'!X193+'2.1meta'!X303+'2.1meta'!X320+'2.1meta'!X337 -> 0 | X22: =SUM(Q22:W22) -> 0 | Y22: =O22+X22 -> 0 | Z22: =C22-Y22 -> 0
A23: 1002 PRODUCTOS ESPECIFICOS PARA REDUCCION DE LA VIOLENCIA CONTRA LA MUJER | C23: =SUBTOTAL(9,C24:C37) -> 0 | F23: =SUBTOTAL(9,F24:F37) -> 0 | G23: =SUBTOTAL(9,G24:G37) -> 0 | H23: =SUBTOTAL(9,H24:H37) -> 0 | I23: =SUBTOTAL(9,I24:I37) -> 0 | J23: =SUBTOTAL(9,J24:J37) -> 0 | K23: =SUBTOTAL(9,K24:K37) -> 0 | L23: =SUBTOTAL(9,L24:L37) -> 0 | M23: =SUBTOTAL(9,M24:M37) -> 0 | ... O23: =SUBTOTAL(9,O24:O37) -> 0 | P23: =C23-O23 -> 0 | Q23: =SUBTOTAL(9,Q24:Q37) -> 0 | R23: =SUBTOTAL(9,R24:R37) -> 0 | S23: =SUBTOTAL(9,S24:S37) -> 0 | T23: =SUBTOTAL(9,T24:T37) -> 0 | U23: =SUBTOTAL(9,U24:U37) -> 0 | V23: =SUBTOTAL(9,V24:V37) -> 0 | W23: =SUBTOTAL(9,W24:W37) -> 0 | X23: =SUBTOTAL(9,X24:X37) -> 0 | ... Z23: =SUBTOTAL(9,Z24:Z37) -> 0
A24: 2.1.1.1.1.2 | B24: PERSONAL ADMINISTRATIVO NOMBRADO (REGIMEN PUBLICO) | C24: ='2.1meta'!D271 -> 0 | D24: ='2.1meta'!E254 -> 0 | E24: ='2.1meta'!F254 -> 0 | F24: ='2.1meta'!G271 -> 0 | G24: ='2.1meta'!H271 -> 0 | H24: ='2.1meta'!I271 -> 0 | I24: ='2.1meta'!J271 -> 0 | J24: ='2.1meta'!K271 -> 0 | K24: ='2.1meta'!L271 -> 0 | L24: ='2.1meta'!M271 -> 0 | M24: ='2.1meta'!N271 -> 0 | N24: ='2.1meta'!O271 -> 0 | O24: =SUM(F24:N24) -> 0 | P24: =C24-O24 -> 0 | Q24: ='2.1meta'!R271 -> 0 | R24: ='2.1meta'!S271 -> 0 | S24: ='2.1meta'!T271 -> 0 | T24: ='2.1meta'!U271 -> 0 | U24: ='2.1meta'!V271 -> 0 | V24: ='2.1meta'!W271 -> 0 | W24: ='2.1meta'!X271 -> 0 | X24: =SUM(Q24:W24) -> 0 | Y24: =O24+X24 -> 0 | Z24: =C24-Y24 -> 0
A25: 2.1.1.1.1.4 | B25: PERSONAL CON CONTRATO A PLAZO INDETERMINADO (REGIMEN LABORAL PRIVADO) | C25: ='2.1meta'!D272 -> 0 | D25: ='2.1meta'!E255 -> 0 | E25: ='2.1meta'!F255 -> 0 | F25: ='2.1meta'!G272 -> 0 | G25: ='2.1meta'!H272 -> 0 | H25: ='2.1meta'!I272 -> 0 | I25: ='2.1meta'!J272 -> 0 | J25: ='2.1meta'!K272 -> 0 | K25: ='2.1meta'!L272 -> 0 | L25: ='2.1meta'!M272 -> 0 | M25: ='2.1meta'!N272 -> 0 | N25: ='2.1meta'!O272 -> 0 | O25: =SUM(F25:N25) -> 0 | P25: =C25-O25 -> 0 | Q25: ='2.1meta'!R272 -> 0 | R25: ='2.1meta'!S272 -> 0 | S25: ='2.1meta'!T272 -> 0 | T25: ='2.1meta'!U272 -> 0 | U25: ='2.1meta'!V272 -> 0 | V25: ='2.1meta'!W272 -> 0 | W25: ='2.1meta'!X272 -> 0 | X25: =SUM(Q25:W25) -> 0 | Y25: =O25+X25 -> 0 | Z25: =C25-Y25 -> 0
A26: 2.1.1.1.1.5 | B26: PERSONAL CON CONTRATO A PLAZO FIJO (REGIMEN LABORAL PRIVADO) | C26: ='2.1meta'!D273 -> 0 | D26: ='2.1meta'!E256 -> 0 | E26: ='2.1meta'!F256 -> 0 | F26: ='2.1meta'!G273 -> 0 | G26: ='2.1meta'!H273 -> 0 | H26: ='2.1meta'!I273 -> 0 | I26: ='2.1meta'!J273 -> 0 | J26: ='2.1meta'!K273 -> 0 | K26: ='2.1meta'!L273 -> 0 | L26: ='2.1meta'!M273 -> 0 | M26: ='2.1meta'!N273 -> 0 | N26: ='2.1meta'!O273 -> 0 | O26: =SUM(F26:N26) -> 0 | P26: =C26-O26 -> 0 | Q26: ='2.1meta'!R273 -> 0 | R26: ='2.1meta'!S273 -> 0 | S26: ='2.1meta'!T273 -> 0 | T26: ='2.1meta'!U273 -> 0 | U26: ='2.1meta'!V273 -> 0 | V26: ='2.1meta'!W273 -> 0 | W26: ='2.1meta'!X273 -> 0 | X26: =SUM(Q26:W26) -> 0 | Y26: =O26+X26 -> 0 | Z26: =C26-Y26 -> 0
A27: 2.1.1.1.2.1 | B27: ASIGNACION A FONDOS PARA PERSONAL | C27: ='2.1meta'!D274 -> 0 | D27: ='2.1meta'!E257 -> 0 | E27: ='2.1meta'!F257 -> 0 | F27: ='2.1meta'!G274 -> 0 | G27: ='2.1meta'!H274 -> 0 | H27: ='2.1meta'!I274 -> 0 | I27: ='2.1meta'!J274 -> 0 | J27: ='2.1meta'!K274 -> 0 | K27: ='2.1meta'!L274 -> 0 | L27: ='2.1meta'!M274 -> 0 | M27: ='2.1meta'!N274 -> 0 | N27: ='2.1meta'!O274 -> 0 | O27: =SUM(F27:N27) -> 0 | P27: =C27-O27 -> 0 | Q27: ='2.1meta'!R274 -> 0 | R27: ='2.1meta'!S274 -> 0 | S27: ='2.1meta'!T274 -> 0 | T27: ='2.1meta'!U274 -> 0 | U27: ='2.1meta'!V274 -> 0 | V27: ='2.1meta'!W274 -> 0 | W27: ='2.1meta'!X274 -> 0 | X27: =SUM(Q27:W27) -> 0 | Y27: =O27+X27 -> 0 | Z27: =C27-Y27 -> 0
A28: 2.1.1.4.1.1 | B28: PERSONAL NOMBRADO | C28: ='2.1meta'!D275 -> 0 | D28: ='2.1meta'!E258 -> 0 | E28: ='2.1meta'!F258 -> 0 | F28: ='2.1meta'!G275 -> 0 | G28: ='2.1meta'!H275 -> 0 | H28: ='2.1meta'!I275 -> 0 | I28: ='2.1meta'!J275 -> 0 | J28: ='2.1meta'!K275 -> 0 | K28: ='2.1meta'!L275 -> 0 | L28: ='2.1meta'!M275 -> 0 | M28: ='2.1meta'!N275 -> 0 | N28: ='2.1meta'!O275 -> 0 | O28: =SUM(F28:N28) -> 0 | P28: =C28-O28 -> 0 | Q28: ='2.1meta'!R275 -> 0 | R28: ='2.1meta'!S275 -> 0 | S28: ='2.1meta'!T275 -> 0 | T28: ='2.1meta'!U275 -> 0 | U28: ='2.1meta'!V275 -> 0 | V28: ='2.1meta'!W275 -> 0 | W28: ='2.1meta'!X275 -> 0 | X28: =SUM(Q28:W28) -> 0 | Y28: =O28+X28 -> 0 | Z28: =C28-Y28 -> 0
A29: 2.1.1.4.2.1 | B29: BONO POR FUNCION JURISDICCIONAL Y FISCAL | C29: ='2.1meta'!D276 -> 0 | D29: ='2.1meta'!E259 -> 0 | E29: ='2.1meta'!F259 -> 0 | F29: ='2.1meta'!G276 -> 0 | G29: ='2.1meta'!H276 -> 0 | H29: ='2.1meta'!I276 -> 0 | I29: ='2.1meta'!J276 -> 0 | J29: ='2.1meta'!K276 -> 0 | K29: ='2.1meta'!L276 -> 0 | L29: ='2.1meta'!M276 -> 0 | M29: ='2.1meta'!N276 -> 0 | N29: ='2.1meta'!O276 -> 0 | O29: =SUM(F29:N29) -> 0 | P29: =C29-O29 -> 0 | Q29: ='2.1meta'!R276 -> 0 | R29: ='2.1meta'!S276 -> 0 | S29: ='2.1meta'!T276 -> 0 | T29: ='2.1meta'!U276 -> 0 | U29: ='2.1meta'!V276 -> 0 | V29: ='2.1meta'!W276 -> 0 | W29: ='2.1meta'!X276 -> 0 | X29: =SUM(Q29:W29) -> 0 | Y29: =O29+X29 -> 0 | Z29: =C29-Y29 -> 0
A30: 2.1.1.4.2.2 | B30: ASIGNACION POR GASTOS OPERATIVOS | C30: ='2.1meta'!D277 -> 0 | D30: ='2.1meta'!E260 -> 0 | E30: ='2.1meta'!F260 -> 0 | F30: ='2.1meta'!G277 -> 0 | G30: ='2.1meta'!H277 -> 0 | H30: ='2.1meta'!I277 -> 0 | I30: ='2.1meta'!J277 -> 0 | J30: ='2.1meta'!K277 -> 0 | K30: ='2.1meta'!L277 -> 0 | L30: ='2.1meta'!M277 -> 0 | M30: ='2.1meta'!N277 -> 0 | N30: ='2.1meta'!O277 -> 0 | O30: =SUM(F30:N30) -> 0 | P30: =C30-O30 -> 0 | Q30: ='2.1meta'!R277 -> 0 | R30: ='2.1meta'!S277 -> 0 | S30: ='2.1meta'!T277 -> 0 | T30: ='2.1meta'!U277 -> 0 | U30: ='2.1meta'!V277 -> 0 | V30: ='2.1meta'!W277 -> 0 | W30: ='2.1meta'!X277 -> 0 | X30: =SUM(Q30:W30) -> 0 | Y30: =O30+X30 -> 0 | Z30: =C30-Y30 -> 0
A31: 2.1.1.9.1.1 | B31: GRATIFICACIONES | C31: ='2.1meta'!D278 -> 0 | D31: ='2.1meta'!E261 -> 0 | E31: ='2.1meta'!F261 -> 0 | F31: ='2.1meta'!G278 -> 0 | G31: ='2.1meta'!H278 -> 0 | H31: ='2.1meta'!I278 -> 0 | I31: ='2.1meta'!J278 -> 0 | J31: ='2.1meta'!K278 -> 0 | K31: ='2.1meta'!L278 -> 0 | L31: ='2.1meta'!M278 -> 0 | M31: ='2.1meta'!N278 -> 0 | N31: ='2.1meta'!O278 -> 0 | O31: =SUM(F31:N31) -> 0 | P31: =C31-O31 -> 0 | Q31: ='2.1meta'!R278 -> 0 | R31: ='2.1meta'!S278 -> 0 | S31: ='2.1meta'!T278 -> 0 | T31: ='2.1meta'!U278 -> 0 | U31: ='2.1meta'!V278 -> 0 | V31: ='2.1meta'!W278 -> 0 | W31: ='2.1meta'!X278 -> 0 | X31: =SUM(Q31:W31) -> 0 | Y31: =O31+X31 -> 0 | Z31: =C31-Y31 -> 0
A32: 2.1.1.9.1.2 | B32: AGUINALDOS | C32: ='2.1meta'!D279 -> 0 | D32: ='2.1meta'!E262 -> 0 | E32: ='2.1meta'!F262 -> 0 | F32: ='2.1meta'!G279 -> 0 | G32: ='2.1meta'!H279 -> 0 | H32: ='2.1meta'!I279 -> 0 | I32: ='2.1meta'!J279 -> 0 | J32: ='2.1meta'!K279 -> 0 | K32: ='2.1meta'!L279 -> 0 | L32: ='2.1meta'!M279 -> 0 | M32: ='2.1meta'!N279 -> 0 | N32: ='2.1meta'!O279 -> 0 | O32: =SUM(F32:N32) -> 0 | P32: =C32-O32 -> 0 | Q32: ='2.1meta'!R279 -> 0 | R32: ='2.1meta'!S279 -> 0 | S32: ='2.1meta'!T279 -> 0 | T32: ='2.1meta'!U279 -> 0 | U32: ='2.1meta'!V279 -> 0 | V32: ='2.1meta'!W279 -> 0 | W32: ='2.1meta'!X279 -> 0 | X32: =SUM(Q32:W32) -> 0 | Y32: =O32+X32 -> 0 | Z32: =C32-Y32 -> 0
A33: 2.1.1.9.1.3 | B33: BONIFICACION POR ESCOLARIDAD | C33: ='2.1meta'!D280 -> 0 | D33: ='2.1meta'!E263 -> 0 | E33: ='2.1meta'!F263 -> 0 | F33: ='2.1meta'!G280 -> 0 | G33: ='2.1meta'!H280 -> 0 | H33: ='2.1meta'!I280 -> 0 | I33: ='2.1meta'!J280 -> 0 | J33: ='2.1meta'!K280 -> 0 | K33: ='2.1meta'!L280 -> 0 | L33: ='2.1meta'!M280 -> 0 | M33: ='2.1meta'!N280 -> 0 | N33: ='2.1meta'!O280 -> 0 | O33: =SUM(F33:N33) -> 0 | P33: =C33-O33 -> 0 | Q33: ='2.1meta'!R280 -> 0 | R33: ='2.1meta'!S280 -> 0 | S33: ='2.1meta'!T280 -> 0 | T33: ='2.1meta'!U280 -> 0 | U33: ='2.1meta'!V280 -> 0 | V33: ='2.1meta'!W280 -> 0 | W33: ='2.1meta'!X280 -> 0 | X33: =SUM(Q33:W33) -> 0 | Y33: =O33+X33 -> 0 | Z33: =C33-Y33 -> 0
A34: 2.1.1.9.2.1 | B34: COMPENSACION POR TIEMPO DE SERVICIOS (CTS) | C34: ='2.1meta'!D281 -> 0 | D34: ='2.1meta'!E264 -> 0 | E34: ='2.1meta'!F264 -> 0 | F34: ='2.1meta'!G281 -> 0 | G34: ='2.1meta'!H281 -> 0 | H34: ='2.1meta'!I281 -> 0 | I34: ='2.1meta'!J281 -> 0 | J34: ='2.1meta'!K281 -> 0 | K34: ='2.1meta'!L281 -> 0 | L34: ='2.1meta'!M281 -> 0 | M34: ='2.1meta'!N281 -> 0 | N34: ='2.1meta'!O281 -> 0 | O34: =SUM(F34:N34) -> 0 | P34: =C34-O34 -> 0 | Q34: ='2.1meta'!R281 -> 0 | R34: ='2.1meta'!S281 -> 0 | S34: ='2.1meta'!T281 -> 0 | T34: ='2.1meta'!U281 -> 0 | U34: ='2.1meta'!V281 -> 0 | V34: ='2.1meta'!W281 -> 0 | W34: ='2.1meta'!X281 -> 0 | X34: =SUM(Q34:W34) -> 0 | Y34: =O34+X34 -> 0 | Z34: =C34-Y34 -> 0
A35: 2.1.1.9.3.99 | B35: OTRAS OCASIONALES | C35: ='2.1meta'!D283 -> 0 | D35: ='2.1meta'!E266 -> 0 | E35: ='2.1meta'!F266 -> 0 | F35: ='2.1meta'!G283 -> 0 | G35: ='2.1meta'!H283 -> 0 | H35: ='2.1meta'!I283 -> 0 | I35: ='2.1meta'!J283 -> 0 | J35: ='2.1meta'!K283 -> 0 | K35: ='2.1meta'!L283 -> 0 | L35: ='2.1meta'!M283 -> 0 | M35: ='2.1meta'!N283 -> 0 | N35: ='2.1meta'!O283 -> 0 | O35: =SUM(F35:N35) -> 0 | P35: =C35-O35 -> 0 | Q35: ='2.1meta'!R283 -> 0 | R35: ='2.1meta'!S283 -> 0 | S35: ='2.1meta'!T283 -> 0 | T35: ='2.1meta'!U283 -> 0 | U35: ='2.1meta'!V283 -> 0 | V35: ='2.1meta'!W283 -> 0 | W35: ='2.1meta'!X283 -> 0 | X35: =SUM(Q35:W35) -> 0 | Y35: =O35+X35 -> 0 | Z35: =C35-Y35 -> 0
A36: 2.1.3.1.1.1 | B36: APORTES A LOS FONDOS DE SALUD | C36: ='2.1meta'!D284 -> 0 | D36: ='2.1meta'!E267 -> 0 | E36: ='2.1meta'!F267 -> 0 | F36: ='2.1meta'!G284 -> 0 | G36: ='2.1meta'!H284 -> 0 | H36: ='2.1meta'!I284 -> 0 | I36: ='2.1meta'!J284 -> 0 | J36: ='2.1meta'!K284 -> 0 | K36: ='2.1meta'!L284 -> 0 | L36: ='2.1meta'!M284 -> 0 | M36: ='2.1meta'!N284 -> 0 | N36: ='2.1meta'!O284 -> 0 | O36: =SUM(F36:N36) -> 0 | P36: =C36-O36 -> 0 | Q36: ='2.1meta'!R284 -> 0 | R36: ='2.1meta'!S284 -> 0 | S36: ='2.1meta'!T284 -> 0 | T36: ='2.1meta'!U284 -> 0 | U36: ='2.1meta'!V284 -> 0 | V36: ='2.1meta'!W284 -> 0 | W36: ='2.1meta'!X284 -> 0 | X36: =SUM(Q36:W36) -> 0 | Y36: =O36+X36 -> 0 | Z36: =C36-Y36 -> 0
A37: 2.1.3.1.1.5 | B37: CONTRIBUCIONES A ESSALUD | C37: ='2.1meta'!D286 -> 0 | D37: ='2.1meta'!E269 -> 0 | E37: ='2.1meta'!F269 -> 0 | F37: ='2.1meta'!G286 -> 0 | G37: ='2.1meta'!H286 -> 0 | H37: ='2.1meta'!I286 -> 0 | I37: ='2.1meta'!J286 -> 0 | J37: ='2.1meta'!K286 -> 0 | K37: ='2.1meta'!L286 -> 0 | L37: ='2.1meta'!M286 -> 0 | M37: ='2.1meta'!N286 -> 0 | N37: ='2.1meta'!O286 -> 0 | O37: =SUM(F37:N37) -> 0 | P37: =C37-O37 -> 0 | Q37: ='2.1meta'!R286 -> 0 | R37: ='2.1meta'!S286 -> 0 | S37: ='2.1meta'!T286 -> 0 | T37: ='2.1meta'!U286 -> 0 | U37: ='2.1meta'!V286 -> 0 | V37: ='2.1meta'!W286 -> 0 | W37: ='2.1meta'!X286 -> 0 | X37: =SUM(Q37:W37) -> 0 | Y37: =O37+X37 -> 0 | Z37: =C37-Y37 -> 0
A38: 9001 ACCIONES CENTRALES | C38: =SUBTOTAL(9,C39:C50) -> 0 | F38: =SUBTOTAL(9,F39:F50) -> 0 | G38: =SUBTOTAL(9,G39:G50) -> 0 | H38: =SUBTOTAL(9,H39:H50) -> 0 | I38: =SUBTOTAL(9,I39:I50) -> 0 | J38: =SUBTOTAL(9,J39:J50) -> 0 | K38: =SUBTOTAL(9,K39:K50) -> 0 | L38: =SUBTOTAL(9,L39:L50) -> 0 | M38: =SUBTOTAL(9,M39:M50) -> 0 | ... O38: =SUBTOTAL(9,O39:O50) -> 0 | P38: =C38-O38 -> 0 | Q38: =SUBTOTAL(9,Q39:Q50) -> 0 | R38: =SUBTOTAL(9,R39:R50) -> 0 | S38: =SUBTOTAL(9,S39:S50) -> 0 | T38: =SUBTOTAL(9,T39:T50) -> 0 | U38: =SUBTOTAL(9,U39:U50) -> 0 | V38: =SUBTOTAL(9,V39:V50) -> 0 | W38: =SUBTOTAL(9,W39:W50) -> 0 | X38: =SUBTOTAL(9,X39:X50) -> 0 | ... Z38: =SUBTOTAL(9,Z39:Z50) -> 0
A39: 2.1.1.1.1.2 | B39: PERSONAL ADMINISTRATIVO NOMBRADO (REGIMEN PUBLICO) | C39: ='2.1meta'!D195+'2.1meta'!D212 -> 0 | D39: ='2.1meta'!E76 -> 0 | E39: ='2.1meta'!F76 -> 0 | F39: ='2.1meta'!G195+'2.1meta'!G212 -> 0 | G39: ='2.1meta'!H195+'2.1meta'!H212 -> 0 | H39: ='2.1meta'!I195+'2.1meta'!I212 -> 0 | I39: ='2.1meta'!J195+'2.1meta'!J212 -> 0 | J39: ='2.1meta'!K195+'2.1meta'!K212 -> 0 | K39: ='2.1meta'!L195+'2.1meta'!L212 -> 0 | L39: ='2.1meta'!M195+'2.1meta'!M212 -> 0 | M39: ='2.1meta'!N195+'2.1meta'!N212 -> 0 | N39: ='2.1meta'!O195+'2.1meta'!O212 -> 0 | O39: =SUM(F39:N39) -> 0 | P39: =C39-O39 -> 0 | Q39: ='2.1meta'!R195+'2.1meta'!R212 -> 0 | R39: ='2.1meta'!S195+'2.1meta'!S212 -> 0 | S39: ='2.1meta'!T195+'2.1meta'!T212 -> 0 | T39: ='2.1meta'!U195+'2.1meta'!U212 -> 0 | U39: ='2.1meta'!V195+'2.1meta'!V212 -> 0 | V39: ='2.1meta'!W195+'2.1meta'!W212 -> 0 | W39: ='2.1meta'!X195+'2.1meta'!X212 -> 0 | X39: =SUM(Q39:W39) -> 0 | Y39: =O39+X39 -> 0 | Z39: =C39-Y39 -> 0
A40: 2.1.1.1.1.4 | B40: PERSONAL CON CONTRATO A PLAZO INDETERMINADO (REGIMEN LABORAL PRIVADO) | C40: ='2.1meta'!D196+'2.1meta'!D213 -> 0 | D40: ='2.1meta'!E77 -> 0 | E40: ='2.1meta'!F77 -> 0 | F40: ='2.1meta'!G196+'2.1meta'!G213 -> 0 | G40: ='2.1meta'!H196+'2.1meta'!H213 -> 0 | H40: ='2.1meta'!I196+'2.1meta'!I213 -> 0 | I40: ='2.1meta'!J196+'2.1meta'!J213 -> 0 | J40: ='2.1meta'!K196+'2.1meta'!K213 -> 0 | K40: ='2.1meta'!L196+'2.1meta'!L213 -> 0 | L40: ='2.1meta'!M196+'2.1meta'!M213 -> 0 | M40: ='2.1meta'!N196+'2.1meta'!N213 -> 0 | N40: ='2.1meta'!O196+'2.1meta'!O213 -> 0 | O40: =SUM(F40:N40) -> 0 | P40: =C40-O40 -> 0 | Q40: ='2.1meta'!R196+'2.1meta'!R213 -> 0 | R40: ='2.1meta'!S196+'2.1meta'!S213 -> 0 | S40: ='2.1meta'!T196+'2.1meta'!T213 -> 0 | T40: ='2.1meta'!U196+'2.1meta'!U213 -> 0 | U40: ='2.1meta'!V196+'2.1meta'!V213 -> 0 | V40: ='2.1meta'!W196+'2.1meta'!W213 -> 0 | W40: ='2.1meta'!X196+'2.1meta'!X213 -> 0 | X40: =SUM(Q40:W40) -> 0 | Y40: =O40+X40 -> 0 | Z40: =C40-Y40 -> 0
A41: 2.1.1.1.1.5 | B41: PERSONAL CON CONTRATO A PLAZO FIJO (REGIMEN LABORAL PRIVADO) | C41: ='2.1meta'!D197+'2.1meta'!D214 -> 0 | D41: ='2.1meta'!E78 -> 0 | E41: ='2.1meta'!F78 -> 0 | F41: ='2.1meta'!G197+'2.1meta'!G214 -> 0 | G41: ='2.1meta'!H197+'2.1meta'!H214 -> 0 | H41: ='2.1meta'!I197+'2.1meta'!I214 -> 0 | I41: ='2.1meta'!J197+'2.1meta'!J214 -> 0 | J41: ='2.1meta'!K197+'2.1meta'!K214 -> 0 | K41: ='2.1meta'!L197+'2.1meta'!L214 -> 0 | L41: ='2.1meta'!M197+'2.1meta'!M214 -> 0 | M41: ='2.1meta'!N197+'2.1meta'!N214 -> 0 | N41: ='2.1meta'!O197+'2.1meta'!O214 -> 0 | O41: =SUM(F41:N41) -> 0 | P41: =C41-O41 -> 0 | Q41: ='2.1meta'!R197+'2.1meta'!R214 -> 0 | R41: ='2.1meta'!S197+'2.1meta'!S214 -> 0 | S41: ='2.1meta'!T197+'2.1meta'!T214 -> 0 | T41: ='2.1meta'!U197+'2.1meta'!U214 -> 0 | U41: ='2.1meta'!V197+'2.1meta'!V214 -> 0 | V41: ='2.1meta'!W197+'2.1meta'!W214 -> 0 | W41: ='2.1meta'!X197+'2.1meta'!X214 -> 0 | X41: =SUM(Q41:W41) -> 0 | Y41: =O41+X41 -> 0 | Z41: =C41-Y41 -> 0
A42: 2.1.1.1.2.1 | B42: ASIGNACION A FONDOS PARA PERSONAL | C42: ='2.1meta'!D198+'2.1meta'!D215 -> 0 | D42: ='2.1meta'!E79 -> 0 | E42: ='2.1meta'!F79 -> 0 | F42: ='2.1meta'!G198+'2.1meta'!G215 -> 0 | G42: ='2.1meta'!H198+'2.1meta'!H215 -> 0 | H42: ='2.1meta'!I198+'2.1meta'!I215 -> 0 | I42: ='2.1meta'!J198+'2.1meta'!J215 -> 0 | J42: ='2.1meta'!K198+'2.1meta'!K215 -> 0 | K42: ='2.1meta'!L198+'2.1meta'!L215 -> 0 | L42: ='2.1meta'!M198+'2.1meta'!M215 -> 0 | M42: ='2.1meta'!N198+'2.1meta'!N215 -> 0 | N42: ='2.1meta'!O198+'2.1meta'!O215 -> 0 | O42: =SUM(F42:N42) -> 0 | P42: =C42-O42 -> 0 | Q42: ='2.1meta'!R198+'2.1meta'!R215 -> 0 | R42: ='2.1meta'!S198+'2.1meta'!S215 -> 0 | S42: ='2.1meta'!T198+'2.1meta'!T215 -> 0 | T42: ='2.1meta'!U198+'2.1meta'!U215 -> 0 | U42: ='2.1meta'!V198+'2.1meta'!V215 -> 0 | V42: ='2.1meta'!W198+'2.1meta'!W215 -> 0 | W42: ='2.1meta'!X198+'2.1meta'!X215 -> 0 | X42: =SUM(Q42:W42) -> 0 | Y42: =O42+X42 -> 0 | Z42: =C42-Y42 -> 0
A43: 2.1.1.9.1.1 | B43: GRATIFICACIONES | C43: ='2.1meta'!D202+'2.1meta'!D219 -> 0 | D43: ='2.1meta'!E83 -> 0 | E43: ='2.1meta'!F83 -> 0 | F43: ='2.1meta'!G202+'2.1meta'!G219 -> 0 | G43: ='2.1meta'!H202+'2.1meta'!H219 -> 0 | H43: ='2.1meta'!I202+'2.1meta'!I219 -> 0 | I43: ='2.1meta'!J202+'2.1meta'!J219 -> 0 | J43: ='2.1meta'!K202+'2.1meta'!K219 -> 0 | K43: ='2.1meta'!L202+'2.1meta'!L219 -> 0 | L43: ='2.1meta'!M202+'2.1meta'!M219 -> 0 | M43: ='2.1meta'!N202+'2.1meta'!N219 -> 0 | N43: ='2.1meta'!O202+'2.1meta'!O219 -> 0 | O43: =SUM(F43:N43) -> 0 | P43: =C43-O43 -> 0 | Q43: ='2.1meta'!R202+'2.1meta'!R219 -> 0 | R43: ='2.1meta'!S202+'2.1meta'!S219 -> 0 | S43: ='2.1meta'!T202+'2.1meta'!T219 -> 0 | T43: ='2.1meta'!U202+'2.1meta'!U219 -> 0 | U43: ='2.1meta'!V202+'2.1meta'!V219 -> 0 | V43: ='2.1meta'!W202+'2.1meta'!W219 -> 0 | W43: ='2.1meta'!X202+'2.1meta'!X219 -> 0 | X43: =SUM(Q43:W43) -> 0 | Y43: =O43+X43 -> 0 | Z43: =C43-Y43 -> 0
A44: 2.1.1.9.1.2 | B44: AGUINALDOS | C44: ='2.1meta'!D203+'2.1meta'!D220 -> 0 | D44: ='2.1meta'!E84 -> 0 | E44: ='2.1meta'!F84 -> 0 | F44: ='2.1meta'!G203+'2.1meta'!G220 -> 0 | G44: ='2.1meta'!H203+'2.1meta'!H220 -> 0 | H44: ='2.1meta'!I203+'2.1meta'!I220 -> 0 | I44: ='2.1meta'!J203+'2.1meta'!J220 -> 0 | J44: ='2.1meta'!K203+'2.1meta'!K220 -> 0 | K44: ='2.1meta'!L203+'2.1meta'!L220 -> 0 | L44: ='2.1meta'!M203+'2.1meta'!M220 -> 0 | M44: ='2.1meta'!N203+'2.1meta'!N220 -> 0 | N44: ='2.1meta'!O203+'2.1meta'!O220 -> 0 | O44: =SUM(F44:N44) -> 0 | P44: =C44-O44 -> 0 | Q44: ='2.1meta'!R203+'2.1meta'!R220 -> 0 | R44: ='2.1meta'!S203+'2.1meta'!S220 -> 0 | S44: ='2.1meta'!T203+'2.1meta'!T220 -> 0 | T44: ='2.1meta'!U203+'2.1meta'!U220 -> 0 | U44: ='2.1meta'!V203+'2.1meta'!V220 -> 0 | V44: ='2.1meta'!W203+'2.1meta'!W220 -> 0 | W44: ='2.1meta'!X203+'2.1meta'!X220 -> 0 | X44: =SUM(Q44:W44) -> 0 | Y44: =O44+X44 -> 0 | Z44: =C44-Y44 -> 0
A45: 2.1.1.9.1.3 | B45: BONIFICACION POR ESCOLARIDAD | C45: ='2.1meta'!D204+'2.1meta'!D221 -> 0 | D45: ='2.1meta'!E85 -> 0 | E45: ='2.1meta'!F85 -> 0 | F45: ='2.1meta'!G204+'2.1meta'!G221 -> 0 | G45: ='2.1meta'!H204+'2.1meta'!H221 -> 0 | H45: ='2.1meta'!I204+'2.1meta'!I221 -> 0 | I45: ='2.1meta'!J204+'2.1meta'!J221 -> 0 | J45: ='2.1meta'!K204+'2.1meta'!K221 -> 0 | K45: ='2.1meta'!L204+'2.1meta'!L221 -> 0 | L45: ='2.1meta'!M204+'2.1meta'!M221 -> 0 | M45: ='2.1meta'!N204+'2.1meta'!N221 -> 0 | N45: ='2.1meta'!O204+'2.1meta'!O221 -> 0 | O45: =SUM(F45:N45) -> 0 | P45: =C45-O45 -> 0 | Q45: ='2.1meta'!R204+'2.1meta'!R221 -> 0 | R45: ='2.1meta'!S204+'2.1meta'!S221 -> 0 | S45: ='2.1meta'!T204+'2.1meta'!T221 -> 0 | T45: ='2.1meta'!U204+'2.1meta'!U221 -> 0 | U45: ='2.1meta'!V204+'2.1meta'!V221 -> 0 | V45: ='2.1meta'!W204+'2.1meta'!W221 -> 0 | W45: ='2.1meta'!X204+'2.1meta'!X221 -> 0 | X45: =SUM(Q45:W45) -> 0 | Y45: =O45+X45 -> 0 | Z45: =C45-Y45 -> 0
A46: 2.1.1.9.2.1 | B46: COMPENSACION POR TIEMPO DE SERVICIOS (CTS) | C46: ='2.1meta'!D205+'2.1meta'!D222 -> 0 | D46: ='2.1meta'!E86 -> 0 | E46: ='2.1meta'!F86 -> 0 | F46: ='2.1meta'!G205+'2.1meta'!G222 -> 0 | G46: ='2.1meta'!H205+'2.1meta'!H222 -> 0 | H46: ='2.1meta'!I205+'2.1meta'!I222 -> 0 | I46: ='2.1meta'!J205+'2.1meta'!J222 -> 0 | J46: ='2.1meta'!K205+'2.1meta'!K222 -> 0 | K46: ='2.1meta'!L205+'2.1meta'!L222 -> 0 | L46: ='2.1meta'!M205+'2.1meta'!M222 -> 0 | M46: ='2.1meta'!N205+'2.1meta'!N222 -> 0 | N46: ='2.1meta'!O205+'2.1meta'!O222 -> 0 | O46: =SUM(F46:N46) -> 0 | P46: =C46-O46 -> 0 | Q46: ='2.1meta'!R205+'2.1meta'!R222 -> 0 | R46: ='2.1meta'!S205+'2.1meta'!S222 -> 0 | S46: ='2.1meta'!T205+'2.1meta'!T222 -> 0 | T46: ='2.1meta'!U205+'2.1meta'!U222 -> 0 | U46: ='2.1meta'!V205+'2.1meta'!V222 -> 0 | V46: ='2.1meta'!W205+'2.1meta'!W222 -> 0 | W46: ='2.1meta'!X205+'2.1meta'!X222 -> 0 | X46: =SUM(Q46:W46) -> 0 | Y46: =O46+X46 -> 0 | Z46: =C46-Y46 -> 0
A47: 2.1.1.9.3.3 | B47: COMPENSACION VACACIONAL (VACACIONES TRUNCAS) | C47: ='2.1meta'!D206+'2.1meta'!D223 -> 0 | D47: ='2.1meta'!E87 -> 0 | E47: ='2.1meta'!F87 -> 0 | F47: ='2.1meta'!G206+'2.1meta'!G223 -> 0 | G47: ='2.1meta'!H206+'2.1meta'!H223 -> 0 | H47: ='2.1meta'!I206+'2.1meta'!I223 -> 0 | I47: ='2.1meta'!J206+'2.1meta'!J223 -> 0 | J47: ='2.1meta'!K206+'2.1meta'!K223 -> 0 | K47: ='2.1meta'!L206+'2.1meta'!L223 -> 0 | L47: ='2.1meta'!M206+'2.1meta'!M223 -> 0 | M47: ='2.1meta'!N206+'2.1meta'!N223 -> 0 | N47: ='2.1meta'!O206+'2.1meta'!O223 -> 0 | O47: =SUM(F47:N47) -> 0 | P47: =C47-O47 -> 0 | Q47: ='2.1meta'!R206+'2.1meta'!R223 -> 0 | R47: ='2.1meta'!S206+'2.1meta'!S223 -> 0 | S47: ='2.1meta'!T206+'2.1meta'!T223 -> 0 | T47: ='2.1meta'!U206+'2.1meta'!U223 -> 0 | U47: ='2.1meta'!V206+'2.1meta'!V223 -> 0 | V47: ='2.1meta'!W206+'2.1meta'!W223 -> 0 | W47: ='2.1meta'!X206+'2.1meta'!X223 -> 0 | X47: =SUM(Q47:W47) -> 0 | Y47: =O47+X47 -> 0 | Z47: =C47-Y47 -> 0
A48: 2.1.1.9.3.99 | B48: OTRAS OCASIONALES | C48: ='2.1meta'!D207+'2.1meta'!D224 -> 0 | D48: ='2.1meta'!E88 -> 0 | E48: ='2.1meta'!F88 -> 0 | F48: ='2.1meta'!G207+'2.1meta'!G224 -> 0 | G48: ='2.1meta'!H207+'2.1meta'!H224 -> 0 | H48: ='2.1meta'!I207+'2.1meta'!I224 -> 0 | I48: ='2.1meta'!J207+'2.1meta'!J224 -> 0 | J48: ='2.1meta'!K207+'2.1meta'!K224 -> 0 | K48: ='2.1meta'!L207+'2.1meta'!L224 -> 0 | L48: ='2.1meta'!M207+'2.1meta'!M224 -> 0 | M48: ='2.1meta'!N207+'2.1meta'!N224 -> 0 | N48: ='2.1meta'!O207+'2.1meta'!O224 -> 0 | O48: =SUM(F48:N48) -> 0 | P48: =C48-O48 -> 0 | Q48: ='2.1meta'!R207+'2.1meta'!R224 -> 0 | R48: ='2.1meta'!S207+'2.1meta'!S224 -> 0 | S48: ='2.1meta'!T207+'2.1meta'!T224 -> 0 | T48: ='2.1meta'!U207+'2.1meta'!U224 -> 0 | U48: ='2.1meta'!V207+'2.1meta'!V224 -> 0 | V48: ='2.1meta'!W207+'2.1meta'!W224 -> 0 | W48: ='2.1meta'!X207+'2.1meta'!X224 -> 0 | X48: =SUM(Q48:W48) -> 0 | Y48: =O48+X48 -> 0 | Z48: =C48-Y48 -> 0
A49: 2.1.3.1.1.1 | B49: APORTES A LOS FONDOS DE SALUD | C49: ='2.1meta'!D208+'2.1meta'!D225 -> 0 | D49: ='2.1meta'!E89 -> 0 | E49: ='2.1meta'!F89 -> 0 | F49: ='2.1meta'!G208+'2.1meta'!G225 -> 0 | G49: ='2.1meta'!H208+'2.1meta'!H225 -> 0 | H49: ='2.1meta'!I208+'2.1meta'!I225 -> 0 | I49: ='2.1meta'!J208+'2.1meta'!J225 -> 0 | J49: ='2.1meta'!K208+'2.1meta'!K225 -> 0 | K49: ='2.1meta'!L208+'2.1meta'!L225 -> 0 | L49: ='2.1meta'!M208+'2.1meta'!M225 -> 0 | M49: ='2.1meta'!N208+'2.1meta'!N225 -> 0 | N49: ='2.1meta'!O208+'2.1meta'!O225 -> 0 | O49: =SUM(F49:N49) -> 0 | P49: =C49-O49 -> 0 | Q49: ='2.1meta'!R208+'2.1meta'!R225 -> 0 | R49: ='2.1meta'!S208+'2.1meta'!S225 -> 0 | S49: ='2.1meta'!T208+'2.1meta'!T225 -> 0 | T49: ='2.1meta'!U208+'2.1meta'!U225 -> 0 | U49: ='2.1meta'!V208+'2.1meta'!V225 -> 0 | V49: ='2.1meta'!W208+'2.1meta'!W225 -> 0 | W49: ='2.1meta'!X208+'2.1meta'!X225 -> 0 | X49: =SUM(Q49:W49) -> 0 | Y49: =O49+X49 -> 0 | Z49: =C49-Y49 -> 0
A50: 2.1.3.1.1.5 | B50: CONTRIBUCIONES A ESSALUD | C50: ='2.1meta'!D210+'2.1meta'!D227 -> 0 | D50: ='2.1meta'!E91 -> 0 | E50: ='2.1meta'!F91 -> 0 | F50: ='2.1meta'!G210+'2.1meta'!G227 -> 0 | G50: ='2.1meta'!H210+'2.1meta'!H227 -> 0 | H50: ='2.1meta'!I210+'2.1meta'!I227 -> 0 | I50: ='2.1meta'!J210+'2.1meta'!J227 -> 0 | J50: ='2.1meta'!K210+'2.1meta'!K227 -> 0 | K50: ='2.1meta'!L210+'2.1meta'!L227 -> 0 | L50: ='2.1meta'!M210+'2.1meta'!M227 -> 0 | M50: ='2.1meta'!N210+'2.1meta'!N227 -> 0 | N50: ='2.1meta'!O210+'2.1meta'!O227 -> 0 | O50: =SUM(F50:N50) -> 0 | P50: =C50-O50 -> 0 | Q50: ='2.1meta'!R210+'2.1meta'!R227 -> 0 | R50: ='2.1meta'!S210+'2.1meta'!S227 -> 0 | S50: ='2.1meta'!T210+'2.1meta'!T227 -> 0 | T50: ='2.1meta'!U210+'2.1meta'!U227 -> 0 | U50: ='2.1meta'!V210+'2.1meta'!V227 -> 0 | V50: ='2.1meta'!W210+'2.1meta'!W227 -> 0 | W50: ='2.1meta'!X210+'2.1meta'!X227 -> 0 | X50: =SUM(Q50:W50) -> 0 | Y50: =O50+X50 -> 0 | Z50: =C50-Y50 -> 0
A51: 9002 ASIGNACIONES PRESUPUESTARIAS QUE NO RESULTAN EN PRODUCTOS | C51: =SUBTOTAL(9,C52:C66) -> 0 | F51: =SUBTOTAL(9,F52:F66) -> 0 | G51: =SUBTOTAL(9,G52:G66) -> 0 | H51: =SUBTOTAL(9,H52:H66) -> 0 | I51: =SUBTOTAL(9,I52:I66) -> 0 | J51: =SUBTOTAL(9,J52:J66) -> 0 | K51: =SUBTOTAL(9,K52:K66) -> 0 | L51: =SUBTOTAL(9,L52:L66) -> 0 | M51: =SUBTOTAL(9,M52:M66) -> 0 | ... O51: =SUBTOTAL(9,O52:O66) -> 0 | P51: =C51-O51 -> 0 | Q51: =SUBTOTAL(9,Q52:Q66) -> 0 | R51: =SUBTOTAL(9,R52:R66) -> 0 | S51: =SUBTOTAL(9,S52:S66) -> 0 | T51: =SUBTOTAL(9,T52:T66) -> 0 | U51: =SUBTOTAL(9,U52:U66) -> 0 | V51: =SUBTOTAL(9,V52:V66) -> 0 | W51: =SUBTOTAL(9,W52:W66) -> 0 | X51: =SUBTOTAL(9,X52:X66) -> 0 | ... Z51: =SUBTOTAL(9,Z52:Z66) -> 0
A52: 2.1.1.1.1.2 | B52: PERSONAL ADMINISTRATIVO NOMBRADO (REGIMEN PUBLICO) | C52: ='2.1meta'!D237+'2.1meta'!D254 -> 0 | D52: ='2.1meta'!E144 -> 0 | E52: ='2.1meta'!F144 -> 0 | F52: ='2.1meta'!G237+'2.1meta'!G254 -> 0 | G52: ='2.1meta'!H237+'2.1meta'!H254 -> 0 | H52: ='2.1meta'!I237+'2.1meta'!I254 -> 0 | I52: ='2.1meta'!J237+'2.1meta'!J254 -> 0 | J52: ='2.1meta'!K237+'2.1meta'!K254 -> 0 | K52: ='2.1meta'!L237+'2.1meta'!L254 -> 0 | L52: ='2.1meta'!M237+'2.1meta'!M254 -> 0 | M52: ='2.1meta'!N237+'2.1meta'!N254 -> 0 | N52: ='2.1meta'!O237+'2.1meta'!O254 -> 0 | O52: =SUM(F52:N52) -> 0 | P52: =C52-O52 -> 0 | Q52: ='2.1meta'!R237+'2.1meta'!R254 -> 0 | R52: ='2.1meta'!S237+'2.1meta'!S254 -> 0 | S52: ='2.1meta'!T237+'2.1meta'!T254 -> 0 | T52: ='2.1meta'!U237+'2.1meta'!U254 -> 0 | U52: ='2.1meta'!V237+'2.1meta'!V254 -> 0 | V52: ='2.1meta'!W237+'2.1meta'!W254 -> 0 | W52: ='2.1meta'!X237+'2.1meta'!X254 -> 0 | X52: =SUM(Q52:W52) -> 0 | Y52: =O52+X52 -> 0 | Z52: =C52-Y52 -> 0
A53: 2.1.1.1.1.4 | B53: PERSONAL CON CONTRATO A PLAZO INDETERMINADO (REGIMEN LABORAL PRIVADO) | C53: ='2.1meta'!D238+'2.1meta'!D255 -> 0 | D53: ='2.1meta'!E145 -> 0 | E53: ='2.1meta'!F145 -> 0 | F53: ='2.1meta'!G238+'2.1meta'!G255 -> 0 | G53: ='2.1meta'!H238+'2.1meta'!H255 -> 0 | H53: ='2.1meta'!I238+'2.1meta'!I255 -> 0 | I53: ='2.1meta'!J238+'2.1meta'!J255 -> 0 | J53: ='2.1meta'!K238+'2.1meta'!K255 -> 0 | K53: ='2.1meta'!L238+'2.1meta'!L255 -> 0 | L53: ='2.1meta'!M238+'2.1meta'!M255 -> 0 | M53: ='2.1meta'!N238+'2.1meta'!N255 -> 0 | N53: ='2.1meta'!O238+'2.1meta'!O255 -> 0 | O53: =SUM(F53:N53) -> 0 | P53: =C53-O53 -> 0 | Q53: ='2.1meta'!R238+'2.1meta'!R255 -> 0 | R53: ='2.1meta'!S238+'2.1meta'!S255 -> 0 | S53: ='2.1meta'!T238+'2.1meta'!T255 -> 0 | T53: ='2.1meta'!U238+'2.1meta'!U255 -> 0 | U53: ='2.1meta'!V238+'2.1meta'!V255 -> 0 | V53: ='2.1meta'!W238+'2.1meta'!W255 -> 0 | W53: ='2.1meta'!X238+'2.1meta'!X255 -> 0 | X53: =SUM(Q53:W53) -> 0 | Y53: =O53+X53 -> 0 | Z53: =C53-Y53 -> 0
A54: 2.1.1.1.1.5 | B54: PERSONAL CON CONTRATO A PLAZO FIJO (REGIMEN LABORAL PRIVADO) | C54: ='2.1meta'!D239+'2.1meta'!D256 -> 0 | D54: ='2.1meta'!E146 -> 0 | E54: ='2.1meta'!F146 -> 0 | F54: ='2.1meta'!G239+'2.1meta'!G256 -> 0 | G54: ='2.1meta'!H239+'2.1meta'!H256 -> 0 | H54: ='2.1meta'!I239+'2.1meta'!I256 -> 0 | I54: ='2.1meta'!J239+'2.1meta'!J256 -> 0 | J54: ='2.1meta'!K239+'2.1meta'!K256 -> 0 | K54: ='2.1meta'!L239+'2.1meta'!L256 -> 0 | L54: ='2.1meta'!M239+'2.1meta'!M256 -> 0 | M54: ='2.1meta'!N239+'2.1meta'!N256 -> 0 | N54: ='2.1meta'!O239+'2.1meta'!O256 -> 0 | O54: =SUM(F54:N54) -> 0 | P54: =C54-O54 -> 0 | Q54: ='2.1meta'!R239+'2.1meta'!R256 -> 0 | R54: ='2.1meta'!S239+'2.1meta'!S256 -> 0 | S54: ='2.1meta'!T239+'2.1meta'!T256 -> 0 | T54: ='2.1meta'!U239+'2.1meta'!U256 -> 0 | U54: ='2.1meta'!V239+'2.1meta'!V256 -> 0 | V54: ='2.1meta'!W239+'2.1meta'!W256 -> 0 | W54: ='2.1meta'!X239+'2.1meta'!X256 -> 0 | X54: =SUM(Q54:W54) -> 0 | Y54: =O54+X54 -> 0 | Z54: =C54-Y54 -> 0
A55: 2.1.1.1.2.1 | B55: ASIGNACION A FONDOS PARA PERSONAL | C55: ='2.1meta'!D240+'2.1meta'!D257 -> 0 | D55: ='2.1meta'!E147 -> 0 | E55: ='2.1meta'!F147 -> 0 | F55: ='2.1meta'!G240+'2.1meta'!G257 -> 0 | G55: ='2.1meta'!H240+'2.1meta'!H257 -> 0 | H55: ='2.1meta'!I240+'2.1meta'!I257 -> 0 | I55: ='2.1meta'!J240+'2.1meta'!J257 -> 0 | J55: ='2.1meta'!K240+'2.1meta'!K257 -> 0 | K55: ='2.1meta'!L240+'2.1meta'!L257 -> 0 | L55: ='2.1meta'!M240+'2.1meta'!M257 -> 0 | M55: ='2.1meta'!N240+'2.1meta'!N257 -> 0 | N55: ='2.1meta'!O240+'2.1meta'!O257 -> 0 | O55: =SUM(F55:N55) -> 0 | P55: =C55-O55 -> 0 | Q55: ='2.1meta'!R240+'2.1meta'!R257 -> 0 | R55: ='2.1meta'!S240+'2.1meta'!S257 -> 0 | S55: ='2.1meta'!T240+'2.1meta'!T257 -> 0 | T55: ='2.1meta'!U240+'2.1meta'!U257 -> 0 | U55: ='2.1meta'!V240+'2.1meta'!V257 -> 0 | V55: ='2.1meta'!W240+'2.1meta'!W257 -> 0 | W55: ='2.1meta'!X240+'2.1meta'!X257 -> 0 | X55: =SUM(Q55:W55) -> 0 | Y55: =O55+X55 -> 0 | Z55: =C55-Y55 -> 0
A56: 2.1.1.4.1.1 | B56: PERSONAL NOMBRADO | C56: ='2.1meta'!D229+'2.1meta'!D241+'2.1meta'!D258 -> 0 | D56: ='2.1meta'!E148 -> 0 | E56: ='2.1meta'!F148 -> 0 | F56: ='2.1meta'!G229+'2.1meta'!G241+'2.1meta'!G258 -> 0 | G56: ='2.1meta'!H229+'2.1meta'!H241+'2.1meta'!H258 -> 0 | H56: ='2.1meta'!I229+'2.1meta'!I241+'2.1meta'!I258 -> 0 | I56: ='2.1meta'!J229+'2.1meta'!J241+'2.1meta'!J258 -> 0 | J56: ='2.1meta'!K229+'2.1meta'!K241+'2.1meta'!K258 -> 0 | K56: ='2.1meta'!L229+'2.1meta'!L241+'2.1meta'!L258 -> 0 | L56: ='2.1meta'!M229+'2.1meta'!M241+'2.1meta'!M258 -> 0 | M56: ='2.1meta'!N229+'2.1meta'!N241+'2.1meta'!N258 -> 0 | N56: ='2.1meta'!O229+'2.1meta'!O241+'2.1meta'!O258 -> 0 | O56: =SUM(F56:N56) -> 0 | P56: =C56-O56 -> 0 | Q56: ='2.1meta'!R229+'2.1meta'!R241+'2.1meta'!R258 -> 0 | R56: ='2.1meta'!S229+'2.1meta'!S241+'2.1meta'!S258 -> 0 | S56: ='2.1meta'!T229+'2.1meta'!T241+'2.1meta'!T258 -> 0 | T56: ='2.1meta'!U229+'2.1meta'!U241+'2.1meta'!U258 -> 0 | U56: ='2.1meta'!V229+'2.1meta'!V241+'2.1meta'!V258 -> 0 | V56: ='2.1meta'!W229+'2.1meta'!W241+'2.1meta'!W258 -> 0 | W56: ='2.1meta'!X229+'2.1meta'!X241+'2.1meta'!X258 -> 0 | X56: =SUM(Q56:W56) -> 0 | Y56: =O56+X56 -> 0 | Z56: =C56-Y56 -> 0
A57: 2.1.1.4.2.1 | B57: BONO POR FUNCION JURISDICCIONAL Y FISCAL | C57: ='2.1meta'!D230+'2.1meta'!D242+'2.1meta'!D259 -> 0 | D57: ='2.1meta'!E149 -> 0 | E57: ='2.1meta'!F149 -> 0 | F57: ='2.1meta'!G230+'2.1meta'!G242+'2.1meta'!G259 -> 0 | G57: ='2.1meta'!H230+'2.1meta'!H242+'2.1meta'!H259 -> 0 | H57: ='2.1meta'!I230+'2.1meta'!I242+'2.1meta'!I259 -> 0 | I57: ='2.1meta'!J230+'2.1meta'!J242+'2.1meta'!J259 -> 0 | J57: ='2.1meta'!K230+'2.1meta'!K242+'2.1meta'!K259 -> 0 | K57: ='2.1meta'!L230+'2.1meta'!L242+'2.1meta'!L259 -> 0 | L57: ='2.1meta'!M230+'2.1meta'!M242+'2.1meta'!M259 -> 0 | M57: ='2.1meta'!N230+'2.1meta'!N242+'2.1meta'!N259 -> 0 | N57: ='2.1meta'!O230+'2.1meta'!O242+'2.1meta'!O259 -> 0 | O57: =SUM(F57:N57) -> 0 | P57: =C57-O57 -> 0 | Q57: ='2.1meta'!R230+'2.1meta'!R242+'2.1meta'!R259 -> 0 | R57: ='2.1meta'!S230+'2.1meta'!S242+'2.1meta'!S259 -> 0 | S57: ='2.1meta'!T230+'2.1meta'!T242+'2.1meta'!T259 -> 0 | T57: ='2.1meta'!U230+'2.1meta'!U242+'2.1meta'!U259 -> 0 | U57: ='2.1meta'!V230+'2.1meta'!V242+'2.1meta'!V259 -> 0 | V57: ='2.1meta'!W230+'2.1meta'!W242+'2.1meta'!W259 -> 0 | W57: ='2.1meta'!X230+'2.1meta'!X242+'2.1meta'!X259 -> 0 | X57: =SUM(Q57:W57) -> 0 | Y57: =O57+X57 -> 0 | Z57: =C57-Y57 -> 0
A58: 2.1.1.4.2.2 | B58: ASIGNACION POR GASTOS OPERATIVOS | C58: ='2.1meta'!D231+'2.1meta'!D243+'2.1meta'!D260 -> 0 | D58: ='2.1meta'!E150 -> 0 | E58: ='2.1meta'!F150 -> 0 | F58: ='2.1meta'!G231+'2.1meta'!G243+'2.1meta'!G260 -> 0 | G58: ='2.1meta'!H231+'2.1meta'!H243+'2.1meta'!H260 -> 0 | H58: ='2.1meta'!I231+'2.1meta'!I243+'2.1meta'!I260 -> 0 | I58: ='2.1meta'!J231+'2.1meta'!J243+'2.1meta'!J260 -> 0 | J58: ='2.1meta'!K231+'2.1meta'!K243+'2.1meta'!K260 -> 0 | K58: ='2.1meta'!L231+'2.1meta'!L243+'2.1meta'!L260 -> 0 | L58: ='2.1meta'!M231+'2.1meta'!M243+'2.1meta'!M260 -> 0 | M58: ='2.1meta'!N231+'2.1meta'!N243+'2.1meta'!N260 -> 0 | N58: ='2.1meta'!O231+'2.1meta'!O243+'2.1meta'!O260 -> 0 | O58: =SUM(F58:N58) -> 0 | P58: =C58-O58 -> 0 | Q58: ='2.1meta'!R231+'2.1meta'!R243+'2.1meta'!R260 -> 0 | R58: ='2.1meta'!S231+'2.1meta'!S243+'2.1meta'!S260 -> 0 | S58: ='2.1meta'!T231+'2.1meta'!T243+'2.1meta'!T260 -> 0 | T58: ='2.1meta'!U231+'2.1meta'!U243+'2.1meta'!U260 -> 0 | U58: ='2.1meta'!V231+'2.1meta'!V243+'2.1meta'!V260 -> 0 | V58: ='2.1meta'!W231+'2.1meta'!W243+'2.1meta'!W260 -> 0 | W58: ='2.1meta'!X231+'2.1meta'!X243+'2.1meta'!X260 -> 0 | X58: =SUM(Q58:W58) -> 0 | Y58: =O58+X58 -> 0 | Z58: =C58-Y58 -> 0
A59: 2.1.1.9.1.1 | B59: GRATIFICACIONES | C59: ='2.1meta'!D244+'2.1meta'!D261 -> 0 | D59: ='2.1meta'!E151 -> 0 | E59: ='2.1meta'!F151 -> 0 | F59: ='2.1meta'!G244+'2.1meta'!G261 -> 0 | G59: ='2.1meta'!H244+'2.1meta'!H261 -> 0 | H59: ='2.1meta'!I244+'2.1meta'!I261 -> 0 | I59: ='2.1meta'!J244+'2.1meta'!J261 -> 0 | J59: ='2.1meta'!K244+'2.1meta'!K261 -> 0 | K59: ='2.1meta'!L244+'2.1meta'!L261 -> 0 | L59: ='2.1meta'!M244+'2.1meta'!M261 -> 0 | M59: ='2.1meta'!N244+'2.1meta'!N261 -> 0 | N59: ='2.1meta'!O244+'2.1meta'!O261 -> 0 | O59: =SUM(F59:N59) -> 0 | P59: =C59-O59 -> 0 | Q59: ='2.1meta'!R244+'2.1meta'!R261 -> 0 | R59: ='2.1meta'!S244+'2.1meta'!S261 -> 0 | S59: ='2.1meta'!T244+'2.1meta'!T261 -> 0 | T59: ='2.1meta'!U244+'2.1meta'!U261 -> 0 | U59: ='2.1meta'!V244+'2.1meta'!V261 -> 0 | V59: ='2.1meta'!W244+'2.1meta'!W261 -> 0 | W59: ='2.1meta'!X244+'2.1meta'!X261 -> 0 | X59: =SUM(Q59:W59) -> 0 | Y59: =O59+X59 -> 0 | Z59: =C59-Y59 -> 0
A60: 2.1.1.9.1.2 | B60: AGUINALDOS | C60: ='2.1meta'!D232+'2.1meta'!D245+'2.1meta'!D262 -> 0 | D60: ='2.1meta'!E152+'2.1meta'!E296 -> 0 | E60: ='2.1meta'!F152+'2.1meta'!F296 -> 0 | F60: ='2.1meta'!G232+'2.1meta'!G245+'2.1meta'!G262 -> 0 | G60: ='2.1meta'!H232+'2.1meta'!H245+'2.1meta'!H262 -> 0 | H60: ='2.1meta'!I232+'2.1meta'!I245+'2.1meta'!I262 -> 0 | I60: ='2.1meta'!J232+'2.1meta'!J245+'2.1meta'!J262 -> 0 | J60: ='2.1meta'!K232+'2.1meta'!K245+'2.1meta'!K262 -> 0 | K60: ='2.1meta'!L232+'2.1meta'!L245+'2.1meta'!L262 -> 0 | L60: ='2.1meta'!M232+'2.1meta'!M245+'2.1meta'!M262 -> 0 | M60: ='2.1meta'!N232+'2.1meta'!N245+'2.1meta'!N262 -> 0 | N60: ='2.1meta'!O232+'2.1meta'!O245+'2.1meta'!O262 -> 0 | O60: =SUM(F60:N60) -> 0 | P60: =C60-O60 -> 0 | Q60: ='2.1meta'!R232+'2.1meta'!R245+'2.1meta'!R262 -> 0 | R60: ='2.1meta'!S232+'2.1meta'!S245+'2.1meta'!S262 -> 0 | S60: ='2.1meta'!T232+'2.1meta'!T245+'2.1meta'!T262 -> 0 | T60: ='2.1meta'!U232+'2.1meta'!U245+'2.1meta'!U262 -> 0 | U60: ='2.1meta'!V232+'2.1meta'!V245+'2.1meta'!V262 -> 0 | V60: ='2.1meta'!W232+'2.1meta'!W245+'2.1meta'!W262 -> 0 | W60: ='2.1meta'!X232+'2.1meta'!X245+'2.1meta'!X262 -> 0 | X60: =SUM(Q60:W60) -> 0 | Y60: =O60+X60 -> 0 | Z60: =C60-Y60 -> 0
A61: 2.1.1.9.1.3 | B61: BONIFICACION POR ESCOLARIDAD | C61: ='2.1meta'!D233+'2.1meta'!D246+'2.1meta'!D263 -> 0 | D61: ='2.1meta'!E153+'2.1meta'!E297 -> 0 | E61: ='2.1meta'!F153+'2.1meta'!F297 -> 0 | F61: ='2.1meta'!G233+'2.1meta'!G246+'2.1meta'!G263 -> 0 | G61: ='2.1meta'!H233+'2.1meta'!H246+'2.1meta'!H263 -> 0 | H61: ='2.1meta'!I233+'2.1meta'!I246+'2.1meta'!I263 -> 0 | I61: ='2.1meta'!J233+'2.1meta'!J246+'2.1meta'!J263 -> 0 | J61: ='2.1meta'!K233+'2.1meta'!K246+'2.1meta'!K263 -> 0 | K61: ='2.1meta'!L233+'2.1meta'!L246+'2.1meta'!L263 -> 0 | L61: ='2.1meta'!M233+'2.1meta'!M246+'2.1meta'!M263 -> 0 | M61: ='2.1meta'!N233+'2.1meta'!N246+'2.1meta'!N263 -> 0 | N61: ='2.1meta'!O233+'2.1meta'!O246+'2.1meta'!O263 -> 0 | O61: =SUM(F61:N61) -> 0 | P61: =C61-O61 -> 0 | Q61: ='2.1meta'!R233+'2.1meta'!R246+'2.1meta'!R263 -> 0 | R61: ='2.1meta'!S233+'2.1meta'!S246+'2.1meta'!S263 -> 0 | S61: ='2.1meta'!T233+'2.1meta'!T246+'2.1meta'!T263 -> 0 | T61: ='2.1meta'!U233+'2.1meta'!U246+'2.1meta'!U263 -> 0 | U61: ='2.1meta'!V233+'2.1meta'!V246+'2.1meta'!V263 -> 0 | V61: ='2.1meta'!W233+'2.1meta'!W246+'2.1meta'!W263 -> 0 | W61: ='2.1meta'!X233+'2.1meta'!X246+'2.1meta'!X263 -> 0 | X61: =SUM(Q61:W61) -> 0 | Y61: =O61+X61 -> 0 | Z61: =C61-Y61 -> 0
A62: 2.1.1.9.2.1 | B62: COMPENSACION POR TIEMPO DE SERVICIOS (CTS) | C62: ='2.1meta'!D247+'2.1meta'!D264 -> 0 | D62: ='2.1meta'!E154 -> 0 | E62: ='2.1meta'!F154 -> 0 | F62: ='2.1meta'!G247+'2.1meta'!G264 -> 0 | G62: ='2.1meta'!H247+'2.1meta'!H264 -> 0 | H62: ='2.1meta'!I247+'2.1meta'!I264 -> 0 | I62: ='2.1meta'!J247+'2.1meta'!J264 -> 0 | J62: ='2.1meta'!K247+'2.1meta'!K264 -> 0 | K62: ='2.1meta'!L247+'2.1meta'!L264 -> 0 | L62: ='2.1meta'!M247+'2.1meta'!M264 -> 0 | M62: ='2.1meta'!N247+'2.1meta'!N264 -> 0 | N62: ='2.1meta'!O247+'2.1meta'!O264 -> 0 | O62: =SUM(F62:N62) -> 0 | P62: =C62-O62 -> 0 | Q62: ='2.1meta'!R247+'2.1meta'!R264 -> 0 | R62: ='2.1meta'!S247+'2.1meta'!S264 -> 0 | S62: ='2.1meta'!T247+'2.1meta'!T264 -> 0 | T62: ='2.1meta'!U247+'2.1meta'!U264 -> 0 | U62: ='2.1meta'!V247+'2.1meta'!V264 -> 0 | V62: ='2.1meta'!W247+'2.1meta'!W264 -> 0 | W62: ='2.1meta'!X247+'2.1meta'!X264 -> 0 | X62: =SUM(Q62:W62) -> 0 | Y62: =O62+X62 -> 0 | Z62: =C62-Y62 -> 0
A63: 2.1.1.9.3.99 | B63: OTRAS OCASIONALES | C63: ='2.1meta'!D249+'2.1meta'!D266 -> 0 | D63: ='2.1meta'!E156+'2.1meta'!E300 -> 0 | E63: ='2.1meta'!F156+'2.1meta'!F300 -> 0 | F63: ='2.1meta'!G249+'2.1meta'!G266 -> 0 | G63: ='2.1meta'!H249+'2.1meta'!H266 -> 0 | H63: ='2.1meta'!I249+'2.1meta'!I266 -> 0 | I63: ='2.1meta'!J249+'2.1meta'!J266 -> 0 | J63: ='2.1meta'!K249+'2.1meta'!K266 -> 0 | K63: ='2.1meta'!L249+'2.1meta'!L266 -> 0 | L63: ='2.1meta'!M249+'2.1meta'!M266 -> 0 | M63: ='2.1meta'!N249+'2.1meta'!N266 -> 0 | N63: ='2.1meta'!O249+'2.1meta'!O266 -> 0 | O63: =SUM(F63:N63) -> 0 | P63: =C63-O63 -> 0 | Q63: ='2.1meta'!R249+'2.1meta'!R266 -> 0 | R63: ='2.1meta'!S249+'2.1meta'!S266 -> 0 | S63: ='2.1meta'!T249+'2.1meta'!T266 -> 0 | T63: ='2.1meta'!U249+'2.1meta'!U266 -> 0 | U63: ='2.1meta'!V249+'2.1meta'!V266 -> 0 | V63: ='2.1meta'!W249+'2.1meta'!W266 -> 0 | W63: ='2.1meta'!X249+'2.1meta'!X266 -> 0 | X63: =SUM(Q63:W63) -> 0 | Y63: =O63+X63 -> 0 | Z63: =C63-Y63 -> 0
A64: 2.1.3.1.1.1 | B64: APORTES A LOS FONDOS DE SALUD | C64: ='2.1meta'!D234+'2.1meta'!D250+'2.1meta'!D267 -> 0 | D64: ='2.1meta'!E157+'2.1meta'!E301 -> 0 | E64: ='2.1meta'!F157+'2.1meta'!F301 -> 0 | F64: ='2.1meta'!G234+'2.1meta'!G250+'2.1meta'!G267 -> 0 | G64: ='2.1meta'!H234+'2.1meta'!H250+'2.1meta'!H267 -> 0 | H64: ='2.1meta'!I234+'2.1meta'!I250+'2.1meta'!I267 -> 0 | I64: ='2.1meta'!J234+'2.1meta'!J250+'2.1meta'!J267 -> 0 | J64: ='2.1meta'!K234+'2.1meta'!K250+'2.1meta'!K267 -> 0 | K64: ='2.1meta'!L234+'2.1meta'!L250+'2.1meta'!L267 -> 0 | L64: ='2.1meta'!M234+'2.1meta'!M250+'2.1meta'!M267 -> 0 | M64: ='2.1meta'!N234+'2.1meta'!N250+'2.1meta'!N267 -> 0 | N64: ='2.1meta'!O234+'2.1meta'!O250+'2.1meta'!O267 -> 0 | O64: =SUM(F64:N64) -> 0 | P64: =C64-O64 -> 0 | Q64: ='2.1meta'!R234+'2.1meta'!R250+'2.1meta'!R267 -> 0 | R64: ='2.1meta'!S234+'2.1meta'!S250+'2.1meta'!S267 -> 0 | S64: ='2.1meta'!T234+'2.1meta'!T250+'2.1meta'!T267 -> 0 | T64: ='2.1meta'!U234+'2.1meta'!U250+'2.1meta'!U267 -> 0 | U64: ='2.1meta'!V234+'2.1meta'!V250+'2.1meta'!V267 -> 0 | V64: ='2.1meta'!W234+'2.1meta'!W250+'2.1meta'!W267 -> 0 | W64: ='2.1meta'!X234+'2.1meta'!X250+'2.1meta'!X267 -> 0 | X64: =SUM(Q64:W64) -> 0 | Y64: =O64+X64 -> 0 | Z64: =C64-Y64 -> 0
A65: 2.1.3.1.1.3 | B65: APORTES A LOS FONDOS DE PENSIONES | C65: ='2.1meta'!D251+'2.1meta'!D268 -> 0 | D65: ='2.1meta'!E158+'2.1meta'!E302 -> 0 | E65: ='2.1meta'!F158+'2.1meta'!F302 -> 0 | F65: ='2.1meta'!G251+'2.1meta'!G268 -> 0 | G65: ='2.1meta'!H251+'2.1meta'!H268 -> 0 | H65: ='2.1meta'!I251+'2.1meta'!I268 -> 0 | I65: ='2.1meta'!J251+'2.1meta'!J268 -> 0 | J65: ='2.1meta'!K251+'2.1meta'!K268 -> 0 | K65: ='2.1meta'!L251+'2.1meta'!L268 -> 0 | L65: ='2.1meta'!M251+'2.1meta'!M268 -> 0 | M65: ='2.1meta'!N251+'2.1meta'!N268 -> 0 | N65: ='2.1meta'!O251+'2.1meta'!O268 -> 0 | O65: =SUM(F65:N65) -> 0 | P65: =C65-O65 -> 0 | Q65: ='2.1meta'!R251+'2.1meta'!R268 -> 0 | R65: ='2.1meta'!S251+'2.1meta'!S268 -> 0 | S65: ='2.1meta'!T251+'2.1meta'!T268 -> 0 | T65: ='2.1meta'!U251+'2.1meta'!U268 -> 0 | U65: ='2.1meta'!V251+'2.1meta'!V268 -> 0 | V65: ='2.1meta'!W251+'2.1meta'!W268 -> 0 | W65: ='2.1meta'!X251+'2.1meta'!X268 -> 0 | X65: =SUM(Q65:W65) -> 0 | Y65: =O65+X65 -> 0 | Z65: =C65-Y65 -> 0
A66: 2.1.3.1.1.5 | B66: CONTRIBUCIONES A ESSALUD | C66: ='2.1meta'!D235+'2.1meta'!D252+'2.1meta'!D269 -> 0 | D66: ='2.1meta'!E159+'2.1meta'!E303 -> 0 | E66: ='2.1meta'!F159+'2.1meta'!F303 -> 0 | F66: ='2.1meta'!G235+'2.1meta'!G252+'2.1meta'!G269 -> 0 | G66: ='2.1meta'!H235+'2.1meta'!H252+'2.1meta'!H269 -> 0 | H66: ='2.1meta'!I235+'2.1meta'!I252+'2.1meta'!I269 -> 0 | I66: ='2.1meta'!J235+'2.1meta'!J252+'2.1meta'!J269 -> 0 | J66: ='2.1meta'!K235+'2.1meta'!K252+'2.1meta'!K269 -> 0 | K66: ='2.1meta'!L235+'2.1meta'!L252+'2.1meta'!L269 -> 0 | L66: ='2.1meta'!M235+'2.1meta'!M252+'2.1meta'!M269 -> 0 | M66: ='2.1meta'!N235+'2.1meta'!N252+'2.1meta'!N269 -> 0 | N66: ='2.1meta'!O235+'2.1meta'!O252+'2.1meta'!O269 -> 0 | O66: =SUM(F66:N66) -> 0 | P66: =C66-O66 -> 0 | Q66: ='2.1meta'!R235+'2.1meta'!R252+'2.1meta'!R269 -> 0 | R66: ='2.1meta'!S235+'2.1meta'!S252+'2.1meta'!S269 -> 0 | S66: ='2.1meta'!T235+'2.1meta'!T252+'2.1meta'!T269 -> 0 | T66: ='2.1meta'!U235+'2.1meta'!U252+'2.1meta'!U269 -> 0 | U66: ='2.1meta'!V235+'2.1meta'!V252+'2.1meta'!V269 -> 0 | V66: ='2.1meta'!W235+'2.1meta'!W252+'2.1meta'!W269 -> 0 | W66: ='2.1meta'!X235+'2.1meta'!X252+'2.1meta'!X269 -> 0 | X66: =SUM(Q66:W66) -> 0 | Y66: =O66+X66 -> 0 | Z66: =C66-Y66 -> 0
A67: TOTAL 2.1 PERSONAL Y OB. SOCIALES | C67: =SUBTOTAL(9,C5:C66) -> 0 | F67: =SUBTOTAL(9,F5:F66) -> 0 | G67: =SUBTOTAL(9,G5:G66) -> 0 | H67: =SUBTOTAL(9,H5:H66) -> 0 | I67: =SUBTOTAL(9,I5:I66) -> 0 | J67: =SUBTOTAL(9,J5:J66) -> 0 | K67: =SUBTOTAL(9,K5:K66) -> 0 | L67: =SUBTOTAL(9,L5:L66) -> 0 | M67: =SUBTOTAL(9,M5:M66) -> 0 | ... O67: =SUBTOTAL(9,O5:O66) -> 0 | P67: =C67-O67 -> 0 | Q67: =SUBTOTAL(9,Q5:Q66) -> 0 | R67: =SUBTOTAL(9,R5:R66) -> 0 | S67: =SUBTOTAL(9,S5:S66) -> 0 | T67: =SUBTOTAL(9,T5:T66) -> 0 | U67: =SUBTOTAL(9,U5:U66) -> 0 | V67: =SUBTOTAL(9,V5:V66) -> 0 | W67: =SUBTOTAL(9,W5:W66) -> 0 | X67: =SUBTOTAL(9,X5:X66) -> 0 | ... Z67: =SUBTOTAL(9,Z5:Z66) -> 0

Sheet ESPECIFICA DE GASTO
A1: EJECUTORA: 0003 MINISTERIO PUBLICO - GERENCIA ADMINISTRATIVA DE AREQUIPA (1419)
A3: Cat pptal/ Detalle Específica de Gasto | C3: PIM | D3: Certificado | E3: Compromiso Anual | F3: Ejecución Devengado UE | O3: T O T A L | P3: Saldo Presupuestal al 17.09.2021 | T3: Proyeccion de plazas vacantes | V3: PAGO FACTURAS EPS | W3: BENEFICIOS | X3: TOTAL PROYECCION | Y3: TOTAL EJECUCION +PROYECCION | Z3: SALDO DISPONIBLE
F4: 01 ENERO | G4: 02 FEBRERO | H4: 03 MARZO | I4: 04 ABRIL | J4: 05 MAYO | K4: 06 JUNIO | L4: 07 JULIO | M4: 08 AGOSTO | N4: 09 SETIEMBRE | Q4: 10 OCTUBRE | R4: 11 NOVIEMBRE | S4: 12 DICIEMBRE | T4: 276 | U4: 728
A5: 2.1.1.1.1.2 | B5: PERSONAL ADMINISTRATIVO NOMBRADO (REGIMEN PUBLICO) | C5: ='2.1meta'!D7+'2.1meta'!D24+'2.1meta'!D41+'2.1meta'!D58+'2.1meta'!D76+'2.1meta'!D93+'2.1meta'!D110+'2.1meta'!D127+'2.1meta'!D144+'2.1meta'!D161++'2.1meta'!D178+'2.1meta'!D195+'2.1meta'!D212+'2.1meta'!D237+'2.1meta'!D254+'2.1meta'!D271+'2.1meta'!D288+'2.1meta'!D305+'2.1meta'!D322 -> 0 | D5: ='2.1meta'!E7+'2.1meta'!E24+'2.1meta'!E41+'2.1meta'!E58+'2.1meta'!E76+'2.1meta'!E93+'2.1meta'!E110+'2.1meta'!E127+'2.1meta'!E144+'2.1meta'!E161++'2.1meta'!E178+'2.1meta'!E195+'2.1meta'!E212+'2.1meta'!E237+'2.1meta'!E254+'2.1meta'!E271+'2.1meta'!E288+'2.1meta'!E305+'2.1meta'!E322 -> 0 | E5: ='2.1meta'!F7+'2.1meta'!F24+'2.1meta'!F41+'2.1meta'!F58+'2.1meta'!F76+'2.1meta'!F93+'2.1meta'!F110+'2.1meta'!F127+'2.1meta'!F144+'2.1meta'!F161++'2.1meta'!F178+'2.1meta'!F195+'2.1meta'!F212+'2.1meta'!F237+'2.1meta'!F254+'2.1meta'!F271+'2.1meta'!F288+'2.1meta'!F305+'2.1meta'!F322 -> 0 | F5: ='2.1meta'!G7+'2.1meta'!G24+'2.1meta'!G41+'2.1meta'!G58+'2.1meta'!G76+'2.1meta'!G93+'2.1meta'!G110+'2.1meta'!G127+'2.1meta'!G144+'2.1meta'!G161++'2.1meta'!G178+'2.1meta'!G195+'2.1meta'!G212+'2.1meta'!G237+'2.1meta'!G254+'2.1meta'!G271+'2.1meta'!G288+'2.1meta'!G305+'2.1meta'!G322 -> 0 | G5: ='2.1meta'!H7+'2.1meta'!H24+'2.1meta'!H41+'2.1meta'!H58+'2.1meta'!H76+'2.1meta'!H93+'2.1meta'!H110+'2.1meta'!H127+'2.1meta'!H144+'2.1meta'!H161++'2.1meta'!H178+'2.1meta'!H195+'2.1meta'!H212+'2.1meta'!H237+'2.1meta'!H254+'2.1meta'!H271+'2.1meta'!H288+'2.1meta'!H305+'2.1meta'!H322 -> 0 | H5: ='2.1meta'!I7+'2.1meta'!I24+'2.1meta'!I41+'2.1meta'!I58+'2.1meta'!I76+'2.1meta'!I93+'2.1meta'!I110+'2.1meta'!I127+'2.1meta'!I144+'2.1meta'!I161++'2.1meta'!I178+'2.1meta'!I195+'2.1meta'!I212+'2.1meta'!I237+'2.1meta'!I254+'2.1meta'!I271+'2.1meta'!I288+'2.1meta'!I305+'2.1meta'!I322 -> 0 | I5: ='2.1meta'!J7+'2.1meta'!J24+'2.1meta'!J41+'2.1meta'!J58+'2.1meta'!J76+'2.1meta'!J93+'2.1meta'!J110+'2.1meta'!J127+'2.1meta'!J144+'2.1meta'!J161++'2.1meta'!J178+'2.1meta'!J195+'2.1meta'!J212+'2.1meta'!J237+'2.1meta'!J254+'2.1meta'!J271+'2.1meta'!J288+'2.1meta'!J305+'2.1meta'!J322 -> 0 | J5: ='2.1meta'!K7+'2.1meta'!K24+'2.1meta'!K41+'2.1meta'!K58+'2.1meta'!K76+'2.1meta'!K93+'2.1meta'!K110+'2.1meta'!K127+'2.1meta'!K144+'2.1meta'!K161++'2.1meta'!K178+'2.1meta'!K195+'2.1meta'!K212+'2.1meta'!K237+'2.1meta'!K254+'2.1meta'!K271+'2.1meta'!K288+'2.1meta'!K305+'2.1meta'!K322 -> 0 | ... N5: ='2.1meta'!O7+'2.1meta'!O24+'2.1meta'!O41+'2.1meta'!O58+'2.1meta'!O76+'2.1meta'!O93+'2.1meta'!O110+'2.1meta'!O127+'2.1meta'!O144+'2.1meta'!O161++'2.1meta'!O178+'2.1meta'!O195+'2.1meta'!O212+'2.1meta'!O237+'2.1meta'!O254+'2.1meta'!O271+'2.1meta'!O288+'2.1meta'!O305+'2.1meta'!O322 -> 0 | O5: =SUM(F5:N5) -> 0 | P5: =C5-O5 -> 0 | Q5: ='2.1meta'!R7+'2.1meta'!R24+'2.1meta'!R41+'2.1meta'!R58+'2.1meta'!R76+'2.1meta'!R93+'2.1meta'!R110+'2.1meta'!R127+'2.1meta'!R144+'2.1meta'!R161++'2.1meta'!R178+'2.1meta'!R195+'2.1meta'!R212+'2.1meta'!R237+'2.1meta'!R254+'2.1meta'!R271+'2.1meta'!R288+'2.1meta'!R305+'2.1meta'!R322 -> 0 | R5: ='2.1meta'!S7+'2.1meta'!S24+'2.1meta'!S41+'2.1meta'!S58+'2.1meta'!S76+'2.1meta'!S93+'2.1meta'!S110+'2.1meta'!S127+'2.1meta'!S144+'2.1meta'!S161++'2.1meta'!S178+'2.1meta'!S195+'2.1meta'!S212+'2.1meta'!S237+'2.1meta'!S254+'2.1meta'!S271+'2.1meta'!S288+'2.1meta'!S305+'2.1meta'!S322 -> 0 | S5: ='2.1meta'!T7+'2.1meta'!T24+'2.1meta'!T41+'2.1meta'!T58+'2.1meta'!T76+'2.1meta'!T93+'2.1meta'!T110+'2.1meta'!T127+'2.1meta'!T144+'2.1meta'!T161++'2.1meta'!T178+'2.1meta'!T195+'2.1meta'!T212+'2.1meta'!T237+'2.1meta'!T254+'2.1meta'!T271+'2.1meta'!T288+'2.1meta'!T305+'2.1meta'!T322 -> 0 | T5: ='2.1meta'!U7+'2.1meta'!U24+'2.1meta'!U41+'2.1meta'!U58+'2.1meta'!U76+'2.1meta'!U93+'2.1meta'!U110+'2.1meta'!U127+'2.1meta'!U144+'2.1meta'!U161++'2.1meta'!U178+'2.1meta'!U195+'2.1meta'!U212+'2.1meta'!U237+'2.1meta'!U254+'2.1meta'!U271+'2.1meta'!U288+'2.1meta'!U305+'2.1meta'!U322 -> 0 | U5: ='2.1meta'!V7+'2.1meta'!V24+'2.1meta'!V41+'2.1meta'!V58+'2.1meta'!V76+'2.1meta'!V93+'2.1meta'!V110+'2.1meta'!V127+'2.1meta'!V144+'2.1meta'!V161++'2.1meta'!V178+'2.1meta'!V195+'2.1meta'!V212+'2.1meta'!V237+'2.1meta'!V254+'2.1meta'!V271+'2.1meta'!V288+'2.1meta'!V305+'2.1meta'!V322 -> 0 | V5: ='2.1meta'!W7+'2.1meta'!W24+'2.1meta'!W41+'2.1meta'!W58+'2.1meta'!W76+'2.1meta'!W93+'2.1meta'!W110+'2.1meta'!W127+'2.1meta'!W144+'2.1meta'!W161++'2.1meta'!W178+'2.1meta'!W195+'2.1meta'!W212+'2.1meta'!W237+'2.1meta'!W254+'2.1meta'!W271+'2.1meta'!W288+'2.1meta'!W305+'2.1meta'!W322 -> 0 | W5: ='2.1meta'!X7+'2.1meta'!X24+'2.1meta'!X41+'2.1meta'!X58+'2.1meta'!X76+'2.1meta'!X93+'2.1meta'!X110+'2.1meta'!X127+'2.1meta'!X144+'2.1meta'!X161++'2.1meta'!X178+'2.1meta'!X195+'2.1meta'!X212+'2.1meta'!X237+'2.1meta'!X254+'2.1meta'!X271+'2.1meta'!X288+'2.1meta'!X305+'2.1meta'!X322 -> 0 | X5: =SUM(Q5:W5) -> 0 | Y5: =O5+X5 -> 0 | Z5: =C5-Y5 -> 0
A6: 2.1.1.1.1.4 | B6: PERSONAL CON CONTRATO A PLAZO INDETERMINADO (REGIMEN LABORAL PRIVADO) | C6: ='2.1meta'!D8+'2.1meta'!D25+'2.1meta'!D42+'2.1meta'!D59+'2.1meta'!D77+'2.1meta'!D94+'2.1meta'!D111+'2.1meta'!D128+'2.1meta'!D145+'2.1meta'!D162++'2.1meta'!D179+'2.1meta'!D196+'2.1meta'!D213+'2.1meta'!D238+'2.1meta'!D255+'2.1meta'!D272+'2.1meta'!D289+'2.1meta'!D306+'2.1meta'!D323 -> 0 | D6: ='2.1meta'!E8+'2.1meta'!E25+'2.1meta'!E42+'2.1meta'!E59+'2.1meta'!E77+'2.1meta'!E94+'2.1meta'!E111+'2.1meta'!E128+'2.1meta'!E145+'2.1meta'!E162++'2.1meta'!E179+'2.1meta'!E196+'2.1meta'!E213+'2.1meta'!E238+'2.1meta'!E255+'2.1meta'!E272+'2.1meta'!E289+'2.1meta'!E306+'2.1meta'!E323 -> 0 | E6: ='2.1meta'!F8+'2.1meta'!F25+'2.1meta'!F42+'2.1meta'!F59+'2.1meta'!F77+'2.1meta'!F94+'2.1meta'!F111+'2.1meta'!F128+'2.1meta'!F145+'2.1meta'!F162++'2.1meta'!F179+'2.1meta'!F196+'2.1meta'!F213+'2.1meta'!F238+'2.1meta'!F255+'2.1meta'!F272+'2.1meta'!F289+'2.1meta'!F306+'2.1meta'!F323 -> 0 | F6: ='2.1meta'!G8+'2.1meta'!G25+'2.1meta'!G42+'2.1meta'!G59+'2.1meta'!G77+'2.1meta'!G94+'2.1meta'!G111+'2.1meta'!G128+'2.1meta'!G145+'2.1meta'!G162++'2.1meta'!G179+'2.1meta'!G196+'2.1meta'!G213+'2.1meta'!G238+'2.1meta'!G255+'2.1meta'!G272+'2.1meta'!G289+'2.1meta'!G306+'2.1meta'!G323 -> 0 | G6: ='2.1meta'!H8+'2.1meta'!H25+'2.1meta'!H42+'2.1meta'!H59+'2.1meta'!H77+'2.1meta'!H94+'2.1meta'!H111+'2.1meta'!H128+'2.1meta'!H145+'2.1meta'!H162++'2.1meta'!H179+'2.1meta'!H196+'2.1meta'!H213+'2.1meta'!H238+'2.1meta'!H255+'2.1meta'!H272+'2.1meta'!H289+'2.1meta'!H306+'2.1meta'!H323 -> 0 | H6: ='2.1meta'!I8+'2.1meta'!I25+'2.1meta'!I42+'2.1meta'!I59+'2.1meta'!I77+'2.1meta'!I94+'2.1meta'!I111+'2.1meta'!I128+'2.1meta'!I145+'2.1meta'!I162++'2.1meta'!I179+'2.1meta'!I196+'2.1meta'!I213+'2.1meta'!I238+'2.1meta'!I255+'2.1meta'!I272+'2.1meta'!I289+'2.1meta'!I306+'2.1meta'!I323 -> 0 | I6: ='2.1meta'!J8+'2.1meta'!J25+'2.1meta'!J42+'2.1meta'!J59+'2.1meta'!J77+'2.1meta'!J94+'2.1meta'!J111+'2.1meta'!J128+'2.1meta'!J145+'2.1meta'!J162++'2.1meta'!J179+'2.1meta'!J196+'2.1meta'!J213+'2.1meta'!J238+'2.1meta'!J255+'2.1meta'!J272+'2.1meta'!J289+'2.1meta'!J306+'2.1meta'!J323 -> 0 | J6: ='2.1meta'!K8+'2.1meta'!K25+'2.1meta'!K42+'2.1meta'!K59+'2.1meta'!K77+'2.1meta'!K94+'2.1meta'!K111+'2.1meta'!K128+'2.1meta'!K145+'2.1meta'!K162++'2.1meta'!K179+'2.1meta'!K196+'2.1meta'!K213+'2.1meta'!K238+'2.1meta'!K255+'2.1meta'!K272+'2.1meta'!K289+'2.1meta'!K306+'2.1meta'!K323 -> 0 | ... N6: ='2.1meta'!O8+'2.1meta'!O25+'2.1meta'!O42+'2.1meta'!O59+'2.1meta'!O77+'2.1meta'!O94+'2.1meta'!O111+'2.1meta'!O128+'2.1meta'!O145+'2.1meta'!O162++'2.1meta'!O179+'2.1meta'!O196+'2.1meta'!O213+'2.1meta'!O238+'2.1meta'!O255+'2.1meta'!O272+'2.1meta'!O289+'2.1meta'!O306+'2.1meta'!O323 -> 0 | O6: =SUM(F6:N6) -> 0 | P6: =C6-O6 -> 0 | Q6: ='2.1meta'!R8+'2.1meta'!R25+'2.1meta'!R42+'2.1meta'!R59+'2.1meta'!R77+'2.1meta'!R94+'2.1meta'!R111+'2.1meta'!R128+'2.1meta'!R145+'2.1meta'!R162++'2.1meta'!R179+'2.1meta'!R196+'2.1meta'!R213+'2.1meta'!R238+'2.1meta'!R255+'2.1meta'!R272+'2.1meta'!R289+'2.1meta'!R306+'2.1meta'!R323 -> 0 | R6: ='2.1meta'!S8+'2.1meta'!S25+'2.1meta'!S42+'2.1meta'!S59+'2.1meta'!S77+'2.1meta'!S94+'2.1meta'!S111+'2.1meta'!S128+'2.1meta'!S145+'2.1meta'!S162++'2.1meta'!S179+'2.1meta'!S196+'2.1meta'!S213+'2.1meta'!S238+'2.1meta'!S255+'2.1meta'!S272+'2.1meta'!S289+'2.1meta'!S306+'2.1meta'!S323 -> 0 | S6: ='2.1meta'!T8+'2.1meta'!T25+'2.1meta'!T42+'2.1meta'!T59+'2.1meta'!T77+'2.1meta'!T94+'2.1meta'!T111+'2.1meta'!T128+'2.1meta'!T145+'2.1meta'!T162++'2.1meta'!T179+'2.1meta'!T196+'2.1meta'!T213+'2.1meta'!T238+'2.1meta'!T255+'2.1meta'!T272+'2.1meta'!T289+'2.1meta'!T306+'2.1meta'!T323 -> 0 | T6: ='2.1meta'!U8+'2.1meta'!U25+'2.1meta'!U42+'2.1meta'!U59+'2.1meta'!U77+'2.1meta'!U94+'2.1meta'!U111+'2.1meta'!U128+'2.1meta'!U145+'2.1meta'!U162++'2.1meta'!U179+'2.1meta'!U196+'2.1meta'!U213+'2.1meta'!U238+'2.1meta'!U255+'2.1meta'!U272+'2.1meta'!U289+'2.1meta'!U306+'2.1meta'!U323 -> 0 | U6: ='2.1meta'!V8+'2.1meta'!V25+'2.1meta'!V42+'2.1meta'!V59+'2.1meta'!V77+'2.1meta'!V94+'2.1meta'!V111+'2.1meta'!V128+'2.1meta'!V145+'2.1meta'!V162++'2.1meta'!V179+'2.1meta'!V196+'2.1meta'!V213+'2.1meta'!V238+'2.1meta'!V255+'2.1meta'!V272+'2.1meta'!V289+'2.1meta'!V306+'2.1meta'!V323 -> 0 | V6: ='2.1meta'!W8+'2.1meta'!W25+'2.1meta'!W42+'2.1meta'!W59+'2.1meta'!W77+'2.1meta'!W94+'2.1meta'!W111+'2.1meta'!W128+'2.1meta'!W145+'2.1meta'!W162++'2.1meta'!W179+'2.1meta'!W196+'2.1meta'!W213+'2.1meta'!W238+'2.1meta'!W255+'2.1meta'!W272+'2.1meta'!W289+'2.1meta'!W306+'2.1meta'!W323 -> 0 | W6: ='2.1meta'!X8+'2.1meta'!X25+'2.1meta'!X42+'2.1meta'!X59+'2.1meta'!X77+'2.1meta'!X94+'2.1meta'!X111+'2.1meta'!X128+'2.1meta'!X145+'2.1meta'!X162++'2.1meta'!X179+'2.1meta'!X196+'2.1meta'!X213+'2.1meta'!X238+'2.1meta'!X255+'2.1meta'!X272+'2.1meta'!X289+'2.1meta'!X306+'2.1meta'!X323 -> 0 | X6: =SUM(Q6:W6) -> 0 | Y6: =O6+X6 -> 0 | Z6: =C6-Y6 -> 0
A7: 2.1.1.1.1.5 | B7: PERSONAL CON CONTRATO A PLAZO FIJO (REGIMEN LABORAL PRIVADO) | C7: ='2.1meta'!D9+'2.1meta'!D26+'2.1meta'!D43+'2.1meta'!D60+'2.1meta'!D78+'2.1meta'!D95+'2.1meta'!D112+'2.1meta'!D129+'2.1meta'!D146+'2.1meta'!D163+'2.1meta'!D180+'2.1meta'!D197+'2.1meta'!D214+'2.1meta'!D239+'2.1meta'!D256+'2.1meta'!D273+'2.1meta'!D290+'2.1meta'!D307+'2.1meta'!D324 -> 0 | D7: ='2.1meta'!E9+'2.1meta'!E26+'2.1meta'!E43+'2.1meta'!E60+'2.1meta'!E78+'2.1meta'!E95+'2.1meta'!E112+'2.1meta'!E129+'2.1meta'!E146+'2.1meta'!E163+'2.1meta'!E180+'2.1meta'!E197+'2.1meta'!E214+'2.1meta'!E239+'2.1meta'!E256+'2.1meta'!E273+'2.1meta'!E290+'2.1meta'!E307+'2.1meta'!E324 -> 0 | E7: ='2.1meta'!F9+'2.1meta'!F26+'2.1meta'!F43+'2.1meta'!F60+'2.1meta'!F78+'2.1meta'!F95+'2.1meta'!F112+'2.1meta'!F129+'2.1meta'!F146+'2.1meta'!F163+'2.1meta'!F180+'2.1meta'!F197+'2.1meta'!F214+'2.1meta'!F239+'2.1meta'!F256+'2.1meta'!F273+'2.1meta'!F290+'2.1meta'!F307+'2.1meta'!F324 -> 0 | F7: ='2.1meta'!G9+'2.1meta'!G26+'2.1meta'!G43+'2.1meta'!G60+'2.1meta'!G78+'2.1meta'!G95+'2.1meta'!G112+'2.1meta'!G129+'2.1meta'!G146+'2.1meta'!G163+'2.1meta'!G180+'2.1meta'!G197+'2.1meta'!G214+'2.1meta'!G239+'2.1meta'!G256+'2.1meta'!G273+'2.1meta'!G290+'2.1meta'!G307+'2.1meta'!G324 -> 0 | G7: ='2.1meta'!H9+'2.1meta'!H26+'2.1meta'!H43+'2.1meta'!H60+'2.1meta'!H78+'2.1meta'!H95+'2.1meta'!H112+'2.1meta'!H129+'2.1meta'!H146+'2.1meta'!H163+'2.1meta'!H180+'2.1meta'!H197+'2.1meta'!H214+'2.1meta'!H239+'2.1meta'!H256+'2.1meta'!H273+'2.1meta'!H290+'2.1meta'!H307+'2.1meta'!H324 -> 0 | H7: ='2.1meta'!I9+'2.1meta'!I26+'2.1meta'!I43+'2.1meta'!I60+'2.1meta'!I78+'2.1meta'!I95+'2.1meta'!I112+'2.1meta'!I129+'2.1meta'!I146+'2.1meta'!I163+'2.1meta'!I180+'2.1meta'!I197+'2.1meta'!I214+'2.1meta'!I239+'2.1meta'!I256+'2.1meta'!I273+'2.1meta'!I290+'2.1meta'!I307+'2.1meta'!I324 -> 0 | I7: ='2.1meta'!J9+'2.1meta'!J26+'2.1meta'!J43+'2.1meta'!J60+'2.1meta'!J78+'2.1meta'!J95+'2.1meta'!J112+'2.1meta'!J129+'2.1meta'!J146+'2.1meta'!J163+'2.1meta'!J180+'2.1meta'!J197+'2.1meta'!J214+'2.1meta'!J239+'2.1meta'!J256+'2.1meta'!J273+'2.1meta'!J290+'2.1meta'!J307+'2.1meta'!J324 -> 0 | J7: ='2.1meta'!K9+'2.1meta'!K26+'2.1meta'!K43+'2.1meta'!K60+'2.1meta'!K78+'2.1meta'!K95+'2.1meta'!K112+'2.1meta'!K129+'2.1meta'!K146+'2.1meta'!K163+'2.1meta'!K180+'2.1meta'!K197+'2.1meta'!K214+'2.1meta'!K239+'2.1meta'!K256+'2.1meta'!K273+'2.1meta'!K290+'2.1meta'!K307+'2.1meta'!K324 -> 0 | ... N7: ='2.1meta'!O9+'2.1meta'!O26+'2.1meta'!O43+'2.1meta'!O60+'2.1meta'!O78+'2.1meta'!O95+'2.1meta'!O112+'2.1meta'!O129+'2.1meta'!O146+'2.1meta'!O163+'2.1meta'!O180+'2.1meta'!O197+'2.1meta'!O214+'2.1meta'!O239+'2.1meta'!O256+'2.1meta'!O273+'2.1meta'!O290+'2.1meta'!O307+'2.1meta'!O324 -> 0 | O7: =SUM(F7:N7) -> 0 | P7: =C7-O7 -> 0 | Q7: ='2.1meta'!R9+'2.1meta'!R26+'2.1meta'!R43+'2.1meta'!R60+'2.1meta'!R78+'2.1meta'!R95+'2.1meta'!R112+'2.1meta'!R129+'2.1meta'!R146+'2.1meta'!R163+'2.1meta'!R180+'2.1meta'!R197+'2.1meta'!R214+'2.1meta'!R239+'2.1meta'!R256+'2.1meta'!R273+'2.1meta'!R290+'2.1meta'!R307+'2.1meta'!R324 -> 0 | R7: ='2.1meta'!S9+'2.1meta'!S26+'2.1meta'!S43+'2.1meta'!S60+'2.1meta'!S78+'2.1meta'!S95+'2.1meta'!S112+'2.1meta'!S129+'2.1meta'!S146+'2.1meta'!S163+'2.1meta'!S180+'2.1meta'!S197+'2.1meta'!S214+'2.1meta'!S239+'2.1meta'!S256+'2.1meta'!S273+'2.1meta'!S290+'2.1meta'!S307+'2.1meta'!S324 -> 0 | S7: ='2.1meta'!T9+'2.1meta'!T26+'2.1meta'!T43+'2.1meta'!T60+'2.1meta'!T78+'2.1meta'!T95+'2.1meta'!T112+'2.1meta'!T129+'2.1meta'!T146+'2.1meta'!T163+'2.1meta'!T180+'2.1meta'!T197+'2.1meta'!T214+'2.1meta'!T239+'2.1meta'!T256+'2.1meta'!T273+'2.1meta'!T290+'2.1meta'!T307+'2.1meta'!T324 -> 0 | T7: ='2.1meta'!U9+'2.1meta'!U26+'2.1meta'!U43+'2.1meta'!U60+'2.1meta'!U78+'2.1meta'!U95+'2.1meta'!U112+'2.1meta'!U129+'2.1meta'!U146+'2.1meta'!U163+'2.1meta'!U180+'2.1meta'!U197+'2.1meta'!U214+'2.1meta'!U239+'2.1meta'!U256+'2.1meta'!U273+'2.1meta'!U290+'2.1meta'!U307+'2.1meta'!U324 -> 0 | U7: ='2.1meta'!V9+'2.1meta'!V26+'2.1meta'!V43+'2.1meta'!V60+'2.1meta'!V78+'2.1meta'!V95+'2.1meta'!V112+'2.1meta'!V129+'2.1meta'!V146+'2.1meta'!V163+'2.1meta'!V180+'2.1meta'!V197+'2.1meta'!V214+'2.1meta'!V239+'2.1meta'!V256+'2.1meta'!V273+'2.1meta'!V290+'2.1meta'!V307+'2.1meta'!V324 -> 0 | V7: ='2.1meta'!W9+'2.1meta'!W26+'2.1meta'!W43+'2.1meta'!W60+'2.1meta'!W78+'2.1meta'!W95+'2.1meta'!W112+'2.1meta'!W129+'2.1meta'!W146+'2.1meta'!W163+'2.1meta'!W180+'2.1meta'!W197+'2.1meta'!W214+'2.1meta'!W239+'2.1meta'!W256+'2.1meta'!W273+'2.1meta'!W290+'2.1meta'!W307+'2.1meta'!W324 -> 0 | W7: ='2.1meta'!X9+'2.1meta'!X26+'2.1meta'!X43+'2.1meta'!X60+'2.1meta'!X78+'2.1meta'!X95+'2.1meta'!X112+'2.1meta'!X129+'2.1meta'!X146+'2.1meta'!X163+'2.1meta'!X180+'2.1meta'!X197+'2.1meta'!X214+'2.1meta'!X239+'2.1meta'!X256+'2.1meta'!X273+'2.1meta'!X290+'2.1meta'!X307+'2.1meta'!X324 -> 0 | X7: =SUM(Q7:W7) -> 0 | Y7: =O7+X7 -> 0 | Z7: =C7-Y7 -> 0
A8: 2.1.1.1.2.1 | B8: ASIGNACION A FONDOS PARA PERSONAL | C8: ='2.1meta'!D10+'2.1meta'!D27+'2.1meta'!D44+'2.1meta'!D61+'2.1meta'!D79+'2.1meta'!D96+'2.1meta'!D113+'2.1meta'!D130+'2.1meta'!D147+'2.1meta'!D164++'2.1meta'!D181+'2.1meta'!D198+'2.1meta'!D215+'2.1meta'!D240+'2.1meta'!D257+'2.1meta'!D274+'2.1meta'!D291+'2.1meta'!D308+'2.1meta'!D325 -> 0 | D8: ='2.1meta'!E10+'2.1meta'!E27+'2.1meta'!E44+'2.1meta'!E61+'2.1meta'!E79+'2.1meta'!E96+'2.1meta'!E113+'2.1meta'!E130+'2.1meta'!E147+'2.1meta'!E164++'2.1meta'!E181+'2.1meta'!E198+'2.1meta'!E215+'2.1meta'!E240+'2.1meta'!E257+'2.1meta'!E274+'2.1meta'!E291+'2.1meta'!E308+'2.1meta'!E325 -> 0 | E8: ='2.1meta'!F10+'2.1meta'!F27+'2.1meta'!F44+'2.1meta'!F61+'2.1meta'!F79+'2.1meta'!F96+'2.1meta'!F113+'2.1meta'!F130+'2.1meta'!F147+'2.1meta'!F164++'2.1meta'!F181+'2.1meta'!F198+'2.1meta'!F215+'2.1meta'!F240+'2.1meta'!F257+'2.1meta'!F274+'2.1meta'!F291+'2.1meta'!F308+'2.1meta'!F325 -> 0 | F8: ='2.1meta'!G10+'2.1meta'!G27+'2.1meta'!G44+'2.1meta'!G61+'2.1meta'!G79+'2.1meta'!G96+'2.1meta'!G113+'2.1meta'!G130+'2.1meta'!G147+'2.1meta'!G164++'2.1meta'!G181+'2.1meta'!G198+'2.1meta'!G215+'2.1meta'!G240+'2.1meta'!G257+'2.1meta'!G274+'2.1meta'!G291+'2.1meta'!G308+'2.1meta'!G325 -> 0 | G8: ='2.1meta'!H10+'2.1meta'!H27+'2.1meta'!H44+'2.1meta'!H61+'2.1meta'!H79+'2.1meta'!H96+'2.1meta'!H113+'2.1meta'!H130+'2.1meta'!H147+'2.1meta'!H164++'2.1meta'!H181+'2.1meta'!H198+'2.1meta'!H215+'2.1meta'!H240+'2.1meta'!H257+'2.1meta'!H274+'2.1meta'!H291+'2.1meta'!H308+'2.1meta'!H325 -> 0 | H8: ='2.1meta'!I10+'2.1meta'!I27+'2.1meta'!I44+'2.1meta'!I61+'2.1meta'!I79+'2.1meta'!I96+'2.1meta'!I113+'2.1meta'!I130+'2.1meta'!I147+'2.1meta'!I164++'2.1meta'!I181+'2.1meta'!I198+'2.1meta'!I215+'2.1meta'!I240+'2.1meta'!I257+'2.1meta'!I274+'2.1meta'!I291+'2.1meta'!I308+'2.1meta'!I325 -> 0 | I8: ='2.1meta'!J10+'2.1meta'!J27+'2.1meta'!J44+'2.1meta'!J61+'2.1meta'!J79+'2.1meta'!J96+'2.1meta'!J113+'2.1meta'!J130+'2.1meta'!J147+'2.1meta'!J164++'2.1meta'!J181+'2.1meta'!J198+'2.1meta'!J215+'2.1meta'!J240+'2.1meta'!J257+'2.1meta'!J274+'2.1meta'!J291+'2.1meta'!J308+'2.1meta'!J325 -> 0 | J8: ='2.1meta'!K10+'2.1meta'!K27+'2.1meta'!K44+'2.1meta'!K61+'2.1meta'!K79+'2.1meta'!K96+'2.1meta'!K113+'2.1meta'!K130+'2.1meta'!K147+'2.1meta'!K164++'2.1meta'!K181+'2.1meta'!K198+'2.1meta'!K215+'2.1meta'!K240+'2.1meta'!K257+'2.1meta'!K274+'2.1meta'!K291+'2.1meta'!K308+'2.1meta'!K325 -> 0 | ... N8: ='2.1meta'!O10+'2.1meta'!O27+'2.1meta'!O44+'2.1meta'!O61+'2.1meta'!O79+'2.1meta'!O96+'2.1meta'!O113+'2.1meta'!O130+'2.1meta'!O147+'2.1meta'!O164++'2.1meta'!O181+'2.1meta'!O198+'2.1meta'!O215+'2.1meta'!O240+'2.1meta'!O257+'2.1meta'!O274+'2.1meta'!O291+'2.1meta'!O308+'2.1meta'!O325 -> 0 | O8: =SUM(F8:N8) -> 0 | P8: =C8-O8 -> 0 | Q8: ='2.1meta'!R10+'2.1meta'!R27+'2.1meta'!R44+'2.1meta'!R61+'2.1meta'!R79+'2.1meta'!R96+'2.1meta'!R113+'2.1meta'!R130+'2.1meta'!R147+'2.1meta'!R164++'2.1meta'!R181+'2.1meta'!R198+'2.1meta'!R215+'2.1meta'!R240+'2.1meta'!R257+'2.1meta'!R274+'2.1meta'!R291+'2.1meta'!R308+'2.1meta'!R325 -> 0 | R8: ='2.1meta'!S10+'2.1meta'!S27+'2.1meta'!S44+'2.1meta'!S61+'2.1meta'!S79+'2.1meta'!S96+'2.1meta'!S113+'2.1meta'!S130+'2.1meta'!S147+'2.1meta'!S164++'2.1meta'!S181+'2.1meta'!S198+'2.1meta'!S215+'2.1meta'!S240+'2.1meta'!S257+'2.1meta'!S274+'2.1meta'!S291+'2.1meta'!S308+'2.1meta'!S325 -> 0 | S8: ='2.1meta'!T10+'2.1meta'!T27+'2.1meta'!T44+'2.1meta'!T61+'2.1meta'!T79+'2.1meta'!T96+'2.1meta'!T113+'2.1meta'!T130+'2.1meta'!T147+'2.1meta'!T164++'2.1meta'!T181+'2.1meta'!T198+'2.1meta'!T215+'2.1meta'!T240+'2.1meta'!T257+'2.1meta'!T274+'2.1meta'!T291+'2.1meta'!T308+'2.1meta'!T325 -> 0 | T8: ='2.1meta'!U10+'2.1meta'!U27+'2.1meta'!U44+'2.1meta'!U61+'2.1meta'!U79+'2.1meta'!U96+'2.1meta'!U113+'2.1meta'!U130+'2.1meta'!U147+'2.1meta'!U164++'2.1meta'!U181+'2.1meta'!U198+'2.1meta'!U215+'2.1meta'!U240+'2.1meta'!U257+'2.1meta'!U274+'2.1meta'!U291+'2.1meta'!U308+'2.1meta'!U325 -> 0 | U8: ='2.1meta'!V10+'2.1meta'!V27+'2.1meta'!V44+'2.1meta'!V61+'2.1meta'!V79+'2.1meta'!V96+'2.1meta'!V113+'2.1meta'!V130+'2.1meta'!V147+'2.1meta'!V164++'2.1meta'!V181+'2.1meta'!V198+'2.1meta'!V215+'2.1meta'!V240+'2.1meta'!V257+'2.1meta'!V274+'2.1meta'!V291+'2.1meta'!V308+'2.1meta'!V325 -> 0 | V8: ='2.1meta'!W10+'2.1meta'!W27+'2.1meta'!W44+'2.1meta'!W61+'2.1meta'!W79+'2.1meta'!W96+'2.1meta'!W113+'2.1meta'!W130+'2.1meta'!W147+'2.1meta'!W164++'2.1meta'!W181+'2.1meta'!W198+'2.1meta'!W215+'2.1meta'!W240+'2.1meta'!W257+'2.1meta'!W274+'2.1meta'!W291+'2.1meta'!W308+'2.1meta'!W325 -> 0 | W8: ='2.1meta'!X10+'2.1meta'!X27+'2.1meta'!X44+'2.1meta'!X61+'2.1meta'!X79+'2.1meta'!X96+'2.1meta'!X113+'2.1meta'!X130+'2.1meta'!X147+'2.1meta'!X164++'2.1meta'!X181+'2.1meta'!X198+'2.1meta'!X215+'2.1meta'!X240+'2.1meta'!X257+'2.1meta'!X274+'2.1meta'!X291+'2.1meta'!X308+'2.1meta'!X325 -> 0 | X8: =SUM(Q8:W8) -> 0 | Y8: =O8+X8 -> 0 | Z8: =C8-Y8 -> 0
A9: 2.1.1. 3.1.2 | B9: PERSONAL CONTRATADO | C9: ='2.1meta'!D62 -> 0 | D9: ='2.1meta'!E62 -> 0 | E9: ='2.1meta'!F62 -> 0 | F9: ='2.1meta'!G62 -> 0 | G9: ='2.1meta'!H62 -> 0 | H9: ='2.1meta'!I62 -> 0 | I9: ='2.1meta'!J62 -> 0 | J9: ='2.1meta'!K62 -> 0 | ... N9: ='2.1meta'!O62 -> 0 | O9: =SUM(F9:N9) -> 0 | P9: =C9-O9 -> 0 | Q9: ='2.1meta'!R62 -> 0 | R9: ='2.1meta'!S62 -> 0 | S9: ='2.1meta'!T62 -> 0 | T9: ='2.1meta'!U62 -> 0 | U9: ='2.1meta'!V62 -> 0 | V9: ='2.1meta'!W62 -> 0 | W9: ='2.1meta'!X62 -> 0 | X9: =SUM(Q9:W9) -> 0 | Y9: =O9+X9 -> 0 | Z9: =C9-Y9 -> 0
A10: 2.1.1.4.1.1 | B10: PERSONAL NOMBRADO | C10: ='2.1meta'!D11+'2.1meta'!D28+'2.1meta'!D45+'2.1meta'!D63+'2.1meta'!D80+'2.1meta'!D97+'2.1meta'!D114+'2.1meta'!D131+'2.1meta'!D148+'2.1meta'!D165+'2.1meta'!D182+'2.1meta'!D199+'2.1meta'!D216+'2.1meta'!D229+'2.1meta'!D241+'2.1meta'!D258+'2.1meta'!D275+'2.1meta'!D292+'2.1meta'!D309+'2.1meta'!D326 -> 0 | D10: ='2.1meta'!E11+'2.1meta'!E28+'2.1meta'!E45+'2.1meta'!E63+'2.1meta'!E80+'2.1meta'!E97+'2.1meta'!E114+'2.1meta'!E131+'2.1meta'!E148+'2.1meta'!E165+'2.1meta'!E182+'2.1meta'!E199+'2.1meta'!E216+'2.1meta'!E229+'2.1meta'!E241+'2.1meta'!E258+'2.1meta'!E275+'2.1meta'!E292+'2.1meta'!E309+'2.1meta'!E326 -> 0 | E10: ='2.1meta'!F11+'2.1meta'!F28+'2.1meta'!F45+'2.1meta'!F63+'2.1meta'!F80+'2.1meta'!F97+'2.1meta'!F114+'2.1meta'!F131+'2.1meta'!F148+'2.1meta'!F165+'2.1meta'!F182+'2.1meta'!F199+'2.1meta'!F216+'2.1meta'!F229+'2.1meta'!F241+'2.1meta'!F258+'2.1meta'!F275+'2.1meta'!F292+'2.1meta'!F309+'2.1meta'!F326 -> 0 | F10: ='2.1meta'!G11+'2.1meta'!G28+'2.1meta'!G45+'2.1meta'!G63+'2.1meta'!G80+'2.1meta'!G97+'2.1meta'!G114+'2.1meta'!G131+'2.1meta'!G148+'2.1meta'!G165+'2.1meta'!G182+'2.1meta'!G199+'2.1meta'!G216+'2.1meta'!G229+'2.1meta'!G241+'2.1meta'!G258+'2.1meta'!G275+'2.1meta'!G292+'2.1meta'!G309+'2.1meta'!G326 -> 0 | G10: ='2.1meta'!H11+'2.1meta'!H28+'2.1meta'!H45+'2.1meta'!H63+'2.1meta'!H80+'2.1meta'!H97+'2.1meta'!H114+'2.1meta'!H131+'2.1meta'!H148+'2.1meta'!H165+'2.1meta'!H182+'2.1meta'!H199+'2.1meta'!H216+'2.1meta'!H229+'2.1meta'!H241+'2.1meta'!H258+'2.1meta'!H275+'2.1meta'!H292+'2.1meta'!H309+'2.1meta'!H326 -> 0 | H10: ='2.1meta'!I11+'2.1meta'!I28+'2.1meta'!I45+'2.1meta'!I63+'2.1meta'!I80+'2.1meta'!I97+'2.1meta'!I114+'2.1meta'!I131+'2.1meta'!I148+'2.1meta'!I165+'2.1meta'!I182+'2.1meta'!I199+'2.1meta'!I216+'2.1meta'!I229+'2.1meta'!I241+'2.1meta'!I258+'2.1meta'!I275+'2.1meta'!I292+'2.1meta'!I309+'2.1meta'!I326 -> 0 | I10: ='2.1meta'!J11+'2.1meta'!J28+'2.1meta'!J45+'2.1meta'!J63+'2.1meta'!J80+'2.1meta'!J97+'2.1meta'!J114+'2.1meta'!J131+'2.1meta'!J148+'2.1meta'!J165+'2.1meta'!J182+'2.1meta'!J199+'2.1meta'!J216+'2.1meta'!J229+'2.1meta'!J241+'2.1meta'!J258+'2.1meta'!J275+'2.1meta'!J292+'2.1meta'!J309+'2.1meta'!J326 -> 0 | J10: ='2.1meta'!K11+'2.1meta'!K28+'2.1meta'!K45+'2.1meta'!K63+'2.1meta'!K80+'2.1meta'!K97+'2.1meta'!K114+'2.1meta'!K131+'2.1meta'!K148+'2.1meta'!K165+'2.1meta'!K182+'2.1meta'!K199+'2.1meta'!K216+'2.1meta'!K229+'2.1meta'!K241+'2.1meta'!K258+'2.1meta'!K275+'2.1meta'!K292+'2.1meta'!K309+'2.1meta'!K326 -> 0 | ... N10: ='2.1meta'!O11+'2.1meta'!O28+'2.1meta'!O45+'2.1meta'!O63+'2.1meta'!O80+'2.1meta'!O97+'2.1meta'!O114+'2.1meta'!O131+'2.1meta'!O148+'2.1meta'!O165+'2.1meta'!O182+'2.1meta'!O199+'2.1meta'!O216+'2.1meta'!O229+'2.1meta'!O241+'2.1meta'!O258+'2.1meta'!O275+'2.1meta'!O292+'2.1meta'!O309+'2.1meta'!O326 -> 0 | O10: =SUM(F10:N10) -> 0 | P10: =C10-O10 -> 0 | Q10: ='2.1meta'!R11+'2.1meta'!R28+'2.1meta'!R45+'2.1meta'!R63+'2.1meta'!R80+'2.1meta'!R97+'2.1meta'!R114+'2.1meta'!R131+'2.1meta'!R148+'2.1meta'!R165+'2.1meta'!R182+'2.1meta'!R199+'2.1meta'!R216+'2.1meta'!R229+'2.1meta'!R241+'2.1meta'!R258+'2.1meta'!R275+'2.1meta'!R292+'2.1meta'!R309+'2.1meta'!R326 -> 0 | R10: ='2.1meta'!S11+'2.1meta'!S28+'2.1meta'!S45+'2.1meta'!S63+'2.1meta'!S80+'2.1meta'!S97+'2.1meta'!S114+'2.1meta'!S131+'2.1meta'!S148+'2.1meta'!S165+'2.1meta'!S182+'2.1meta'!S199+'2.1meta'!S216+'2.1meta'!S229+'2.1meta'!S241+'2.1meta'!S258+'2.1meta'!S275+'2.1meta'!S292+'2.1meta'!S309+'2.1meta'!S326 -> 0 | S10: ='2.1meta'!T11+'2.1meta'!T28+'2.1meta'!T45+'2.1meta'!T63+'2.1meta'!T80+'2.1meta'!T97+'2.1meta'!T114+'2.1meta'!T131+'2.1meta'!T148+'2.1meta'!T165+'2.1meta'!T182+'2.1meta'!T199+'2.1meta'!T216+'2.1meta'!T229+'2.1meta'!T241+'2.1meta'!T258+'2.1meta'!T275+'2.1meta'!T292+'2.1meta'!T309+'2.1meta'!T326 -> 0 | T10: ='2.1meta'!U11+'2.1meta'!U28+'2.1meta'!U45+'2.1meta'!U63+'2.1meta'!U80+'2.1meta'!U97+'2.1meta'!U114+'2.1meta'!U131+'2.1meta'!U148+'2.1meta'!U165+'2.1meta'!U182+'2.1meta'!U199+'2.1meta'!U216+'2.1meta'!U229+'2.1meta'!U241+'2.1meta'!U258+'2.1meta'!U275+'2.1meta'!U292+'2.1meta'!U309+'2.1meta'!U326 -> 0 | U10: ='2.1meta'!V11+'2.1meta'!V28+'2.1meta'!V45+'2.1meta'!V63+'2.1meta'!V80+'2.1meta'!V97+'2.1meta'!V114+'2.1meta'!V131+'2.1meta'!V148+'2.1meta'!V165+'2.1meta'!V182+'2.1meta'!V199+'2.1meta'!V216+'2.1meta'!V229+'2.1meta'!V241+'2.1meta'!V258+'2.1meta'!V275+'2.1meta'!V292+'2.1meta'!V309+'2.1meta'!V326 -> 0 | V10: ='2.1meta'!W11+'2.1meta'!W28+'2.1meta'!W45+'2.1meta'!W63+'2.1meta'!W80+'2.1meta'!W97+'2.1meta'!W114+'2.1meta'!W131+'2.1meta'!W148+'2.1meta'!W165+'2.1meta'!W182+'2.1meta'!W199+'2.1meta'!W216+'2.1meta'!W229+'2.1meta'!W241+'2.1meta'!W258+'2.1meta'!W275+'2.1meta'!W292+'2.1meta'!W309+'2.1meta'!W326 -> 0 | W10: ='2.1meta'!X11+'2.1meta'!X28+'2.1meta'!X45+'2.1meta'!X63+'2.1meta'!X80+'2.1meta'!X97+'2.1meta'!X114+'2.1meta'!X131+'2.1meta'!X148+'2.1meta'!X165+'2.1meta'!X182+'2.1meta'!X199+'2.1meta'!X216+'2.1meta'!X229+'2.1meta'!X241+'2.1meta'!X258+'2.1meta'!X275+'2.1meta'!X292+'2.1meta'!X309+'2.1meta'!X326 -> 0 | X10: =SUM(Q10:W10) -> 0 | Y10: =O10+X10 -> 0 | Z10: =C10-Y10 -> 0
A11: 2.1.1.4.2.1 | B11: BONO POR FUNCION JURISDICCIONAL Y FISCAL | C11: ='2.1meta'!D12+'2.1meta'!D29+'2.1meta'!D46+'2.1meta'!D64+'2.1meta'!D81+'2.1meta'!D98+'2.1meta'!D115+'2.1meta'!D132+'2.1meta'!D149+'2.1meta'!D166+'2.1meta'!D183+'2.1meta'!D200+'2.1meta'!D217+'2.1meta'!D230+'2.1meta'!D242+'2.1meta'!D259+'2.1meta'!D276+'2.1meta'!D293+'2.1meta'!D310+'2.1meta'!D327 -> 0 | D11: ='2.1meta'!E12+'2.1meta'!E29+'2.1meta'!E46+'2.1meta'!E64+'2.1meta'!E81+'2.1meta'!E98+'2.1meta'!E115+'2.1meta'!E132+'2.1meta'!E149+'2.1meta'!E166+'2.1meta'!E183+'2.1meta'!E200+'2.1meta'!E217+'2.1meta'!E230+'2.1meta'!E242+'2.1meta'!E259+'2.1meta'!E276+'2.1meta'!E293+'2.1meta'!E310+'2.1meta'!E327 -> 0 | E11: ='2.1meta'!F12+'2.1meta'!F29+'2.1meta'!F46+'2.1meta'!F64+'2.1meta'!F81+'2.1meta'!F98+'2.1meta'!F115+'2.1meta'!F132+'2.1meta'!F149+'2.1meta'!F166+'2.1meta'!F183+'2.1meta'!F200+'2.1meta'!F217+'2.1meta'!F230+'2.1meta'!F242+'2.1meta'!F259+'2.1meta'!F276+'2.1meta'!F293+'2.1meta'!F310+'2.1meta'!F327 -> 0 | F11: ='2.1meta'!G12+'2.1meta'!G29+'2.1meta'!G46+'2.1meta'!G64+'2.1meta'!G81+'2.1meta'!G98+'2.1meta'!G115+'2.1meta'!G132+'2.1meta'!G149+'2.1meta'!G166+'2.1meta'!G183+'2.1meta'!G200+'2.1meta'!G217+'2.1meta'!G230+'2.1meta'!G242+'2.1meta'!G259+'2.1meta'!G276+'2.1meta'!G293+'2.1meta'!G310+'2.1meta'!G327 -> 0 | G11: ='2.1meta'!H12+'2.1meta'!H29+'2.1meta'!H46+'2.1meta'!H64+'2.1meta'!H81+'2.1meta'!H98+'2.1meta'!H115+'2.1meta'!H132+'2.1meta'!H149+'2.1meta'!H166+'2.1meta'!H183+'2.1meta'!H200+'2.1meta'!H217+'2.1meta'!H230+'2.1meta'!H242+'2.1meta'!H259+'2.1meta'!H276+'2.1meta'!H293+'2.1meta'!H310+'2.1meta'!H327 -> 0 | H11: ='2.1meta'!I12+'2.1meta'!I29+'2.1meta'!I46+'2.1meta'!I64+'2.1meta'!I81+'2.1meta'!I98+'2.1meta'!I115+'2.1meta'!I132+'2.1meta'!I149+'2.1meta'!I166+'2.1meta'!I183+'2.1meta'!I200+'2.1meta'!I217+'2.1meta'!I230+'2.1meta'!I242+'2.1meta'!I259+'2.1meta'!I276+'2.1meta'!I293+'2.1meta'!I310+'2.1meta'!I327 -> 0 | I11: ='2.1meta'!J12+'2.1meta'!J29+'2.1meta'!J46+'2.1meta'!J64+'2.1meta'!J81+'2.1meta'!J98+'2.1meta'!J115+'2.1meta'!J132+'2.1meta'!J149+'2.1meta'!J166+'2.1meta'!J183+'2.1meta'!J200+'2.1meta'!J217+'2.1meta'!J230+'2.1meta'!J242+'2.1meta'!J259+'2.1meta'!J276+'2.1meta'!J293+'2.1meta'!J310+'2.1meta'!J327 -> 0 | J11: ='2.1meta'!K12+'2.1meta'!K29+'2.1meta'!K46+'2.1meta'!K64+'2.1meta'!K81+'2.1meta'!K98+'2.1meta'!K115+'2.1meta'!K132+'2.1meta'!K149+'2.1meta'!K166+'2.1meta'!K183+'2.1meta'!K200+'2.1meta'!K217+'2.1meta'!K230+'2.1meta'!K242+'2.1meta'!K259+'2.1meta'!K276+'2.1meta'!K293+'2.1meta'!K310+'2.1meta'!K327 -> 0 | ... N11: ='2.1meta'!O12+'2.1meta'!O29+'2.1meta'!O46+'2.1meta'!O64+'2.1meta'!O81+'2.1meta'!O98+'2.1meta'!O115+'2.1meta'!O132+'2.1meta'!O149+'2.1meta'!O166+'2.1meta'!O183+'2.1meta'!O200+'2.1meta'!O217+'2.1meta'!O230+'2.1meta'!O242+'2.1meta'!O259+'2.1meta'!O276+'2.1meta'!O293+'2.1meta'!O310+'2.1meta'!O327 -> 0 | O11: =SUM(F11:N11) -> 0 | P11: =C11-O11 -> 0 | Q11: ='2.1meta'!R12+'2.1meta'!R29+'2.1meta'!R46+'2.1meta'!R64+'2.1meta'!R81+'2.1meta'!R98+'2.1meta'!R115+'2.1meta'!R132+'2.1meta'!R149+'2.1meta'!R166+'2.1meta'!R183+'2.1meta'!R200+'2.1meta'!R217+'2.1meta'!R230+'2.1meta'!R242+'2.1meta'!R259+'2.1meta'!R276+'2.1meta'!R293+'2.1meta'!R310+'2.1meta'!R327 -> 0 | R11: ='2.1meta'!S12+'2.1meta'!S29+'2.1meta'!S46+'2.1meta'!S64+'2.1meta'!S81+'2.1meta'!S98+'2.1meta'!S115+'2.1meta'!S132+'2.1meta'!S149+'2.1meta'!S166+'2.1meta'!S183+'2.1meta'!S200+'2.1meta'!S217+'2.1meta'!S230+'2.1meta'!S242+'2.1meta'!S259+'2.1meta'!S276+'2.1meta'!S293+'2.1meta'!S310+'2.1meta'!S327 -> 0 | S11: ='2.1meta'!T12+'2.1meta'!T29+'2.1meta'!T46+'2.1meta'!T64+'2.1meta'!T81+'2.1meta'!T98+'2.1meta'!T115+'2.1meta'!T132+'2.1meta'!T149+'2.1meta'!T166+'2.1meta'!T183+'2.1meta'!T200+'2.1meta'!T217+'2.1meta'!T230+'2.1meta'!T242+'2.1meta'!T259+'2.1meta'!T276+'2.1meta'!T293+'2.1meta'!T310+'2.1meta'!T327 -> 0 | T11: ='2.1meta'!U12+'2.1meta'!U29+'2.1meta'!U46+'2.1meta'!U64+'2.1meta'!U81+'2.1meta'!U98+'2.1meta'!U115+'2.1meta'!U132+'2.1meta'!U149+'2.1meta'!U166+'2.1meta'!U183+'2.1meta'!U200+'2.1meta'!U217+'2.1meta'!U230+'2.1meta'!U242+'2.1meta'!U259+'2.1meta'!U276+'2.1meta'!U293+'2.1meta'!U310+'2.1meta'!U327 -> 0 | U11: ='2.1meta'!V12+'2.1meta'!V29+'2.1meta'!V46+'2.1meta'!V64+'2.1meta'!V81+'2.1meta'!V98+'2.1meta'!V115+'2.1meta'!V132+'2.1meta'!V149+'2.1meta'!V166+'2.1meta'!V183+'2.1meta'!V200+'2.1meta'!V217+'2.1meta'!V230+'2.1meta'!V242+'2.1meta'!V259+'2.1meta'!V276+'2.1meta'!V293+'2.1meta'!V310+'2.1meta'!V327 -> 0 | V11: ='2.1meta'!W12+'2.1meta'!W29+'2.1meta'!W46+'2.1meta'!W64+'2.1meta'!W81+'2.1meta'!W98+'2.1meta'!W115+'2.1meta'!W132+'2.1meta'!W149+'2.1meta'!W166+'2.1meta'!W183+'2.1meta'!W200+'2.1meta'!W217+'2.1meta'!W230+'2.1meta'!W242+'2.1meta'!W259+'2.1meta'!W276+'2.1meta'!W293+'2.1meta'!W310+'2.1meta'!W327 -> 0 | W11: ='2.1meta'!X12+'2.1meta'!X29+'2.1meta'!X46+'2.1meta'!X64+'2.1meta'!X81+'2.1meta'!X98+'2.1meta'!X115+'2.1meta'!X132+'2.1meta'!X149+'2.1meta'!X166+'2.1meta'!X183+'2.1meta'!X200+'2.1meta'!X217+'2.1meta'!X230+'2.1meta'!X242+'2.1meta'!X259+'2.1meta'!X276+'2.1meta'!X293+'2.1meta'!X310+'2.1meta'!X327 -> 0 | X11: =SUM(Q11:W11) -> 0 | Y11: =O11+X11 -> 0 | Z11: =C11-Y11 -> 0
A12: 2.1.1.4.2.2 | B12: ASIGNACION POR GASTOS OPERATIVOS | C12: ='2.1meta'!D13+'2.1meta'!D30+'2.1meta'!D47+'2.1meta'!D65+'2.1meta'!D82+'2.1meta'!D99+'2.1meta'!D116+'2.1meta'!D133+'2.1meta'!D150+'2.1meta'!D167+'2.1meta'!D184+'2.1meta'!D201+'2.1meta'!D218+'2.1meta'!D231+'2.1meta'!D243+'2.1meta'!D260+'2.1meta'!D277+'2.1meta'!D294+'2.1meta'!D311+'2.1meta'!D328 -> 0 | D12: ='2.1meta'!E13+'2.1meta'!E30+'2.1meta'!E47+'2.1meta'!E65+'2.1meta'!E82+'2.1meta'!E99+'2.1meta'!E116+'2.1meta'!E133+'2.1meta'!E150+'2.1meta'!E167+'2.1meta'!E184+'2.1meta'!E201+'2.1meta'!E218+'2.1meta'!E231+'2.1meta'!E243+'2.1meta'!E260+'2.1meta'!E277+'2.1meta'!E294+'2.1meta'!E311+'2.1meta'!E328 -> 0 | E12: ='2.1meta'!F13+'2.1meta'!F30+'2.1meta'!F47+'2.1meta'!F65+'2.1meta'!F82+'2.1meta'!F99+'2.1meta'!F116+'2.1meta'!F133+'2.1meta'!F150+'2.1meta'!F167+'2.1meta'!F184+'2.1meta'!F201+'2.1meta'!F218+'2.1meta'!F231+'2.1meta'!F243+'2.1meta'!F260+'2.1meta'!F277+'2.1meta'!F294+'2.1meta'!F311+'2.1meta'!F328 -> 0 | F12: ='2.1meta'!G13+'2.1meta'!G30+'2.1meta'!G47+'2.1meta'!G65+'2.1meta'!G82+'2.1meta'!G99+'2.1meta'!G116+'2.1meta'!G133+'2.1meta'!G150+'2.1meta'!G167+'2.1meta'!G184+'2.1meta'!G201+'2.1meta'!G218+'2.1meta'!G231+'2.1meta'!G243+'2.1meta'!G260+'2.1meta'!G277+'2.1meta'!G294+'2.1meta'!G311+'2.1meta'!G328 -> 0 | G12: ='2.1meta'!H13+'2.1meta'!H30+'2.1meta'!H47+'2.1meta'!H65+'2.1meta'!H82+'2.1meta'!H99+'2.1meta'!H116+'2.1meta'!H133+'2.1meta'!H150+'2.1meta'!H167+'2.1meta'!H184+'2.1meta'!H201+'2.1meta'!H218+'2.1meta'!H231+'2.1meta'!H243+'2.1meta'!H260+'2.1meta'!H277+'2.1meta'!H294+'2.1meta'!H311+'2.1meta'!H328 -> 0 | H12: ='2.1meta'!I13+'2.1meta'!I30+'2.1meta'!I47+'2.1meta'!I65+'2.1meta'!I82+'2.1meta'!I99+'2.1meta'!I116+'2.1meta'!I133+'2.1meta'!I150+'2.1meta'!I167+'2.1meta'!I184+'2.1meta'!I201+'2.1meta'!I218+'2.1meta'!I231+'2.1meta'!I243+'2.1meta'!I260+'2.1meta'!I277+'2.1meta'!I294+'2.1meta'!I311+'2.1meta'!I328 -> 0 | I12: ='2.1meta'!J13+'2.1meta'!J30+'2.1meta'!J47+'2.1meta'!J65+'2.1meta'!J82+'2.1meta'!J99+'2.1meta'!J116+'2.1meta'!J133+'2.1meta'!J150+'2.1meta'!J167+'2.1meta'!J184+'2.1meta'!J201+'2.1meta'!J218+'2.1meta'!J231+'2.1meta'!J243+'2.1meta'!J260+'2.1meta'!J277+'2.1meta'!J294+'2.1meta'!J311+'2.1meta'!J328 -> 0 | J12: ='2.1meta'!K13+'2.1meta'!K30+'2.1meta'!K47+'2.1meta'!K65+'2.1meta'!K82+'2.1meta'!K99+'2.1meta'!K116+'2.1meta'!K133+'2.1meta'!K150+'2.1meta'!K167+'2.1meta'!K184+'2.1meta'!K201+'2.1meta'!K218+'2.1meta'!K231+'2.1meta'!K243+'2.1meta'!K260+'2.1meta'!K277+'2.1meta'!K294+'2.1meta'!K311+'2.1meta'!K328 -> 0 | ... N12: ='2.1meta'!O13+'2.1meta'!O30+'2.1meta'!O47+'2.1meta'!O65+'2.1meta'!O82+'2.1meta'!O99+'2.1meta'!O116+'2.1meta'!O133+'2.1meta'!O150+'2.1meta'!O167+'2.1meta'!O184+'2.1meta'!O201+'2.1meta'!O218+'2.1meta'!O231+'2.1meta'!O243+'2.1meta'!O260+'2.1meta'!O277+'2.1meta'!O294+'2.1meta'!O311+'2.1meta'!O328 -> 0 | O12: =SUM(F12:N12) -> 0 | P12: =C12-O12 -> 0 | Q12: ='2.1meta'!R13+'2.1meta'!R30+'2.1meta'!R47+'2.1meta'!R65+'2.1meta'!R82+'2.1meta'!R99+'2.1meta'!R116+'2.1meta'!R133+'2.1meta'!R150+'2.1meta'!R167+'2.1meta'!R184+'2.1meta'!R201+'2.1meta'!R218+'2.1meta'!R231+'2.1meta'!R243+'2.1meta'!R260+'2.1meta'!R277+'2.1meta'!R294+'2.1meta'!R311+'2.1meta'!R328 -> 0 | R12: ='2.1meta'!S13+'2.1meta'!S30+'2.1meta'!S47+'2.1meta'!S65+'2.1meta'!S82+'2.1meta'!S99+'2.1meta'!S116+'2.1meta'!S133+'2.1meta'!S150+'2.1meta'!S167+'2.1meta'!S184+'2.1meta'!S201+'2.1meta'!S218+'2.1meta'!S231+'2.1meta'!S243+'2.1meta'!S260+'2.1meta'!S277+'2.1meta'!S294+'2.1meta'!S311+'2.1meta'!S328 -> 0 | S12: ='2.1meta'!T13+'2.1meta'!T30+'2.1meta'!T47+'2.1meta'!T65+'2.1meta'!T82+'2.1meta'!T99+'2.1meta'!T116+'2.1meta'!T133+'2.1meta'!T150+'2.1meta'!T167+'2.1meta'!T184+'2.1meta'!T201+'2.1meta'!T218+'2.1meta'!T231+'2.1meta'!T243+'2.1meta'!T260+'2.1meta'!T277+'2.1meta'!T294+'2.1meta'!T311+'2.1meta'!T328 -> 0 | T12: ='2.1meta'!U13+'2.1meta'!U30+'2.1meta'!U47+'2.1meta'!U65+'2.1meta'!U82+'2.1meta'!U99+'2.1meta'!U116+'2.1meta'!U133+'2.1meta'!U150+'2.1meta'!U167+'2.1meta'!U184+'2.1meta'!U201+'2.1meta'!U218+'2.1meta'!U231+'2.1meta'!U243+'2.1meta'!U260+'2.1meta'!U277+'2.1meta'!U294+'2.1meta'!U311+'2.1meta'!U328 -> 0 | U12: ='2.1meta'!V13+'2.1meta'!V30+'2.1meta'!V47+'2.1meta'!V65+'2.1meta'!V82+'2.1meta'!V99+'2.1meta'!V116+'2.1meta'!V133+'2.1meta'!V150+'2.1meta'!V167+'2.1meta'!V184+'2.1meta'!V201+'2.1meta'!V218+'2.1meta'!V231+'2.1meta'!V243+'2.1meta'!V260+'2.1meta'!V277+'2.1meta'!V294+'2.1meta'!V311+'2.1meta'!V328 -> 0 | V12: ='2.1meta'!W13+'2.1meta'!W30+'2.1meta'!W47+'2.1meta'!W65+'2.1meta'!W82+'2.1meta'!W99+'2.1meta'!W116+'2.1meta'!W133+'2.1meta'!W150+'2.1meta'!W167+'2.1meta'!W184+'2.1meta'!W201+'2.1meta'!W218+'2.1meta'!W231+'2.1meta'!W243+'2.1meta'!W260+'2.1meta'!W277+'2.1meta'!W294+'2.1meta'!W311+'2.1meta'!W328 -> 0 | W12: ='2.1meta'!X13+'2.1meta'!X30+'2.1meta'!X47+'2.1meta'!X65+'2.1meta'!X82+'2.1meta'!X99+'2.1meta'!X116+'2.1meta'!X133+'2.1meta'!X150+'2.1meta'!X167+'2.1meta'!X184+'2.1meta'!X201+'2.1meta'!X218+'2.1meta'!X231+'2.1meta'!X243+'2.1meta'!X260+'2.1meta'!X277+'2.1meta'!X294+'2.1meta'!X311+'2.1meta'!X328 -> 0 | X12: =SUM(Q12:W12) -> 0 | Y12: =O12+X12 -> 0 | Z12: =C12-Y12 -> 0
A13: 2.1.1.9.1.1 | B13: GRATIFICACIONES | C13: ='2.1meta'!D14+'2.1meta'!D31+'2.1meta'!D48+'2.1meta'!D66+'2.1meta'!D83+'2.1meta'!D100+'2.1meta'!D117+'2.1meta'!D134+'2.1meta'!D151+'2.1meta'!D168+'2.1meta'!D185+'2.1meta'!D202+'2.1meta'!D219+'2.1meta'!D244+'2.1meta'!D261+'2.1meta'!D278+'2.1meta'!D295+'2.1meta'!D312+'2.1meta'!D329 -> 0 | D13: ='2.1meta'!E14+'2.1meta'!E31+'2.1meta'!E48+'2.1meta'!E66+'2.1meta'!E83+'2.1meta'!E100+'2.1meta'!E117+'2.1meta'!E134+'2.1meta'!E151+'2.1meta'!E168+'2.1meta'!E185+'2.1meta'!E202+'2.1meta'!E219+'2.1meta'!E244+'2.1meta'!E261+'2.1meta'!E278+'2.1meta'!E295+'2.1meta'!E312+'2.1meta'!E329 -> 0 | E13: ='2.1meta'!F14+'2.1meta'!F31+'2.1meta'!F48+'2.1meta'!F66+'2.1meta'!F83+'2.1meta'!F100+'2.1meta'!F117+'2.1meta'!F134+'2.1meta'!F151+'2.1meta'!F168+'2.1meta'!F185+'2.1meta'!F202+'2.1meta'!F219+'2.1meta'!F244+'2.1meta'!F261+'2.1meta'!F278+'2.1meta'!F295+'2.1meta'!F312+'2.1meta'!F329 -> 0 | F13: ='2.1meta'!G14+'2.1meta'!G31+'2.1meta'!G48+'2.1meta'!G66+'2.1meta'!G83+'2.1meta'!G100+'2.1meta'!G117+'2.1meta'!G134+'2.1meta'!G151+'2.1meta'!G168+'2.1meta'!G185+'2.1meta'!G202+'2.1meta'!G219+'2.1meta'!G244+'2.1meta'!G261+'2.1meta'!G278+'2.1meta'!G295+'2.1meta'!G312+'2.1meta'!G329 -> 0 | G13: ='2.1meta'!H14+'2.1meta'!H31+'2.1meta'!H48+'2.1meta'!H66+'2.1meta'!H83+'2.1meta'!H100+'2.1meta'!H117+'2.1meta'!H134+'2.1meta'!H151+'2.1meta'!H168+'2.1meta'!H185+'2.1meta'!H202+'2.1meta'!H219+'2.1meta'!H244+'2.1meta'!H261+'2.1meta'!H278+'2.1meta'!H295+'2.1meta'!H312+'2.1meta'!H329 -> 0 | H13: ='2.1meta'!I14+'2.1meta'!I31+'2.1meta'!I48+'2.1meta'!I66+'2.1meta'!I83+'2.1meta'!I100+'2.1meta'!I117+'2.1meta'!I134+'2.1meta'!I151+'2.1meta'!I168+'2.1meta'!I185+'2.1meta'!I202+'2.1meta'!I219+'2.1meta'!I244+'2.1meta'!I261+'2.1meta'!I278+'2.1meta'!I295+'2.1meta'!I312+'2.1meta'!I329 -> 0 | I13: ='2.1meta'!J14+'2.1meta'!J31+'2.1meta'!J48+'2.1meta'!J66+'2.1meta'!J83+'2.1meta'!J100+'2.1meta'!J117+'2.1meta'!J134+'2.1meta'!J151+'2.1meta'!J168+'2.1meta'!J185+'2.1meta'!J202+'2.1meta'!J219+'2.1meta'!J244+'2.1meta'!J261+'2.1meta'!J278+'2.1meta'!J295+'2.1meta'!J312+'2.1meta'!J329 -> 0 | J13: ='2.1meta'!K14+'2.1meta'!K31+'2.1meta'!K48+'2.1meta'!K66+'2.1meta'!K83+'2.1meta'!K100+'2.1meta'!K117+'2.1meta'!K134+'2.1meta'!K151+'2.1meta'!K168+'2.1meta'!K185+'2.1meta'!K202+'2.1meta'!K219+'2.1meta'!K244+'2.1meta'!K261+'2.1meta'!K278+'2.1meta'!K295+'2.1meta'!K312+'2.1meta'!K329 -> 0 | ... N13: ='2.1meta'!O14+'2.1meta'!O31+'2.1meta'!O48+'2.1meta'!O66+'2.1meta'!O83+'2.1meta'!O100+'2.1meta'!O117+'2.1meta'!O134+'2.1meta'!O151+'2.1meta'!O168+'2.1meta'!O185+'2.1meta'!O202+'2.1meta'!O219+'2.1meta'!O244+'2.1meta'!O261+'2.1meta'!O278+'2.1meta'!O295+'2.1meta'!O312+'2.1meta'!O329 -> 0 | O13: =SUM(F13:N13) -> 0 | P13: =C13-O13 -> 0 | Q13: ='2.1meta'!R14+'2.1meta'!R31+'2.1meta'!R48+'2.1meta'!R66+'2.1meta'!R83+'2.1meta'!R100+'2.1meta'!R117+'2.1meta'!R134+'2.1meta'!R151+'2.1meta'!R168+'2.1meta'!R185+'2.1meta'!R202+'2.1meta'!R219+'2.1meta'!R244+'2.1meta'!R261+'2.1meta'!R278+'2.1meta'!R295+'2.1meta'!R312+'2.1meta'!R329 -> 0 | R13: ='2.1meta'!S14+'2.1meta'!S31+'2.1meta'!S48+'2.1meta'!S66+'2.1meta'!S83+'2.1meta'!S100+'2.1meta'!S117+'2.1meta'!S134+'2.1meta'!S151+'2.1meta'!S168+'2.1meta'!S185+'2.1meta'!S202+'2.1meta'!S219+'2.1meta'!S244+'2.1meta'!S261+'2.1meta'!S278+'2.1meta'!S295+'2.1meta'!S312+'2.1meta'!S329 -> 0 | S13: ='2.1meta'!T14+'2.1meta'!T31+'2.1meta'!T48+'2.1meta'!T66+'2.1meta'!T83+'2.1meta'!T100+'2.1meta'!T117+'2.1meta'!T134+'2.1meta'!T151+'2.1meta'!T168+'2.1meta'!T185+'2.1meta'!T202+'2.1meta'!T219+'2.1meta'!T244+'2.1meta'!T261+'2.1meta'!T278+'2.1meta'!T295+'2.1meta'!T312+'2.1meta'!T329 -> 0 | T13: ='2.1meta'!U14+'2.1meta'!U31+'2.1meta'!U48+'2.1meta'!U66+'2.1meta'!U83+'2.1meta'!U100+'2.1meta'!U117+'2.1meta'!U134+'2.1meta'!U151+'2.1meta'!U168+'2.1meta'!U185+'2.1meta'!U202+'2.1meta'!U219+'2.1meta'!U244+'2.1meta'!U261+'2.1meta'!U278+'2.1meta'!U295+'2.1meta'!U312+'2.1meta'!U329 -> 0 | U13: ='2.1meta'!V14+'2.1meta'!V31+'2.1meta'!V48+'2.1meta'!V66+'2.1meta'!V83+'2.1meta'!V100+'2.1meta'!V117+'2.1meta'!V134+'2.1meta'!V151+'2.1meta'!V168+'2.1meta'!V185+'2.1meta'!V202+'2.1meta'!V219+'2.1meta'!V244+'2.1meta'!V261+'2.1meta'!V278+'2.1meta'!V295+'2.1meta'!V312+'2.1meta'!V329 -> 0 | V13: ='2.1meta'!W14+'2.1meta'!W31+'2.1meta'!W48+'2.1meta'!W66+'2.1meta'!W83+'2.1meta'!W100+'2.1meta'!W117+'2.1meta'!W134+'2.1meta'!W151+'2.1meta'!W168+'2.1meta'!W185+'2.1meta'!W202+'2.1meta'!W219+'2.1meta'!W244+'2.1meta'!W261+'2.1meta'!W278+'2.1meta'!W295+'2.1meta'!W312+'2.1meta'!W329 -> 0 | W13: ='2.1meta'!X14+'2.1meta'!X31+'2.1meta'!X48+'2.1meta'!X66+'2.1meta'!X83+'2.1meta'!X100+'2.1meta'!X117+'2.1meta'!X134+'2.1meta'!X151+'2.1meta'!X168+'2.1meta'!X185+'2.1meta'!X202+'2.1meta'!X219+'2.1meta'!X244+'2.1meta'!X261+'2.1meta'!X278+'2.1meta'!X295+'2.1meta'!X312+'2.1meta'!X329 -> 0 | X13: =SUM(Q13:W13) -> 0 | Y13: =O13+X13 -> 0 | Z13: =C13-Y13 -> 0
A14: 2.1.1.9.1.2 | B14: AGUINALDOS | C14: ='2.1meta'!D15+'2.1meta'!D32+'2.1meta'!D49+'2.1meta'!D67+'2.1meta'!D84+'2.1meta'!D101+'2.1meta'!D118+'2.1meta'!D135+'2.1meta'!D152+'2.1meta'!D169+'2.1meta'!D186+'2.1meta'!D203+'2.1meta'!D220+'2.1meta'!D232+'2.1meta'!D245+'2.1meta'!D262+'2.1meta'!D279+'2.1meta'!D296+'2.1meta'!D313+'2.1meta'!D330 -> 0 | D14: ='2.1meta'!E15+'2.1meta'!E32+'2.1meta'!E49+'2.1meta'!E67+'2.1meta'!E84+'2.1meta'!E101+'2.1meta'!E118+'2.1meta'!E135+'2.1meta'!E152+'2.1meta'!E169+'2.1meta'!E186+'2.1meta'!E203+'2.1meta'!E220+'2.1meta'!E232+'2.1meta'!E245+'2.1meta'!E262+'2.1meta'!E279+'2.1meta'!E296+'2.1meta'!E313+'2.1meta'!E330 -> 0 | E14: ='2.1meta'!F15+'2.1meta'!F32+'2.1meta'!F49+'2.1meta'!F67+'2.1meta'!F84+'2.1meta'!F101+'2.1meta'!F118+'2.1meta'!F135+'2.1meta'!F152+'2.1meta'!F169+'2.1meta'!F186+'2.1meta'!F203+'2.1meta'!F220+'2.1meta'!F232+'2.1meta'!F245+'2.1meta'!F262+'2.1meta'!F279+'2.1meta'!F296+'2.1meta'!F313+'2.1meta'!F330 -> 0 | F14: ='2.1meta'!G15+'2.1meta'!G32+'2.1meta'!G49+'2.1meta'!G67+'2.1meta'!G84+'2.1meta'!G101+'2.1meta'!G118+'2.1meta'!G135+'2.1meta'!G152+'2.1meta'!G169+'2.1meta'!G186+'2.1meta'!G203+'2.1meta'!G220+'2.1meta'!G232+'2.1meta'!G245+'2.1meta'!G262+'2.1meta'!G279+'2.1meta'!G296+'2.1meta'!G313+'2.1meta'!G330 -> 0 | G14: ='2.1meta'!H15+'2.1meta'!H32+'2.1meta'!H49+'2.1meta'!H67+'2.1meta'!H84+'2.1meta'!H101+'2.1meta'!H118+'2.1meta'!H135+'2.1meta'!H152+'2.1meta'!H169+'2.1meta'!H186+'2.1meta'!H203+'2.1meta'!H220+'2.1meta'!H232+'2.1meta'!H245+'2.1meta'!H262+'2.1meta'!H279+'2.1meta'!H296+'2.1meta'!H313+'2.1meta'!H330 -> 0 | H14: ='2.1meta'!I15+'2.1meta'!I32+'2.1meta'!I49+'2.1meta'!I67+'2.1meta'!I84+'2.1meta'!I101+'2.1meta'!I118+'2.1meta'!I135+'2.1meta'!I152+'2.1meta'!I169+'2.1meta'!I186+'2.1meta'!I203+'2.1meta'!I220+'2.1meta'!I232+'2.1meta'!I245+'2.1meta'!I262+'2.1meta'!I279+'2.1meta'!I296+'2.1meta'!I313+'2.1meta'!I330 -> 0 | I14: ='2.1meta'!J15+'2.1meta'!J32+'2.1meta'!J49+'2.1meta'!J67+'2.1meta'!J84+'2.1meta'!J101+'2.1meta'!J118+'2.1meta'!J135+'2.1meta'!J152+'2.1meta'!J169+'2.1meta'!J186+'2.1meta'!J203+'2.1meta'!J220+'2.1meta'!J232+'2.1meta'!J245+'2.1meta'!J262+'2.1meta'!J279+'2.1meta'!J296+'2.1meta'!J313+'2.1meta'!J330 -> 0 | J14: ='2.1meta'!K15+'2.1meta'!K32+'2.1meta'!K49+'2.1meta'!K67+'2.1meta'!K84+'2.1meta'!K101+'2.1meta'!K118+'2.1meta'!K135+'2.1meta'!K152+'2.1meta'!K169+'2.1meta'!K186+'2.1meta'!K203+'2.1meta'!K220+'2.1meta'!K232+'2.1meta'!K245+'2.1meta'!K262+'2.1meta'!K279+'2.1meta'!K296+'2.1meta'!K313+'2.1meta'!K330 -> 0 | ... N14: ='2.1meta'!O15+'2.1meta'!O32+'2.1meta'!O49+'2.1meta'!O67+'2.1meta'!O84+'2.1meta'!O101+'2.1meta'!O118+'2.1meta'!O135+'2.1meta'!O152+'2.1meta'!O169+'2.1meta'!O186+'2.1meta'!O203+'2.1meta'!O220+'2.1meta'!O232+'2.1meta'!O245+'2.1meta'!O262+'2.1meta'!O279+'2.1meta'!O296+'2.1meta'!O313+'2.1meta'!O330 -> 0 | O14: =SUM(F14:N14) -> 0 | P14: =C14-O14 -> 0 | Q14: ='2.1meta'!R15+'2.1meta'!R32+'2.1meta'!R49+'2.1meta'!R67+'2.1meta'!R84+'2.1meta'!R101+'2.1meta'!R118+'2.1meta'!R135+'2.1meta'!R152+'2.1meta'!R169+'2.1meta'!R186+'2.1meta'!R203+'2.1meta'!R220+'2.1meta'!R232+'2.1meta'!R245+'2.1meta'!R262+'2.1meta'!R279+'2.1meta'!R296+'2.1meta'!R313+'2.1meta'!R330 -> 0 | R14: ='2.1meta'!S15+'2.1meta'!S32+'2.1meta'!S49+'2.1meta'!S67+'2.1meta'!S84+'2.1meta'!S101+'2.1meta'!S118+'2.1meta'!S135+'2.1meta'!S152+'2.1meta'!S169+'2.1meta'!S186+'2.1meta'!S203+'2.1meta'!S220+'2.1meta'!S232+'2.1meta'!S245+'2.1meta'!S262+'2.1meta'!S279+'2.1meta'!S296+'2.1meta'!S313+'2.1meta'!S330 -> 0 | S14: ='2.1meta'!T15+'2.1meta'!T32+'2.1meta'!T49+'2.1meta'!T67+'2.1meta'!T84+'2.1meta'!T101+'2.1meta'!T118+'2.1meta'!T135+'2.1meta'!T152+'2.1meta'!T169+'2.1meta'!T186+'2.1meta'!T203+'2.1meta'!T220+'2.1meta'!T232+'2.1meta'!T245+'2.1meta'!T262+'2.1meta'!T279+'2.1meta'!T296+'2.1meta'!T313+'2.1meta'!T330 -> 0 | T14: ='2.1meta'!U15+'2.1meta'!U32+'2.1meta'!U49+'2.1meta'!U67+'2.1meta'!U84+'2.1meta'!U101+'2.1meta'!U118+'2.1meta'!U135+'2.1meta'!U152+'2.1meta'!U169+'2.1meta'!U186+'2.1meta'!U203+'2.1meta'!U220+'2.1meta'!U232+'2.1meta'!U245+'2.1meta'!U262+'2.1meta'!U279+'2.1meta'!U296+'2.1meta'!U313+'2.1meta'!U330 -> 0 | U14: ='2.1meta'!V15+'2.1meta'!V32+'2.1meta'!V49+'2.1meta'!V67+'2.1meta'!V84+'2.1meta'!V101+'2.1meta'!V118+'2.1meta'!V135+'2.1meta'!V152+'2.1meta'!V169+'2.1meta'!V186+'2.1meta'!V203+'2.1meta'!V220+'2.1meta'!V232+'2.1meta'!V245+'2.1meta'!V262+'2.1meta'!V279+'2.1meta'!V296+'2.1meta'!V313+'2.1meta'!V330 -> 0 | V14: ='2.1meta'!W15+'2.1meta'!W32+'2.1meta'!W49+'2.1meta'!W67+'2.1meta'!W84+'2.1meta'!W101+'2.1meta'!W118+'2.1meta'!W135+'2.1meta'!W152+'2.1meta'!W169+'2.1meta'!W186+'2.1meta'!W203+'2.1meta'!W220+'2.1meta'!W232+'2.1meta'!W245+'2.1meta'!W262+'2.1meta'!W279+'2.1meta'!W296+'2.1meta'!W313+'2.1meta'!W330 -> 0 | W14: ='2.1meta'!X15+'2.1meta'!X32+'2.1meta'!X49+'2.1meta'!X67+'2.1meta'!X84+'2.1meta'!X101+'2.1meta'!X118+'2.1meta'!X135+'2.1meta'!X152+'2.1meta'!X169+'2.1meta'!X186+'2.1meta'!X203+'2.1meta'!X220+'2.1meta'!X232+'2.1meta'!X245+'2.1meta'!X262+'2.1meta'!X279+'2.1meta'!X296+'2.1meta'!X313+'2.1meta'!X330 -> 0 | X14: =SUM(Q14:W14) -> 0 | Y14: =O14+X14 -> 0 | Z14: =C14-Y14 -> 0
A15: 2.1.1.9.1.3 | B15: BONIFICACION POR ESCOLARIDAD | C15: ='2.1meta'!D16+'2.1meta'!D33+'2.1meta'!D50+'2.1meta'!D68+'2.1meta'!D85+'2.1meta'!D102+'2.1meta'!D119+'2.1meta'!D136+'2.1meta'!D153+'2.1meta'!D170+'2.1meta'!D187+'2.1meta'!D204+'2.1meta'!D221+'2.1meta'!D233+'2.1meta'!D246+'2.1meta'!D263+'2.1meta'!D280+'2.1meta'!D297+'2.1meta'!D314+'2.1meta'!D331 -> 0 | D15: ='2.1meta'!E16+'2.1meta'!E33+'2.1meta'!E50+'2.1meta'!E68+'2.1meta'!E85+'2.1meta'!E102+'2.1meta'!E119+'2.1meta'!E136+'2.1meta'!E153+'2.1meta'!E170+'2.1meta'!E187+'2.1meta'!E204+'2.1meta'!E221+'2.1meta'!E233+'2.1meta'!E246+'2.1meta'!E263+'2.1meta'!E280+'2.1meta'!E297+'2.1meta'!E314+'2.1meta'!E331 -> 0 | E15: ='2.1meta'!F16+'2.1meta'!F33+'2.1meta'!F50+'2.1meta'!F68+'2.1meta'!F85+'2.1meta'!F102+'2.1meta'!F119+'2.1meta'!F136+'2.1meta'!F153+'2.1meta'!F170+'2.1meta'!F187+'2.1meta'!F204+'2.1meta'!F221+'2.1meta'!F233+'2.1meta'!F246+'2.1meta'!F263+'2.1meta'!F280+'2.1meta'!F297+'2.1meta'!F314+'2.1meta'!F331 -> 0 | F15: ='2.1meta'!G16+'2.1meta'!G33+'2.1meta'!G50+'2.1meta'!G68+'2.1meta'!G85+'2.1meta'!G102+'2.1meta'!G119+'2.1meta'!G136+'2.1meta'!G153+'2.1meta'!G170+'2.1meta'!G187+'2.1meta'!G204+'2.1meta'!G221+'2.1meta'!G233+'2.1meta'!G246+'2.1meta'!G263+'2.1meta'!G280+'2.1meta'!G297+'2.1meta'!G314+'2.1meta'!G331 -> 0 | G15: ='2.1meta'!H16+'2.1meta'!H33+'2.1meta'!H50+'2.1meta'!H68+'2.1meta'!H85+'2.1meta'!H102+'2.1meta'!H119+'2.1meta'!H136+'2.1meta'!H153+'2.1meta'!H170+'2.1meta'!H187+'2.1meta'!H204+'2.1meta'!H221+'2.1meta'!H233+'2.1meta'!H246+'2.1meta'!H263+'2.1meta'!H280+'2.1meta'!H297+'2.1meta'!H314+'2.1meta'!H331 -> 0 | H15: ='2.1meta'!I16+'2.1meta'!I33+'2.1meta'!I50+'2.1meta'!I68+'2.1meta'!I85+'2.1meta'!I102+'2.1meta'!I119+'2.1meta'!I136+'2.1meta'!I153+'2.1meta'!I170+'2.1meta'!I187+'2.1meta'!I204+'2.1meta'!I221+'2.1meta'!I233+'2.1meta'!I246+'2.1meta'!I263+'2.1meta'!I280+'2.1meta'!I297+'2.1meta'!I314+'2.1meta'!I331 -> 0 | I15: ='2.1meta'!J16+'2.1meta'!J33+'2.1meta'!J50+'2.1meta'!J68+'2.1meta'!J85+'2.1meta'!J102+'2.1meta'!J119+'2.1meta'!J136+'2.1meta'!J153+'2.1meta'!J170+'2.1meta'!J187+'2.1meta'!J204+'2.1meta'!J221+'2.1meta'!J233+'2.1meta'!J246+'2.1meta'!J263+'2.1meta'!J280+'2.1meta'!J297+'2.1meta'!J314+'2.1meta'!J331 -> 0 | J15: ='2.1meta'!K16+'2.1meta'!K33+'2.1meta'!K50+'2.1meta'!K68+'2.1meta'!K85+'2.1meta'!K102+'2.1meta'!K119+'2.1meta'!K136+'2.1meta'!K153+'2.1meta'!K170+'2.1meta'!K187+'2.1meta'!K204+'2.1meta'!K221+'2.1meta'!K233+'2.1meta'!K246+'2.1meta'!K263+'2.1meta'!K280+'2.1meta'!K297+'2.1meta'!K314+'2.1meta'!K331 -> 0 | ... N15: ='2.1meta'!O16+'2.1meta'!O33+'2.1meta'!O50+'2.1meta'!O68+'2.1meta'!O85+'2.1meta'!O102+'2.1meta'!O119+'2.1meta'!O136+'2.1meta'!O153+'2.1meta'!O170+'2.1meta'!O187+'2.1meta'!O204+'2.1meta'!O221+'2.1meta'!O233+'2.1meta'!O246+'2.1meta'!O263+'2.1meta'!O280+'2.1meta'!O297+'2.1meta'!O314+'2.1meta'!O331 -> 0 | O15: =SUM(F15:N15) -> 0 | P15: =C15-O15 -> 0 | Q15: ='2.1meta'!R16+'2.1meta'!R33+'2.1meta'!R50+'2.1meta'!R68+'2.1meta'!R85+'2.1meta'!R102+'2.1meta'!R119+'2.1meta'!R136+'2.1meta'!R153+'2.1meta'!R170+'2.1meta'!R187+'2.1meta'!R204+'2.1meta'!R221+'2.1meta'!R233+'2.1meta'!R246+'2.1meta'!R263+'2.1meta'!R280+'2.1meta'!R297+'2.1meta'!R314+'2.1meta'!R331 -> 0 | R15: ='2.1meta'!S16+'2.1meta'!S33+'2.1meta'!S50+'2.1meta'!S68+'2.1meta'!S85+'2.1meta'!S102+'2.1meta'!S119+'2.1meta'!S136+'2.1meta'!S153+'2.1meta'!S170+'2.1meta'!S187+'2.1meta'!S204+'2.1meta'!S221+'2.1meta'!S233+'2.1meta'!S246+'2.1meta'!S263+'2.1meta'!S280+'2.1meta'!S297+'2.1meta'!S314+'2.1meta'!S331 -> 0 | S15: ='2.1meta'!T16+'2.1meta'!T33+'2.1meta'!T50+'2.1meta'!T68+'2.1meta'!T85+'2.1meta'!T102+'2.1meta'!T119+'2.1meta'!T136+'2.1meta'!T153+'2.1meta'!T170+'2.1meta'!T187+'2.1meta'!T204+'2.1meta'!T221+'2.1meta'!T233+'2.1meta'!T246+'2.1meta'!T263+'2.1meta'!T280+'2.1meta'!T297+'2.1meta'!T314+'2.1meta'!T331 -> 0 | T15: ='2.1meta'!U16+'2.1meta'!U33+'2.1meta'!U50+'2.1meta'!U68+'2.1meta'!U85+'2.1meta'!U102+'2.1meta'!U119+'2.1meta'!U136+'2.1meta'!U153+'2.1meta'!U170+'2.1meta'!U187+'2.1meta'!U204+'2.1meta'!U221+'2.1meta'!U233+'2.1meta'!U246+'2.1meta'!U263+'2.1meta'!U280+'2.1meta'!U297+'2.1meta'!U314+'2.1meta'!U331 -> 0 | U15: ='2.1meta'!V16+'2.1meta'!V33+'2.1meta'!V50+'2.1meta'!V68+'2.1meta'!V85+'2.1meta'!V102+'2.1meta'!V119+'2.1meta'!V136+'2.1meta'!V153+'2.1meta'!V170+'2.1meta'!V187+'2.1meta'!V204+'2.1meta'!V221+'2.1meta'!V233+'2.1meta'!V246+'2.1meta'!V263+'2.1meta'!V280+'2.1meta'!V297+'2.1meta'!V314+'2.1meta'!V331 -> 0 | V15: ='2.1meta'!W16+'2.1meta'!W33+'2.1meta'!W50+'2.1meta'!W68+'2.1meta'!W85+'2.1meta'!W102+'2.1meta'!W119+'2.1meta'!W136+'2.1meta'!W153+'2.1meta'!W170+'2.1meta'!W187+'2.1meta'!W204+'2.1meta'!W221+'2.1meta'!W233+'2.1meta'!W246+'2.1meta'!W263+'2.1meta'!W280+'2.1meta'!W297+'2.1meta'!W314+'2.1meta'!W331 -> 0 | W15: ='2.1meta'!X16+'2.1meta'!X33+'2.1meta'!X50+'2.1meta'!X68+'2.1meta'!X85+'2.1meta'!X102+'2.1meta'!X119+'2.1meta'!X136+'2.1meta'!X153+'2.1meta'!X170+'2.1meta'!X187+'2.1meta'!X204+'2.1meta'!X221+'2.1meta'!X233+'2.1meta'!X246+'2.1meta'!X263+'2.1meta'!X280+'2.1meta'!X297+'2.1meta'!X314+'2.1meta'!X331 -> 0 | X15: =SUM(Q15:W15) -> 0 | Y15: =O15+X15 -> 0 | Z15: =C15-Y15 -> 0
A16: 2.1.1.9.2.1 | B16: COMPENSACION POR TIEMPO DE SERVICIOS (CTS) | C16: ='2.1meta'!D17+'2.1meta'!D34+'2.1meta'!D51+'2.1meta'!D69+'2.1meta'!D86+'2.1meta'!D103+'2.1meta'!D120+'2.1meta'!D137+'2.1meta'!D154+'2.1meta'!D171++'2.1meta'!D188+'2.1meta'!D205+'2.1meta'!D222+'2.1meta'!D247+'2.1meta'!D264+'2.1meta'!D281+'2.1meta'!D298+'2.1meta'!D315+'2.1meta'!D332 -> 0 | D16: ='2.1meta'!E17+'2.1meta'!E34+'2.1meta'!E51+'2.1meta'!E69+'2.1meta'!E86+'2.1meta'!E103+'2.1meta'!E120+'2.1meta'!E137+'2.1meta'!E154+'2.1meta'!E171++'2.1meta'!E188+'2.1meta'!E205+'2.1meta'!E222+'2.1meta'!E247+'2.1meta'!E264+'2.1meta'!E281+'2.1meta'!E298+'2.1meta'!E315+'2.1meta'!E332 -> 0 | E16: ='2.1meta'!F17+'2.1meta'!F34+'2.1meta'!F51+'2.1meta'!F69+'2.1meta'!F86+'2.1meta'!F103+'2.1meta'!F120+'2.1meta'!F137+'2.1meta'!F154+'2.1meta'!F171++'2.1meta'!F188+'2.1meta'!F205+'2.1meta'!F222+'2.1meta'!F247+'2.1meta'!F264+'2.1meta'!F281+'2.1meta'!F298+'2.1meta'!F315+'2.1meta'!F332 -> 0 | F16: ='2.1meta'!G17+'2.1meta'!G34+'2.1meta'!G51+'2.1meta'!G69+'2.1meta'!G86+'2.1meta'!G103+'2.1meta'!G120+'2.1meta'!G137+'2.1meta'!G154+'2.1meta'!G171++'2.1meta'!G188+'2.1meta'!G205+'2.1meta'!G222+'2.1meta'!G247+'2.1meta'!G264+'2.1meta'!G281+'2.1meta'!G298+'2.1meta'!G315+'2.1meta'!G332 -> 0 | G16: ='2.1meta'!H17+'2.1meta'!H34+'2.1meta'!H51+'2.1meta'!H69+'2.1meta'!H86+'2.1meta'!H103+'2.1meta'!H120+'2.1meta'!H137+'2.1meta'!H154+'2.1meta'!H171++'2.1meta'!H188+'2.1meta'!H205+'2.1meta'!H222+'2.1meta'!H247+'2.1meta'!H264+'2.1meta'!H281+'2.1meta'!H298+'2.1meta'!H315+'2.1meta'!H332 -> 0 | H16: ='2.1meta'!I17+'2.1meta'!I34+'2.1meta'!I51+'2.1meta'!I69+'2.1meta'!I86+'2.1meta'!I103+'2.1meta'!I120+'2.1meta'!I137+'2.1meta'!I154+'2.1meta'!I171++'2.1meta'!I188+'2.1meta'!I205+'2.1meta'!I222+'2.1meta'!I247+'2.1meta'!I264+'2.1meta'!I281+'2.1meta'!I298+'2.1meta'!I315+'2.1meta'!I332 -> 0 | I16: ='2.1meta'!J17+'2.1meta'!J34+'2.1meta'!J51+'2.1meta'!J69+'2.1meta'!J86+'2.1meta'!J103+'2.1meta'!J120+'2.1meta'!J137+'2.1meta'!J154+'2.1meta'!J171++'2.1meta'!J188+'2.1meta'!J205+'2.1meta'!J222+'2.1meta'!J247+'2.1meta'!J264+'2.1meta'!J281+'2.1meta'!J298+'2.1meta'!J315+'2.1meta'!J332 -> 0 | J16: ='2.1meta'!K17+'2.1meta'!K34+'2.1meta'!K51+'2.1meta'!K69+'2.1meta'!K86+'2.1meta'!K103+'2.1meta'!K120+'2.1meta'!K137+'2.1meta'!K154+'2.1meta'!K171++'2.1meta'!K188+'2.1meta'!K205+'2.1meta'!K222+'2.1meta'!K247+'2.1meta'!K264+'2.1meta'!K281+'2.1meta'!K298+'2.1meta'!K315+'2.1meta'!K332 -> 0 | ... N16: ='2.1meta'!O17+'2.1meta'!O34+'2.1meta'!O51+'2.1meta'!O69+'2.1meta'!O86+'2.1meta'!O103+'2.1meta'!O120+'2.1meta'!O137+'2.1meta'!O154+'2.1meta'!O171++'2.1meta'!O188+'2.1meta'!O205+'2.1meta'!O222+'2.1meta'!O247+'2.1meta'!O264+'2.1meta'!O281+'2.1meta'!O298+'2.1meta'!O315+'2.1meta'!O332 -> 0 | O16: =SUM(F16:N16) -> 0 | P16: =C16-O16 -> 0 | Q16: ='2.1meta'!R17+'2.1meta'!R34+'2.1meta'!R51+'2.1meta'!R69+'2.1meta'!R86+'2.1meta'!R103+'2.1meta'!R120+'2.1meta'!R137+'2.1meta'!R154+'2.1meta'!R171++'2.1meta'!R188+'2.1meta'!R205+'2.1meta'!R222+'2.1meta'!R247+'2.1meta'!R264+'2.1meta'!R281+'2.1meta'!R298+'2.1meta'!R315+'2.1meta'!R332 -> 0 | R16: ='2.1meta'!S17+'2.1meta'!S34+'2.1meta'!S51+'2.1meta'!S69+'2.1meta'!S86+'2.1meta'!S103+'2.1meta'!S120+'2.1meta'!S137+'2.1meta'!S154+'2.1meta'!S171++'2.1meta'!S188+'2.1meta'!S205+'2.1meta'!S222+'2.1meta'!S247+'2.1meta'!S264+'2.1meta'!S281+'2.1meta'!S298+'2.1meta'!S315+'2.1meta'!S332 -> 0 | S16: ='2.1meta'!T17+'2.1meta'!T34+'2.1meta'!T51+'2.1meta'!T69+'2.1meta'!T86+'2.1meta'!T103+'2.1meta'!T120+'2.1meta'!T137+'2.1meta'!T154+'2.1meta'!T171++'2.1meta'!T188+'2.1meta'!T205+'2.1meta'!T222+'2.1meta'!T247+'2.1meta'!T264+'2.1meta'!T281+'2.1meta'!T298+'2.1meta'!T315+'2.1meta'!T332 -> 0 | T16: ='2.1meta'!U17+'2.1meta'!U34+'2.1meta'!U51+'2.1meta'!U69+'2.1meta'!U86+'2.1meta'!U103+'2.1meta'!U120+'2.1meta'!U137+'2.1meta'!U154+'2.1meta'!U171++'2.1meta'!U188+'2.1meta'!U205+'2.1meta'!U222+'2.1meta'!U247+'2.1meta'!U264+'2.1meta'!U281+'2.1meta'!U298+'2.1meta'!U315+'2.1meta'!U332 -> 0 | U16: ='2.1meta'!V17+'2.1meta'!V34+'2.1meta'!V51+'2.1meta'!V69+'2.1meta'!V86+'2.1meta'!V103+'2.1meta'!V120+'2.1meta'!V137+'2.1meta'!V154+'2.1meta'!V171++'2.1meta'!V188+'2.1meta'!V205+'2.1meta'!V222+'2.1meta'!V247+'2.1meta'!V264+'2.1meta'!V281+'2.1meta'!V298+'2.1meta'!V315+'2.1meta'!V332 -> 0 | V16: ='2.1meta'!W17+'2.1meta'!W34+'2.1meta'!W51+'2.1meta'!W69+'2.1meta'!W86+'2.1meta'!W103+'2.1meta'!W120+'2.1meta'!W137+'2.1meta'!W154+'2.1meta'!W171++'2.1meta'!W188+'2.1meta'!W205+'2.1meta'!W222+'2.1meta'!W247+'2.1meta'!W264+'2.1meta'!W281+'2.1meta'!W298+'2.1meta'!W315+'2.1meta'!W332 -> 0 | W16: ='2.1meta'!X17+'2.1meta'!X34+'2.1meta'!X51+'2.1meta'!X69+'2.1meta'!X86+'2.1meta'!X103+'2.1meta'!X120+'2.1meta'!X137+'2.1meta'!X154+'2.1meta'!X171++'2.1meta'!X188+'2.1meta'!X205+'2.1meta'!X222+'2.1meta'!X247+'2.1meta'!X264+'2.1meta'!X281+'2.1meta'!X298+'2.1meta'!X315+'2.1meta'!X332 -> 0 | X16: =SUM(Q16:W16) -> 0 | Y16: =O16+X16 -> 0 | Z16: =C16-Y16 -> 0
A17: 2.1.1.9.3.3 | B17: COMPENSACION VACACIONAL (VACACIONES TRUNCAS) | C17: ='2.1meta'!D18+'2.1meta'!D35+'2.1meta'!D52+'2.1meta'!D70+'2.1meta'!D87+'2.1meta'!D104+'2.1meta'!D121+'2.1meta'!D138+'2.1meta'!D155+'2.1meta'!D172+'2.1meta'!D189+'2.1meta'!D206+'2.1meta'!D223+'2.1meta'!D248+'2.1meta'!D265+'2.1meta'!D282+'2.1meta'!D299+'2.1meta'!D316+'2.1meta'!D333 -> 0 | D17: ='2.1meta'!E18+'2.1meta'!E35+'2.1meta'!E52+'2.1meta'!E70+'2.1meta'!E87+'2.1meta'!E104+'2.1meta'!E121+'2.1meta'!E138+'2.1meta'!E155+'2.1meta'!E172+'2.1meta'!E189+'2.1meta'!E206+'2.1meta'!E223+'2.1meta'!E248+'2.1meta'!E265+'2.1meta'!E282+'2.1meta'!E299+'2.1meta'!E316+'2.1meta'!E333 -> 0 | E17: ='2.1meta'!F18+'2.1meta'!F35+'2.1meta'!F52+'2.1meta'!F70+'2.1meta'!F87+'2.1meta'!F104+'2.1meta'!F121+'2.1meta'!F138+'2.1meta'!F155+'2.1meta'!F172+'2.1meta'!F189+'2.1meta'!F206+'2.1meta'!F223+'2.1meta'!F248+'2.1meta'!F265+'2.1meta'!F282+'2.1meta'!F299+'2.1meta'!F316+'2.1meta'!F333 -> 0 | F17: ='2.1meta'!G18+'2.1meta'!G35+'2.1meta'!G52+'2.1meta'!G70+'2.1meta'!G87+'2.1meta'!G104+'2.1meta'!G121+'2.1meta'!G138+'2.1meta'!G155+'2.1meta'!G172+'2.1meta'!G189+'2.1meta'!G206+'2.1meta'!G223+'2.1meta'!G248+'2.1meta'!G265+'2.1meta'!G282+'2.1meta'!G299+'2.1meta'!G316+'2.1meta'!G333 -> 0 | G17: ='2.1meta'!H18+'2.1meta'!H35+'2.1meta'!H52+'2.1meta'!H70+'2.1meta'!H87+'2.1meta'!H104+'2.1meta'!H121+'2.1meta'!H138+'2.1meta'!H155+'2.1meta'!H172+'2.1meta'!H189+'2.1meta'!H206+'2.1meta'!H223+'2.1meta'!H248+'2.1meta'!H265+'2.1meta'!H282+'2.1meta'!H299+'2.1meta'!H316+'2.1meta'!H333 -> 0 | H17: ='2.1meta'!I18+'2.1meta'!I35+'2.1meta'!I52+'2.1meta'!I70+'2.1meta'!I87+'2.1meta'!I104+'2.1meta'!I121+'2.1meta'!I138+'2.1meta'!I155+'2.1meta'!I172+'2.1meta'!I189+'2.1meta'!I206+'2.1meta'!I223+'2.1meta'!I248+'2.1meta'!I265+'2.1meta'!I282+'2.1meta'!I299+'2.1meta'!I316+'2.1meta'!I333 -> 0 | I17: ='2.1meta'!J18+'2.1meta'!J35+'2.1meta'!J52+'2.1meta'!J70+'2.1meta'!J87+'2.1meta'!J104+'2.1meta'!J121+'2.1meta'!J138+'2.1meta'!J155+'2.1meta'!J172+'2.1meta'!J189+'2.1meta'!J206+'2.1meta'!J223+'2.1meta'!J248+'2.1meta'!J265+'2.1meta'!J282+'2.1meta'!J299+'2.1meta'!J316+'2.1meta'!J333 -> 0 | J17: ='2.1meta'!K18+'2.1meta'!K35+'2.1meta'!K52+'2.1meta'!K70+'2.1meta'!K87+'2.1meta'!K104+'2.1meta'!K121+'2.1meta'!K138+'2.1meta'!K155+'2.1meta'!K172+'2.1meta'!K189+'2.1meta'!K206+'2.1meta'!K223+'2.1meta'!K248+'2.1meta'!K265+'2.1meta'!K282+'2.1meta'!K299+'2.1meta'!K316+'2.1meta'!K333 -> 0 | ... N17: ='2.1meta'!O18+'2.1meta'!O35+'2.1meta'!O52+'2.1meta'!O70+'2.1meta'!O87+'2.1meta'!O104+'2.1meta'!O121+'2.1meta'!O138+'2.1meta'!O155+'2.1meta'!O172+'2.1meta'!O189+'2.1meta'!O206+'2.1meta'!O223+'2.1meta'!O248+'2.1meta'!O265+'2.1meta'!O282+'2.1meta'!O299+'2.1meta'!O316+'2.1meta'!O333 -> 0 | O17: =SUM(F17:N17) -> 0 | P17: =C17-O17 -> 0 | Q17: ='2.1meta'!R18+'2.1meta'!R35+'2.1meta'!R52+'2.1meta'!R70+'2.1meta'!R87+'2.1meta'!R104+'2.1meta'!R121+'2.1meta'!R138+'2.1meta'!R155+'2.1meta'!R172+'2.1meta'!R189+'2.1meta'!R206+'2.1meta'!R223+'2.1meta'!R248+'2.1meta'!R265+'2.1meta'!R282+'2.1meta'!R299+'2.1meta'!R316+'2.1meta'!R333 -> 0 | R17: ='2.1meta'!S18+'2.1meta'!S35+'2.1meta'!S52+'2.1meta'!S70+'2.1meta'!S87+'2.1meta'!S104+'2.1meta'!S121+'2.1meta'!S138+'2.1meta'!S155+'2.1meta'!S172+'2.1meta'!S189+'2.1meta'!S206+'2.1meta'!S223+'2.1meta'!S248+'2.1meta'!S265+'2.1meta'!S282+'2.1meta'!S299+'2.1meta'!S316+'2.1meta'!S333 -> 0 | S17: ='2.1meta'!T18+'2.1meta'!T35+'2.1meta'!T52+'2.1meta'!T70+'2.1meta'!T87+'2.1meta'!T104+'2.1meta'!T121+'2.1meta'!T138+'2.1meta'!T155+'2.1meta'!T172+'2.1meta'!T189+'2.1meta'!T206+'2.1meta'!T223+'2.1meta'!T248+'2.1meta'!T265+'2.1meta'!T282+'2.1meta'!T299+'2.1meta'!T316+'2.1meta'!T333 -> 0 | T17: ='2.1meta'!U18+'2.1meta'!U35+'2.1meta'!U52+'2.1meta'!U70+'2.1meta'!U87+'2.1meta'!U104+'2.1meta'!U121+'2.1meta'!U138+'2.1meta'!U155+'2.1meta'!U172+'2.1meta'!U189+'2.1meta'!U206+'2.1meta'!U223+'2.1meta'!U248+'2.1meta'!U265+'2.1meta'!U282+'2.1meta'!U299+'2.1meta'!U316+'2.1meta'!U333 -> 0 | U17: ='2.1meta'!V18+'2.1meta'!V35+'2.1meta'!V52+'2.1meta'!V70+'2.1meta'!V87+'2.1meta'!V104+'2.1meta'!V121+'2.1meta'!V138+'2.1meta'!V155+'2.1meta'!V172+'2.1meta'!V189+'2.1meta'!V206+'2.1meta'!V223+'2.1meta'!V248+'2.1meta'!V265+'2.1meta'!V282+'2.1meta'!V299+'2.1meta'!V316+'2.1meta'!V333 -> 0 | V17: ='2.1meta'!W18+'2.1meta'!W35+'2.1meta'!W52+'2.1meta'!W70+'2.1meta'!W87+'2.1meta'!W104+'2.1meta'!W121+'2.1meta'!W138+'2.1meta'!W155+'2.1meta'!W172+'2.1meta'!W189+'2.1meta'!W206+'2.1meta'!W223+'2.1meta'!W248+'2.1meta'!W265+'2.1meta'!W282+'2.1meta'!W299+'2.1meta'!W316+'2.1meta'!W333 -> 0 | W17: ='2.1meta'!X18+'2.1meta'!X35+'2.1meta'!X52+'2.1meta'!X70+'2.1meta'!X87+'2.1meta'!X104+'2.1meta'!X121+'2.1meta'!X138+'2.1meta'!X155+'2.1meta'!X172+'2.1meta'!X189+'2.1meta'!X206+'2.1meta'!X223+'2.1meta'!X248+'2.1meta'!X265+'2.1meta'!X282+'2.1meta'!X299+'2.1meta'!X316+'2.1meta'!X333 -> 0 | X17: =SUM(Q17:W17) -> 0 | Y17: =O17+X17 -> 0 | Z17: =C17-Y17 -> 0
A18: 2.1.1.9.3.99 | B18: OTRAS OCASIONALES | C18: ='2.1meta'!D19+'2.1meta'!D36+'2.1meta'!D53+'2.1meta'!D71+'2.1meta'!D88+'2.1meta'!D105+'2.1meta'!D122+'2.1meta'!D139+'2.1meta'!D156+'2.1meta'!D173++'2.1meta'!D190+'2.1meta'!D207+'2.1meta'!D224+'2.1meta'!D249+'2.1meta'!D266+'2.1meta'!D283+'2.1meta'!D300+'2.1meta'!D317+'2.1meta'!D334 -> 0 | D18: ='2.1meta'!E19+'2.1meta'!E36+'2.1meta'!E53+'2.1meta'!E71+'2.1meta'!E88+'2.1meta'!E105+'2.1meta'!E122+'2.1meta'!E139+'2.1meta'!E156+'2.1meta'!E173++'2.1meta'!E190+'2.1meta'!E207+'2.1meta'!E224+'2.1meta'!E249+'2.1meta'!E266+'2.1meta'!E283+'2.1meta'!E300+'2.1meta'!E317+'2.1meta'!E334 -> 0 | E18: ='2.1meta'!F19+'2.1meta'!F36+'2.1meta'!F53+'2.1meta'!F71+'2.1meta'!F88+'2.1meta'!F105+'2.1meta'!F122+'2.1meta'!F139+'2.1meta'!F156+'2.1meta'!F173++'2.1meta'!F190+'2.1meta'!F207+'2.1meta'!F224+'2.1meta'!F249+'2.1meta'!F266+'2.1meta'!F283+'2.1meta'!F300+'2.1meta'!F317+'2.1meta'!F334 -> 0 | F18: ='2.1meta'!G19+'2.1meta'!G36+'2.1meta'!G53+'2.1meta'!G71+'2.1meta'!G88+'2.1meta'!G105+'2.1meta'!G122+'2.1meta'!G139+'2.1meta'!G156+'2.1meta'!G173++'2.1meta'!G190+'2.1meta'!G207+'2.1meta'!G224+'2.1meta'!G249+'2.1meta'!G266+'2.1meta'!G283+'2.1meta'!G300+'2.1meta'!G317+'2.1meta'!G334 -> 0 | G18: ='2.1meta'!H19+'2.1meta'!H36+'2.1meta'!H53+'2.1meta'!H71+'2.1meta'!H88+'2.1meta'!H105+'2.1meta'!H122+'2.1meta'!H139+'2.1meta'!H156+'2.1meta'!H173++'2.1meta'!H190+'2.1meta'!H207+'2.1meta'!H224+'2.1meta'!H249+'2.1meta'!H266+'2.1meta'!H283+'2.1meta'!H300+'2.1meta'!H317+'2.1meta'!H334 -> 0 | H18: ='2.1meta'!I19+'2.1meta'!I36+'2.1meta'!I53+'2.1meta'!I71+'2.1meta'!I88+'2.1meta'!I105+'2.1meta'!I122+'2.1meta'!I139+'2.1meta'!I156+'2.1meta'!I173++'2.1meta'!I190+'2.1meta'!I207+'2.1meta'!I224+'2.1meta'!I249+'2.1meta'!I266+'2.1meta'!I283+'2.1meta'!I300+'2.1meta'!I317+'2.1meta'!I334 -> 0 | I18: ='2.1meta'!J19+'2.1meta'!J36+'2.1meta'!J53+'2.1meta'!J71+'2.1meta'!J88+'2.1meta'!J105+'2.1meta'!J122+'2.1meta'!J139+'2.1meta'!J156+'2.1meta'!J173++'2.1meta'!J190+'2.1meta'!J207+'2.1meta'!J224+'2.1meta'!J249+'2.1meta'!J266+'2.1meta'!J283+'2.1meta'!J300+'2.1meta'!J317+'2.1meta'!J334 -> 0 | J18: ='2.1meta'!K19+'2.1meta'!K36+'2.1meta'!K53+'2.1meta'!K71+'2.1meta'!K88+'2.1meta'!K105+'2.1meta'!K122+'2.1meta'!K139+'2.1meta'!K156+'2.1meta'!K173++'2.1meta'!K190+'2.1meta'!K207+'2.1meta'!K224+'2.1meta'!K249+'2.1meta'!K266+'2.1meta'!K283+'2.1meta'!K300+'2.1meta'!K317+'2.1meta'!K334 -> 0 | ... N18: ='2.1meta'!O19+'2.1meta'!O36+'2.1meta'!O53+'2.1meta'!O71+'2.1meta'!O88+'2.1meta'!O105+'2.1meta'!O122+'2.1meta'!O139+'2.1meta'!O156+'2.1meta'!O173++'2.1meta'!O190+'2.1meta'!O207+'2.1meta'!O224+'2.1meta'!O249+'2.1meta'!O266+'2.1meta'!O283+'2.1meta'!O300+'2.1meta'!O317+'2.1meta'!O334 -> 0 | O18: =SUM(F18:N18) -> 0 | P18: =C18-O18 -> 0 | Q18: ='2.1meta'!R19+'2.1meta'!R36+'2.1meta'!R53+'2.1meta'!R71+'2.1meta'!R88+'2.1meta'!R105+'2.1meta'!R122+'2.1meta'!R139+'2.1meta'!R156+'2.1meta'!R173++'2.1meta'!R190+'2.1meta'!R207+'2.1meta'!R224+'2.1meta'!R249+'2.1meta'!R266+'2.1meta'!R283+'2.1meta'!R300+'2.1meta'!R317+'2.1meta'!R334 -> 0 | R18: ='2.1meta'!S19+'2.1meta'!S36+'2.1meta'!S53+'2.1meta'!S71+'2.1meta'!S88+'2.1meta'!S105+'2.1meta'!S122+'2.1meta'!S139+'2.1meta'!S156+'2.1meta'!S173++'2.1meta'!S190+'2.1meta'!S207+'2.1meta'!S224+'2.1meta'!S249+'2.1meta'!S266+'2.1meta'!S283+'2.1meta'!S300+'2.1meta'!S317+'2.1meta'!S334 -> 0 | S18: ='2.1meta'!T19+'2.1meta'!T36+'2.1meta'!T53+'2.1meta'!T71+'2.1meta'!T88+'2.1meta'!T105+'2.1meta'!T122+'2.1meta'!T139+'2.1meta'!T156+'2.1meta'!T173++'2.1meta'!T190+'2.1meta'!T207+'2.1meta'!T224+'2.1meta'!T249+'2.1meta'!T266+'2.1meta'!T283+'2.1meta'!T300+'2.1meta'!T317+'2.1meta'!T334 -> 0 | T18: ='2.1meta'!U19+'2.1meta'!U36+'2.1meta'!U53+'2.1meta'!U71+'2.1meta'!U88+'2.1meta'!U105+'2.1meta'!U122+'2.1meta'!U139+'2.1meta'!U156+'2.1meta'!U173++'2.1meta'!U190+'2.1meta'!U207+'2.1meta'!U224+'2.1meta'!U249+'2.1meta'!U266+'2.1meta'!U283+'2.1meta'!U300+'2.1meta'!U317+'2.1meta'!U334 -> 0 | U18: ='2.1meta'!V19+'2.1meta'!V36+'2.1meta'!V53+'2.1meta'!V71+'2.1meta'!V88+'2.1meta'!V105+'2.1meta'!V122+'2.1meta'!V139+'2.1meta'!V156+'2.1meta'!V173++'2.1meta'!V190+'2.1meta'!V207+'2.1meta'!V224+'2.1meta'!V249+'2.1meta'!V266+'2.1meta'!V283+'2.1meta'!V300+'2.1meta'!V317+'2.1meta'!V334 -> 0 | V18: ='2.1meta'!W19+'2.1meta'!W36+'2.1meta'!W53+'2.1meta'!W71+'2.1meta'!W88+'2.1meta'!W105+'2.1meta'!W122+'2.1meta'!W139+'2.1meta'!W156+'2.1meta'!W173++'2.1meta'!W190+'2.1meta'!W207+'2.1meta'!W224+'2.1meta'!W249+'2.1meta'!W266+'2.1meta'!W283+'2.1meta'!W300+'2.1meta'!W317+'2.1meta'!W334 -> 0 | W18: ='2.1meta'!X19+'2.1meta'!X36+'2.1meta'!X53+'2.1meta'!X71+'2.1meta'!X88+'2.1meta'!X105+'2.1meta'!X122+'2.1meta'!X139+'2.1meta'!X156+'2.1meta'!X173++'2.1meta'!X190+'2.1meta'!X207+'2.1meta'!X224+'2.1meta'!X249+'2.1meta'!X266+'2.1meta'!X283+'2.1meta'!X300+'2.1meta'!X317+'2.1meta'!X334 -> 0 | X18: =SUM(Q18:W18) -> 0 | Y18: =O18+X18 -> 0 | Z18: =C18-Y18 -> 0
A19: 2.1.3.1.1.1 | B19: APORTES A LOS FONDOS DE SALUD | C19: ='2.1meta'!D20+'2.1meta'!D37+'2.1meta'!D54+'2.1meta'!D72+'2.1meta'!D89+'2.1meta'!D106+'2.1meta'!D123+'2.1meta'!D140+'2.1meta'!D157+'2.1meta'!D174+'2.1meta'!D191+'2.1meta'!D208+'2.1meta'!D225+'2.1meta'!D234+'2.1meta'!D250+'2.1meta'!D267+'2.1meta'!D284+'2.1meta'!D301+'2.1meta'!D318+'2.1meta'!D335 -> 0 | D19: ='2.1meta'!E20+'2.1meta'!E37+'2.1meta'!E54+'2.1meta'!E72+'2.1meta'!E89+'2.1meta'!E106+'2.1meta'!E123+'2.1meta'!E140+'2.1meta'!E157+'2.1meta'!E174+'2.1meta'!E191+'2.1meta'!E208+'2.1meta'!E225+'2.1meta'!E234+'2.1meta'!E250+'2.1meta'!E267+'2.1meta'!E284+'2.1meta'!E301+'2.1meta'!E318+'2.1meta'!E335 -> 0 | E19: ='2.1meta'!F20+'2.1meta'!F37+'2.1meta'!F54+'2.1meta'!F72+'2.1meta'!F89+'2.1meta'!F106+'2.1meta'!F123+'2.1meta'!F140+'2.1meta'!F157+'2.1meta'!F174+'2.1meta'!F191+'2.1meta'!F208+'2.1meta'!F225+'2.1meta'!F234+'2.1meta'!F250+'2.1meta'!F267+'2.1meta'!F284+'2.1meta'!F301+'2.1meta'!F318+'2.1meta'!F335 -> 0 | F19: ='2.1meta'!G20+'2.1meta'!G37+'2.1meta'!G54+'2.1meta'!G72+'2.1meta'!G89+'2.1meta'!G106+'2.1meta'!G123+'2.1meta'!G140+'2.1meta'!G157+'2.1meta'!G174+'2.1meta'!G191+'2.1meta'!G208+'2.1meta'!G225+'2.1meta'!G234+'2.1meta'!G250+'2.1meta'!G267+'2.1meta'!G284+'2.1meta'!G301+'2.1meta'!G318+'2.1meta'!G335 -> 0 | G19: ='2.1meta'!H20+'2.1meta'!H37+'2.1meta'!H54+'2.1meta'!H72+'2.1meta'!H89+'2.1meta'!H106+'2.1meta'!H123+'2.1meta'!H140+'2.1meta'!H157+'2.1meta'!H174+'2.1meta'!H191+'2.1meta'!H208+'2.1meta'!H225+'2.1meta'!H234+'2.1meta'!H250+'2.1meta'!H267+'2.1meta'!H284+'2.1meta'!H301+'2.1meta'!H318+'2.1meta'!H335 -> 0 | H19: ='2.1meta'!I20+'2.1meta'!I37+'2.1meta'!I54+'2.1meta'!I72+'2.1meta'!I89+'2.1meta'!I106+'2.1meta'!I123+'2.1meta'!I140+'2.1meta'!I157+'2.1meta'!I174+'2.1meta'!I191+'2.1meta'!I208+'2.1meta'!I225+'2.1meta'!I234+'2.1meta'!I250+'2.1meta'!I267+'2.1meta'!I284+'2.1meta'!I301+'2.1meta'!I318+'2.1meta'!I335 -> 0 | I19: ='2.1meta'!J20+'2.1meta'!J37+'2.1meta'!J54+'2.1meta'!J72+'2.1meta'!J89+'2.1meta'!J106+'2.1meta'!J123+'2.1meta'!J140+'2.1meta'!J157+'2.1meta'!J174+'2.1meta'!J191+'2.1meta'!J208+'2.1meta'!J225+'2.1meta'!J234+'2.1meta'!J250+'2.1meta'!J267+'2.1meta'!J284+'2.1meta'!J301+'2.1meta'!J318+'2.1meta'!J335 -> 0 | J19: ='2.1meta'!K20+'2.1meta'!K37+'2.1meta'!K54+'2.1meta'!K72+'2.1meta'!K89+'2.1meta'!K106+'2.1meta'!K123+'2.1meta'!K140+'2.1meta'!K157+'2.1meta'!K174+'2.1meta'!K191+'2.1meta'!K208+'2.1meta'!K225+'2.1meta'!K234+'2.1meta'!K250+'2.1meta'!K267+'2.1meta'!K284+'2.1meta'!K301+'2.1meta'!K318+'2.1meta'!K335 -> 0 | ... N19: ='2.1meta'!O20+'2.1meta'!O37+'2.1meta'!O54+'2.1meta'!O72+'2.1meta'!O89+'2.1meta'!O106+'2.1meta'!O123+'2.1meta'!O140+'2.1meta'!O157+'2.1meta'!O174+'2.1meta'!O191+'2.1meta'!O208+'2.1meta'!O225+'2.1meta'!O234+'2.1meta'!O250+'2.1meta'!O267+'2.1meta'!O284+'2.1meta'!O301+'2.1meta'!O318+'2.1meta'!O335 -> 0 | O19: =SUM(F19:N19) -> 0 | P19: =C19-O19 -> 0 | Q19: ='2.1meta'!R20+'2.1meta'!R37+'2.1meta'!R54+'2.1meta'!R72+'2.1meta'!R89+'2.1meta'!R106+'2.1meta'!R123+'2.1meta'!R140+'2.1meta'!R157+'2.1meta'!R174+'2.1meta'!R191+'2.1meta'!R208+'2.1meta'!R225+'2.1meta'!R234+'2.1meta'!R250+'2.1meta'!R267+'2.1meta'!R284+'2.1meta'!R301+'2.1meta'!R318+'2.1meta'!R335 -> 0 | R19: ='2.1meta'!S20+'2.1meta'!S37+'2.1meta'!S54+'2.1meta'!S72+'2.1meta'!S89+'2.1meta'!S106+'2.1meta'!S123+'2.1meta'!S140+'2.1meta'!S157+'2.1meta'!S174+'2.1meta'!S191+'2.1meta'!S208+'2.1meta'!S225+'2.1meta'!S234+'2.1meta'!S250+'2.1meta'!S267+'2.1meta'!S284+'2.1meta'!S301+'2.1meta'!S318+'2.1meta'!S335 -> 0 | S19: ='2.1meta'!T20+'2.1meta'!T37+'2.1meta'!T54+'2.1meta'!T72+'2.1meta'!T89+'2.1meta'!T106+'2.1meta'!T123+'2.1meta'!T140+'2.1meta'!T157+'2.1meta'!T174+'2.1meta'!T191+'2.1meta'!T208+'2.1meta'!T225+'2.1meta'!T234+'2.1meta'!T250+'2.1meta'!T267+'2.1meta'!T284+'2.1meta'!T301+'2.1meta'!T318+'2.1meta'!T335 -> 0 | T19: ='2.1meta'!U20+'2.1meta'!U37+'2.1meta'!U54+'2.1meta'!U72+'2.1meta'!U89+'2.1meta'!U106+'2.1meta'!U123+'2.1meta'!U140+'2.1meta'!U157+'2.1meta'!U174+'2.1meta'!U191+'2.1meta'!U208+'2.1meta'!U225+'2.1meta'!U234+'2.1meta'!U250+'2.1meta'!U267+'2.1meta'!U284+'2.1meta'!U301+'2.1meta'!U318+'2.1meta'!U335 -> 0 | U19: ='2.1meta'!V20+'2.1meta'!V37+'2.1meta'!V54+'2.1meta'!V72+'2.1meta'!V89+'2.1meta'!V106+'2.1meta'!V123+'2.1meta'!V140+'2.1meta'!V157+'2.1meta'!V174+'2.1meta'!V191+'2.1meta'!V208+'2.1meta'!V225+'2.1meta'!V234+'2.1meta'!V250+'2.1meta'!V267+'2.1meta'!V284+'2.1meta'!V301+'2.1meta'!V318+'2.1meta'!V335 -> 0 | V19: ='2.1meta'!W20+'2.1meta'!W37+'2.1meta'!W54+'2.1meta'!W72+'2.1meta'!W89+'2.1meta'!W106+'2.1meta'!W123+'2.1meta'!W140+'2.1meta'!W157+'2.1meta'!W174+'2.1meta'!W191+'2.1meta'!W208+'2.1meta'!W225+'2.1meta'!W234+'2.1meta'!W250+'2.1meta'!W267+'2.1meta'!W284+'2.1meta'!W301+'2.1meta'!W318+'2.1meta'!W335 -> 0 | W19: ='2.1meta'!X20+'2.1meta'!X37+'2.1meta'!X54+'2.1meta'!X72+'2.1meta'!X89+'2.1meta'!X106+'2.1meta'!X123+'2.1meta'!X140+'2.1meta'!X157+'2.1meta'!X174+'2.1meta'!X191+'2.1meta'!X208+'2.1meta'!X225+'2.1meta'!X234+'2.1meta'!X250+'2.1meta'!X267+'2.1meta'!X284+'2.1meta'!X301+'2.1meta'!X318+'2.1meta'!X335 -> 0 | X19: =SUM(Q19:W19) -> 0 | Y19: =O19+X19 -> 0 | Z19: =C19-Y19 -> 0
