Workbook

Sheet 2.1meta
A1: CUADRO DE EJECUCION Y PROYECCIÓN DE GASTOS DE LA GG 2.1 - EJERCICIO 2021 AL 17 DE SETIEMBRE 2021
A2: UE: 003 G.A AREQUIPA
A4: Meta | B4: E.G. | C4: Descripción Específica Gasto | D4: PIM (1) | E4: Certificado | F4: Compromiso Anual | H4: Saldo Presupuestal al 17.09.2021 | I4: Proyección Planillas Activas | U4: Proyeccion de plazas vacantes | W4: PAGO FACTURAS EPS | X4: BENEFICIOS | Y4: TOTAL PROYECCIÓN | Z4: TOTAL EJECUCION +PROYECCION (2) | AA4: Saldo disponible ( 1-2)
G5: TOTAL EJECUCION | I5: Enero | J5: Febrero | K5: Marzo | L5: Abril | M5: Mayo | N5: Junio | O5: Julio | P5: Agosto | Q5: Setiembre | R5: Octubre | S5: Noviembre | T5: Diciembre | U5: 276 | V5: 728
A6: 0002 | D6: =SUBTOTAL(9,D7:D21) -> 0 | E6: =SUBTOTAL(9,E7:E21) -> 0 | F6: =SUBTOTAL(9,F7:F21) -> 0 | G6: 0 | H6: =D6-G6 -> 0 | I6: =SUBTOTAL(9,I7:I21) -> 0 | J6: =SUBTOTAL(9,J7:J21) -> 0 | K6: =SUBTOTAL(9,K7:K21) -> 0 | L6: =SUBTOTAL(9,L7:L21) -> 0 | M6: =SUBTOTAL(9,M7:M21) -> 0 | N6: =SUBTOTAL(9,N7:N21) -> 0 | O6: =SUBTOTAL(9,O7:O21) -> 0 | P6: =SUBTOTAL(9,P7:P21) -> 0 | ... X6: =SUBTOTAL(9,X7:X21) -> 0 | Y6: =SUM(I6:X6) -> 0 | Z6: =+G6+Y6 -> 0 | AA6: =+D6-Z6 -> 0
A7: 0002 | B7: 2.1.1.1.1.2 | C7: PERSONAL ADMINISTRATIVO NOMBRADO (REGIMEN PUBLICO) | G7: 0 | H7: =D7-G7 -> 0 | Y7: =SUM(I7:X7) -> 0 | Z7: =+G7+Y7 -> 0 | AA7: =+D7-Z7 -> 0
A8: 0002 | B8: 2.1.1.1.1.4 | C8: PERSONAL CON CONTRATO A PLAZO INDETERMINADO (REGIMEN | G8: 0 | H8: =D8-G8 -> 0 | Y8: =SUM(I8:X8) -> 0 | Z8: =+G8+Y8 -> 0 | AA8: =+D8-Z8 -> 0
A9: 0002 | B9: 2.1.1.1.1.5 | C9: PERSONAL CON CONTRATO A PLAZO FIJO (REGIMEN LABORAL | G9: 0 | H9: =D9-G9 -> 0 | Y9: =SUM(I9:X9) -> 0 | Z9: =+G9+Y9 -> 0 | AA9: =+D9-Z9 -> 0
A10: 0002 | B10: 2.1.1.1.2.1 | C10: ASIGNACION A FONDOS PARA PERSONAL | G10: 0 | H10: =D10-G10 -> 0 | Y10: =SUM(I10:X10) -> 0 | Z10: =+G10+Y10 -> 0 | AA10: =+D10-Z10 -> 0
A11: 0002 | B11: 2.1.1.4.1.1 | C11: PERSONAL NOMBRADO | G11: 0 | H11: =D11-G11 -> 0 | Y11: =SUM(I11:X11) -> 0 | Z11: =+G11+Y11 -> 0 | AA11: =+D11-Z11 -> 0
A12: 0002 | B12: 2.1.1.4.2.1 | C12: BONO POR FUNCION JURISDICCIONAL Y FISCAL | G12: 0 | H12: =D12-G12 -> 0 | Y12: =SUM(I12:X12) -> 0 | Z12: =+G12+Y12 -> 0 | AA12: =+D12-Z12 -> 0
A13: 0002 | B13: 2.1.1.4.2.2 | C13: ASIGNACION POR GASTOS OPERATIVOS | G13: 0 | H13: =D13-G13 -> 0 | Y13: =SUM(I13:X13) -> 0 | Z13: =+G13+Y13 -> 0 | AA13: =+D13-Z13 -> 0
A14: 0002 | B14: 2.1.1.9.1.1 | C14: GRATIFICACIONES | G14: 0 | H14: =D14-G14 -> 0 | Y14: =SUM(I14:X14) -> 0 | Z14: =+G14+Y14 -> 0 | AA14: =+D14-Z14 -> 0
A15: 0002 | B15: 2.1.1.9.1.2 | C15: AGUINALDOS | G15: 0 | H15: =D15-G15 -> 0 | Y15: =SUM(I15:X15) -> 0 | Z15: =+G15+Y15 -> 0 | AA15: =+D15-Z15 -> 0
A16: 0002 | B16: 2.1.1.9.1.3 | C16: BONIFICACION POR ESCOLARIDAD | G16: 0 | H16: =D16-G16 -> 0 | Y16: =SUM(I16:X16) -> 0 | Z16: =+G16+Y16 -> 0 | AA16: =+D16-Z16 -> 0
A17: 0002 | B17: 2.1.1.9.2.1 | C17: COMPENSACION POR TIEMPO DE SERVICIOS (CTS) | G17: 0 | H17: =D17-G17 -> 0 | Y17: =SUM(I17:X17) -> 0 | Z17: =+G17+Y17 -> 0 | AA17: =+D17-Z17 -> 0
A18: 0002 | B18: 2.1.1.9.3.99 | C18: OTRAS OCASIONALES | G18: 0 | H18: =D18-G18 -> 0 | Y18: =SUM(I18:X18) -> 0 | Z18: =+G18+Y18 -> 0 | AA18: =+D18-Z18 -> 0
... A21: 0002 | B21: 2.1.3.1.1.5 | C21: CONTRIBUCIONES A ESSALUD | G21: 0 | H21: =D21-G21 -> 0 | Y21: =SUM(I21:X21) -> 0 | Z21: =+G21+Y21 -> 0 | AA21: =+D21-Z21 -> 0
A22: 0003 | D22: =SUBTOTAL(9,D23:D38) -> 0 | E22: =SUBTOTAL(9,E23:E38) -> 0 | F22: =SUBTOTAL(9,F23:F38) -> 0 | G22: 0 | H22: =D22-G22 -> 0 | I22: =SUBTOTAL(9,I23:I38) -> 0 | J22: =SUBTOTAL(9,J23:J38) -> 0 | K22: =SUBTOTAL(9,K23:K38) -> 0 | L22: =SUBTOTAL(9,L23:L38) -> 0 | M22: =SUBTOTAL(9,M23:M38) -> 0 | N22: =SUBTOTAL(9,N23:N38) -> 0 | O22: =SUBTOTAL(9,O23:O38) -> 0 | P22: =SUBTOTAL(9,P23:P38) -> 0 | ... X22: =SUBTOTAL(9,X23:X38) -> 0 | Y22: =SUM(I22:X22) -> 0 | Z22: =+G22+Y22 -> 0 | AA22: =+D22-Z22 -> 0
A23: 0003 | B23: 2.1.1.1.1.2 | C23: PERSONAL ADMINISTRATIVO NOMBRADO (REGIMEN PUBLICO) | G23: 0 | H23: =D23-G23 -> 0 | Y23: =SUM(I23:X23) -> 0 | Z23: =+G23+Y23 -> 0 | AA23: =+D23-Z23 -> 0
A24: 0003 | B24: 2.1.1.1.1.4 | C24: PERSONAL CON CONTRATO A PLAZO INDETERMINADO (REGIMEN | G24: 0 | H24: =D24-G24 -> 0 | Y24: =SUM(I24:X24) -> 0 | Z24: =+G24+Y24 -> 0 | AA24: =+D24-Z24 -> 0
A25: 0003 | B25: 2.1.1.1.1.5 | C25: PERSONAL CON CONTRATO A PLAZO FIJO (REGIMEN LABORAL | G25: 0 | H25: =D25-G25 -> 0 | Y25: =SUM(I25:X25) -> 0 | Z25: =+G25+Y25 -> 0 | AA25: =+D25-Z25 -> 0
A26: 0003 | B26: 2.1.1.1.2.1 | C26: ASIGNACION A FONDOS PARA PERSONAL | G26: 0 | H26: =D26-G26 -> 0 | Y26: =SUM(I26:X26) -> 0 | Z26: =+G26+Y26 -> 0 | AA26: =+D26-Z26 -> 0
A27: 0003 | B27: 2.1.1.4.1.1 | C27: PERSONAL NOMBRADO | G27: 0 | H27: =D27-G27 -> 0 | Y27: =SUM(I27:X27) -> 0 | Z27: =+G27+Y27 -> 0 | AA27: =+D27-Z27 -> 0
A28: 0003 | B28: 2.1.1.4.2.1 | C28: BONO POR FUNCION JURISDICCIONAL Y FISCAL | G28: 0 | H28: =D28-G28 -> 0 | Y28: =SUM(I28:X28) -> 0 | Z28: =+G28+Y28 -> 0 | AA28: =+D28-Z28 -> 0
A29: 0003 | B29: 2.1.1.4.2.2 | C29: ASIGNACION POR GASTOS OPERATIVOS | G29: 0 | H29: =D29-G29 -> 0 | Y29: =SUM(I29:X29) -> 0 | Z29: =+G29+Y29 -> 0 | AA29: =+D29-Z29 -> 0
A30: 0003 | B30: 2.1.1.9.1.1 | C30: GRATIFICACIONES | G30: 0 | H30: =D30-G30 -> 0 | Y30: =SUM(I30:X30) -> 0 | Z30: =+G30+Y30 -> 0 | AA30: =+D30-Z30 -> 0
A31: 0003 | B31: 2.1.1.9.1.2 | C31: AGUINALDOS | G31: 0 | H31: =D31-G31 -> 0 | Y31: =SUM(I31:X31) -> 0 | Z31: =+G31+Y31 -> 0 | AA31: =+D31-Z31 -> 0
A32: 0003 | B32: 2.1.1.9.1.3 | C32: BONIFICACION POR ESCOLARIDAD | G32: 0 | H32: =D32-G32 -> 0 | Y32: =SUM(I32:X32) -> 0 | Z32: =+G32+Y32 -> 0 | AA32: =+D32-Z32 -> 0
A33: 0003 | B33: 2.1.1.9.2.1 | C33: COMPENSACION POR TIEMPO DE SERVICIOS (CTS) | G33: 0 | H33: =D33-G33 -> 0 | Y33: =SUM(I33:X33) -> 0 | Z33: =+G33+Y33 -> 0 | AA33: =+D33-Z33 -> 0
A34: 0003 | B34: 2.1.1.9.3.3 | C34: COMPENSACION VACACIONAL (VACACIONES TRUNCAS) | G34: 0 | H34: =D34-G34 -> 0 | Y34: =SUM(I34:X34) -> 0 | Z34: =+G34+Y34 -> 0 | AA34: =+D34-Z34 -> 0
... A38: 0003 | B38: 2.1.3.1.1.5 | C38: CONTRIBUCIONES A ESSALUD | G38: 0 | H38: =D38-G38 -> 0 | Y38: =SUM(I38:X38) -> 0 | Z38: =+G38+Y38 -> 0 | AA38: =+D38-Z38 -> 0
A39: 0004 | D39: =SUBTOTAL(9,D40:D48) -> 0 | E39: =SUBTOTAL(9,E40:E48) -> 0 | F39: =SUBTOTAL(9,F40:F48) -> 0 | G39: 0 | H39: =D39-G39 -> 0 | I39: =SUBTOTAL(9,I40:I48) -> 0 | J39: =SUBTOTAL(9,J40:J48) -> 0 | K39: =SUBTOTAL(9,K40:K48) -> 0 | L39: =SUBTOTAL(9,L40:L48) -> 0 | M39: =SUBTOTAL(9,M40:M48) -> 0 | N39: =SUBTOTAL(9,N40:N48) -> 0 | O39: =SUBTOTAL(9,O40:O48) -> 0 | P39: =SUBTOTAL(9,P40:P48) -> 0 | ... X39: =SUBTOTAL(9,X40:X48) -> 0 | Y39: =SUM(I39:X39) -> 0 | Z39: =+G39+Y39 -> 0 | AA39: =+D39-Z39 -> 0
A40: 0004 | B40: 2.1.1.1.1.4 | C40: PERSONAL CON CONTRATO A PLAZO INDETERMINADO (REGIMEN | G40: 0 | H40: =D40-G40 -> 0 | Y40: =SUM(I40:X40) -> 0 | Z40: =+G40+Y40 -> 0 | AA40: =+D40-Z40 -> 0
A41: 0004 | B41: 2.1.1.1.1.5 | C41: PERSONAL CON CONTRATO A PLAZO FIJO (REGIMEN LABORAL | G41: 0 | H41: =D41-G41 -> 0 | Y41: =SUM(I41:X41) -> 0 | Z41: =+G41+Y41 -> 0 | AA41: =+D41-Z41 -> 0
A42: 0004 | B42: 2.1.1.3.1.2 | C42: PERSONAL CONTRATADO | G42: 0 | H42: =D42-G42 -> 0 | Y42: =SUM(I42:X42) -> 0 | Z42: =+G42+Y42 -> 0 | AA42: =+D42-Z42 -> 0
A43: 0004 | B43: 2.1.1.9.1.1 | C43: GRATIFICACIONES | G43: 0 | H43: =D43-G43 -> 0 | Y43: =SUM(I43:X43) -> 0 | Z43: =+G43+Y43 -> 0 | AA43: =+D43-Z43 -> 0
A44: 0004 | B44: 2.1.1.9.1.3 | C44: BONIFICACION POR ESCOLARIDAD | G44: 0 | H44: =D44-G44 -> 0 | Y44: =SUM(I44:X44) -> 0 | Z44: =+G44+Y44 -> 0 | AA44: =+D44-Z44 -> 0
A45: 0004 | B45: 2.1.1.9.2.1 | C45: COMPENSACION POR TIEMPO DE SERVICIOS (CTS) | G45: 0 | H45: =D45-G45 -> 0 | Y45: =SUM(I45:X45) -> 0 | Z45: =+G45+Y45 -> 0 | AA45: =+D45-Z45 -> 0
A46: 0004 | B46: 2.1.1.9.3.99 | C46: OTRAS OCASIONALES | G46: 0 | H46: =D46-G46 -> 0 | Y46: =SUM(I46:X46) -> 0 | Z46: =+G46+Y46 -> 0 | AA46: =+D46-Z46 -> 0
A47: 0004 | B47: 2.1.3.1.1.1 | C47: APORTES A LOS FONDOS DE SALUD | G47: 0 | H47: =D47-G47 -> 0 | Y47: =SUM(I47:X47) -> 0 | Z47: =+G47+Y47 -> 0 | AA47: =+D47-Z47 -> 0
A48: 0004 | B48: 2.1.3.1.1.5 | C48: CONTRIBUCIONES A ESSALUD | G48: 0 | H48: =D48-G48 -> 0 | Y48: =SUM(I48:X48) -> 0 | Z48: =+G48+Y48 -> 0 | AA48: =+D48-Z48 -> 0
A49: 0005 | D49: =SUBTOTAL(9,D50:D61) -> 0 | E49: =SUBTOTAL(9,E50:E61) -> 0 | F49: =SUBTOTAL(9,F50:F61) -> 0 | G49: 0 | H49: =D49-G49 -> 0 | I49: =SUBTOTAL(9,I50:I61) -> 0 | J49: =SUBTOTAL(9,J50:J61) -> 0 | K49: =SUBTOTAL(9,K50:K61) -> 0 | L49: =SUBTOTAL(9,L50:L61) -> 0 | M49: =SUBTOTAL(9,M50:M61) -> 0 | N49: =SUBTOTAL(9,N50:N61) -> 0 | O49: =SUBTOTAL(9,O50:O61) -> 0 | P49: =SUBTOTAL(9,P50:P61) -> 0 | ... X49: =SUBTOTAL(9,X50:X61) -> 0 | Y49: =SUM(I49:X49) -> 0 | Z49: =+G49+Y49 -> 0 | AA49: =+D49-Z49 -> 0
A50: 0005 | B50: 2.1.1.1.1.2 | C50: PERSONAL ADMINISTRATIVO NOMBRADO (REGIMEN PUBLICO) | G50: 0 | H50: =D50-G50 -> 0 | Y50: =SUM(I50:X50) -> 0 | Z50: =+G50+Y50 -> 0 | AA50: =+D50-Z50 -> 0
A51: 0005 | B51: 2.1.1.1.1.4 | C51: PERSONAL CON CONTRATO A PLAZO INDETERMINADO (REGIMEN | G51: 0 | H51: =D51-G51 -> 0 | Y51: =SUM(I51:X51) -> 0 | Z51: =+G51+Y51 -> 0 | AA51: =+D51-Z51 -> 0
A52: 0005 | B52: 2.1.1.1.1.5 | C52: PERSONAL CON CONTRATO A PLAZO FIJO (REGIMEN LABORAL | G52: 0 | H52: =D52-G52 -> 0 | Y52: =SUM(I52:X52) -> 0 | Z52: =+G52+Y52 -> 0 | AA52: =+D52-Z52 -> 0
A53: 0005 | B53: 2.1.1.1.2.1 | C53: ASIGNACION A FONDOS PARA PERSONAL | G53: 0 | H53: =D53-G53 -> 0 | Y53: =SUM(I53:X53) -> 0 | Z53: =+G53+Y53 -> 0 | AA53: =+D53-Z53 -> 0
A54: 0005 | B54: 2.1.1.9.1.1 | C54: GRATIFICACIONES | G54: 0 | H54: =D54-G54 -> 0 | Y54: =SUM(I54:X54) -> 0 | Z54: =+G54+Y54 -> 0 | AA54: =+D54-Z54 -> 0
A55: 0005 | B55: 2.1.1.9.1.2 | C55: AGUINALDOS | G55: 0 | H55: =D55-G55 -> 0 | Y55: =SUM(I55:X55) -> 0 | Z55: =+G55+Y55 -> 0 | AA55: =+D55-Z55 -> 0
A56: 0005 | B56: 2.1.1.9.1.3 | C56: BONIFICACION POR ESCOLARIDAD | G56: 0 | H56: =D56-G56 -> 0 | Y56: =SUM(I56:X56) -> 0 | Z56: =+G56+Y56 -> 0 | AA56: =+D56-Z56 -> 0
A57: 0005 | B57: 2.1.1.9.2.1 | C57: COMPENSACION POR TIEMPO DE SERVICIOS (CTS) | G57: 0 | H57: =D57-G57 -> 0 | Y57: =SUM(I57:X57) -> 0 | Z57: =+G57+Y57 -> 0 | AA57: =+D57-Z57 -> 0
A58: 0005 | B58: 2.1.1.9.3.3 | C58: COMPENSACION VACACIONAL (VACACIONES TRUNCAS) | G58: 0 | H58: =D58-G58 -> 0 | Y58: =SUM(I58:X58) -> 0 | Z58: =+G58+Y58 -> 0 | AA58: =+D58-Z58 -> 0
A59: 0005 | B59: 2.1.1.9.3.99 | C59: OTRAS OCASIONALES | G59: 0 | H59: =D59-G59 -> 0 | Y59: =SUM(I59:X59) -> 0 | Z59: =+G59+Y59 -> 0 | AA59: =+D59-Z59 -> 0
A60: 0005 | B60: 2.1.3.1.1.1 | C60: APORTES A LOS FONDOS DE SALUD | G60: 0 | H60: =D60-G60 -> 0 | Y60: =SUM(I60:X60) -> 0 | Z60: =+G60+Y60 -> 0 | AA60: =+D60-Z60 -> 0
A61: 0005 | B61: 2.1.3.1.1.5 | C61: CONTRIBUCIONES A ESSALUD | G61: 0 | H61: =D61-G61 -> 0 | Y61: =SUM(I61:X61) -> 0 | Z61: =+G61+Y61 -> 0 | AA61: =+D61-Z61 -> 0
A62: 0009 | D62: =SUBTOTAL(9,D63:D77) -> 0 | E62: =SUBTOTAL(9,E63:E77) -> 0 | F62: =SUBTOTAL(9,F63:F77) -> 0 | G62: 0 | H62: =D62-G62 -> 0 | I62: =SUBTOTAL(9,I63:I77) -> 0 | J62: =SUBTOTAL(9,J63:J77) -> 0 | K62: =SUBTOTAL(9,K63:K77) -> 0 | L62: =SUBTOTAL(9,L63:L77) -> 0 | M62: =SUBTOTAL(9,M63:M77) -> 0 | N62: =SUBTOTAL(9,N63:N77) -> 0 | O62: =SUBTOTAL(9,O63:O77) -> 0 | P62: =SUBTOTAL(9,P63:P77) -> 0 | ... X62: =SUBTOTAL(9,X63:X77) -> 0 | Y62: =SUM(I62:X62) -> 0 | Z62: =+G62+Y62 -> 0 | AA62: =+D62-Z62 -> 0
A63: 0009 | B63: 2.1.1.1.1.2 | C63: PERSONAL ADMINISTRATIVO NOMBRADO (REGIMEN PUBLICO) | G63: 0 | H63: =D63-G63 -> 0 | Y63: =SUM(I63:X63) -> 0 | Z63: =+G63+Y63 -> 0 | AA63: =+D63-Z63 -> 0
A64: 0009 | B64: 2.1.1.1.1.4 | C64: PERSONAL CON CONTRATO A PLAZO INDETERMINADO (REGIMEN | G64: 0 | H64: =D64-G64 -> 0 | Y64: =SUM(I64:X64) -> 0 | Z64: =+G64+Y64 -> 0 | AA64: =+D64-Z64 -> 0
A65: 0009 | B65: 2.1.1.1.1.5 | C65: PERSONAL CON CONTRATO A PLAZO FIJO (REGIMEN LABORAL | G65: 0 | H65: =D65-G65 -> 0 | Y65: =SUM(I65:X65) -> 0 | Z65: =+G65+Y65 -> 0 | AA65: =+D65-Z65 -> 0
A66: 0009 | B66: 2.1.1.1.2.1 | C66: ASIGNACION A FONDOS PARA PERSONAL | G66: 0 | H66: =D66-G66 -> 0 | Y66: =SUM(I66:X66) -> 0 | Z66: =+G66+Y66 -> 0 | AA66: =+D66-Z66 -> 0
A67: 0009 | B67: 2.1.1.4.1.1 | C67: PERSONAL NOMBRADO | G67: 0 | H67: =D67-G67 -> 0 | Y67: =SUM(I67:X67) -> 0 | Z67: =+G67+Y67 -> 0 | AA67: =+D67-Z67 -> 0
A68: 0009 | B68: 2.1.1.4.2.1 | C68: BONO POR FUNCION JURISDICCIONAL Y FISCAL | G68: 0 | H68: =D68-G68 -> 0 | Y68: =SUM(I68:X68) -> 0 | Z68: =+G68+Y68 -> 0 | AA68: =+D68-Z68 -> 0
A69: 0009 | B69: 2.1.1.4.2.2 | C69: ASIGNACION POR GASTOS OPERATIVOS | G69: 0 | H69: =D69-G69 -> 0 | Y69: =SUM(I69:X69) -> 0 | Z69: =+G69+Y69 -> 0 | AA69: =+D69-Z69 -> 0
A70: 0009 | B70: 2.1.1.9.1.1 | C70: GRATIFICACIONES | G70: 0 | H70: =D70-G70 -> 0 | Y70: =SUM(I70:X70) -> 0 | Z70: =+G70+Y70 -> 0 | AA70: =+D70-Z70 -> 0
A71: 0009 | B71: 2.1.1.9.1.2 | C71: AGUINALDOS | G71: 0 | H71: =D71-G71 -> 0 | Y71: =SUM(I71:X71) -> 0 | Z71: =+G71+Y71 -> 0 | AA71: =+D71-Z71 -> 0
A72: 0009 | B72: 2.1.1.9.1.3 | C72: BONIFICACION POR ESCOLARIDAD | G72: 0 | H72: =D72-G72 -> 0 | Y72: =SUM(I72:X72) -> 0 | Z72: =+G72+Y72 -> 0 | AA72: =+D72-Z72 -> 0
A73: 0009 | B73: 2.1.1.9.2.1 | C73: COMPENSACION POR TIEMPO DE SERVICIOS (CTS) | G73: 0 | H73: =D73-G73 -> 0 | Y73: =SUM(I73:X73) -> 0 | Z73: =+G73+Y73 -> 0 | AA73: =+D73-Z73 -> 0
A74: 0009 | B74: 2.1.1.9.3.99 | C74: OTRAS OCASIONALES | G74: 0 | H74: =D74-G74 -> 0 | Y74: =SUM(I74:X74) -> 0 | Z74: =+G74+Y74 -> 0 | AA74: =+D74-Z74 -> 0
... A77: 0009 | B77: 2.1.3.1.1.5 | C77: CONTRIBUCIONES A ESSALUD | G77: 0 | H77: =D77-G77 -> 0 | Y77: =SUM(I77:X77) -> 0 | Z77: =+G77+Y77 -> 0 | AA77: =+D77-Z77 -> 0
A78: 0010 | D78: =SUBTOTAL(9,D79:D90) -> 0 | E78: =SUBTOTAL(9,E79:E90) -> 0 | F78: =SUBTOTAL(9,F79:F90) -> 0 | G78: 0 | H78: =D78-G78 -> 0 | I78: =SUBTOTAL(9,I79:I90) -> 0 | J78: =SUBTOTAL(9,J79:J90) -> 0 | K78: =SUBTOTAL(9,K79:K90) -> 0 | L78: =SUBTOTAL(9,L79:L90) -> 0 | M78: =SUBTOTAL(9,M79:M90) -> 0 | N78: =SUBTOTAL(9,N79:N90) -> 0 | O78: =SUBTOTAL(9,O79:O90) -> 0 | P78: =SUBTOTAL(9,P79:P90) -> 0 | ... X78: =SUBTOTAL(9,X79:X90) -> 0 | Y78: =SUM(I78:X78) -> 0 | Z78: =+G78+Y78 -> 0 | AA78: =+D78-Z78 -> 0
A79: 0010 | B79: 2.1.1.1.1.4 | C79: PERSONAL CON CONTRATO A PLAZO INDETERMINADO (REGIMEN | G79: 0 | H79: =D79-G79 -> 0 | Y79: =SUM(I79:X79) -> 0 | Z79: =+G79+Y79 -> 0 | AA79: =+D79-Z79 -> 0
A80: 0010 | B80: 2.1.1.4.1.1 | C80: PERSONAL NOMBRADO | G80: 0 | H80: =D80-G80 -> 0 | Y80: =SUM(I80:X80) -> 0 | Z80: =+G80+Y80 -> 0 | AA80: =+D80-Z80 -> 0
A81: 0010 | B81: 2.1.1.4.2.1 | C81: BONO POR FUNCION JURISDICCIONAL Y FISCAL | G81: 0 | H81: =D81-G81 -> 0 | Y81: =SUM(I81:X81) -> 0 | Z81: =+G81+Y81 -> 0 | AA81: =+D81-Z81 -> 0
A82: 0010 | B82: 2.1.1.4.2.2 | C82: ASIGNACION POR GASTOS OPERATIVOS | G82: 0 | H82: =D82-G82 -> 0 | Y82: =SUM(I82:X82) -> 0 | Z82: =+G82+Y82 -> 0 | AA82: =+D82-Z82 -> 0
A83: 0010 | B83: 2.1.1.9.1.1 | C83: GRATIFICACIONES | G83: 0 | H83: =D83-G83 -> 0 | Y83: =SUM(I83:X83) -> 0 | Z83: =+G83+Y83 -> 0 | AA83: =+D83-Z83 -> 0
A84: 0010 | B84: 2.1.1.9.1.2 | C84: AGUINALDOS | G84: 0 | H84: =D84-G84 -> 0 | Y84: =SUM(I84:X84) -> 0 | Z84: =+G84+Y84 -> 0 | AA84: =+D84-Z84 -> 0
A85: 0010 | B85: 2.1.1.9.1.3 | C85: BONIFICACION POR ESCOLARIDAD | G85: 0 | H85: =D85-G85 -> 0 | Y85: =SUM(I85:X85) -> 0 | Z85: =+G85+Y85 -> 0 | AA85: =+D85-Z85 -> 0
A86: 0010 | B86: 2.1.1.9.2.1 | C86: COMPENSACION POR TIEMPO DE SERVICIOS (CTS) | G86: 0 | H86: =D86-G86 -> 0 | Y86: =SUM(I86:X86) -> 0 | Z86: =+G86+Y86 -> 0 | AA86: =+D86-Z86 -> 0
A87: 0010 | B87: 2.1.1.9.3.99 | C87: OTRAS OCASIONALES | G87: 0 | H87: =D87-G87 -> 0 | Y87: =SUM(I87:X87) -> 0 | Z87: =+G87+Y87 -> 0 | AA87: =+D87-Z87 -> 0
A88: 0010 | B88: 2.1.3.1.1.1 | C88: APORTES A LOS FONDOS DE SALUD | G88: 0 | H88: =D88-G88 -> 0 | Y88: =SUM(I88:X88) -> 0 | Z88: =+G88+Y88 -> 0 | AA88: =+D88-Z88 -> 0
A89: 0010 | B89: 2.1.3.1.1.3 | C89: APORTES A LOS FONDOS DE PENSIONES | G89: 0 | H89: =D89-G89 -> 0 | Y89: =SUM(I89:X89) -> 0 | Z89: =+G89+Y89 -> 0 | AA89: =+D89-Z89 -> 0
A90: 0010 | B90: 2.1.3.1.1.5 | C90: CONTRIBUCIONES A ESSALUD | G90: 0 | H90: =D90-G90 -> 0 | Y90: =SUM(I90:X90) -> 0 | Z90: =+G90+Y90 -> 0 | AA90: =+D90-Z90 -> 0
A91: 0011 | D91: =SUBTOTAL(9,D92:D102) -> 0 | E91: =SUBTOTAL(9,E92:E102) -> 0 | F91: =SUBTOTAL(9,F92:F102) -> 0 | G91: 0 | H91: =D91-G91 -> 0 | I91: =SUBTOTAL(9,I92:I102) -> 0 | J91: =SUBTOTAL(9,J92:J102) -> 0 | K91: =SUBTOTAL(9,K92:K102) -> 0 | L91: =SUBTOTAL(9,L92:L102) -> 0 | M91: =SUBTOTAL(9,M92:M102) -> 0 | N91: =SUBTOTAL(9,N92:N102) -> 0 | O91: =SUBTOTAL(9,O92:O102) -> 0 | P91: =SUBTOTAL(9,P92:P102) -> 0 | ... X91: =SUBTOTAL(9,X92:X102) -> 0 | Y91: =SUM(I91:X91) -> 0 | Z91: =+G91+Y91 -> 0 | AA91: =+D91-Z91 -> 0
A92: 0011 | B92: 2.1.1.1.1.4 | C92: PERSONAL CON CONTRATO A PLAZO INDETERMINADO (REGIMEN | G92: 0 | H92: =D92-G92 -> 0 | Y92: =SUM(I92:X92) -> 0 | Z92: =+G92+Y92 -> 0 | AA92: =+D92-Z92 -> 0
A93: 0011 | B93: 2.1.1.1.1.5 | C93: PERSONAL CON CONTRATO A PLAZO FIJO (REGIMEN LABORAL | G93: 0 | H93: =D93-G93 -> 0 | Y93: =SUM(I93:X93) -> 0 | Z93: =+G93+Y93 -> 0 | AA93: =+D93-Z93 -> 0
A94: 0011 | B94: 2.1.1.4.1.1 | C94: PERSONAL NOMBRADO | G94: 0 | H94: =D94-G94 -> 0 | Y94: =SUM(I94:X94) -> 0 | Z94: =+G94+Y94 -> 0 | AA94: =+D94-Z94 -> 0
A95: 0011 | B95: 2.1.1.4.2.1 | C95: BONO POR FUNCION JURISDICCIONAL Y FISCAL | G95: 0 | H95: =D95-G95 -> 0 | Y95: =SUM(I95:X95) -> 0 | Z95: =+G95+Y95 -> 0 | AA95: =+D95-Z95 -> 0
A96: 0011 | B96: 2.1.1.4.2.2 | C96: ASIGNACION POR GASTOS OPERATIVOS | G96: 0 | H96: =D96-G96 -> 0 | Y96: =SUM(I96:X96) -> 0 | Z96: =+G96+Y96 -> 0 | AA96: =+D96-Z96 -> 0
A97: 0011 | B97: 2.1.1.9.1.1 | C97: GRATIFICACIONES | G97: 0 | H97: =D97-G97 -> 0 | Y97: =SUM(I97:X97) -> 0 | Z97: =+G97+Y97 -> 0 | AA97: =+D97-Z97 -> 0
A98: 0011 | B98: 2.1.1.9.1.2 | C98: AGUINALDOS | G98: 0 | H98: =D98-G98 -> 0 | Y98: =SUM(I98:X98) -> 0 | Z98: =+G98+Y98 -> 0 | AA98: =+D98-Z98 -> 0
A99: 0011 | B99: 2.1.1.9.1.3 | C99: BONIFICACION POR ESCOLARIDAD | G99: 0 | H99: =D99-G99 -> 0 | Y99: =SUM(I99:X99) -> 0 | Z99: =+G99+Y99 -> 0 | AA99: =+D99-Z99 -> 0
A100: 0011 | B100: 2.1.1.9.2.1 | C100: COMPENSACION POR TIEMPO DE SERVICIOS (CTS) | G100: 0 | H100: =D100-G100 -> 0 | Y100: =SUM(I100:X100) -> 0 | Z100: =+G100+Y100 -> 0 | AA100: =+D100-Z100 -> 0
A101: 0011 | B101: 2.1.1.9.3.99 | C101: OTRAS OCASIONALES | G101: 0 | H101: =D101-G101 -> 0 | Y101: =SUM(I101:X101) -> 0 | Z101: =+G101+Y101 -> 0 | AA101: =+D101-Z101 -> 0
A102: 0011 | B102: 2.1.3.1.1.5 | C102: CONTRIBUCIONES A ESSALUD | G102: 0 | H102: =D102-G102 -> 0 | Y102: =SUM(I102:X102) -> 0 | Z102: =+G102+Y102 -> 0 | AA102: =+D102-Z102 -> 0
A103: 0012 | D103: =SUBTOTAL(9,D104:D113) -> 0 | E103: =SUBTOTAL(9,E104:E113) -> 0 | F103: =SUBTOTAL(9,F104:F113) -> 0 | G103: 0 | H103: =D103-G103 -> 0 | I103: =SUBTOTAL(9,I104:I113) -> 0 | J103: =SUBTOTAL(9,J104:J113) -> 0 | K103: =SUBTOTAL(9,K104:K113) -> 0 | L103: =SUBTOTAL(9,L104:L113) -> 0 | M103: =SUBTOTAL(9,M104:M113) -> 0 | N103: =SUBTOTAL(9,N104:N113) -> 0 | O103: =SUBTOTAL(9,O104:O113) -> 0 | P103: =SUBTOTAL(9,P104:P113) -> 0 | ... X103: =SUBTOTAL(9,X104:X113) -> 0 | Y103: =SUM(I103:X103) -> 0 | Z103: =+G103+Y103 -> 0 | AA103: =+D103-Z103 -> 0
A104: 0012 | B104: 2.1.1.1.1.4 | C104: PERSONAL CON CONTRATO A PLAZO INDETERMINADO (REGIMEN | G104: 0 | H104: =D104-G104 -> 0 | Y104: =SUM(I104:X104) -> 0 | Z104: =+G104+Y104 -> 0 | AA104: =+D104-Z104 -> 0
A105: 0012 | B105: 2.1.1.4.1.1 | C105: PERSONAL NOMBRADO | G105: 0 | H105: =D105-G105 -> 0 | Y105: =SUM(I105:X105) -> 0 | Z105: =+G105+Y105 -> 0 | AA105: =+D105-Z105 -> 0
A106: 0012 | B106: 2.1.1.4.2.1 | C106: BONO POR FUNCION JURISDICCIONAL Y FISCAL | G106: 0 | H106: =D106-G106 -> 0 | Y106: =SUM(I106:X106) -> 0 | Z106: =+G106+Y106 -> 0 | AA106: =+D106-Z106 -> 0
A107: 0012 | B107: 2.1.1.4.2.2 | C107: ASIGNACION POR GASTOS OPERATIVOS | G107: 0 | H107: =D107-G107 -> 0 | Y107: =SUM(I107:X107) -> 0 | Z107: =+G107+Y107 -> 0 | AA107: =+D107-Z107 -> 0
A108: 0012 | B108: 2.1.1.9.1.1 | C108: GRATIFICACIONES | G108: 0 | H108: =D108-G108 -> 0 | Y108: =SUM(I108:X108) -> 0 | Z108: =+G108+Y108 -> 0 | AA108: =+D108-Z108 -> 0
...

Sheet CATEGORIA PRESUPUESTAL
A1: EJECUTORA: 0003 MINISTERIO PUBLICO - GERENCIA ADMINISTRATIVA DE AREQUIPA (1419)
A3: Cat pptal/ Detalle Específica de Gasto | C3: PIM | D3: Certificado | E3: Compromiso Anual | F3: T O T A L | G3: Saldo Presupuestal al 17.09.2021 | H3: Proyección Planillas Activa | T3: Proyeccion de plazas vacantes | V3: PAGO FACTURAS EPS | W3: BENEFICIOS | X3: TOTAL PROYECCION | Y3: TOTAL EJECUCION +PROYECCION | Z3: SALDO DISPONIBLE
H4: 01 ENERO | I4: 02 FEBRERO | J4: 03 MARZO | K4: 04 ABRIL | L4: 05 MAYO | M4: 06 JUNIO | N4: 07 JULIO | O4: 08 AGOSTO | P4: 09 SETIEMBRE | Q4: 10 OCTUBRE | R4: 11 OCTUBRE | S4: 12 OCTUBRE | T4: 276 | U4: 728
A5: 0086 MEJORA DE LOS SERVICIOS DEL SISTEMA DE JUSTICIA PENAL | C5: =SUBTOTAL(9,C6:C22) -> 0 | D5: =SUBTOTAL(9,D6:D22) -> 0 | E5: =SUBTOTAL(9,E6:E22) -> 0 | F5: =SUBTOTAL(9,F6:F22) -> 0 | G5: =C5-F5 -> 0 | H5: =SUBTOTAL(9,H6:H22) -> 0 | I5: =SUBTOTAL(9,I6:I22) -> 0 | J5: =SUBTOTAL(9,J6:J22) -> 0 | K5: =SUBTOTAL(9,K6:K22) -> 0 | L5: =SUBTOTAL(9,L6:L22) -> 0 | M5: =SUBTOTAL(9,M6:M22) -> 0 | N5: =SUBTOTAL(9,N6:N22) -> 0 | O5: =SUBTOTAL(9,O6:O22) -> 0 | ... Z5: =SUBTOTAL(9,Z6:Z22) -> 0
A6: 2.1.1.1.1.2 | B6: PERSONAL ADMINISTRATIVO NOMBRADO (REGIMEN PUBLICO) | C6: ='2.1meta'!D7+'2.1meta'!D23 -> 0 | D6: ='2.1meta'!E7+'2.1meta'!E23 -> 0 | E6: ='2.1meta'!F7+'2.1meta'!F23 -> 0 | F6: 0 | G6: =C6-F6 -> 0 | H6: ='2.1meta'!I7+'2.1meta'!I23 -> 0 | I6: ='2.1meta'!J7+'2.1meta'!J23 -> 0 | J6: ='2.1meta'!K7+'2.1meta'!K23 -> 0 | K6: ='2.1meta'!L7+'2.1meta'!L23 -> 0 | L6: ='2.1meta'!M7+'2.1meta'!M23 -> 0 | M6: ='2.1meta'!N7+'2.1meta'!N23 -> 0 | N6: ='2.1meta'!O7+'2.1meta'!O23 -> 0 | O6: ='2.1meta'!P7+'2.1meta'!P23 -> 0 | ... W6: ='2.1meta'!X7+'2.1meta'!X23 -> 0 | X6: =SUM(H6:W6) -> 0 | Y6: =F6+X6 -> 0 | Z6: =C6-Y6 -> 0
A7: 2.1.1.1.1.4 | B7: PERSONAL CON CONTRATO A PLAZO INDETERMINADO (REGIMEN LABORAL PRIVADO) | C7: ='2.1meta'!D8+'2.1meta'!D24+'2.1meta'!D40+'2.1meta'!D79+'2.1meta'!D92+'2.1meta'!D104+'2.1meta'!D145 -> 0 | D7: ='2.1meta'!E8+'2.1meta'!E24+'2.1meta'!E40+'2.1meta'!E79+'2.1meta'!E92+'2.1meta'!E104+'2.1meta'!E145 -> 0 | E7: ='2.1meta'!F8+'2.1meta'!F24+'2.1meta'!F40+'2.1meta'!F79+'2.1meta'!F92+'2.1meta'!F104+'2.1meta'!F145 -> 0 | F7: 0 | G7: =C7-F7 -> 0 | H7: ='2.1meta'!I8+'2.1meta'!I24+'2.1meta'!I40+'2.1meta'!I79+'2.1meta'!I92+'2.1meta'!I104+'2.1meta'!I145 -> 0 | I7: ='2.1meta'!J8+'2.1meta'!J24+'2.1meta'!J40+'2.1meta'!J79+'2.1meta'!J92+'2.1meta'!J104+'2.1meta'!J145 -> 0 | J7: ='2.1meta'!K8+'2.1meta'!K24+'2.1meta'!K40+'2.1meta'!K79+'2.1meta'!K92+'2.1meta'!K104+'2.1meta'!K145 -> 0 | K7: ='2.1meta'!L8+'2.1meta'!L24+'2.1meta'!L40+'2.1meta'!L79+'2.1meta'!L92+'2.1meta'!L104+'2.1meta'!L145 -> 0 | L7: ='2.1meta'!M8+'2.1meta'!M24+'2.1meta'!M40+'2.1meta'!M79+'2.1meta'!M92+'2.1meta'!M104+'2.1meta'!M145 -> 0 | M7: ='2.1meta'!N8+'2.1meta'!N24+'2.1meta'!N40+'2.1meta'!N79+'2.1meta'!N92+'2.1meta'!N104+'2.1meta'!N145 -> 0 | N7: ='2.1meta'!O8+'2.1meta'!O24+'2.1meta'!O40+'2.1meta'!O79+'2.1meta'!O92+'2.1meta'!O104+'2.1meta'!O145 -> 0 | O7: ='2.1meta'!P8+'2.1meta'!P24+'2.1meta'!P40+'2.1meta'!P79+'2.1meta'!P92+'2.1meta'!P104+'2.1meta'!P145 -> 0 | ... W7: ='2.1meta'!X8+'2.1meta'!X24+'2.1meta'!X40+'2.1meta'!X79+'2.1meta'!X92+'2.1meta'!X104+'2.1meta'!X145 -> 0 | X7: =SUM(H7:W7) -> 0 | Y7: =F7+X7 -> 0 | Z7: =C7-Y7 -> 0
A8: 2.1.1.1.1.5 | B8: PERSONAL CON CONTRATO A PLAZO FIJO (REGIMEN LABORAL PRIVADO) | C8: ='2.1meta'!D9+'2.1meta'!D25+'2.1meta'!D41+'2.1meta'!D93 -> 0 | D8: ='2.1meta'!E9+'2.1meta'!E25+'2.1meta'!E41+'2.1meta'!E93 -> 0 | E8: ='2.1meta'!F9+'2.1meta'!F25+'2.1meta'!F41+'2.1meta'!F93 -> 0 | F8: 0 | G8: =C8-F8 -> 0 | H8: ='2.1meta'!I9+'2.1meta'!I25+'2.1meta'!I41+'2.1meta'!I93 -> 0 | I8: ='2.1meta'!J9+'2.1meta'!J25+'2.1meta'!J41+'2.1meta'!J93 -> 0 | J8: ='2.1meta'!K9+'2.1meta'!K25+'2.1meta'!K41+'2.1meta'!K93 -> 0 | K8: ='2.1meta'!L9+'2.1meta'!L25+'2.1meta'!L41+'2.1meta'!L93 -> 0 | L8: ='2.1meta'!M9+'2.1meta'!M25+'2.1meta'!M41+'2.1meta'!M93 -> 0 | M8: ='2.1meta'!N9+'2.1meta'!N25+'2.1meta'!N41+'2.1meta'!N93 -> 0 | N8: ='2.1meta'!O9+'2.1meta'!O25+'2.1meta'!O41+'2.1meta'!O93 -> 0 | O8: ='2.1meta'!P9+'2.1meta'!P25+'2.1meta'!P41+'2.1meta'!P93 -> 0 | ... W8: ='2.1meta'!X9+'2.1meta'!X25+'2.1meta'!X41+'2.1meta'!X93 -> 0 | X8: =SUM(H8:W8) -> 0 | Y8: =F8+X8 -> 0 | Z8: =C8-Y8 -> 0
A9: 2.1.1.1.2.1 | B9: ASIGNACION A FONDOS PARA PERSONAL | C9: ='2.1meta'!D10+'2.1meta'!D26 -> 0 | D9: ='2.1meta'!E10+'2.1meta'!E26 -> 0 | E9: ='2.1meta'!F10+'2.1meta'!F26 -> 0 | F9: 0 | G9: =C9-F9 -> 0 | H9: ='2.1meta'!I10+'2.1meta'!I26 -> 0 | I9: ='2.1meta'!J10+'2.1meta'!J26 -> 0 | J9: ='2.1meta'!K10+'2.1meta'!K26 -> 0 | K9: ='2.1meta'!L10+'2.1meta'!L26 -> 0 | L9: ='2.1meta'!M10+'2.1meta'!M26 -> 0 | M9: ='2.1meta'!N10+'2.1meta'!N26 -> 0 | N9: ='2.1meta'!O10+'2.1meta'!O26 -> 0 | O9: ='2.1meta'!P10+'2.1meta'!P26 -> 0 | ... W9: ='2.1meta'!X10+'2.1meta'!X26 -> 0 | X9: =SUM(H9:W9) -> 0 | Y9: =F9+X9 -> 0 | Z9: =C9-Y9 -> 0
A10: 2.1.1.3.1.2 | B10: PERSONAL CONTRATADO | C10: ='2.1meta'!D42 -> 0 | D10: ='2.1meta'!E42 -> 0 | E10: ='2.1meta'!F42 -> 0 | F10: 0 | G10: =C10-F10 -> 0 | H10: ='2.1meta'!I42 -> 0 | I10: ='2.1meta'!J42 -> 0 | J10: ='2.1meta'!K42 -> 0 | K10: ='2.1meta'!L42 -> 0 | L10: ='2.1meta'!M42 -> 0 | M10: ='2.1meta'!N42 -> 0 | N10: ='2.1meta'!O42 -> 0 | O10: ='2.1meta'!P42 -> 0 | ... W10: ='2.1meta'!X42 -> 0 | X10: =SUM(H10:W10) -> 0 | Y10: =F10+X10 -> 0 | Z10: =C10-Y10 -> 0
A11: 2.1.1.4.1.1 | B11: PERSONAL NOMBRADO | C11: ='2.1meta'!D11+'2.1meta'!D27+'2.1meta'!D80+'2.1meta'!D94+'2.1meta'!D105+'2.1meta'!D115+'2.1meta'!D122+'2.1meta'!D146 -> 0 | D11: ='2.1meta'!E11+'2.1meta'!E27+'2.1meta'!E80+'2.1meta'!E94+'2.1meta'!E105+'2.1meta'!E115+'2.1meta'!E122+'2.1meta'!E146 -> 0 | E11: ='2.1meta'!F11+'2.1meta'!F27+'2.1meta'!F80+'2.1meta'!F94+'2.1meta'!F105+'2.1meta'!F115+'2.1meta'!F122+'2.1meta'!F146 -> 0 | F11: 0 | G11: =C11-F11 -> 0 | H11: ='2.1meta'!I11+'2.1meta'!I27+'2.1meta'!I80+'2.1meta'!I94+'2.1meta'!I105+'2.1meta'!I115+'2.1meta'!I122+'2.1meta'!I146 -> 0 | I11: ='2.1meta'!J11+'2.1meta'!J27+'2.1meta'!J80+'2.1meta'!J94+'2.1meta'!J105+'2.1meta'!J115+'2.1meta'!J122+'2.1meta'!J146 -> 0 | J11: ='2.1meta'!K11+'2.1meta'!K27+'2.1meta'!K80+'2.1meta'!K94+'2.1meta'!K105+'2.1meta'!K115+'2.1meta'!K122+'2.1meta'!K146 -> 0 | K11: ='2.1meta'!L11+'2.1meta'!L27+'2.1meta'!L80+'2.1meta'!L94+'2.1meta'!L105+'2.1meta'!L115+'2.1meta'!L122+'2.1meta'!L146 -> 0 | L11: ='2.1meta'!M11+'2.1meta'!M27+'2.1meta'!M80+'2.1meta'!M94+'2.1meta'!M105+'2.1meta'!M115+'2.1meta'!M122+'2.1meta'!M146 -> 0 | M11: ='2.1meta'!N11+'2.1meta'!N27+'2.1meta'!N80+'2.1meta'!N94+'2.1meta'!N105+'2.1meta'!N115+'2.1meta'!N122+'2.1meta'!N146 -> 0 | N11: ='2.1meta'!O11+'2.1meta'!O27+'2.1meta'!O80+'2.1meta'!O94+'2.1meta'!O105+'2.1meta'!O115+'2.1meta'!O122+'2.1meta'!O146 -> 0 | O11: ='2.1meta'!P11+'2.1meta'!P27+'2.1meta'!P80+'2.1meta'!P94+'2.1meta'!P105+'2.1meta'!P115+'2.1meta'!P122+'2.1meta'!P146 -> 0 | ... W11: ='2.1meta'!X11+'2.1meta'!X27+'2.1meta'!X80+'2.1meta'!X94+'2.1meta'!X105+'2.1meta'!X115+'2.1meta'!X122+'2.1meta'!X146 -> 0 | X11: =SUM(H11:W11) -> 0 | Y11: =F11+X11 -> 0 | Z11: =C11-Y11 -> 0
A12: 2.1.1.4.2.1 | B12: BONO POR FUNCION JURISDICCIONAL Y FISCAL | C12: ='2.1meta'!D12+'2.1meta'!D28+'2.1meta'!D81+'2.1meta'!D95+'2.1meta'!D106+'2.1meta'!D116+'2.1meta'!D123+'2.1meta'!D147 -> 0 | D12: ='2.1meta'!E12+'2.1meta'!E28+'2.1meta'!E81+'2.1meta'!E95+'2.1meta'!E106+'2.1meta'!E116+'2.1meta'!E123+'2.1meta'!E147 -> 0 | E12: ='2.1meta'!F12+'2.1meta'!F28+'2.1meta'!F81+'2.1meta'!F95+'2.1meta'!F106+'2.1meta'!F116+'2.1meta'!F123+'2.1meta'!F147 -> 0 | F12: 0 | G12: =C12-F12 -> 0 | H12: ='2.1meta'!I12+'2.1meta'!I28+'2.1meta'!I81+'2.1meta'!I95+'2.1meta'!I106+'2.1meta'!I116+'2.1meta'!I123+'2.1meta'!I147 -> 0 | I12: ='2.1meta'!J12+'2.1meta'!J28+'2.1meta'!J81+'2.1meta'!J95+'2.1meta'!J106+'2.1meta'!J116+'2.1meta'!J123+'2.1meta'!J147 -> 0 | J12: ='2.1meta'!K12+'2.1meta'!K28+'2.1meta'!K81+'2.1meta'!K95+'2.1meta'!K106+'2.1meta'!K116+'2.1meta'!K123+'2.1meta'!K147 -> 0 | K12: ='2.1meta'!L12+'2.1meta'!L28+'2.1meta'!L81+'2.1meta'!L95+'2.1meta'!L106+'2.1meta'!L116+'2.1meta'!L123+'2.1meta'!L147 -> 0 | L12: ='2.1meta'!M12+'2.1meta'!M28+'2.1meta'!M81+'2.1meta'!M95+'2.1meta'!M106+'2.1meta'!M116+'2.1meta'!M123+'2.1meta'!M147 -> 0 | M12: ='2.1meta'!N12+'2.1meta'!N28+'2.1meta'!N81+'2.1meta'!N95+'2.1meta'!N106+'2.1meta'!N116+'2.1meta'!N123+'2.1meta'!N147 -> 0 | N12: ='2.1meta'!O12+'2.1meta'!O28+'2.1meta'!O81+'2.1meta'!O95+'2.1meta'!O106+'2.1meta'!O116+'2.1meta'!O123+'2.1meta'!O147 -> 0 | O12: ='2.1meta'!P12+'2.1meta'!P28+'2.1meta'!P81+'2.1meta'!P95+'2.1meta'!P106+'2.1meta'!P116+'2.1meta'!P123+'2.1meta'!P147 -> 0 | ... W12: ='2.1meta'!X12+'2.1meta'!X28+'2.1meta'!X81+'2.1meta'!X95+'2.1meta'!X106+'2.1meta'!X116+'2.1meta'!X123+'2.1meta'!X147 -> 0 | X12: =SUM(H12:W12) -> 0 | Y12: =F12+X12 -> 0 | Z12: =C12-Y12 -> 0
A13: 2.1.1.4.2.2 | B13: ASIGNACION POR GASTOS OPERATIVOS | C13: ='2.1meta'!D13+'2.1meta'!D29+'2.1meta'!D82+'2.1meta'!D96+'2.1meta'!D107+'2.1meta'!D117+'2.1meta'!D124+'2.1meta'!D148 -> 0 | D13: ='2.1meta'!E13+'2.1meta'!E29+'2.1meta'!E82+'2.1meta'!E96+'2.1meta'!E107+'2.1meta'!E117+'2.1meta'!E124+'2.1meta'!E148 -> 0 | E13: ='2.1meta'!F13+'2.1meta'!F29+'2.1meta'!F82+'2.1meta'!F96+'2.1meta'!F107+'2.1meta'!F117+'2.1meta'!F124+'2.1meta'!F148 -> 0 | F13: 0 | G13: =C13-F13 -> 0 | H13: ='2.1meta'!I13+'2.1meta'!I29+'2.1meta'!I82+'2.1meta'!I96+'2.1meta'!I107+'2.1meta'!I117+'2.1meta'!I124+'2.1meta'!I148 -> 0 | I13: ='2.1meta'!J13+'2.1meta'!J29+'2.1meta'!J82+'2.1meta'!J96+'2.1meta'!J107+'2.1meta'!J117+'2.1meta'!J124+'2.1meta'!J148 -> 0 | J13: ='2.1meta'!K13+'2.1meta'!K29+'2.1meta'!K82+'2.1meta'!K96+'2.1meta'!K107+'2.1meta'!K117+'2.1meta'!K124+'2.1meta'!K148 -> 0 | K13: ='2.1meta'!L13+'2.1meta'!L29+'2.1meta'!L82+'2.1meta'!L96+'2.1meta'!L107+'2.1meta'!L117+'2.1meta'!L124+'2.1meta'!L148 -> 0 | L13: ='2.1meta'!M13+'2.1meta'!M29+'2.1meta'!M82+'2.1meta'!M96+'2.1meta'!M107+'2.1meta'!M117+'2.1meta'!M124+'2.1meta'!M148 -> 0 | M13: ='2.1meta'!N13+'2.1meta'!N29+'2.1meta'!N82+'2.1meta'!N96+'2.1meta'!N107+'2.1meta'!N117+'2.1meta'!N124+'2.1meta'!N148 -> 0 | N13: ='2.1meta'!O13+'2.1meta'!O29+'2.1meta'!O82+'2.1meta'!O96+'2.1meta'!O107+'2.1meta'!O117+'2.1meta'!O124+'2.1meta'!O148 -> 0 | O13: ='2.1meta'!P13+'2.1meta'!P29+'2.1meta'!P82+'2.1meta'!P96+'2.1meta'!P107+'2.1meta'!P117+'2.1meta'!P124+'2.1meta'!P148 -> 0 | ... W13: ='2.1meta'!X13+'2.1meta'!X29+'2.1meta'!X82+'2.1meta'!X96+'2.1meta'!X107+'2.1meta'!X117+'2.1meta'!X124+'2.1meta'!X148 -> 0 | X13: =SUM(H13:W13) -> 0 | Y13: =F13+X13 -> 0 | Z13: =C13-Y13 -> 0
A14: 2.1.1.9.1.1 | B14: GRATIFICACIONES | C14: ='2.1meta'!D14+'2.1meta'!D30+'2.1meta'!D43+'2.1meta'!D83+'2.1meta'!D97+'2.1meta'!D108+'2.1meta'!D149 -> 0 | D14: ='2.1meta'!E14+'2.1meta'!E30+'2.1meta'!E43+'2.1meta'!E83+'2.1meta'!E97+'2.1meta'!E108+'2.1meta'!E149 -> 0 | E14: ='2.1meta'!F14+'2.1meta'!F30+'2.1meta'!F43+'2.1meta'!F83+'2.1meta'!F97+'2.1meta'!F108+'2.1meta'!F149 -> 0 | F14: 0 | G14: =C14-F14 -> 0 | H14: ='2.1meta'!I14+'2.1meta'!I30+'2.1meta'!I43+'2.1meta'!I83+'2.1meta'!I97+'2.1meta'!I108+'2.1meta'!I149 -> 0 | I14: ='2.1meta'!J14+'2.1meta'!J30+'2.1meta'!J43+'2.1meta'!J83+'2.1meta'!J97+'2.1meta'!J108+'2.1meta'!J149 -> 0 | J14: ='2.1meta'!K14+'2.1meta'!K30+'2.1meta'!K43+'2.1meta'!K83+'2.1meta'!K97+'2.1meta'!K108+'2.1meta'!K149 -> 0 | K14: ='2.1meta'!L14+'2.1meta'!L30+'2.1meta'!L43+'2.1meta'!L83+'2.1meta'!L97+'2.1meta'!L108+'2.1meta'!L149 -> 0 | L14: ='2.1meta'!M14+'2.1meta'!M30+'2.1meta'!M43+'2.1meta'!M83+'2.1meta'!M97+'2.1meta'!M108+'2.1meta'!M149 -> 0 | M14: ='2.1meta'!N14+'2.1meta'!N30+'2.1meta'!N43+'2.1meta'!N83+'2.1meta'!N97+'2.1meta'!N108+'2.1meta'!N149 -> 0 | N14: ='2.1meta'!O14+'2.1meta'!O30+'2.1meta'!O43+'2.1meta'!O83+'2.1meta'!O97+'2.1meta'!O108+'2.1meta'!O149 -> 0 | O14: ='2.1meta'!P14+'2.1meta'!P30+'2.1meta'!P43+'2.1meta'!P83+'2.1meta'!P97+'2.1meta'!P108+'2.1meta'!P149 -> 0 | ... W14: ='2.1meta'!X14+'2.1meta'!X30+'2.1meta'!X43+'2.1meta'!X83+'2.1meta'!X97+'2.1meta'!X108+'2.1meta'!X149 -> 0 | X14: =SUM(H14:W14) -> 0 | Y14: =F14+X14 -> 0 | Z14: =C14-Y14 -> 0
A15: 2.1.1.9.1.2 | B15: AGUINALDOS | C15: ='2.1meta'!D15+'2.1meta'!D31+'2.1meta'!D84+'2.1meta'!D98+'2.1meta'!D109+'2.1meta'!D118+'2.1meta'!D125+'2.1meta'!D150 -> 0 | D15: ='2.1meta'!E15+'2.1meta'!E31+'2.1meta'!E84+'2.1meta'!E98+'2.1meta'!E109+'2.1meta'!E118+'2.1meta'!E125+'2.1meta'!E150 -> 0 | E15: ='2.1meta'!F15+'2.1meta'!F31+'2.1meta'!F84+'2.1meta'!F98+'2.1meta'!F109+'2.1meta'!F118+'2.1meta'!F125+'2.1meta'!F150 -> 0 | F15: 0 | G15: =C15-F15 -> 0 | H15: ='2.1meta'!I15+'2.1meta'!I31+'2.1meta'!I84+'2.1meta'!I98+'2.1meta'!I109+'2.1meta'!I118+'2.1meta'!I125+'2.1meta'!I150 -> 0 | I15: ='2.1meta'!J15+'2.1meta'!J31+'2.1meta'!J84+'2.1meta'!J98+'2.1meta'!J109+'2.1meta'!J118+'2.1meta'!J125+'2.1meta'!J150 -> 0 | J15: ='2.1meta'!K15+'2.1meta'!K31+'2.1meta'!K84+'2.1meta'!K98+'2.1meta'!K109+'2.1meta'!K118+'2.1meta'!K125+'2.1meta'!K150 -> 0 | K15: ='2.1meta'!L15+'2.1meta'!L31+'2.1meta'!L84+'2.1meta'!L98+'2.1meta'!L109+'2.1meta'!L118+'2.1meta'!L125+'2.1meta'!L150 -> 0 | L15: ='2.1meta'!M15+'2.1meta'!M31+'2.1meta'!M84+'2.1meta'!M98+'2.1meta'!M109+'2.1meta'!M118+'2.1meta'!M125+'2.1meta'!M150 -> 0 | M15: ='2.1meta'!N15+'2.1meta'!N31+'2.1meta'!N84+'2.1meta'!N98+'2.1meta'!N109+'2.1meta'!N118+'2.1meta'!N125+'2.1meta'!N150 -> 0 | N15: ='2.1meta'!O15+'2.1meta'!O31+'2.1meta'!O84+'2.1meta'!O98+'2.1meta'!O109+'2.1meta'!O118+'2.1meta'!O125+'2.1meta'!O150 -> 0 | O15: ='2.1meta'!P15+'2.1meta'!P31+'2.1meta'!P84+'2.1meta'!P98+'2.1meta'!P109+'2.1meta'!P118+'2.1meta'!P125+'2.1meta'!P150 -> 0 | ... W15: ='2.1meta'!X15+'2.1meta'!X31+'2.1meta'!X84+'2.1meta'!X98+'2.1meta'!X109+'2.1meta'!X118+'2.1meta'!X125+'2.1meta'!X150 -> 0 | X15: =SUM(H15:W15) -> 0 | Y15: =F15+X15 -> 0 | Z15: =C15-Y15 -> 0
A16: 2.1.1.9.1.3 | B16: BONIFICACION POR ESCOLARIDAD | C16: ='2.1meta'!D16+'2.1meta'!D32+'2.1meta'!D44+'2.1meta'!D85+'2.1meta'!D99+'2.1meta'!D110+'2.1meta'!D119+'2.1meta'!D126+'2.1meta'!D151 -> 0 | D16: ='2.1meta'!E16+'2.1meta'!E32+'2.1meta'!E44+'2.1meta'!E85+'2.1meta'!E99+'2.1meta'!E110+'2.1meta'!E119+'2.1meta'!E126+'2.1meta'!E151 -> 0 | E16: ='2.1meta'!F16+'2.1meta'!F32+'2.1meta'!F44+'2.1meta'!F85+'2.1meta'!F99+'2.1meta'!F110+'2.1meta'!F119+'2.1meta'!F126+'2.1meta'!F151 -> 0 | F16: 0 | G16: =C16-F16 -> 0 | H16: ='2.1meta'!I16+'2.1meta'!I32+'2.1meta'!I44+'2.1meta'!I85+'2.1meta'!I99+'2.1meta'!I110+'2.1meta'!I119+'2.1meta'!I126+'2.1meta'!I151 -> 0 | I16: ='2.1meta'!J16+'2.1meta'!J32+'2.1meta'!J44+'2.1meta'!J85+'2.1meta'!J99+'2.1meta'!J110+'2.1meta'!J119+'2.1meta'!J126+'2.1meta'!J151 -> 0 | J16: ='2.1meta'!K16+'2.1meta'!K32+'2.1meta'!K44+'2.1meta'!K85+'2.1meta'!K99+'2.1meta'!K110+'2.1meta'!K119+'2.1meta'!K126+'2.1meta'!K151 -> 0 | K16: ='2.1meta'!L16+'2.1meta'!L32+'2.1meta'!L44+'2.1meta'!L85+'2.1meta'!L99+'2.1meta'!L110+'2.1meta'!L119+'2.1meta'!L126+'2.1meta'!L151 -> 0 | L16: ='2.1meta'!M16+'2.1meta'!M32+'2.1meta'!M44+'2.1meta'!M85+'2.1meta'!M99+'2.1meta'!M110+'2.1meta'!M119+'2.1meta'!M126+'2.1meta'!M151 -> 0 | M16: ='2.1meta'!N16+'2.1meta'!N32+'2.1meta'!N44+'2.1meta'!N85+'2.1meta'!N99+'2.1meta'!N110+'2.1meta'!N119+'2.1meta'!N126+'2.1meta'!N151 -> 0 | N16: ='2.1meta'!O16+'2.1meta'!O32+'2.1meta'!O44+'2.1meta'!O85+'2.1meta'!O99+'2.1meta'!O110+'2.1meta'!O119+'2.1meta'!O126+'2.1meta'!O151 -> 0 | O16: ='2.1meta'!P16+'2.1meta'!P32+'2.1meta'!P44+'2.1meta'!P85+'2.1meta'!P99+'2.1meta'!P110+'2.1meta'!P119+'2.1meta'!P126+'2.1meta'!P151 -> 0 | ... W16: ='2.1meta'!X16+'2.1meta'!X32+'2.1meta'!X44+'2.1meta'!X85+'2.1meta'!X99+'2.1meta'!X110+'2.1meta'!X119+'2.1meta'!X126+'2.1meta'!X151 -> 0 | X16: =SUM(H16:W16) -> 0 | Y16: =F16+X16 -> 0 | Z16: =C16-Y16 -> 0
A17: 2.1.1.9.2.1 | B17: COMPENSACION POR TIEMPO DE SERVICIOS (CTS) | C17: ='2.1meta'!D17+'2.1meta'!D33+'2.1meta'!D45+'2.1meta'!D86+'2.1meta'!D100+'2.1meta'!D111+'2.1meta'!D152 -> 0 | D17: ='2.1meta'!E17+'2.1meta'!E33+'2.1meta'!E45+'2.1meta'!E86+'2.1meta'!E100+'2.1meta'!E111+'2.1meta'!E152 -> 0 | E17: ='2.1meta'!F17+'2.1meta'!F33+'2.1meta'!F45+'2.1meta'!F86+'2.1meta'!F100+'2.1meta'!F111+'2.1meta'!F152 -> 0 | F17: 0 | G17: =C17-F17 -> 0 | H17: ='2.1meta'!I17+'2.1meta'!I33+'2.1meta'!I45+'2.1meta'!I86+'2.1meta'!I100+'2.1meta'!I111+'2.1meta'!I152 -> 0 | I17: ='2.1meta'!J17+'2.1meta'!J33+'2.1meta'!J45+'2.1meta'!J86+'2.1meta'!J100+'2.1meta'!J111+'2.1meta'!J152 -> 0 | J17: ='2.1meta'!K17+'2.1meta'!K33+'2.1meta'!K45+'2.1meta'!K86+'2.1meta'!K100+'2.1meta'!K111+'2.1meta'!K152 -> 0 | K17: ='2.1meta'!L17+'2.1meta'!L33+'2.1meta'!L45+'2.1meta'!L86+'2.1meta'!L100+'2.1meta'!L111+'2.1meta'!L152 -> 0 | L17: ='2.1meta'!M17+'2.1meta'!M33+'2.1meta'!M45+'2.1meta'!M86+'2.1meta'!M100+'2.1meta'!M111+'2.1meta'!M152 -> 0 | M17: ='2.1meta'!N17+'2.1meta'!N33+'2.1meta'!N45+'2.1meta'!N86+'2.1meta'!N100+'2.1meta'!N111+'2.1meta'!N152 -> 0 | N17: ='2.1meta'!O17+'2.1meta'!O33+'2.1meta'!O45+'2.1meta'!O86+'2.1meta'!O100+'2.1meta'!O111+'2.1meta'!O152 -> 0 | O17: ='2.1meta'!P17+'2.1meta'!P33+'2.1meta'!P45+'2.1meta'!P86+'2.1meta'!P100+'2.1meta'!P111+'2.1meta'!P152 -> 0 | ... W17: ='2.1meta'!X17+'2.1meta'!X33+'2.1meta'!X45+'2.1meta'!X86+'2.1meta'!X100+'2.1meta'!X111+'2.1meta'!X152 -> 0 | X17: =SUM(H17:W17) -> 0 | Y17: =F17+X17 -> 0 | Z17: =C17-Y17 -> 0
A18: 2.1.1.9.3.3 | B18: COMPENSACION VACACIONAL (VACACIONES TRUNCAS) | C18: ='2.1meta'!D34 -> 0 | D18: ='2.1meta'!E34 -> 0 | E18: ='2.1meta'!F34 -> 0 | F18: 0 | G18: =C18-F18 -> 0 | H18: ='2.1meta'!I34 -> 0 | I18: ='2.1meta'!J34 -> 0 | J18: ='2.1meta'!K34 -> 0 | K18: ='2.1meta'!L34 -> 0 | L18: ='2.1meta'!M34 -> 0 | M18: ='2.1meta'!N34 -> 0 | N18: ='2.1meta'!O34 -> 0 | O18: ='2.1meta'!P34 -> 0 | ... W18: ='2.1meta'!X34 -> 0 | X18: =SUM(H18:W18) -> 0 | Y18: =F18+X18 -> 0 | Z18: =C18-Y18 -> 0
A19: 2.1.1.9.3.99 | B19: OTRAS OCASIONALES | C19: ='2.1meta'!D18+'2.1meta'!D35+'2.1meta'!D46+'2.1meta'!D87+'2.1meta'!D101+'2.1meta'!D112+'2.1meta'!D153 -> 0 | D19: ='2.1meta'!E18+'2.1meta'!E35+'2.1meta'!E46+'2.1meta'!E87+'2.1meta'!E101+'2.1meta'!E112+'2.1meta'!E153 -> 0 | E19: ='2.1meta'!F18+'2.1meta'!F35+'2.1meta'!F46+'2.1meta'!F87+'2.1meta'!F101+'2.1meta'!F112+'2.1meta'!F153 -> 0 | F19: 0 | G19: =C19-F19 -> 0 | H19: ='2.1meta'!I18+'2.1meta'!I35+'2.1meta'!I46+'2.1meta'!I87+'2.1meta'!I101+'2.1meta'!I112+'2.1meta'!I153 -> 0 | I19: ='2.1meta'!J18+'2.1meta'!J35+'2.1meta'!J46+'2.1meta'!J87+'2.1meta'!J101+'2.1meta'!J112+'2.1meta'!J153 -> 0 | J19: ='2.1meta'!K18+'2.1meta'!K35+'2.1meta'!K46+'2.1meta'!K87+'2.1meta'!K101+'2.1meta'!K112+'2.1meta'!K153 -> 0 | K19: ='2.1meta'!L18+'2.1meta'!L35+'2.1meta'!L46+'2.1meta'!L87+'2.1meta'!L101+'2.1meta'!L112+'2.1meta'!L153 -> 0 | L19: ='2.1meta'!M18+'2.1meta'!M35+'2.1meta'!M46+'2.1meta'!M87+'2.1meta'!M101+'2.1meta'!M112+'2.1meta'!M153 -> 0 | M19: ='2.1meta'!N18+'2.1meta'!N35+'2.1meta'!N46+'2.1meta'!N87+'2.1meta'!N101+'2.1meta'!N112+'2.1meta'!N153 -> 0 | N19: ='2.1meta'!O18+'2.1meta'!O35+'2.1meta'!O46+'2.1meta'!O87+'2.1meta'!O101+'2.1meta'!O112+'2.1meta'!O153 -> 0 | O19: ='2.1meta'!P18+'2.1meta'!P35+'2.1meta'!P46+'2.1meta'!P87+'2.1meta'!P101+'2.1meta'!P112+'2.1meta'!P153 -> 0 | ... W19: ='2.1meta'!X18+'2.1meta'!X35+'2.1meta'!X46+'2.1meta'!X87+'2.1meta'!X101+'2.1meta'!X112+'2.1meta'!X153 -> 0 | X19: =SUM(H19:W19) -> 0 | Y19: =F19+X19 -> 0 | Z19: =C19-Y19 -> 0
A20: 2.1.3.1.1.1 | B20: APORTES A LOS FONDOS DE SALUD | C20: ='2.1meta'!D19+'2.1meta'!D36+'2.1meta'!D47+'2.1meta'!D88+'2.1meta'!D127+'2.1meta'!D154 -> 0 | D20: ='2.1meta'!E19+'2.1meta'!E36+'2.1meta'!E47+'2.1meta'!E88+'2.1meta'!E127+'2.1meta'!E154 -> 0 | E20: ='2.1meta'!F19+'2.1meta'!F36+'2.1meta'!F47+'2.1meta'!F88+'2.1meta'!F127+'2.1meta'!F154 -> 0 | F20: 0 | G20: =C20-F20 -> 0 | H20: ='2.1meta'!I19+'2.1meta'!I36+'2.1meta'!I47+'2.1meta'!I88+'2.1meta'!I127+'2.1meta'!I154 -> 0 | I20: ='2.1meta'!J19+'2.1meta'!J36+'2.1meta'!J47+'2.1meta'!J88+'2.1meta'!J127+'2.1meta'!J154 -> 0 | J20: ='2.1meta'!K19+'2.1meta'!K36+'2.1meta'!K47+'2.1meta'!K88+'2.1meta'!K127+'2.1meta'!K154 -> 0 | K20: ='2.1meta'!L19+'2.1meta'!L36+'2.1meta'!L47+'2.1meta'!L88+'2.1meta'!L127+'2.1meta'!L154 -> 0 | L20: ='2.1meta'!M19+'2.1meta'!M36+'2.1meta'!M47+'2.1meta'!M88+'2.1meta'!M127+'2.1meta'!M154 -> 0 | M20: ='2.1meta'!N19+'2.1meta'!N36+'2.1meta'!N47+'2.1meta'!N88+'2.1meta'!N127+'2.1meta'!N154 -> 0 | N20: ='2.1meta'!O19+'2.1meta'!O36+'2.1meta'!O47+'2.1meta'!O88+'2.1meta'!O127+'2.1meta'!O154 -> 0 | O20: ='2.1meta'!P19+'2.1meta'!P36+'2.1meta'!P47+'2.1meta'!P88+'2.1meta'!P127+'2.1meta'!P154 -> 0 | ... W20: ='2.1meta'!X19+'2.1meta'!X36+'2.1meta'!X47+'2.1meta'!X88+'2.1meta'!X127+'2.1meta'!X154 -> 0 | X20: =SUM(H20:W20) -> 0 | Y20: =F20+X20 -> 0 | Z20: =C20-Y20 -> 0
A21: 2.1.3.1.1.3 | B21: APORTES A LOS FONDOS DE PENSIONES | C21: ='2.1meta'!D20+'2.1meta'!D37+'2.1meta'!D89 -> 0 | D21: ='2.1meta'!E20+'2.1meta'!E37+'2.1meta'!E89 -> 0 | E21: ='2.1meta'!F20+'2.1meta'!F37+'2.1meta'!F89 -> 0 | F21: 0 | G21: =C21-F21 -> 0 | H21: ='2.1meta'!I20+'2.1meta'!I37+'2.1meta'!I89 -> 0 | I21: ='2.1meta'!J20+'2.1meta'!J37+'2.1meta'!J89 -> 0 | J21: ='2.1meta'!K20+'2.1meta'!K37+'2.1meta'!K89 -> 0 | K21: ='2.1meta'!L20+'2.1meta'!L37+'2.1meta'!L89 -> 0 | L21: ='2.1meta'!M20+'2.1meta'!M37+'2.1meta'!M89 -> 0 | M21: ='2.1meta'!N20+'2.1meta'!N37+'2.1meta'!N89 -> 0 | N21: ='2.1meta'!O20+'2.1meta'!O37+'2.1meta'!O89 -> 0 | O21: ='2.1meta'!P20+'2.1meta'!P37+'2.1meta'!P89 -> 0 | ... W21: ='2.1meta'!X20+'2.1meta'!X37+'2.1meta'!X89 -> 0 | X21: =SUM(H21:W21) -> 0 | Y21: =F21+X21 -> 0 | Z21: =C21-Y21 -> 0
A22: 2.1.3.1.1.5 | B22: CONTRIBUCIONES A ESSALUD | C22: ='2.1meta'!D21+'2.1meta'!D38+'2.1meta'!D48+'2.1meta'!D90+'2.1meta'!D102+'2.1meta'!D113+'2.1meta'!D120+'2.1meta'!D128+'2.1meta'!D155 -> 0 | D22: ='2.1meta'!E21+'2.1meta'!E38+'2.1meta'!E48+'2.1meta'!E90+'2.1meta'!E102+'2.1meta'!E113+'2.1meta'!E120+'2.1meta'!E128+'2.1meta'!E155 -> 0 | E22: ='2.1meta'!F21+'2.1meta'!F38+'2.1meta'!F48+'2.1meta'!F90+'2.1meta'!F102+'2.1meta'!F113+'2.1meta'!F120+'2.1meta'!F128+'2.1meta'!F155 -> 0 | F22: 0 | G22: =C22-F22 -> 0 | H22: ='2.1meta'!I21+'2.1meta'!I38+'2.1meta'!I48+'2.1meta'!I90+'2.1meta'!I102+'2.1meta'!I113+'2.1meta'!I120+'2.1meta'!I128+'2.1meta'!I155 -> 0 | I22: ='2.1meta'!J21+'2.1meta'!J38+'2.1meta'!J48+'2.1meta'!J90+'2.1meta'!J102+'2.1meta'!J113+'2.1meta'!J120+'2.1meta'!J128+'2.1meta'!J155 -> 0 | J22: ='2.1meta'!K21+'2.1meta'!K38+'2.1meta'!K48+'2.1meta'!K90+'2.1meta'!K102+'2.1meta'!K113+'2.1meta'!K120+'2.1meta'!K128+'2.1meta'!K155 -> 0 | K22: ='2.1meta'!L21+'2.1meta'!L38+'2.1meta'!L48+'2.1meta'!L90+'2.1meta'!L102+'2.1meta'!L113+'2.1meta'!L120+'2.1meta'!L128+'2.1meta'!L155 -> 0 | L22: ='2.1meta'!M21+'2.1meta'!M38+'2.1meta'!M48+'2.1meta'!M90+'2.1meta'!M102+'2.1meta'!M113+'2.1meta'!M120+'2.1meta'!M128+'2.1meta'!M155 -> 0 | M22: ='2.1meta'!N21+'2.1meta'!N38+'2.1meta'!N48+'2.1meta'!N90+'2.1meta'!N102+'2.1meta'!N113+'2.1meta'!N120+'2.1meta'!N128+'2.1meta'!N155 -> 0 | N22: ='2.1meta'!O21+'2.1meta'!O38+'2.1meta'!O48+'2.1meta'!O90+'2.1meta'!O102+'2.1meta'!O113+'2.1meta'!O120+'2.1meta'!O128+'2.1meta'!O155 -> 0 | O22: ='2.1meta'!P21+'2.1meta'!P38+'2.1meta'!P48+'2.1meta'!P90+'2.1meta'!P102+'2.1meta'!P113+'2.1meta'!P120+'2.1meta'!P128+'2.1meta'!P155 -> 0 | ... W22: ='2.1meta'!X21+'2.1meta'!X38+'2.1meta'!X48+'2.1meta'!X90+'2.1meta'!X102+'2.1meta'!X113+'2.1meta'!X120+'2.1meta'!X128+'2.1meta'!X155 -> 0 | X22: =SUM(H22:W22) -> 0 | Y22: =F22+X22 -> 0 | Z22: =C22-Y22 -> 0
A23: 1002 PRODUCTOS ESPECIFICOS PARA REDUCCION DE LA VIOLENCIA CONTRA LA MUJER | C23: =SUBTOTAL(9,C24:C37) -> 0 | F23: =SUBTOTAL(9,F24:F37) -> 0 | G23: =C23-F23 -> 0 | H23: =SUBTOTAL(9,H24:H37) -> 0 | I23: =SUBTOTAL(9,I24:I37) -> 0 | J23: =SUBTOTAL(9,J24:J37) -> 0 | K23: =SUBTOTAL(9,K24:K37) -> 0 | L23: =SUBTOTAL(9,L24:L37) -> 0 | M23: =SUBTOTAL(9,M24:M37) -> 0 | N23: =SUBTOTAL(9,N24:N37) -> 0 | O23: =SUBTOTAL(9,O24:O37) -> 0 | ... Z23: =SUBTOTAL(9,Z24:Z37) -> 0
A24: 2.1.1.1.1.2 | B24: PERSONAL ADMINISTRATIVO NOMBRADO (REGIMEN PUBLICO) | C24: ='2.1meta'!D130 -> 0 | D24: ='2.1meta'!E130 -> 0 | E24: ='2.1meta'!F130 -> 0 | F24: 0 | G24: =C24-F24 -> 0 | H24: ='2.1meta'!I130 -> 0 | I24: ='2.1meta'!J130 -> 0 | J24: ='2.1meta'!K130 -> 0 | K24: ='2.1meta'!L130 -> 0 | L24: ='2.1meta'!M130 -> 0 | M24: ='2.1meta'!N130 -> 0 | N24: ='2.1meta'!O130 -> 0 | O24: ='2.1meta'!P130 -> 0 | ... W24: ='2.1meta'!X130 -> 0 | X24: =SUM(H24:W24) -> 0 | Y24: =F24+X24 -> 0 | Z24: =C24-Y24 -> 0
A25: 2.1.1.1.1.4 | B25: PERSONAL CON CONTRATO A PLAZO INDETERMINADO (REGIMEN LABORAL PRIVADO) | C25: ='2.1meta'!D131 -> 0 | D25: ='2.1meta'!E131 -> 0 | E25: ='2.1meta'!F131 -> 0 | F25: 0 | G25: =C25-F25 -> 0 | H25: ='2.1meta'!I131 -> 0 | I25: ='2.1meta'!J131 -> 0 | J25: ='2.1meta'!K131 -> 0 | K25: ='2.1meta'!L131 -> 0 | L25: ='2.1meta'!M131 -> 0 | M25: ='2.1meta'!N131 -> 0 | N25: ='2.1meta'!O131 -> 0 | O25: ='2.1meta'!P131 -> 0 | ... W25: ='2.1meta'!X131 -> 0 | X25: =SUM(H25:W25) -> 0 | Y25: =F25+X25 -> 0 | Z25: =C25-Y25 -> 0
A26: 2.1.1.1.1.5 | B26: PERSONAL CON CONTRATO A PLAZO FIJO (REGIMEN LABORAL PRIVADO) | C26: ='2.1meta'!D132 -> 0 | D26: ='2.1meta'!E132 -> 0 | E26: ='2.1meta'!F132 -> 0 | F26: 0 | G26: =C26-F26 -> 0 | H26: ='2.1meta'!I132 -> 0 | I26: ='2.1meta'!J132 -> 0 | J26: ='2.1meta'!K132 -> 0 | K26: ='2.1meta'!L132 -> 0 | L26: ='2.1meta'!M132 -> 0 | M26: ='2.1meta'!N132 -> 0 | N26: ='2.1meta'!O132 -> 0 | O26: ='2.1meta'!P132 -> 0 | ... W26: ='2.1meta'!X132 -> 0 | X26: =SUM(H26:W26) -> 0 | Y26: =F26+X26 -> 0 | Z26: =C26-Y26 -> 0
A27: 2.1.1.1.2.1 | B27: ASIGNACION A FONDOS PARA PERSONAL | C27: ='2.1meta'!D133 -> 0 | D27: ='2.1meta'!E133 -> 0 | E27: ='2.1meta'!F133 -> 0 | F27: 0 | G27: =C27-F27 -> 0 | H27: ='2.1meta'!I133 -> 0 | I27: ='2.1meta'!J133 -> 0 | J27: ='2.1meta'!K133 -> 0 | K27: ='2.1meta'!L133 -> 0 | L27: ='2.1meta'!M133 -> 0 | M27: ='2.1meta'!N133 -> 0 | N27: ='2.1meta'!O133 -> 0 | O27: ='2.1meta'!P133 -> 0 | ... W27: ='2.1meta'!X133 -> 0 | X27: =SUM(H27:W27) -> 0 | Y27: =F27+X27 -> 0 | Z27: =C27-Y27 -> 0
A28: 2.1.1.4.1.1 | B28: PERSONAL NOMBRADO | C28: ='2.1meta'!D134 -> 0 | D28: ='2.1meta'!E134 -> 0 | E28: ='2.1meta'!F134 -> 0 | F28: 0 | G28: =C28-F28 -> 0 | H28: ='2.1meta'!I134 -> 0 | I28: ='2.1meta'!J134 -> 0 | J28: ='2.1meta'!K134 -> 0 | K28: ='2.1meta'!L134 -> 0 | L28: ='2.1meta'!M134 -> 0 | M28: ='2.1meta'!N134 -> 0 | N28: ='2.1meta'!O134 -> 0 | O28: ='2.1meta'!P134 -> 0 | ... W28: ='2.1meta'!X134 -> 0 | X28: =SUM(H28:W28) -> 0 | Y28: =F28+X28 -> 0 | Z28: =C28-Y28 -> 0
A29: 2.1.1.4.2.1 | B29: BONO POR FUNCION JURISDICCIONAL Y FISCAL | C29: ='2.1meta'!D135 -> 0 | D29: ='2.1meta'!E135 -> 0 | E29: ='2.1meta'!F135 -> 0 | F29: 0 | G29: =C29-F29 -> 0 | H29: ='2.1meta'!I135 -> 0 | I29: ='2.1meta'!J135 -> 0 | J29: ='2.1meta'!K135 -> 0 | K29: ='2.1meta'!L135 -> 0 | L29: ='2.1meta'!M135 -> 0 | M29: ='2.1meta'!N135 -> 0 | N29: ='2.1meta'!O135 -> 0 | O29: ='2.1meta'!P135 -> 0 | ... W29: ='2.1meta'!X135 -> 0 | X29: =SUM(H29:W29) -> 0 | Y29: =F29+X29 -> 0 | Z29: =C29-Y29 -> 0
A30: 2.1.1.4.2.2 | B30: ASIGNACION POR GASTOS OPERATIVOS | C30: ='2.1meta'!D136 -> 0 | D30: ='2.1meta'!E136 -> 0 | E30: ='2.1meta'!F136 -> 0 | F30: 0 | G30: =C30-F30 -> 0 | H30: ='2.1meta'!I136 -> 0 | I30: ='2.1meta'!J136 -> 0 | J30: ='2.1meta'!K136 -> 0 | K30: ='2.1meta'!L136 -> 0 | L30: ='2.1meta'!M136 -> 0 | M30: ='2.1meta'!N136 -> 0 | N30: ='2.1meta'!O136 -> 0 | O30: ='2.1meta'!P136 -> 0 | ... W30: ='2.1meta'!X136 -> 0 | X30: =SUM(H30:W30) -> 0 | Y30: =F30+X30 -> 0 | Z30: =C30-Y30 -> 0
A31: 2.1.1.9.1.1 | B31: GRATIFICACIONES | C31: ='2.1meta'!D137 -> 0 | D31: ='2.1meta'!E137 -> 0 | E31: ='2.1meta'!F137 -> 0 | F31: 0 | G31: =C31-F31 -> 0 | H31: ='2.1meta'!I137 -> 0 | I31: ='2.1meta'!J137 -> 0 | J31: ='2.1meta'!K137 -> 0 | K31: ='2.1meta'!L137 -> 0 | L31: ='2.1meta'!M137 -> 0 | M31: ='2.1meta'!N137 -> 0 | N31: ='2.1meta'!O137 -> 0 | O31: ='2.1meta'!P137 -> 0 | ... W31: ='2.1meta'!X137 -> 0 | X31: =SUM(H31:W31) -> 0 | Y31: =F31+X31 -> 0 | Z31: =C31-Y31 -> 0
A32: 2.1.1.9.1.2 | B32: AGUINALDOS | C32: ='2.1meta'!D138 -> 0 | D32: ='2.1meta'!E138 -> 0 | E32: ='2.1meta'!F138 -> 0 | F32: 0 | G32: =C32-F32 -> 0 | H32: ='2.1meta'!I138 -> 0 | I32: ='2.1meta'!J138 -> 0 | J32: ='2.1meta'!K138 -> 0 | K32: ='2.1meta'!L138 -> 0 | L32: ='2.1meta'!M138 -> 0 | M32: ='2.1meta'!N138 -> 0 | N32: ='2.1meta'!O138 -> 0 | O32: ='2.1meta'!P138 -> 0 | ... W32: ='2.1meta'!X138 -> 0 | X32: =SUM(H32:W32) -> 0 | Y32: =F32+X32 -> 0 | Z32: =C32-Y32 -> 0
A33: 2.1.1.9.1.3 | B33: BONIFICACION POR ESCOLARIDAD | C33: ='2.1meta'!D139 -> 0 | D33: ='2.1meta'!E139 -> 0 | E33: ='2.1meta'!F139 -> 0 | F33: 0 | G33: =C33-F33 -> 0 | H33: ='2.1meta'!I139 -> 0 | I33: ='2.1meta'!J139 -> 0 | J33: ='2.1meta'!K139 -> 0 | K33: ='2.1meta'!L139 -> 0 | L33: ='2.1meta'!M139 -> 0 | M33: ='2.1meta'!N139 -> 0 | N33: ='2.1meta'!O139 -> 0 | O33: ='2.1meta'!P139 -> 0 | ... W33: ='2.1meta'!X139 -> 0 | X33: =SUM(H33:W33) -> 0 | Y33: =F33+X33 -> 0 | Z33: =C33-Y33 -> 0
A34: 2.1.1.9.2.1 | B34: COMPENSACION POR TIEMPO DE SERVICIOS (CTS) | C34: ='2.1meta'!D140 -> 0 | D34: ='2.1meta'!E140 -> 0 | E34: ='2.1meta'!F140 -> 0 | F34: 0 | G34: =C34-F34 -> 0 | H34: ='2.1meta'!I140 -> 0 | I34: ='2.1meta'!J140 -> 0 | J34: ='2.1meta'!K140 -> 0 | K34: ='2.1meta'!L140 -> 0 | L34: ='2.1meta'!M140 -> 0 | M34: ='2.1meta'!N140 -> 0 | N34: ='2.1meta'!O140 -> 0 | O34: ='2.1meta'!P140 -> 0 | ... W34: ='2.1meta'!X140 -> 0 | X34: =SUM(H34:W34) -> 0 | Y34: =F34+X34 -> 0 | Z34: =C34-Y34 -> 0
A35: 2.1.1.9.3.99 | B35: OTRAS OCASIONALES | C35: ='2.1meta'!D141 -> 0 | D35: ='2.1meta'!E141 -> 0 | E35: ='2.1meta'!F141 -> 0 | F35: 0 | G35: =C35-F35 -> 0 | H35: ='2.1meta'!I141 -> 0 | I35: ='2.1meta'!J141 -> 0 | J35: ='2.1meta'!K141 -> 0 | K35: ='2.1meta'!L141 -> 0 | L35: ='2.1meta'!M141 -> 0 | M35: ='2.1meta'!N141 -> 0 | N35: ='2.1meta'!O141 -> 0 | O35: ='2.1meta'!P141 -> 0 | ... W35: ='2.1meta'!X141 -> 0 | X35: =SUM(H35:W35) -> 0 | Y35: =F35+X35 -> 0 | Z35: =C35-Y35 -> 0
... A37: 2.1.3.1.1.5 | B37: CONTRIBUCIONES A ESSALUD | C37: ='2.1meta'!D143 -> 0 | D37: ='2.1meta'!E143 -> 0 | E37: ='2.1meta'!F143 -> 0 | F37: 0 | G37: =C37-F37 -> 0 | H37: ='2.1meta'!I143 -> 0 | I37: ='2.1meta'!J143 -> 0 | J37: ='2.1meta'!K143 -> 0 | K37: ='2.1meta'!L143 -> 0 | L37: ='2.1meta'!M143 -> 0 | M37: ='2.1meta'!N143 -> 0 | N37: ='2.1meta'!O143 -> 0 | O37: ='2.1meta'!P143 -> 0 | ... W37: ='2.1meta'!X143 -> 0 | X37: =SUM(H37:W37) -> 0 | Y37: =F37+X37 -> 0 | Z37: =C37-Y37 -> 0
A38: 9001 ACCIONES CENTRALES | C38: =SUBTOTAL(9,C39:C50) -> 0 | F38: =SUBTOTAL(9,F39:F50) -> 0 | G38: =C38-F38 -> 0 | H38: =SUBTOTAL(9,H39:H50) -> 0 | I38: =SUBTOTAL(9,I39:I50) -> 0 | J38: =SUBTOTAL(9,J39:J50) -> 0 | K38: =SUBTOTAL(9,K39:K50) -> 0 | L38: =SUBTOTAL(9,L39:L50) -> 0 | M38: =SUBTOTAL(9,M39:M50) -> 0 | N38: =SUBTOTAL(9,N39:N50) -> 0 | O38: =SUBTOTAL(9,O39:O50) -> 0 | ... S38: =SUBTOTAL(9,S39:S50) -> 0 | X38: =SUBTOTAL(9,X39:X50) -> 0 | Y38: =SUBTOTAL(9,Y39:Y50) -> 0 | Z38: =SUBTOTAL(9,Z39:Z50) -> 0
A39: 2.1.1.1.1.2 | B39: PERSONAL ADMINISTRATIVO NOMBRADO (REGIMEN PUBLICO) | C39: ='2.1meta'!D50 -> 0 | D39: ='2.1meta'!E50 -> 0 | E39: ='2.1meta'!F50 -> 0 | F39: 0 | G39: =C39-F39 -> 0 | H39: ='2.1meta'!I50 -> 0 | I39: ='2.1meta'!J50 -> 0 | J39: ='2.1meta'!K50 -> 0 | K39: ='2.1meta'!L50 -> 0 | L39: ='2.1meta'!M50 -> 0 | M39: ='2.1meta'!N50 -> 0 | N39: ='2.1meta'!O50 -> 0 | O39: ='2.1meta'!P50 -> 0 | ... W39: ='2.1meta'!X50 -> 0 | X39: =SUM(H39:W39) -> 0 | Y39: =F39+X39 -> 0 | Z39: =C39-Y39 -> 0
A40: 2.1.1.1.1.4 | B40: PERSONAL CON CONTRATO A PLAZO INDETERMINADO (REGIMEN LABORAL PRIVADO) | C40: ='2.1meta'!D51 -> 0 | D40: ='2.1meta'!E51 -> 0 | E40: ='2.1meta'!F51 -> 0 | F40: 0 | G40: =C40-F40 -> 0 | H40: ='2.1meta'!I51 -> 0 | I40: ='2.1meta'!J51 -> 0 | J40: ='2.1meta'!K51 -> 0 | K40: ='2.1meta'!L51 -> 0 | L40: ='2.1meta'!M51 -> 0 | M40: ='2.1meta'!N51 -> 0 | N40: ='2.1meta'!O51 -> 0 | O40: ='2.1meta'!P51 -> 0 | ... W40: ='2.1meta'!X51 -> 0 | X40: =SUM(H40:W40) -> 0 | Y40: =F40+X40 -> 0 | Z40: =C40-Y40 -> 0
A41: 2.1.1.1.1.5 | B41: PERSONAL CON CONTRATO A PLAZO FIJO (REGIMEN LABORAL PRIVADO) | C41: ='2.1meta'!D52 -> 0 | D41: ='2.1meta'!E52 -> 0 | E41: ='2.1meta'!F52 -> 0 | F41: 0 | G41: =C41-F41 -> 0 | H41: ='2.1meta'!I52 -> 0 | I41: ='2.1meta'!J52 -> 0 | J41: ='2.1meta'!K52 -> 0 | K41: ='2.1meta'!L52 -> 0 | L41: ='2.1meta'!M52 -> 0 | M41: ='2.1meta'!N52 -> 0 | N41: ='2.1meta'!O52 -> 0 | O41: ='2.1meta'!P52 -> 0 | ... W41: ='2.1meta'!X52 -> 0 | X41: =SUM(H41:W41) -> 0 | Y41: =F41+X41 -> 0 | Z41: =C41-Y41 -> 0
A42: 2.1.1.1.2.1 | B42: ASIGNACION A FONDOS PARA PERSONAL | C42: ='2.1meta'!D53 -> 0 | D42: ='2.1meta'!E53 -> 0 | E42: ='2.1meta'!F53 -> 0 | F42: 0 | G42: =C42-F42 -> 0 | H42: ='2.1meta'!I53 -> 0 | I42: ='2.1meta'!J53 -> 0 | J42: ='2.1meta'!K53 -> 0 | K42: ='2.1meta'!L53 -> 0 | L42: ='2.1meta'!M53 -> 0 | M42: ='2.1meta'!N53 -> 0 | N42: ='2.1meta'!O53 -> 0 | O42: ='2.1meta'!P53 -> 0 | ... W42: ='2.1meta'!X53 -> 0 | X42: =SUM(H42:W42) -> 0 | Y42: =F42+X42 -> 0 | Z42: =C42-Y42 -> 0
A43: 2.1.1.9.1.1 | B43: GRATIFICACIONES | C43: ='2.1meta'!D54 -> 0 | D43: ='2.1meta'!E54 -> 0 | E43: ='2.1meta'!F54 -> 0 | F43: 0 | G43: =C43-F43 -> 0 | H43: ='2.1meta'!I54 -> 0 | I43: ='2.1meta'!J54 -> 0 | J43: ='2.1meta'!K54 -> 0 | K43: ='2.1meta'!L54 -> 0 | L43: ='2.1meta'!M54 -> 0 | M43: ='2.1meta'!N54 -> 0 | N43: ='2.1meta'!O54 -> 0 | O43: ='2.1meta'!P54 -> 0 | ... W43: ='2.1meta'!X54 -> 0 | X43: =SUM(H43:W43) -> 0 | Y43: =F43+X43 -> 0 | Z43: =C43-Y43 -> 0
A44: 2.1.1.9.1.2 | B44: AGUINALDOS | C44: ='2.1meta'!D55 -> 0 | D44: ='2.1meta'!E55 -> 0 | E44: ='2.1meta'!F55 -> 0 | F44: 0 | G44: =C44-F44 -> 0 | H44: ='2.1meta'!I55 -> 0 | I44: ='2.1meta'!J55 -> 0 | J44: ='2.1meta'!K55 -> 0 | K44: ='2.1meta'!L55 -> 0 | L44: ='2.1meta'!M55 -> 0 | M44: ='2.1meta'!N55 -> 0 | N44: ='2.1meta'!O55 -> 0 | O44: ='2.1meta'!P55 -> 0 | ... W44: ='2.1meta'!X55 -> 0 | X44: =SUM(H44:W44) -> 0 | Y44: =F44+X44 -> 0 | Z44: =C44-Y44 -> 0
A45: 2.1.1.9.1.3 | B45: BONIFICACION POR ESCOLARIDAD | C45: ='2.1meta'!D56 -> 0 | D45: ='2.1meta'!E56 -> 0 | E45: ='2.1meta'!F56 -> 0 | F45: 0 | G45: =C45-F45 -> 0 | H45: ='2.1meta'!I56 -> 0 | I45: ='2.1meta'!J56 -> 0 | J45: ='2.1meta'!K56 -> 0 | K45: ='2.1meta'!L56 -> 0 | L45: ='2.1meta'!M56 -> 0 | M45: ='2.1meta'!N56 -> 0 | N45: ='2.1meta'!O56 -> 0 | O45: ='2.1meta'!P56 -> 0 | ... W45: ='2.1meta'!X56 -> 0 | X45: =SUM(H45:W45) -> 0 | Y45: =F45+X45 -> 0 | Z45: =C45-Y45 -> 0
A46: 2.1.1.9.2.1 | B46: COMPENSACION POR TIEMPO DE SERVICIOS (CTS) | C46: ='2.1meta'!D57 -> 0 | D46: ='2.1meta'!E57 -> 0 | E46: ='2.1meta'!F57 -> 0 | F46: 0 | G46: =C46-F46 -> 0 | H46: ='2.1meta'!I57 -> 0 | I46: ='2.1meta'!J57 -> 0 | J46: ='2.1meta'!K57 -> 0 | K46: ='2.1meta'!L57 -> 0 | L46: ='2.1meta'!M57 -> 0 | M46: ='2.1meta'!N57 -> 0 | N46: ='2.1meta'!O57 -> 0 | O46: ='2.1meta'!P57 -> 0 | ... W46: ='2.1meta'!X57 -> 0 | X46: =SUM(H46:W46) -> 0 | Y46: =F46+X46 -> 0 | Z46: =C46-Y46 -> 0
A47: 2.1.1.9.3.3 | B47: COMPENSACION VACACIONAL (VACACIONES TRUNCAS) | C47: ='2.1meta'!D58 -> 0 | D47: ='2.1meta'!E58 -> 0 | E47: ='2.1meta'!F58 -> 0 | F47: 0 | G47: =C47-F47 -> 0 | H47: ='2.1meta'!I58 -> 0 | I47: ='2.1meta'!J58 -> 0 | J47: ='2.1meta'!K58 -> 0 | K47: ='2.1meta'!L58 -> 0 | L47: ='2.1meta'!M58 -> 0 | M47: ='2.1meta'!N58 -> 0 | N47: ='2.1meta'!O58 -> 0 | O47: ='2.1meta'!P58 -> 0 | ... W47: ='2.1meta'!X58 -> 0 | X47: =SUM(H47:W47) -> 0 | Y47: =F47+X47 -> 0 | Z47: =C47-Y47 -> 0
A48: 2.1.1.9.3.99 | B48: OTRAS OCASIONALES | C48: ='2.1meta'!D59 -> 0 | D48: ='2.1meta'!E59 -> 0 | E48: ='2.1meta'!F59 -> 0 | F48: 0 | G48: =C48-F48 -> 0 | H48: ='2.1meta'!I59 -> 0 | I48: ='2.1meta'!J59 -> 0 | J48: ='2.1meta'!K59 -> 0 | K48: ='2.1meta'!L59 -> 0 | L48: ='2.1meta'!M59 -> 0 | M48: ='2.1meta'!N59 -> 0 | N48: ='2.1meta'!O59 -> 0 | O48: ='2.1meta'!P59 -> 0 | ... W48: ='2.1meta'!X59 -> 0 | X48: =SUM(H48:W48) -> 0 | Y48: =F48+X48 -> 0 | Z48: =C48-Y48 -> 0
A49: 2.1.3.1.1.1 | B49: APORTES A LOS FONDOS DE SALUD | C49: ='2.1meta'!D60 -> 0 | D49: ='2.1meta'!E60 -> 0 | E49: ='2.1meta'!F60 -> 0 | F49: 0 | G49: =C49-F49 -> 0 | H49: ='2.1meta'!I60 -> 0 | I49: ='2.1meta'!J60 -> 0 | J49: ='2.1meta'!K60 -> 0 | K49: ='2.1meta'!L60 -> 0 | L49: ='2.1meta'!M60 -> 0 | M49: ='2.1meta'!N60 -> 0 | N49: ='2.1meta'!O60 -> 0 | O49: ='2.1meta'!P60 -> 0 | ... W49: ='2.1meta'!X60 -> 0 | X49: =SUM(H49:W49) -> 0 | Y49: =F49+X49 -> 0 | Z49: =C49-Y49 -> 0
A50: 2.1.3.1.1.5 | B50: CONTRIBUCIONES A ESSALUD | C50: ='2.1meta'!D61 -> 0 | D50: ='2.1meta'!E61 -> 0 | E50: ='2.1meta'!F61 -> 0 | F50: 0 | G50: =C50-F50 -> 0 | H50: ='2.1meta'!I61 -> 0 | I50: ='2.1meta'!J61 -> 0 | J50: ='2.1meta'!K61 -> 0 | K50: ='2.1meta'!L61 -> 0 | L50: ='2.1meta'!M61 -> 0 | M50: ='2.1meta'!N61 -> 0 | N50: ='2.1meta'!O61 -> 0 | O50: ='2.1meta'!P61 -> 0 | ... W50: ='2.1meta'!X61 -> 0 | X50: =SUM(H50:W50) -> 0 | Y50: =F50+X50 -> 0 | Z50: =C50-Y50 -> 0
A51: 9002 ASIGNACIONES PRESUPUESTARIAS QUE NO RESULTAN EN PRODUCTOS | C51: =SUBTOTAL(9,C52:C66) -> 0 | F51: =SUBTOTAL(9,F52:F66) -> 0 | G51: =C51-F51 -> 0 | H51: =SUBTOTAL(9,H52:H66) -> 0 | I51: =SUBTOTAL(9,I52:I66) -> 0 | J51: =SUBTOTAL(9,J52:J66) -> 0 | K51: =SUBTOTAL(9,K52:K66) -> 0 | L51: =SUBTOTAL(9,L52:L66) -> 0 | M51: =SUBTOTAL(9,M52:M66) -> 0 | N51: =SUBTOTAL(9,N52:N66) -> 0 | O51: =SUBTOTAL(9,O52:O66) -> 0 | ... Z51: =SUBTOTAL(9,Z52:Z66) -> 0
A52: 2.1.1.1.1.2 | B52: PERSONAL ADMINISTRATIVO NOMBRADO (REGIMEN PUBLICO) | C52: ='2.1meta'!D63 -> 0 | D52: ='2.1meta'!E63 -> 0 | E52: ='2.1meta'!F63 -> 0 | F52: 0 | G52: =C52-F52 -> 0 | H52: ='2.1meta'!I63 -> 0 | I52: ='2.1meta'!J63 -> 0 | J52: ='2.1meta'!K63 -> 0 | K52: ='2.1meta'!L63 -> 0 | L52: ='2.1meta'!M63 -> 0 | M52: ='2.1meta'!N63 -> 0 | N52: ='2.1meta'!O63 -> 0 | O52: ='2.1meta'!P63 -> 0 | ... W52: ='2.1meta'!X63 -> 0 | X52: =SUM(H52:W52) -> 0 | Y52: =F52+X52 -> 0 | Z52: =C52-Y52 -> 0
A53: 2.1.1.1.1.4 | B53: PERSONAL CON CONTRATO A PLAZO INDETERMINADO (REGIMEN LABORAL PRIVADO) | C53: ='2.1meta'!D64 -> 0 | D53: ='2.1meta'!E64 -> 0 | E53: ='2.1meta'!F64 -> 0 | F53: 0 | G53: =C53-F53 -> 0 | H53: ='2.1meta'!I64 -> 0 | I53: ='2.1meta'!J64 -> 0 | J53: ='2.1meta'!K64 -> 0 | K53: ='2.1meta'!L64 -> 0 | L53: ='2.1meta'!M64 -> 0 | M53: ='2.1meta'!N64 -> 0 | N53: ='2.1meta'!O64 -> 0 | O53: ='2.1meta'!P64 -> 0 | ... W53: ='2.1meta'!X64 -> 0 | X53: =SUM(H53:W53) -> 0 | Y53: =F53+X53 -> 0 | Z53: =C53-Y53 -> 0
A54: 2.1.1.1.1.5 | B54: PERSONAL CON CONTRATO A PLAZO FIJO (REGIMEN LABORAL PRIVADO) | C54: ='2.1meta'!D65+'2.1meta'!D157 -> 0 | D54: ='2.1meta'!E65+'2.1meta'!E157 -> 0 | E54: ='2.1meta'!F65+'2.1meta'!F157 -> 0 | F54: 0 | G54: =C54-F54 -> 0 | H54: ='2.1meta'!I65+'2.1meta'!I157 -> 0 | I54: ='2.1meta'!J65+'2.1meta'!J157 -> 0 | J54: ='2.1meta'!K65+'2.1meta'!K157 -> 0 | K54: ='2.1meta'!L65+'2.1meta'!L157 -> 0 | L54: ='2.1meta'!M65+'2.1meta'!M157 -> 0 | M54: ='2.1meta'!N65+'2.1meta'!N157 -> 0 | N54: ='2.1meta'!O65+'2.1meta'!O157 -> 0 | O54: ='2.1meta'!P65+'2.1meta'!P157 -> 0 | ... W54: ='2.1meta'!X65+'2.1meta'!X157 -> 0 | X54: =SUM(H54:W54) -> 0 | Y54: =F54+X54 -> 0 | Z54: =C54-Y54 -> 0
A55: 2.1.1.1.2.1 | B55: ASIGNACION A FONDOS PARA PERSONAL | C55: ='2.1meta'!D66 -> 0 | D55: ='2.1meta'!E66 -> 0 | E55: ='2.1meta'!F66 -> 0 | F55: 0 | G55: =C55-F55 -> 0 | H55: ='2.1meta'!I66 -> 0 | I55: ='2.1meta'!J66 -> 0 | J55: ='2.1meta'!K66 -> 0 | K55: ='2.1meta'!L66 -> 0 | L55: ='2.1meta'!M66 -> 0 | M55: ='2.1meta'!N66 -> 0 | N55: ='2.1meta'!O66 -> 0 | O55: ='2.1meta'!P66 -> 0 | ... W55: ='2.1meta'!X66 -> 0 | X55: =SUM(H55:W55) -> 0 | Y55: =F55+X55 -> 0 | Z55: =C55-Y55 -> 0
A56: 2.1.1.4.1.1 | B56: PERSONAL NOMBRADO | C56: ='2.1meta'!D67+'2.1meta'!D158 -> 0 | D56: ='2.1meta'!E67+'2.1meta'!E158 -> 0 | E56: ='2.1meta'!F67+'2.1meta'!F158 -> 0 | F56: 0 | G56: =C56-F56 -> 0 | H56: ='2.1meta'!I67+'2.1meta'!I158 -> 0 | I56: ='2.1meta'!J67+'2.1meta'!J158 -> 0 | J56: ='2.1meta'!K67+'2.1meta'!K158 -> 0 | K56: ='2.1meta'!L67+'2.1meta'!L158 -> 0 | L56: ='2.1meta'!M67+'2.1meta'!M158 -> 0 | M56: ='2.1meta'!N67+'2.1meta'!N158 -> 0 | N56: ='2.1meta'!O67+'2.1meta'!O158 -> 0 | O56: ='2.1meta'!P67+'2.1meta'!P158 -> 0 | ... W56: ='2.1meta'!X67+'2.1meta'!X158 -> 0 | X56: =SUM(H56:W56) -> 0 | Y56: =F56+X56 -> 0 | Z56: =C56-Y56 -> 0
A57: 2.1.1.4.2.1 | B57: BONO POR FUNCION JURISDICCIONAL Y FISCAL | C57: ='2.1meta'!D68+'2.1meta'!D159 -> 0 | D57: ='2.1meta'!E68+'2.1meta'!E159 -> 0 | E57: ='2.1meta'!F68+'2.1meta'!F159 -> 0 | F57: 0 | G57: =C57-F57 -> 0 | H57: ='2.1meta'!I68+'2.1meta'!I159 -> 0 | I57: ='2.1meta'!J68+'2.1meta'!J159 -> 0 | J57: ='2.1meta'!K68+'2.1meta'!K159 -> 0 | K57: ='2.1meta'!L68+'2.1meta'!L159 -> 0 | L57: ='2.1meta'!M68+'2.1meta'!M159 -> 0 | M57: ='2.1meta'!N68+'2.1meta'!N159 -> 0 | N57: ='2.1meta'!O68+'2.1meta'!O159 -> 0 | O57: ='2.1meta'!P68+'2.1meta'!P159 -> 0 | ... W57: ='2.1meta'!X68+'2.1meta'!X159 -> 0 | X57: =SUM(H57:W57) -> 0 | Y57: =F57+X57 -> 0 | Z57: =C57-Y57 -> 0
A58: 2.1.1.4.2.2 | B58: ASIGNACION POR GASTOS OPERATIVOS | C58: ='2.1meta'!D69+'2.1meta'!D160 -> 0 | D58: ='2.1meta'!E69+'2.1meta'!E160 -> 0 | E58: ='2.1meta'!F69+'2.1meta'!F160 -> 0 | F58: 0 | G58: =C58-F58 -> 0 | H58: ='2.1meta'!I69+'2.1meta'!I160 -> 0 | I58: ='2.1meta'!J69+'2.1meta'!J160 -> 0 | J58: ='2.1meta'!K69+'2.1meta'!K160 -> 0 | K58: ='2.1meta'!L69+'2.1meta'!L160 -> 0 | L58: ='2.1meta'!M69+'2.1meta'!M160 -> 0 | M58: ='2.1meta'!N69+'2.1meta'!N160 -> 0 | N58: ='2.1meta'!O69+'2.1meta'!O160 -> 0 | O58: ='2.1meta'!P69+'2.1meta'!P160 -> 0 | ... W58: ='2.1meta'!X69+'2.1meta'!X160 -> 0 | X58: =SUM(H58:W58) -> 0 | Y58: =F58+X58 -> 0 | Z58: =C58-Y58 -> 0
A59: 2.1.1.9.1.1 | B59: GRATIFICACIONES | C59: ='2.1meta'!D70+'2.1meta'!D161 -> 0 | D59: ='2.1meta'!E70+'2.1meta'!E161 -> 0 | E59: ='2.1meta'!F70+'2.1meta'!F161 -> 0 | F59: 0 | G59: =C59-F59 -> 0 | H59: ='2.1meta'!I70+'2.1meta'!I161 -> 0 | I59: ='2.1meta'!J70+'2.1meta'!J161 -> 0 | J59: ='2.1meta'!K70+'2.1meta'!K161 -> 0 | K59: ='2.1meta'!L70+'2.1meta'!L161 -> 0 | L59: ='2.1meta'!M70+'2.1meta'!M161 -> 0 | M59: ='2.1meta'!N70+'2.1meta'!N161 -> 0 | N59: ='2.1meta'!O70+'2.1meta'!O161 -> 0 | O59: ='2.1meta'!P70+'2.1meta'!P161 -> 0 | ... W59: ='2.1meta'!X70+'2.1meta'!X161 -> 0 | X59: =SUM(H59:W59) -> 0 | Y59: =F59+X59 -> 0 | Z59: =C59-Y59 -> 0
A60: 2.1.1.9.1.2 | B60: AGUINALDOS | C60: ='2.1meta'!D71+'2.1meta'!D162 -> 0 | D60: ='2.1meta'!E71+'2.1meta'!E162 -> 0 | E60: ='2.1meta'!F71+'2.1meta'!F162 -> 0 | F60: 0 | G60: =C60-F60 -> 0 | H60: ='2.1meta'!I71+'2.1meta'!I162 -> 0 | I60: ='2.1meta'!J71+'2.1meta'!J162 -> 0 | J60: ='2.1meta'!K71+'2.1meta'!K162 -> 0 | K60: ='2.1meta'!L71+'2.1meta'!L162 -> 0 | L60: ='2.1meta'!M71+'2.1meta'!M162 -> 0 | M60: ='2.1meta'!N71+'2.1meta'!N162 -> 0 | N60: ='2.1meta'!O71+'2.1meta'!O162 -> 0 | O60: ='2.1meta'!P71+'2.1meta'!P162 -> 0 | ... W60: ='2.1meta'!X71+'2.1meta'!X162 -> 0 | X60: =SUM(H60:W60) -> 0 | Y60: =F60+X60 -> 0 | Z60: =C60-Y60 -> 0
A61: 2.1.1.9.1.3 | B61: BONIFICACION POR ESCOLARIDAD | C61: ='2.1meta'!D72+'2.1meta'!D163 -> 0 | D61: ='2.1meta'!E72+'2.1meta'!E163 -> 0 | E61: ='2.1meta'!F72+'2.1meta'!F163 -> 0 | F61: 0 | G61: =C61-F61 -> 0 | H61: ='2.1meta'!I72+'2.1meta'!I163 -> 0 | I61: ='2.1meta'!J72+'2.1meta'!J163 -> 0 | J61: ='2.1meta'!K72+'2.1meta'!K163 -> 0 | K61: ='2.1meta'!L72+'2.1meta'!L163 -> 0 | L61: ='2.1meta'!M72+'2.1meta'!M163 -> 0 | M61: ='2.1meta'!N72+'2.1meta'!N163 -> 0 | N61: ='2.1meta'!O72+'2.1meta'!O163 -> 0 | O61: ='2.1meta'!P72+'2.1meta'!P163 -> 0 | ... W61: ='2.1meta'!X72+'2.1meta'!X163 -> 0 | X61: =SUM(H61:W61) -> 0 | Y61: =F61+X61 -> 0 | Z61: =C61-Y61 -> 0
A62: 2.1.1.9.2.1 | B62: COMPENSACION POR TIEMPO DE SERVICIOS (CTS) | C62: ='2.1meta'!D73+'2.1meta'!D164 -> 0 | D62: ='2.1meta'!E73+'2.1meta'!E164 -> 0 | E62: ='2.1meta'!F73+'2.1meta'!F164 -> 0 | F62: 0 | G62: =C62-F62 -> 0 | H62: ='2.1meta'!I73+'2.1meta'!I164 -> 0 | I62: ='2.1meta'!J73+'2.1meta'!J164 -> 0 | J62: ='2.1meta'!K73+'2.1meta'!K164 -> 0 | K62: ='2.1meta'!L73+'2.1meta'!L164 -> 0 | L62: ='2.1meta'!M73+'2.1meta'!M164 -> 0 | M62: ='2.1meta'!N73+'2.1meta'!N164 -> 0 | N62: ='2.1meta'!O73+'2.1meta'!O164 -> 0 | O62: ='2.1meta'!P73+'2.1meta'!P164 -> 0 | ... W62: ='2.1meta'!X73+'2.1meta'!X164 -> 0 | X62: =SUM(H62:W62) -> 0 | Y62: =F62+X62 -> 0 | Z62: =C62-Y62 -> 0
A63: 2.1.1.9.3.99 | B63: OTRAS OCASIONALES | C63: ='2.1meta'!D74+'2.1meta'!D165 -> 0 | D63: ='2.1meta'!E74+'2.1meta'!E165 -> 0 | E63: ='2.1meta'!F74+'2.1meta'!F165 -> 0 | F63: 0 | G63: =C63-F63 -> 0 | H63: ='2.1meta'!I74+'2.1meta'!I165 -> 0 | I63: ='2.1meta'!J74+'2.1meta'!J165 -> 0 | J63: ='2.1meta'!K74+'2.1meta'!K165 -> 0 | K63: ='2.1meta'!L74+'2.1meta'!L165 -> 0 | L63: ='2.1meta'!M74+'2.1meta'!M165 -> 0 | M63: ='2.1meta'!N74+'2.1meta'!N165 -> 0 | N63: ='2.1meta'!O74+'2.1meta'!O165 -> 0 | O63: ='2.1meta'!P74+'2.1meta'!P165 -> 0 | ... W63: ='2.1meta'!X74+'2.1meta'!X165 -> 0 | X63: =SUM(H63:W63) -> 0 | Y63: =F63+X63 -> 0 | Z63: =C63-Y63 -> 0
A64: 2.1.3.1.1.1 | B64: APORTES A LOS FONDOS DE SALUD | C64: ='2.1meta'!D75+'2.1meta'!D166 -> 0 | D64: ='2.1meta'!E75+'2.1meta'!E166 -> 0 | E64: ='2.1meta'!F75+'2.1meta'!F166 -> 0 | F64: 0 | G64: =C64-F64 -> 0 | H64: ='2.1meta'!I75+'2.1meta'!I166 -> 0 | I64: ='2.1meta'!J75+'2.1meta'!J166 -> 0 | J64: ='2.1meta'!K75+'2.1meta'!K166 -> 0 | K64: ='2.1meta'!L75+'2.1meta'!L166 -> 0 | L64: ='2.1meta'!M75+'2.1meta'!M166 -> 0 | M64: ='2.1meta'!N75+'2.1meta'!N166 -> 0 | N64: ='2.1meta'!O75+'2.1meta'!O166 -> 0 | O64: ='2.1meta'!P75+'2.1meta'!P166 -> 0 | ... W64: ='2.1meta'!X75+'2.1meta'!X166 -> 0 | X64: =SUM(H64:W64) -> 0 | Y64: =F64+X64 -> 0 | Z64: =C64-Y64 -> 0
A65: 2.1.3.1.1.3 | B65: APORTES A LOS FONDOS DE PENSIONES | C65: ='2.1meta'!D76 -> 0 | D65: ='2.1meta'!E76 -> 0 | E65: ='2.1meta'!F76 -> 0 | F65: 0 | G65: =C65-F65 -> 0 | H65: ='2.1meta'!I76 -> 0 | I65: ='2.1meta'!J76 -> 0 | J65: ='2.1meta'!K76 -> 0 | K65: ='2.1meta'!L76 -> 0 | L65: ='2.1meta'!M76 -> 0 | M65: ='2.1meta'!N76 -> 0 | N65: ='2.1meta'!O76 -> 0 | O65: ='2.1meta'!P76 -> 0 | ... W65: ='2.1meta'!X76 -> 0 | X65: =SUM(H65:W65) -> 0 | Y65: =F65+X65 -> 0 | Z65: =C65-Y65 -> 0
A66: 2.1.3.1.1.5 | B66: CONTRIBUCIONES A ESSALUD | C66: ='2.1meta'!D77+'2.1meta'!D167 -> 0 | D66: ='2.1meta'!E77+'2.1meta'!E167 -> 0 | E66: ='2.1meta'!F77+'2.1meta'!F167 -> 0 | F66: 0 | G66: =C66-F66 -> 0 | H66: ='2.1meta'!I77+'2.1meta'!I167 -> 0 | I66: ='2.1meta'!J77+'2.1meta'!J167 -> 0 | J66: ='2.1meta'!K77+'2.1meta'!K167 -> 0 | K66: ='2.1meta'!L77+'2.1meta'!L167 -> 0 | L66: ='2.1meta'!M77+'2.1meta'!M167 -> 0 | M66: ='2.1meta'!N77+'2.1meta'!N167 -> 0 | N66: ='2.1meta'!O77+'2.1meta'!O167 -> 0 | O66: ='2.1meta'!P77+'2.1meta'!P167 -> 0 | ... W66: ='2.1meta'!X77+'2.1meta'!X167 -> 0 | X66: =SUM(H66:W66) -> 0 | Y66: =F66+X66 -> 0 | Z66: =C66-Y66 -> 0
A67: TOTAL 2.1 PERSONAL Y OB. SOCIALES | C67: =SUBTOTAL(9,C5:C66) -> 0 | F67: =SUBTOTAL(9,F5:F66) -> 0 | G67: =C67-F67 -> 0 | H67: =SUBTOTAL(9,H5:H66) -> 0 | I67: =SUBTOTAL(9,I5:I66) -> 0 | J67: =SUBTOTAL(9,J5:J66) -> 0 | K67: =SUBTOTAL(9,K5:K66) -> 0 | L67: =SUBTOTAL(9,L5:L66) -> 0 | M67: =SUBTOTAL(9,M5:M66) -> 0 | N67: =SUBTOTAL(9,N5:N66) -> 0 | O67: =SUBTOTAL(9,O5:O66) -> 0 | ... Z67: =SUBTOTAL(9,Z5:Z66) -> 0

Sheet ESPECIFICA DE GASTO
A1: EJECUTORA: 0003 MINISTERIO PUBLICO - GERENCIA ADMINISTRATIVA DE AREQUIPA (1419)
A3: Cat pptal/ Detalle Específica de Gasto | C3: PIM | D3: Certificado | E3: Compromiso Anual | F3: T O T A L | G3: Saldo Presupuestal al 17.09.2021 | H3: Proyección Planillas Activa | T3: Proyeccion de plazas vacantes | V3: PAGO FACTURAS EPS | W3: BENEFICIOS | X3: TOTAL PROYECCION | Y3: TOTAL EJECUCION +PROYECCION | Z3: SALDO DISPONIBLE
H4: 01 ENERO | I4: 02 FEBRERO | J4: 03 MARZO | K4: 04 ABRIL | L4: 05 MAYO | M4: 06 JUNIO | N4: 07 JULIO | O4: 08 AGOSTO | P4: 09 SETIEMBRE | Q4: 10 OCTUBRE | R4: 11 OCTUBRE | S4: 12 OCTUBRE | T4: 276 | U4: 728
A5: 2.1.1.1.1.2 | B5: PERSONAL ADMINISTRATIVO NOMBRADO (REGIMEN PUBLICO) | C5: ='2.1meta'!D7+'2.1meta'!D23+'2.1meta'!D50+'2.1meta'!D63+'2.1meta'!D130 -> 0 | D5: ='2.1meta'!E7+'2.1meta'!E23+'2.1meta'!E50+'2.1meta'!E63+'2.1meta'!E130 -> 0 | E5: ='2.1meta'!F7+'2.1meta'!F23+'2.1meta'!F50+'2.1meta'!F63+'2.1meta'!F130 -> 0 | F5: 0 | G5: =C5-F5 -> 0 | H5: ='2.1meta'!I7+'2.1meta'!I23+'2.1meta'!I50+'2.1meta'!I63+'2.1meta'!I130 -> 0 | I5: ='2.1meta'!J7+'2.1meta'!J23+'2.1meta'!J50+'2.1meta'!J63+'2.1meta'!J130 -> 0 | J5: ='2.1meta'!K7+'2.1meta'!K23+'2.1meta'!K50+'2.1meta'!K63+'2.1meta'!K130 -> 0 | K5: ='2.1meta'!L7+'2.1meta'!L23+'2.1meta'!L50+'2.1meta'!L63+'2.1meta'!L130 -> 0 | L5: ='2.1meta'!M7+'2.1meta'!M23+'2.1meta'!M50+'2.1meta'!M63+'2.1meta'!M130 -> 0 | M5: ='2.1meta'!N7+'2.1meta'!N23+'2.1meta'!N50+'2.1meta'!N63+'2.1meta'!N130 -> 0 | N5: ='2.1meta'!O7+'2.1meta'!O23+'2.1meta'!O50+'2.1meta'!O63+'2.1meta'!O130 -> 0 | O5: ='2.1meta'!P7+'2.1meta'!P23+'2.1meta'!P50+'2.1meta'!P63+'2.1meta'!P130 -> 0 | ... W5: ='2.1meta'!X7+'2.1meta'!X23+'2.1meta'!X50+'2.1meta'!X63+'2.1meta'!X130 -> 0 | X5: =SUM(H5:W5) -> 0 | Y5: =F5+X5 -> 0 | Z5: =C5-Y5 -> 0
A6: 2.1.1.1.1.4 | B6: PERSONAL CON CONTRATO A PLAZO INDETERMINADO (REGIMEN LABORAL PRIVADO) | C6: ='2.1meta'!D8+'2.1meta'!D24+'2.1meta'!D40+'2.1meta'!D51+'2.1meta'!D64+'2.1meta'!D79+'2.1meta'!D92+'2.1meta'!D104+'2.1meta'!D131+'2.1meta'!D145 -> 0 | D6: ='2.1meta'!E8+'2.1meta'!E24+'2.1meta'!E40+'2.1meta'!E51+'2.1meta'!E64+'2.1meta'!E79+'2.1meta'!E92+'2.1meta'!E104+'2.1meta'!E131+'2.1meta'!E145 -> 0 | E6: ='2.1meta'!F8+'2.1meta'!F24+'2.1meta'!F40+'2.1meta'!F51+'2.1meta'!F64+'2.1meta'!F79+'2.1meta'!F92+'2.1meta'!F104+'2.1meta'!F131+'2.1meta'!F145 -> 0 | F6: 0 | G6: =C6-F6 -> 0 | H6: ='2.1meta'!I8+'2.1meta'!I24+'2.1meta'!I40+'2.1meta'!I51+'2.1meta'!I64+'2.1meta'!I79+'2.1meta'!I92+'2.1meta'!I104+'2.1meta'!I131+'2.1meta'!I145 -> 0 | I6: ='2.1meta'!J8+'2.1meta'!J24+'2.1meta'!J40+'2.1meta'!J51+'2.1meta'!J64+'2.1meta'!J79+'2.1meta'!J92+'2.1meta'!J104+'2.1meta'!J131+'2.1meta'!J145 -> 0 | J6: ='2.1meta'!K8+'2.1meta'!K24+'2.1meta'!K40+'2.1meta'!K51+'2.1meta'!K64+'2.1meta'!K79+'2.1meta'!K92+'2.1meta'!K104+'2.1meta'!K131+'2.1meta'!K145 -> 0 | K6: ='2.1meta'!L8+'2.1meta'!L24+'2.1meta'!L40+'2.1meta'!L51+'2.1meta'!L64+'2.1meta'!L79+'2.1meta'!L92+'2.1meta'!L104+'2.1meta'!L131+'2.1meta'!L145 -> 0 | L6: ='2.1meta'!M8+'2.1meta'!M24+'2.1meta'!M40+'2.1meta'!M51+'2.1meta'!M64+'2.1meta'!M79+'2.1meta'!M92+'2.1meta'!M104+'2.1meta'!M131+'2.1meta'!M145 -> 0 | M6: ='2.1meta'!N8+'2.1meta'!N24+'2.1meta'!N40+'2.1meta'!N51+'2.1meta'!N64+'2.1meta'!N79+'2.1meta'!N92+'2.1meta'!N104+'2.1meta'!N131+'2.1meta'!N145 -> 0 | N6: ='2.1meta'!O8+'2.1meta'!O24+'2.1meta'!O40+'2.1meta'!O51+'2.1meta'!O64+'2.1meta'!O79+'2.1meta'!O92+'2.1meta'!O104+'2.1meta'!O131+'2.1meta'!O145 -> 0 | O6: ='2.1meta'!P8+'2.1meta'!P24+'2.1meta'!P40+'2.1meta'!P51+'2.1meta'!P64+'2.1meta'!P79+'2.1meta'!P92+'2.1meta'!P104+'2.1meta'!P131+'2.1meta'!P145 -> 0 | ... W6: ='2.1meta'!X8+'2.1meta'!X24+'2.1meta'!X40+'2.1meta'!X51+'2.1meta'!X64+'2.1meta'!X79+'2.1meta'!X92+'2.1meta'!X104+'2.1meta'!X131+'2.1meta'!X145 -> 0 | X6: =SUM(H6:W6) -> 0 | Y6: =F6+X6 -> 0 | Z6: =C6-Y6 -> 0
A7: 2.1.1.1.1.5 | B7: PERSONAL CON CONTRATO A PLAZO FIJO (REGIMEN LABORAL PRIVADO) | C7: ='2.1meta'!D9+'2.1meta'!D25+'2.1meta'!D41+'2.1meta'!D52+'2.1meta'!D65+'2.1meta'!D93+'2.1meta'!D132+'2.1meta'!D157 -> 0 | D7: ='2.1meta'!E9+'2.1meta'!E25+'2.1meta'!E41+'2.1meta'!E52+'2.1meta'!E65+'2.1meta'!E93+'2.1meta'!E132+'2.1meta'!E157 -> 0 | E7: ='2.1meta'!F9+'2.1meta'!F25+'2.1meta'!F41+'2.1meta'!F52+'2.1meta'!F65+'2.1meta'!F93+'2.1meta'!F132+'2.1meta'!F157 -> 0 | F7: 0 | G7: =C7-F7 -> 0 | H7: ='2.1meta'!I9+'2.1meta'!I25+'2.1meta'!I41+'2.1meta'!I52+'2.1meta'!I65+'2.1meta'!I93+'2.1meta'!I132+'2.1meta'!I157 -> 0 | I7: ='2.1meta'!J9+'2.1meta'!J25+'2.1meta'!J41+'2.1meta'!J52+'2.1meta'!J65+'2.1meta'!J93+'2.1meta'!J132+'2.1meta'!J157 -> 0 | J7: ='2.1meta'!K9+'2.1meta'!K25+'2.1meta'!K41+'2.1meta'!K52+'2.1meta'!K65+'2.1meta'!K93+'2.1meta'!K132+'2.1meta'!K157 -> 0 | K7: ='2.1meta'!L9+'2.1meta'!L25+'2.1meta'!L41+'2.1meta'!L52+'2.1meta'!L65+'2.1meta'!L93+'2.1meta'!L132+'2.1meta'!L157 -> 0 | L7: ='2.1meta'!M9+'2.1meta'!M25+'2.1meta'!M41+'2.1meta'!M52+'2.1meta'!M65+'2.1meta'!M93+'2.1meta'!M132+'2.1meta'!M157 -> 0 | M7: ='2.1meta'!N9+'2.1meta'!N25+'2.1meta'!N41+'2.1meta'!N52+'2.1meta'!N65+'2.1meta'!N93+'2.1meta'!N132+'2.1meta'!N157 -> 0 | N7: ='2.1meta'!O9+'2.1meta'!O25+'2.1meta'!O41+'2.1meta'!O52+'2.1meta'!O65+'2.1meta'!O93+'2.1meta'!O132+'2.1meta'!O157 -> 0 | O7: ='2.1meta'!P9+'2.1meta'!P25+'2.1meta'!P41+'2.1meta'!P52+'2.1meta'!P65+'2.1meta'!P93+'2.1meta'!P132+'2.1meta'!P157 -> 0 | ... W7: ='2.1meta'!X9+'2.1meta'!X25+'2.1meta'!X41+'2.1meta'!X52+'2.1meta'!X65+'2.1meta'!X93+'2.1meta'!X132+'2.1meta'!X157 -> 0 | X7: =SUM(H7:W7) -> 0 | Y7: =F7+X7 -> 0 | Z7: =C7-Y7 -> 0
A8: 2.1.1.1.2.1 | B8: ASIGNACION A FONDOS PARA PERSONAL | C8: ='2.1meta'!D10+'2.1meta'!D26+'2.1meta'!D53+'2.1meta'!D66+'2.1meta'!D133 -> 0 | D8: ='2.1meta'!E10+'2.1meta'!E26+'2.1meta'!E53+'2.1meta'!E66+'2.1meta'!E133 -> 0 | E8: ='2.1meta'!F10+'2.1meta'!F26+'2.1meta'!F53+'2.1meta'!F66+'2.1meta'!F133 -> 0 | F8: 0 | G8: =C8-F8 -> 0 | H8: ='2.1meta'!I10+'2.1meta'!I26+'2.1meta'!I53+'2.1meta'!I66+'2.1meta'!I133 -> 0 | I8: ='2.1meta'!J10+'2.1meta'!J26+'2.1meta'!J53+'2.1meta'!J66+'2.1meta'!J133 -> 0 | J8: ='2.1meta'!K10+'2.1meta'!K26+'2.1meta'!K53+'2.1meta'!K66+'2.1meta'!K133 -> 0 | K8: ='2.1meta'!L10+'2.1meta'!L26+'2.1meta'!L53+'2.1meta'!L66+'2.1meta'!L133 -> 0 | L8: ='2.1meta'!M10+'2.1meta'!M26+'2.1meta'!M53+'2.1meta'!M66+'2.1meta'!M133 -> 0 | M8: ='2.1meta'!N10+'2.1meta'!N26+'2.1meta'!N53+'2.1meta'!N66+'2.1meta'!N133 -> 0 | N8: ='2.1meta'!O10+'2.1meta'!O26+'2.1meta'!O53+'2.1meta'!O66+'2.1meta'!O133 -> 0 | O8: ='2.1meta'!P10+'2.1meta'!P26+'2.1meta'!P53+'2.1meta'!P66+'2.1meta'!P133 -> 0 | ... W8: ='2.1meta'!X10+'2.1meta'!X26+'2.1meta'!X53+'2.1meta'!X66+'2.1meta'!X133 -> 0 | X8: =SUM(H8:W8) -> 0 | Y8: =F8+X8 -> 0 | Z8: =C8-Y8 -> 0
A9: 2.1.1. 3.1. 2 | B9: PERSONAL CONTRATADO | C9: ='2.1meta'!D42 -> 0 | D9: ='2.1meta'!E42 -> 0 | E9: ='2.1meta'!F42 -> 0 | F9: 0 | G9: =C9-F9 -> 0 | H9: ='2.1meta'!I42 -> 0 | I9: ='2.1meta'!J42 -> 0 | J9: ='2.1meta'!K42 -> 0 | K9: ='2.1meta'!L42 -> 0 | L9: ='2.1meta'!M42 -> 0 | M9: ='2.1meta'!N42 -> 0 | N9: ='2.1meta'!O42 -> 0 | O9: ='2.1meta'!P42 -> 0 | ... W9: ='2.1meta'!X42 -> 0 | X9: =SUM(H9:W9) -> 0 | Y9: =F9+X9 -> 0 | Z9: =C9-Y9 -> 0
A10: 2.1.1.4.1.1 | B10: PERSONAL NOMBRADO | C10: ='2.1meta'!D11+'2.1meta'!D27+'2.1meta'!D67+'2.1meta'!D80+'2.1meta'!D94+'2.1meta'!D105+'2.1meta'!D115+'2.1meta'!D122+'2.1meta'!D134+'2.1meta'!D146+'2.1meta'!D158 -> 0 | D10: ='2.1meta'!E11+'2.1meta'!E27+'2.1meta'!E67+'2.1meta'!E80+'2.1meta'!E94+'2.1meta'!E105+'2.1meta'!E115+'2.1meta'!E122+'2.1meta'!E134+'2.1meta'!E146+'2.1meta'!E158 -> 0 | E10: ='2.1meta'!F11+'2.1meta'!F27+'2.1meta'!F67+'2.1meta'!F80+'2.1meta'!F94+'2.1meta'!F105+'2.1meta'!F115+'2.1meta'!F122+'2.1meta'!F134+'2.1meta'!F146+'2.1meta'!F158 -> 0 | F10: 0 | G10: =C10-F10 -> 0 | H10: ='2.1meta'!I11+'2.1meta'!I27+'2.1meta'!I67+'2.1meta'!I80+'2.1meta'!I94+'2.1meta'!I105+'2.1meta'!I115+'2.1meta'!I122+'2.1meta'!I134+'2.1meta'!I146+'2.1meta'!I158 -> 0 | I10: ='2.1meta'!J11+'2.1meta'!J27+'2.1meta'!J67+'2.1meta'!J80+'2.1meta'!J94+'2.1meta'!J105+'2.1meta'!J115+'2.1meta'!J122+'2.1meta'!J134+'2.1meta'!J146+'2.1meta'!J158 -> 0 | J10: ='2.1meta'!K11+'2.1meta'!K27+'2.1meta'!K67+'2.1meta'!K80+'2.1meta'!K94+'2.1meta'!K105+'2.1meta'!K115+'2.1meta'!K122+'2.1meta'!K134+'2.1meta'!K146+'2.1meta'!K158 -> 0 | K10: ='2.1meta'!L11+'2.1meta'!L27+'2.1meta'!L67+'2.1meta'!L80+'2.1meta'!L94+'2.1meta'!L105+'2.1meta'!L115+'2.1meta'!L122+'2.1meta'!L134+'2.1meta'!L146+'2.1meta'!L158 -> 0 | L10: ='2.1meta'!M11+'2.1meta'!M27+'2.1meta'!M67+'2.1meta'!M80+'2.1meta'!M94+'2.1meta'!M105+'2.1meta'!M115+'2.1meta'!M122+'2.1meta'!M134+'2.1meta'!M146+'2.1meta'!M158 -> 0 | M10: ='2.1meta'!N11+'2.1meta'!N27+'2.1meta'!N67+'2.1meta'!N80+'2.1meta'!N94+'2.1meta'!N105+'2.1meta'!N115+'2.1meta'!N122+'2.1meta'!N134+'2.1meta'!N146+'2.1meta'!N158 -> 0 | N10: ='2.1meta'!O11+'2.1meta'!O27+'2.1meta'!O67+'2.1meta'!O80+'2.1meta'!O94+'2.1meta'!O105+'2.1meta'!O115+'2.1meta'!O122+'2.1meta'!O134+'2.1meta'!O146+'2.1meta'!O158 -> 0 | O10: ='2.1meta'!P11+'2.1meta'!P27+'2.1meta'!P67+'2.1meta'!P80+'2.1meta'!P94+'2.1meta'!P105+'2.1meta'!P115+'2.1meta'!P122+'2.1meta'!P134+'2.1meta'!P146+'2.1meta'!P158 -> 0 | ... W10: ='2.1meta'!X11+'2.1meta'!X27+'2.1meta'!X67+'2.1meta'!X80+'2.1meta'!X94+'2.1meta'!X105+'2.1meta'!X115+'2.1meta'!X122+'2.1meta'!X134+'2.1meta'!X146+'2.1meta'!X158 -> 0 | X10: =SUM(H10:W10) -> 0 | Y10: =F10+X10 -> 0 | Z10: =C10-Y10 -> 0
A11: 2.1.1.4.2.1 | B11: BONO POR FUNCION JURISDICCIONAL Y FISCAL | C11: ='2.1meta'!D12+'2.1meta'!D28+'2.1meta'!D68+'2.1meta'!D81+'2.1meta'!D95+'2.1meta'!D106+'2.1meta'!D116+'2.1meta'!D123+'2.1meta'!D135+'2.1meta'!D147+'2.1meta'!D159 -> 0 | D11: ='2.1meta'!E12+'2.1meta'!E28+'2.1meta'!E68+'2.1meta'!E81+'2.1meta'!E95+'2.1meta'!E106+'2.1meta'!E116+'2.1meta'!E123+'2.1meta'!E135+'2.1meta'!E147+'2.1meta'!E159 -> 0 | E11: ='2.1meta'!F12+'2.1meta'!F28+'2.1meta'!F68+'2.1meta'!F81+'2.1meta'!F95+'2.1meta'!F106+'2.1meta'!F116+'2.1meta'!F123+'2.1meta'!F135+'2.1meta'!F147+'2.1meta'!F159 -> 0 | F11: 0 | G11: =C11-F11 -> 0 | H11: ='2.1meta'!I12+'2.1meta'!I28+'2.1meta'!I68+'2.1meta'!I81+'2.1meta'!I95+'2.1meta'!I106+'2.1meta'!I116+'2.1meta'!I123+'2.1meta'!I135+'2.1meta'!I147+'2.1meta'!I159 -> 0 | I11: ='2.1meta'!J12+'2.1meta'!J28+'2.1meta'!J68+'2.1meta'!J81+'2.1meta'!J95+'2.1meta'!J106+'2.1meta'!J116+'2.1meta'!J123+'2.1meta'!J135+'2.1meta'!J147+'2.1meta'!J159 -> 0 | J11: ='2.1meta'!K12+'2.1meta'!K28+'2.1meta'!K68+'2.1meta'!K81+'2.1meta'!K95+'2.1meta'!K106+'2.1meta'!K116+'2.1meta'!K123+'2.1meta'!K135+'2.1meta'!K147+'2.1meta'!K159 -> 0 | K11: ='2.1meta'!L12+'2.1meta'!L28+'2.1meta'!L68+'2.1meta'!L81+'2.1meta'!L95+'2.1meta'!L106+'2.1meta'!L116+'2.1meta'!L123+'2.1meta'!L135+'2.1meta'!L147+'2.1meta'!L159 -> 0 | L11: ='2.1meta'!M12+'2.1meta'!M28+'2.1meta'!M68+'2.1meta'!M81+'2.1meta'!M95+'2.1meta'!M106+'2.1meta'!M116+'2.1meta'!M123+'2.1meta'!M135+'2.1meta'!M147+'2.1meta'!M159 -> 0 | M11: ='2.1meta'!N12+'2.1meta'!N28+'2.1meta'!N68+'2.1meta'!N81+'2.1meta'!N95+'2.1meta'!N106+'2.1meta'!N116+'2.1meta'!N123+'2.1meta'!N135+'2.1meta'!N147+'2.1meta'!N159 -> 0 | N11: ='2.1meta'!O12+'2.1meta'!O28+'2.1meta'!O68+'2.1meta'!O81+'2.1meta'!O95+'2.1meta'!O106+'2.1meta'!O116+'2.1meta'!O123+'2.1meta'!O135+'2.1meta'!O147+'2.1meta'!O159 -> 0 | O11: ='2.1meta'!P12+'2.1meta'!P28+'2.1meta'!P68+'2.1meta'!P81+'2.1meta'!P95+'2.1meta'!P106+'2.1meta'!P116+'2.1meta'!P123+'2.1meta'!P135+'2.1meta'!P147+'2.1meta'!P159 -> 0 | ... W11: ='2.1meta'!X12+'2.1meta'!X28+'2.1meta'!X68+'2.1meta'!X81+'2.1meta'!X95+'2.1meta'!X106+'2.1meta'!X116+'2.1meta'!X123+'2.1meta'!X135+'2.1meta'!X147+'2.1meta'!X159 -> 0 | X11: =SUM(H11:W11) -> 0 | Y11: =F11+X11 -> 0 | Z11: =C11-Y11 -> 0
A12: 2.1.1.4.2.2 | B12: ASIGNACION POR GASTOS OPERATIVOS | C12: ='2.1meta'!D13+'2.1meta'!D29+'2.1meta'!D69+'2.1meta'!D82+'2.1meta'!D96+'2.1meta'!D107+'2.1meta'!D117+'2.1meta'!D124+'2.1meta'!D136+'2.1meta'!D148+'2.1meta'!D160 -> 0 | D12: ='2.1meta'!E13+'2.1meta'!E29+'2.1meta'!E69+'2.1meta'!E82+'2.1meta'!E96+'2.1meta'!E107+'2.1meta'!E117+'2.1meta'!E124+'2.1meta'!E136+'2.1meta'!E148+'2.1meta'!E160 -> 0 | E12: ='2.1meta'!F13+'2.1meta'!F29+'2.1meta'!F69+'2.1meta'!F82+'2.1meta'!F96+'2.1meta'!F107+'2.1meta'!F117+'2.1meta'!F124+'2.1meta'!F136+'2.1meta'!F148+'2.1meta'!F160 -> 0 | F12: 0 | G12: =C12-F12 -> 0 | H12: ='2.1meta'!I13+'2.1meta'!I29+'2.1meta'!I69+'2.1meta'!I82+'2.1meta'!I96+'2.1meta'!I107+'2.1meta'!I117+'2.1meta'!I124+'2.1meta'!I136+'2.1meta'!I148+'2.1meta'!I160 -> 0 | I12: ='2.1meta'!J13+'2.1meta'!J29+'2.1meta'!J69+'2.1meta'!J82+'2.1meta'!J96+'2.1meta'!J107+'2.1meta'!J117+'2.1meta'!J124+'2.1meta'!J136+'2.1meta'!J148+'2.1meta'!J160 -> 0 | J12: ='2.1meta'!K13+'2.1meta'!K29+'2.1meta'!K69+'2.1meta'!K82+'2.1meta'!K96+'2.1meta'!K107+'2.1meta'!K117+'2.1meta'!K124+'2.1meta'!K136+'2.1meta'!K148+'2.1meta'!K160 -> 0 | K12: ='2.1meta'!L13+'2.1meta'!L29+'2.1meta'!L69+'2.1meta'!L82+'2.1meta'!L96+'2.1meta'!L107+'2.1meta'!L117+'2.1meta'!L124+'2.1meta'!L136+'2.1meta'!L148+'2.1meta'!L160 -> 0 | L12: ='2.1meta'!M13+'2.1meta'!M29+'2.1meta'!M69+'2.1meta'!M82+'2.1meta'!M96+'2.1meta'!M107+'2.1meta'!M117+'2.1meta'!M124+'2.1meta'!M136+'2.1meta'!M148+'2.1meta'!M160 -> 0 | M12: ='2.1meta'!N13+'2.1meta'!N29+'2.1meta'!N69+'2.1meta'!N82+'2.1meta'!N96+'2.1meta'!N107+'2.1meta'!N117+'2.1meta'!N124+'2.1meta'!N136+'2.1meta'!N148+'2.1meta'!N160 -> 0 | N12: ='2.1meta'!O13+'2.1meta'!O29+'2.1meta'!O69+'2.1meta'!O82+'2.1meta'!O96+'2.1meta'!O107+'2.1meta'!O117+'2.1meta'!O124+'2.1meta'!O136+'2.1meta'!O148+'2.1meta'!O160 -> 0 | O12: ='2.1meta'!P13+'2.1meta'!P29+'2.1meta'!P69+'2.1meta'!P82+'2.1meta'!P96+'2.1meta'!P107+'2.1meta'!P117+'2.1meta'!P124+'2.1meta'!P136+'2.1meta'!P148+'2.1meta'!P160 -> 0 | ... W12: ='2.1meta'!X13+'2.1meta'!X29+'2.1meta'!X69+'2.1meta'!X82+'2.1meta'!X96+'2.1meta'!X107+'2.1meta'!X117+'2.1meta'!X124+'2.1meta'!X136+'2.1meta'!X148+'2.1meta'!X160 -> 0 | X12: =SUM(H12:W12) -> 0 | Y12: =F12+X12 -> 0 | Z12: =C12-Y12 -> 0
A13: 2.1.1.9.1.1 | B13: GRATIFICACIONES | C13: ='2.1meta'!D14+'2.1meta'!D30+'2.1meta'!D43+'2.1meta'!D54+'2.1meta'!D70+'2.1meta'!D83+'2.1meta'!D97+'2.1meta'!D108+'2.1meta'!D137+'2.1meta'!D149+'2.1meta'!D161 -> 0 | D13: ='2.1meta'!E14+'2.1meta'!E30+'2.1meta'!E43+'2.1meta'!E54+'2.1meta'!E70+'2.1meta'!E83+'2.1meta'!E97+'2.1meta'!E108+'2.1meta'!E137+'2.1meta'!E149+'2.1meta'!E161 -> 0 | E13: ='2.1meta'!F14+'2.1meta'!F30+'2.1meta'!F43+'2.1meta'!F54+'2.1meta'!F70+'2.1meta'!F83+'2.1meta'!F97+'2.1meta'!F108+'2.1meta'!F137+'2.1meta'!F149+'2.1meta'!F161 -> 0 | F13: 0 | G13: =C13-F13 -> 0 | H13: ='2.1meta'!I14+'2.1meta'!I30+'2.1meta'!I43+'2.1meta'!I54+'2.1meta'!I70+'2.1meta'!I83+'2.1meta'!I97+'2.1meta'!I108+'2.1meta'!I137+'2.1meta'!I149+'2.1meta'!I161 -> 0 | I13: ='2.1meta'!J14+'2.1meta'!J30+'2.1meta'!J43+'2.1meta'!J54+'2.1meta'!J70+'2.1meta'!J83+'2.1meta'!J97+'2.1meta'!J108+'2.1meta'!J137+'2.1meta'!J149+'2.1meta'!J161 -> 0 | J13: ='2.1meta'!K14+'2.1meta'!K30+'2.1meta'!K43+'2.1meta'!K54+'2.1meta'!K70+'2.1meta'!K83+'2.1meta'!K97+'2.1meta'!K108+'2.1meta'!K137+'2.1meta'!K149+'2.1meta'!K161 -> 0 | K13: ='2.1meta'!L14+'2.1meta'!L30+'2.1meta'!L43+'2.1meta'!L54+'2.1meta'!L70+'2.1meta'!L83+'2.1meta'!L97+'2.1meta'!L108+'2.1meta'!L137+'2.1meta'!L149+'2.1meta'!L161 -> 0 | L13: ='2.1meta'!M14+'2.1meta'!M30+'2.1meta'!M43+'2.1meta'!M54+'2.1meta'!M70+'2.1meta'!M83+'2.1meta'!M97+'2.1meta'!M108+'2.1meta'!M137+'2.1meta'!M149+'2.1meta'!M161 -> 0 | M13: ='2.1meta'!N14+'2.1meta'!N30+'2.1meta'!N43+'2.1meta'!N54+'2.1meta'!N70+'2.1meta'!N83+'2.1meta'!N97+'2.1meta'!N108+'2.1meta'!N137+'2.1meta'!N149+'2.1meta'!N161 -> 0 | N13: ='2.1meta'!O14+'2.1meta'!O30+'2.1meta'!O43+'2.1meta'!O54+'2.1meta'!O70+'2.1meta'!O83+'2.1meta'!O97+'2.1meta'!O108+'2.1meta'!O137+'2.1meta'!O149+'2.1meta'!O161 -> 0 | O13: ='2.1meta'!P14+'2.1meta'!P30+'2.1meta'!P43+'2.1meta'!P54+'2.1meta'!P70+'2.1meta'!P83+'2.1meta'!P97+'2.1meta'!P108+'2.1meta'!P137+'2.1meta'!P149+'2.1meta'!P161 -> 0 | ... W13: ='2.1meta'!X14+'2.1meta'!X30+'2.1meta'!X43+'2.1meta'!X54+'2.1meta'!X70+'2.1meta'!X83+'2.1meta'!X97+'2.1meta'!X108+'2.1meta'!X137+'2.1meta'!X149+'2.1meta'!X161 -> 0 | X13: =SUM(H13:W13) -> 0 | Y13: =F13+X13 -> 0 | Z13: =C13-Y13 -> 0
A14: 2.1.1.9.1.2 | B14: AGUINALDOS | C14: ='2.1meta'!D15+'2.1meta'!D31+'2.1meta'!D55+'2.1meta'!D71+'2.1meta'!D84+'2.1meta'!D98+'2.1meta'!D109+'2.1meta'!D118+'2.1meta'!D125+'2.1meta'!D138+'2.1meta'!D150+'2.1meta'!D162 -> 0 | D14: ='2.1meta'!E15+'2.1meta'!E31+'2.1meta'!E55+'2.1meta'!E71+'2.1meta'!E84+'2.1meta'!E98+'2.1meta'!E109+'2.1meta'!E118+'2.1meta'!E125+'2.1meta'!E138+'2.1meta'!E150+'2.1meta'!E162 -> 0 | E14: ='2.1meta'!F15+'2.1meta'!F31+'2.1meta'!F55+'2.1meta'!F71+'2.1meta'!F84+'2.1meta'!F98+'2.1meta'!F109+'2.1meta'!F118+'2.1meta'!F125+'2.1meta'!F138+'2.1meta'!F150+'2.1meta'!F162 -> 0 | F14: 0 | G14: =C14-F14 -> 0 | H14: ='2.1meta'!I15+'2.1meta'!I31+'2.1meta'!I55+'2.1meta'!I71+'2.1meta'!I84+'2.1meta'!I98+'2.1meta'!I109+'2.1meta'!I118+'2.1meta'!I125+'2.1meta'!I138+'2.1meta'!I150+'2.1meta'!I162 -> 0 | I14: ='2.1meta'!J15+'2.1meta'!J31+'2.1meta'!J55+'2.1meta'!J71+'2.1meta'!J84+'2.1meta'!J98+'2.1meta'!J109+'2.1meta'!J118+'2.1meta'!J125+'2.1meta'!J138+'2.1meta'!J150+'2.1meta'!J162 -> 0 | J14: ='2.1meta'!K15+'2.1meta'!K31+'2.1meta'!K55+'2.1meta'!K71+'2.1meta'!K84+'2.1meta'!K98+'2.1meta'!K109+'2.1meta'!K118+'2.1meta'!K125+'2.1meta'!K138+'2.1meta'!K150+'2.1meta'!K162 -> 0 | K14: ='2.1meta'!L15+'2.1meta'!L31+'2.1meta'!L55+'2.1meta'!L71+'2.1meta'!L84+'2.1meta'!L98+'2.1meta'!L109+'2.1meta'!L118+'2.1meta'!L125+'2.1meta'!L138+'2.1meta'!L150+'2.1meta'!L162 -> 0 | L14: ='2.1meta'!M15+'2.1meta'!M31+'2.1meta'!M55+'2.1meta'!M71+'2.1meta'!M84+'2.1meta'!M98+'2.1meta'!M109+'2.1meta'!M118+'2.1meta'!M125+'2.1meta'!M138+'2.1meta'!M150+'2.1meta'!M162 -> 0 | M14: ='2.1meta'!N15+'2.1meta'!N31+'2.1meta'!N55+'2.1meta'!N71+'2.1meta'!N84+'2.1meta'!N98+'2.1meta'!N109+'2.1meta'!N118+'2.1meta'!N125+'2.1meta'!N138+'2.1meta'!N150+'2.1meta'!N162 -> 0 | N14: ='2.1meta'!O15+'2.1meta'!O31+'2.1meta'!O55+'2.1meta'!O71+'2.1meta'!O84+'2.1meta'!O98+'2.1meta'!O109+'2.1meta'!O118+'2.1meta'!O125+'2.1meta'!O138+'2.1meta'!O150+'2.1meta'!O162 -> 0 | O14: ='2.1meta'!P15+'2.1meta'!P31+'2.1meta'!P55+'2.1meta'!P71+'2.1meta'!P84+'2.1meta'!P98+'2.1meta'!P109+'2.1meta'!P118+'2.1meta'!P125+'2.1meta'!P138+'2.1meta'!P150+'2.1meta'!P162 -> 0 | ... W14: ='2.1meta'!X15+'2.1meta'!X31+'2.1meta'!X55+'2.1meta'!X71+'2.1meta'!X84+'2.1meta'!X98+'2.1meta'!X109+'2.1meta'!X118+'2.1meta'!X125+'2.1meta'!X138+'2.1meta'!X150+'2.1meta'!X162 -> 0 | X14: =SUM(H14:W14) -> 0 | Y14: =F14+X14 -> 0 | Z14: =C14-Y14 -> 0
A15: 2.1.1.9.1.3 | B15: BONIFICACION POR ESCOLARIDAD | C15: ='2.1meta'!D16+'2.1meta'!D32+'2.1meta'!D44+'2.1meta'!D56+'2.1meta'!D72+'2.1meta'!D85+'2.1meta'!D99+'2.1meta'!D110+'2.1meta'!D119+'2.1meta'!D126+'2.1meta'!D139+'2.1meta'!D151+'2.1meta'!D163 -> 0 | D15: ='2.1meta'!E16+'2.1meta'!E32+'2.1meta'!E44+'2.1meta'!E56+'2.1meta'!E72+'2.1meta'!E85+'2.1meta'!E99+'2.1meta'!E110+'2.1meta'!E119+'2.1meta'!E126+'2.1meta'!E139+'2.1meta'!E151+'2.1meta'!E163 -> 0 | E15: ='2.1meta'!F16+'2.1meta'!F32+'2.1meta'!F44+'2.1meta'!F56+'2.1meta'!F72+'2.1meta'!F85+'2.1meta'!F99+'2.1meta'!F110+'2.1meta'!F119+'2.1meta'!F126+'2.1meta'!F139+'2.1meta'!F151+'2.1meta'!F163 -> 0 | F15: 0 | G15: =C15-F15 -> 0 | H15: ='2.1meta'!I16+'2.1meta'!I32+'2.1meta'!I44+'2.1meta'!I56+'2.1meta'!I72+'2.1meta'!I85+'2.1meta'!I99+'2.1meta'!I110+'2.1meta'!I119+'2.1meta'!I126+'2.1meta'!I139+'2.1meta'!I151+'2.1meta'!I163 -> 0 | I15: ='2.1meta'!J16+'2.1meta'!J32+'2.1meta'!J44+'2.1meta'!J56+'2.1meta'!J72+'2.1meta'!J85+'2.1meta'!J99+'2.1meta'!J110+'2.1meta'!J119+'2.1meta'!J126+'2.1meta'!J139+'2.1meta'!J151+'2.1meta'!J163 -> 0 | J15: ='2.1meta'!K16+'2.1meta'!K32+'2.1meta'!K44+'2.1meta'!K56+'2.1meta'!K72+'2.1meta'!K85+'2.1meta'!K99+'2.1meta'!K110+'2.1meta'!K119+'2.1meta'!K126+'2.1meta'!K139+'2.1meta'!K151+'2.1meta'!K163 -> 0 | K15: ='2.1meta'!L16+'2.1meta'!L32+'2.1meta'!L44+'2.1meta'!L56+'2.1meta'!L72+'2.1meta'!L85+'2.1meta'!L99+'2.1meta'!L110+'2.1meta'!L119+'2.1meta'!L126+'2.1meta'!L139+'2.1meta'!L151+'2.1meta'!L163 -> 0 | L15: ='2.1meta'!M16+'2.1meta'!M32+'2.1meta'!M44+'2.1meta'!M56+'2.1meta'!M72+'2.1meta'!M85+'2.1meta'!M99+'2.1meta'!M110+'2.1meta'!M119+'2.1meta'!M126+'2.1meta'!M139+'2.1meta'!M151+'2.1meta'!M163 -> 0 | M15: ='2.1meta'!N16+'2.1meta'!N32+'2.1meta'!N44+'2.1meta'!N56+'2.1meta'!N72+'2.1meta'!N85+'2.1meta'!N99+'2.1meta'!N110+'2.1meta'!N119+'2.1meta'!N126+'2.1meta'!N139+'2.1meta'!N151+'2.1meta'!N163 -> 0 | N15: ='2.1meta'!O16+'2.1meta'!O32+'2.1meta'!O44+'2.1meta'!O56+'2.1meta'!O72+'2.1meta'!O85+'2.1meta'!O99+'2.1meta'!O110+'2.1meta'!O119+'2.1meta'!O126+'2.1meta'!O139+'2.1meta'!O151+'2.1meta'!O163 -> 0 | O15: ='2.1meta'!P16+'2.1meta'!P32+'2.1meta'!P44+'2.1meta'!P56+'2.1meta'!P72+'2.1meta'!P85+'2.1meta'!P99+'2.1meta'!P110+'2.1meta'!P119+'2.1meta'!P126+'2.1meta'!P139+'2.1meta'!P151+'2.1meta'!P163 -> 0 | ... W15: ='2.1meta'!X16+'2.1meta'!X32+'2.1meta'!X44+'2.1meta'!X56+'2.1meta'!X72+'2.1meta'!X85+'2.1meta'!X99+'2.1meta'!X110+'2.1meta'!X119+'2.1meta'!X126+'2.1meta'!X139+'2.1meta'!X151+'2.1meta'!X163 -> 0 | X15: =SUM(H15:W15) -> 0 | Y15: =F15+X15 -> 0 | Z15: =C15-Y15 -> 0
A16: 2.1.1.9.2.1 | B16: COMPENSACION POR TIEMPO DE SERVICIOS (CTS) | C16: ='2.1meta'!D17+'2.1meta'!D33+'2.1meta'!D45+'2.1meta'!D57+'2.1meta'!D73+'2.1meta'!D86+'2.1meta'!D100+'2.1meta'!D111+'2.1meta'!D140+'2.1meta'!D152+'2.1meta'!D164 -> 0 | D16: ='2.1meta'!E17+'2.1meta'!E33+'2.1meta'!E45+'2.1meta'!E57+'2.1meta'!E73+'2.1meta'!E86+'2.1meta'!E100+'2.1meta'!E111+'2.1meta'!E140+'2.1meta'!E152+'2.1meta'!E164 -> 0 | E16: ='2.1meta'!F17+'2.1meta'!F33+'2.1meta'!F45+'2.1meta'!F57+'2.1meta'!F73+'2.1meta'!F86+'2.1meta'!F100+'2.1meta'!F111+'2.1meta'!F140+'2.1meta'!F152+'2.1meta'!F164 -> 0 | F16: 0 | G16: =C16-F16 -> 0 | H16: ='2.1meta'!I17+'2.1meta'!I33+'2.1meta'!I45+'2.1meta'!I57+'2.1meta'!I73+'2.1meta'!I86+'2.1meta'!I100+'2.1meta'!I111+'2.1meta'!I140+'2.1meta'!I152+'2.1meta'!I164 -> 0 | I16: ='2.1meta'!J17+'2.1meta'!J33+'2.1meta'!J45+'2.1meta'!J57+'2.1meta'!J73+'2.1meta'!J86+'2.1meta'!J100+'2.1meta'!J111+'2.1meta'!J140+'2.1meta'!J152+'2.1meta'!J164 -> 0 | J16: ='2.1meta'!K17+'2.1meta'!K33+'2.1meta'!K45+'2.1meta'!K57+'2.1meta'!K73+'2.1meta'!K86+'2.1meta'!K100+'2.1meta'!K111+'2.1meta'!K140+'2.1meta'!K152+'2.1meta'!K164 -> 0 | K16: ='2.1meta'!L17+'2.1meta'!L33+'2.1meta'!L45+'2.1meta'!L57+'2.1meta'!L73+'2.1meta'!L86+'2.1meta'!L100+'2.1meta'!L111+'2.1meta'!L140+'2.1meta'!L152+'2.1meta'!L164 -> 0 | L16: ='2.1meta'!M17+'2.1meta'!M33+'2.1meta'!M45+'2.1meta'!M57+'2.1meta'!M73+'2.1meta'!M86+'2.1meta'!M100+'2.1meta'!M111+'2.1meta'!M140+'2.1meta'!M152+'2.1meta'!M164 -> 0 | M16: ='2.1meta'!N17+'2.1meta'!N33+'2.1meta'!N45+'2.1meta'!N57+'2.1meta'!N73+'2.1meta'!N86+'2.1meta'!N100+'2.1meta'!N111+'2.1meta'!N140+'2.1meta'!N152+'2.1meta'!N164 -> 0 | N16: ='2.1meta'!O17+'2.1meta'!O33+'2.1meta'!O45+'2.1meta'!O57+'2.1meta'!O73+'2.1meta'!O86+'2.1meta'!O100+'2.1meta'!O111+'2.1meta'!O140+'2.1meta'!O152+'2.1meta'!O164 -> 0 | O16: ='2.1meta'!P17+'2.1meta'!P33+'2.1meta'!P45+'2.1meta'!P57+'2.1meta'!P73+'2.1meta'!P86+'2.1meta'!P100+'2.1meta'!P111+'2.1meta'!P140+'2.1meta'!P152+'2.1meta'!P164 -> 0 | ... W16: ='2.1meta'!X17+'2.1meta'!X33+'2.1meta'!X45+'2.1meta'!X57+'2.1meta'!X73+'2.1meta'!X86+'2.1meta'!X100+'2.1meta'!X111+'2.1meta'!X140+'2.1meta'!X152+'2.1meta'!X164 -> 0 | X16: =SUM(H16:W16) -> 0 | Y16: =F16+X16 -> 0 | Z16: =C16-Y16 -> 0
A17: 2.1.1.9.3.3 | B17: COMPENSACION VACACIONAL (VACACIONES TRUNCAS) | C17: ='2.1meta'!D34+'2.1meta'!D58 -> 0 | D17: ='2.1meta'!E34+'2.1meta'!E58 -> 0 | E17: ='2.1meta'!F34+'2.1meta'!F58 -> 0 | F17: 0 | G17: =C17-F17 -> 0 | H17: ='2.1meta'!I34+'2.1meta'!I58 -> 0 | I17: ='2.1meta'!J34+'2.1meta'!J58 -> 0 | J17: ='2.1meta'!K34+'2.1meta'!K58 -> 0 | K17: ='2.1meta'!L34+'2.1meta'!L58 -> 0 | L17: ='2.1meta'!M34+'2.1meta'!M58 -> 0 | M17: ='2.1meta'!N34+'2.1meta'!N58 -> 0 | N17: ='2.1meta'!O34+'2.1meta'!O58 -> 0 | O17: ='2.1meta'!P34+'2.1meta'!P58 -> 0 | ... W17: ='2.1meta'!X34+'2.1meta'!X58 -> 0 | X17: =SUM(H17:W17) -> 0 | Y17: =F17+X17 -> 0 | Z17: =C17-Y17 -> 0
A18: 2.1.1.9.3.99 | B18: OTRAS OCASIONALES | C18: ='2.1meta'!D18+'2.1meta'!D35+'2.1meta'!D46+'2.1meta'!D59+'2.1meta'!D74+'2.1meta'!D87+'2.1meta'!D101+'2.1meta'!D112+'2.1meta'!D141+'2.1meta'!D153+'2.1meta'!D165 -> 0 | D18: ='2.1meta'!E18+'2.1meta'!E35+'2.1meta'!E46+'2.1meta'!E59+'2.1meta'!E74+'2.1meta'!E87+'2.1meta'!E101+'2.1meta'!E112+'2.1meta'!E141+'2.1meta'!E153+'2.1meta'!E165 -> 0 | E18: ='2.1meta'!F18+'2.1meta'!F35+'2.1meta'!F46+'2.1meta'!F59+'2.1meta'!F74+'2.1meta'!F87+'2.1meta'!F101+'2.1meta'!F112+'2.1meta'!F141+'2.1meta'!F153+'2.1meta'!F165 -> 0 | F18: 0 | G18: =C18-F18 -> 0 | H18: ='2.1meta'!I18+'2.1meta'!I35+'2.1meta'!I46+'2.1meta'!I59+'2.1meta'!I74+'2.1meta'!I87+'2.1meta'!I101+'2.1meta'!I112+'2.1meta'!I141+'2.1meta'!I153+'2.1meta'!I165 -> 0 | I18: ='2.1meta'!J18+'2.1meta'!J35+'2.1meta'!J46+'2.1meta'!J59+'2.1meta'!J74+'2.1meta'!J87+'2.1meta'!J101+'2.1meta'!J112+'2.1meta'!J141+'2.1meta'!J153+'2.1meta'!J165 -> 0 | J18: ='2.1meta'!K18+'2.1meta'!K35+'2.1meta'!K46+'2.1meta'!K59+'2.1meta'!K74+'2.1meta'!K87+'2.1meta'!K101+'2.1meta'!K112+'2.1meta'!K141+'2.1meta'!K153+'2.1meta'!K165 -> 0 | K18: ='2.1meta'!L18+'2.1meta'!L35+'2.1meta'!L46+'2.1meta'!L59+'2.1meta'!L74+'2.1meta'!L87+'2.1meta'!L101+'2.1meta'!L112+'2.1meta'!L141+'2.1meta'!L153+'2.1meta'!L165 -> 0 | L18: ='2.1meta'!M18+'2.1meta'!M35+'2.1meta'!M46+'2.1meta'!M59+'2.1meta'!M74+'2.1meta'!M87+'2.1meta'!M101+'2.1meta'!M112+'2.1meta'!M141+'2.1meta'!M153+'2.1meta'!M165 -> 0 | M18: ='2.1meta'!N18+'2.1meta'!N35+'2.1meta'!N46+'2.1meta'!N59+'2.1meta'!N74+'2.1meta'!N87+'2.1meta'!N101+'2.1meta'!N112+'2.1meta'!N141+'2.1meta'!N153+'2.1meta'!N165 -> 0 | N18: ='2.1meta'!O18+'2.1meta'!O35+'2.1meta'!O46+'2.1meta'!O59+'2.1meta'!O74+'2.1meta'!O87+'2.1meta'!O101+'2.1meta'!O112+'2.1meta'!O141+'2.1meta'!O153+'2.1meta'!O165 -> 0 | O18: ='2.1meta'!P18+'2.1meta'!P35+'2.1meta'!P46+'2.1meta'!P59+'2.1meta'!P74+'2.1meta'!P87+'2.1meta'!P101+'2.1meta'!P112+'2.1meta'!P141+'2.1meta'!P153+'2.1meta'!P165 -> 0 | ... W18: ='2.1meta'!X18+'2.1meta'!X35+'2.1meta'!X46+'2.1meta'!X59+'2.1meta'!X74+'2.1meta'!X87+'2.1meta'!X101+'2.1meta'!X112+'2.1meta'!X141+'2.1meta'!X153+'2.1meta'!X165 -> 0 | X18: =SUM(H18:W18) -> 0 | Y18: =F18+X18 -> 0 | Z18: =C18-Y18 -> 0
A19: 2.1.3.1.1.1 | B19: APORTES A LOS FONDOS DE SALUD | C19: ='2.1meta'!D19+'2.1meta'!D36+'2.1meta'!D47+'2.1meta'!D60+'2.1meta'!D75+'2.1meta'!D88+'2.1meta'!D127+'2.1meta'!D142+'2.1meta'!D154+'2.1meta'!D166 -> 0 | D19: ='2.1meta'!E19+'2.1meta'!E36+'2.1meta'!E47+'2.1meta'!E60+'2.1meta'!E75+'2.1meta'!E88+'2.1meta'!E127+'2.1meta'!E142+'2.1meta'!E154+'2.1meta'!E166 -> 0 | E19: ='2.1meta'!F19+'2.1meta'!F36+'2.1meta'!F47+'2.1meta'!F60+'2.1meta'!F75+'2.1meta'!F88+'2.1meta'!F127+'2.1meta'!F142+'2.1meta'!F154+'2.1meta'!F166 -> 0 | F19: 0 | G19: =C19-F19 -> 0 | H19: ='2.1meta'!I19+'2.1meta'!I36+'2.1meta'!I47+'2.1meta'!I60+'2.1meta'!I75+'2.1meta'!I88+'2.1meta'!I127+'2.1meta'!I142+'2.1meta'!I154+'2.1meta'!I166 -> 0 | I19: ='2.1meta'!J19+'2.1meta'!J36+'2.1meta'!J47+'2.1meta'!J60+'2.1meta'!J75+'2.1meta'!J88+'2.1meta'!J127+'2.1meta'!J142+'2.1meta'!J154+'2.1meta'!J166 -> 0 | J19: ='2.1meta'!K19+'2.1meta'!K36+'2.1meta'!K47+'2.1meta'!K60+'2.1meta'!K75+'2.1meta'!K88+'2.1meta'!K127+'2.1meta'!K142+'2.1meta'!K154+'2.1meta'!K166 -> 0 | K19: ='2.1meta'!L19+'2.1meta'!L36+'2.1meta'!L47+'2.1meta'!L60+'2.1meta'!L75+'2.1meta'!L88+'2.1meta'!L127+'2.1meta'!L142+'2.1meta'!L154+'2.1meta'!L166 -> 0 | L19: ='2.1meta'!M19+'2.1meta'!M36+'2.1meta'!M47+'2.1meta'!M60+'2.1meta'!M75+'2.1meta'!M88+'2.1meta'!M127+'2.1meta'!M142+'2.1meta'!M154+'2.1meta'!M166 -> 0 | M19: ='2.1meta'!N19+'2.1meta'!N36+'2.1meta'!N47+'2.1meta'!N60+'2.1meta'!N75+'2.1meta'!N88+'2.1meta'!N127+'2.1meta'!N142+'2.1meta'!N154+'2.1meta'!N166 -> 0 | N19: ='2.1meta'!O19+'2.1meta'!O36+'2.1meta'!O47+'2.1meta'!O60+'2.1meta'!O75+'2.1meta'!O88+'2.1meta'!O127+'2.1meta'!O142+'2.1meta'!O154+'2.1meta'!O166 -> 0 | O19: ='2.1meta'!P19+'2.1meta'!P36+'2.1meta'!P47+'2.1meta'!P60+'2.1meta'!P75+'2.1meta'!P88+'2.1meta'!P127+'2.1meta'!P142+'2.1meta'!P154+'2.1meta'!P166 -> 0 | ... W19: ='2.1meta'!X19+'2.1meta'!X36+'2.1meta'!X47+'2.1meta'!X60+'2.1meta'!X75+'2.1meta'!X88+'2.1meta'!X127+'2.1meta'!X142+'2.1meta'!X154+'2.1meta'!X166 -> 0 | X19: =SUM(H19:W19) -> 0 | Y19: =F19+X19 -> 0 | Z19: =C19-Y19 -> 0
A20: 2.1.3.1.1.3 | B20: APORTES A LOS FONDOS DE PENSIONES | C20: ='2.1meta'!D20+'2.1meta'!D37+'2.1meta'!D76+'2.1meta'!D89 -> 0 | D20: ='2.1meta'!E20+'2.1meta'!E37+'2.1meta'!E76+'2.1meta'!E89 -> 0 | E20: ='2.1meta'!F20+'2.1meta'!F37+'2.1meta'!F76+'2.1meta'!F89 -> 0 | F20: 0 | G20: =C20-F20 -> 0 | H20: ='2.1meta'!I20+'2.1meta'!I37+'2.1meta'!I76+'2.1meta'!I89 -> 0 | I20: ='2.1meta'!J20+'2.1meta'!J37+'2.1meta'!J76+'2.1meta'!J89 -> 0 | J20: ='2.1meta'!K20+'2.1meta'!K37+'2.1meta'!K76+'2.1meta'!K89 -> 0 | K20: ='2.1meta'!L20+'2.1meta'!L37+'2.1meta'!L76+'2.1meta'!L89 -> 0 | L20: ='2.1meta'!M20+'2.1meta'!M37+'2.1meta'!M76+'2.1meta'!M89 -> 0 | M20: ='2.1meta'!N20+'2.1meta'!N37+'2.1meta'!N76+'2.1meta'!N89 -> 0 | N20: ='2.1meta'!O20+'2.1meta'!O37+'2.1meta'!O76+'2.1meta'!O89 -> 0 | O20: ='2.1meta'!P20+'2.1meta'!P37+'2.1meta'!P76+'2.1meta'!P89 -> 0 | ... W20: ='2.1meta'!X20+'2.1meta'!X37+'2.1meta'!X76+'2.1meta'!X89 -> 0 | X20: =SUM(H20:W20) -> 0 | Y20: =F20+X20 -> 0 | Z20: =C20-Y20 -> 0
A21: 2.1.3.1.1.5 | B21: CONTRIBUCIONES A ESSALUD | C21: ='2.1meta'!D21+'2.1meta'!D38+'2.1meta'!D48+'2.1meta'!D61+'2.1meta'!D77+'2.1meta'!D90+'2.1meta'!D102+'2.1meta'!D113+'2.1meta'!D120+'2.1meta'!D128+'2.1meta'!D143+'2.1meta'!D155+'2.1meta'!D167 -> 0 | D21: ='2.1meta'!E21+'2.1meta'!E38+'2.1meta'!E48+'2.1meta'!E61+'2.1meta'!E77+'2.1meta'!E90+'2.1meta'!E102+'2.1meta'!E113+'2.1meta'!E120+'2.1meta'!E128+'2.1meta'!E143+'2.1meta'!E155+'2.1meta'!E167 -> 0 | E21: ='2.1meta'!F21+'2.1meta'!F38+'2.1meta'!F48+'2.1meta'!F61+'2.1meta'!F77+'2.1meta'!F90+'2.1meta'!F102+'2.1meta'!F113+'2.1meta'!F120+'2.1meta'!F128+'2.1meta'!F143+'2.1meta'!F155+'2.1meta'!F167 -> 0 | F21: 0 | G21: =C21-F21 -> 0 | H21: ='2.1meta'!I21+'2.1meta'!I38+'2.1meta'!I48+'2.1meta'!I61+'2.1meta'!I77+'2.1meta'!I90+'2.1meta'!I102+'2.1meta'!I113+'2.1meta'!I120+'2.1meta'!I128+'2.1meta'!I143+'2.1meta'!I155+'2.1meta'!I167 -> 0 | I21: ='2.1meta'!J21+'2.1meta'!J38+'2.1meta'!J48+'2.1meta'!J61+'2.1meta'!J77+'2.1meta'!J90+'2.1meta'!J102+'2.1meta'!J113+'2.1meta'!J120+'2.1meta'!J128+'2.1meta'!J143+'2.1meta'!J155+'2.1meta'!J167 -> 0 | J21: ='2.1meta'!K21+'2.1meta'!K38+'2.1meta'!K48+'2.1meta'!K61+'2.1meta'!K77+'2.1meta'!K90+'2.1meta'!K102+'2.1meta'!K113+'2.1meta'!K120+'2.1meta'!K128+'2.1meta'!K143+'2.1meta'!K155+'2.1meta'!K167 -> 0 | K21: ='2.1meta'!L21+'2.1meta'!L38+'2.1meta'!L48+'2.1meta'!L61+'2.1meta'!L77+'2.1meta'!L90+'2.1meta'!L102+'2.1meta'!L113+'2.1meta'!L120+'2.1meta'!L128+'2.1meta'!L143+'2.1meta'!L155+'2.1meta'!L167 -> 0 | L21: ='2.1meta'!M21+'2.1meta'!M38+'2.1meta'!M48+'2.1meta'!M61+'2.1meta'!M77+'2.1meta'!M90+'2.1meta'!M102+'2.1meta'!M113+'2.1meta'!M120+'2.1meta'!M128+'2.1meta'!M143+'2.1meta'!M155+'2.1meta'!M167 -> 0 | M21: ='2.1meta'!N21+'2.1meta'!N38+'2.1meta'!N48+'2.1meta'!N61+'2.1meta'!N77+'2.1meta'!N90+'2.1meta'!N102+'2.1meta'!N113+'2.1meta'!N120+'2.1meta'!N128+'2.1meta'!N143+'2.1meta'!N155+'2.1meta'!N167 -> 0 | N21: ='2.1meta'!O21+'2.1meta'!O38+'2.1meta'!O48+'2.1meta'!O61+'2.1meta'!O77+'2.1meta'!O90+'2.1meta'!O102+'2.1meta'!O113+'2.1meta'!O120+'2.1meta'!O128+'2.1meta'!O143+'2.1meta'!O155+'2.1meta'!O167 -> 0 | O21: ='2.1meta'!P21+'2.1meta'!P38+'2.1meta'!P48+'2.1meta'!P61+'2.1meta'!P77+'2.1meta'!P90+'2.1meta'!P102+'2.1meta'!P113+'2.1meta'!P120+'2.1meta'!P128+'2.1meta'!P143+'2.1meta'!P155+'2.1meta'!P167 -> 0 | ... W21: ='2.1meta'!X21+'2.1meta'!X38+'2.1meta'!X48+'2.1meta'!X61+'2.1meta'!X77+'2.1meta'!X90+'2.1meta'!X102+'2.1meta'!X113+'2.1meta'!X120+'2.1meta'!X128+'2.1meta'!X143+'2.1meta'!X155+'2.1meta'!X167 -> 0 | X21: =SUM(H21:W21) -> 0 | Y21: =F21+X21 -> 0 | Z21: =C21-Y21 -> 0
A22: TOTAL 2.1 PERSONAL Y OB. SOCIALES | C22: =SUBTOTAL(9,C5:C21) -> 0 | D22: =SUBTOTAL(9,D5:D21) -> 0 | E22: =SUBTOTAL(9,E5:E21) -> 0 | F22: =SUBTOTAL(9,F5:F21) -> 0 | G22: =C22-F22 -> 0 | H22: =SUBTOTAL(9,H5:H21) -> 0 | I22: =SUBTOTAL(9,I5:I21) -> 0 | J22: =SUBTOTAL(9,J5:J21) -> 0 | K22: =SUBTOTAL(9,K5:K21) -> 0 | L22: =SUBTOTAL(9,L5:L21) -> 0 | M22: =SUBTOTAL(9,M5:M21) -> 0 | N22: =SUBTOTAL(9,N5:N21) -> 0 | O22: =SUBTOTAL(9,O5:O21) -> 0 | ... Z22: =SUBTOTAL(9,Z5:Z21) -> 0

Sheet CAS x categ.ptal
A1: RUBRO DE FINANCIAMIENTO: 00 RECURSOS ORDINARIOS
A3: Cat pptal/ Detalle Específica de Gasto | C3: PIM (1) | D3: Ejecución Devengado UE | K3: Saldo Presupuestal al 08.06.2021 | L3: Proyección del gasto | T3: TOTAL EJECUCION +PROYECCION (2) | U3: Saldo disponible ( 1-2)
D4: Enero | E4: Febrero | F4: Marzo | G4: Abril | H4: Mayo | I4: Junio( 01 al 08) | J4: TOTAL EJECUCION | L4: Junio( 09 al 30) | M4: Julio | N4: Agosto | O4: Setiembre | P4: Octubre | Q4: Noviembre | R4: Diciembre | S4: TOTAL PROYECCIÓN
A5: 0086 MEJORA DE LOS SERVICIOS DEL SISTEMA DE JUSTICIA PENAL | C5: =SUBTOTAL(9,C6:C8) -> 3774042 | D5: =SUBTOTAL(9,D6:D8) -> 285013.57 | E5: =SUBTOTAL(9,E6:E8) -> 275120.57 | F5: =SUBTOTAL(9,F6:F8) -> 276794.9 | G5: =SUBTOTAL(9,G6:G8) -> 272368.6 | H5: =SUBTOTAL(9,H6:H8) -> 286455.73 | I5: =SUBTOTAL(9,I6:I8) -> 0 | J5: =SUM(D5:I5) -> 1395753.4 | K5: =C5-J5 -> 2378288.6 | L5: =SUBTOTAL(9,L6:L8) -> 306988.2 | M5: =SUBTOTAL(9,M6:M8) -> 337888.2 | N5: =SUBTOTAL(9,N6:N8) -> 306988.2 | O5: =SUBTOTAL(9,O6:O8) -> 306988.2 | P5: =SUBTOTAL(9,P6:P8) -> 306988.2 | Q5: =SUBTOTAL(9,Q6:Q8) -> 306988.2 | R5: =SUBTOTAL(9,R6:R8) -> 337888.2 | S5: =SUM(L5:R5) -> 2210717.4 | T5: =+J5+S5 -> 3606470.8 | U5: =+C5-T5 -> 167571.23
A6: 2.3.2.8.1.1 | B6: CONTRATO ADMINISTRATIVO DE SERVICIOS | C6: 3461120 | D6: 266240 | E6: 256598.01 | F6: 258560 | G6: 254386.67 | H6: 267214.03 | I6: 0 | J6: =SUM(D6:I6) -> 1302998.7 | K6: =C6-J6 -> 2158121.3 | L6: 286560 | M6: 286560 | N6: 286560 | O6: 286560 | P6: 286560 | Q6: 286560 | R6: 286560 | S6: =SUM(L6:R6) -> 2005920 | T6: =+J6+S6 -> 3308918.7 | U6: =+C6-T6 -> 152201.29
A7: 2.3.2.8.1.2 | B7: CONTRIBUCIONES A ESSALUD DE C.A.S. | C7: 246103 | D7: 18773.57 | E7: 18522.56 | F7: 18234.9 | G7: 17981.93 | H7: 19241.7 | I7: 0 | J7: =SUM(D7:I7) -> 92754.66 | K7: =C7-J7 -> 153348.34 | L7: 20428.2 | M7: 20428.2 | N7: 20428.2 | O7: 20428.2 | P7: 20428.2 | Q7: 20428.2 | R7: 20428.2 | S7: =SUM(L7:R7) -> 142997.4 | T7: =+J7+S7 -> 235752.06 | U7: =+C7-T7 -> 10350.94
A8: 2.3.2.8.1.4 | B8: AGUINALDOS DE C.A.S. | C8: 66819 | D8: 0 | E8: 0 | F8: 0 | G8: 0 | H8: 0 | I8: 0 | J8: =SUM(D8:I8) -> 0 | K8: =C8-J8 -> 66819 | M8: 30900 | R8: 30900 | S8: =SUM(L8:R8) -> 61800 | T8: =+J8+S8 -> 61800 | U8: =+C8-T8 -> 5019
A9: 1002 PRODUCTOS ESPECIFICOS PARA REDUCCION DE LA VIOLENCIA CONTRA LA MUJER | C9: =SUBTOTAL(9,C10:C12) -> 135112 | D9: =SUBTOTAL(9,D10:D12) -> 33778 | E9: =SUBTOTAL(9,E10:E12) -> 33778 | F9: =SUBTOTAL(9,F10:F12) -> 33778 | G9: =SUBTOTAL(9,G10:G12) -> 31639.13 | H9: =SUBTOTAL(9,H10:H12) -> -44 | I9: =SUBTOTAL(9,I10:I12) -> 0 | J9: =SUM(D9:I9) -> 132929.13 | K9: =C9-J9 -> 2182.87 | L9: =SUBTOTAL(9,L10:L12) -> 0 | M9: =SUBTOTAL(9,M10:M12) -> 33060.2 | N9: =SUBTOTAL(9,N10:N12) -> 30360.2 | O9: =SUBTOTAL(9,O10:O12) -> 30360.2 | P9: =SUBTOTAL(9,P10:P12) -> 30360.2 | Q9: =SUBTOTAL(9,Q10:Q12) -> 30360.2 | R9: =SUBTOTAL(9,R10:R12) -> 33060.2 | S9: =SUM(L9:R9) -> 187561.2 | T9: =+J9+S9 -> 320490.33 | U9: =+C9-T9 -> -185378.33
A10: 2.3.2.8.1.1 | B10: CONTRATO ADMINISTRATIVO DE SERVICIOS | C10: 126400 | D10: 31600 | E10: 31600 | F10: 31600 | G10: 29573.33 | H10: -44 | I10: 0 | J10: =SUM(D10:I10) -> 124329.33 | K10: =C10-J10 -> 2070.67 | L10: 0 | M10: 28400 | N10: 28400 | O10: 28400 | P10: 28400 | Q10: 28400 | R10: 28400 | S10: =SUM(L10:R10) -> 170400 | T10: =+J10+S10 -> 294729.33 | U10: =+C10-T10 -> -168329.33
A11: 2.3.2.8.1.2 | B11: CONTRIBUCIONES A ESSALUD DE C.A.S. | C11: 8712 | D11: 2178 | E11: 2178 | F11: 2178 | G11: 2065.8 | I11: 0 | J11: =SUM(D11:I11) -> 8599.8 | K11: =C11-J11 -> 112.2 | L11: 0 | M11: 1960.2 | N11: 1960.2 | O11: 1960.2 | P11: 1960.2 | Q11: 1960.2 | R11: 1960.2 | S11: =SUM(L11:R11) -> 11761.2 | T11: =+J11+S11 -> 20361 | U11: =+C11-T11 -> -11649
A12: 2.3.2.8.1.4 | B12: AGUINALDOS DE C.A.S. | C12: 0 | D12: 0 | E12: 0 | F12: 0 | G12: 0 | H12: 0 | I12: 0 | J12: =SUM(D12:I12) -> 0 | K12: =C12-J12 -> 0 | M12: 2700 | R12: 2700 | S12: =SUM(L12:R12) -> 5400 | T12: =+J12+S12 -> 5400 | U12: =+C12-T12 -> -5400
A13: 9001 ACCIONES CENTRALES | C13: =SUBTOTAL(9,C14:C16) -> 690499 | D13: =SUBTOTAL(9,D14:D16) -> 66560.04 | E13: =SUBTOTAL(9,E14:E16) -> 66338.92 | F13: =SUBTOTAL(9,F14:F16) -> 66560.2 | G13: =SUBTOTAL(9,G14:G16) -> 66553.61 | H13: =SUBTOTAL(9,H14:H16) -> 64877.07 | I13: =SUBTOTAL(9,I14:I16) -> 0 | J13: =SUM(D13:I13) -> 330889.84 | K13: =C13-J13 -> 359609.16 | L13: =SUBTOTAL(9,L14:L16) -> 62842.4 | M13: =SUBTOTAL(9,M14:M16) -> 70342.4 | N13: =SUBTOTAL(9,N14:N16) -> 62842.4 | O13: =SUBTOTAL(9,O14:O16) -> 62842.4 | P13: =SUBTOTAL(9,P14:P16) -> 62842.4 | Q13: =SUBTOTAL(9,Q14:Q16) -> 62842.4 | R13: =SUBTOTAL(9,R14:R16) -> 70342.4 | S13: =SUM(L13:R13) -> 454896.8 | T13: =+J13+S13 -> 785786.64 | U13: =+C13-T13 -> -95287.64
A14: 2.3.2.8.1.1 | B14: CONTRATO ADMINISTRATIVO DE SERVICIOS | C14: 625841 | D14: 61720 | E14: 61506.67 | F14: 61720 | G14: 61720 | H14: 60086.67 | I14: 0 | J14: =SUM(D14:I14) -> 306753.34 | K14: =C14-J14 -> 319087.66 | L14: 58220 | M14: 58220 | N14: 58220 | O14: 58220 | P14: 58220 | Q14: 58220 | R14: 58220 | S14: =SUM(L14:R14) -> 407540 | T14: =+J14+S14 -> 714293.34 | U14: =+C14-T14 -> -88452.34
A15: 2.3.2.8.1.2 | B15: CONTRIBUCIONES A ESSALUD DE C.A.S. | C15: 50642 | D15: 4840.04 | E15: 4832.25 | F15: 4840.2 | G15: 4833.61 | H15: 4790.4 | I15: 0 | J15: =SUM(D15:I15) -> 24136.5 | K15: =C15-J15 -> 26505.5 | L15: 4622.4 | M15: 4622.4 | N15: 4622.4 | O15: 4622.4 | P15: 4622.4 | Q15: 4622.4 | R15: 4622.4 | S15: =SUM(L15:R15) -> 32356.8 | T15: =+J15+S15 -> 56493.3 | U15: =+C15-T15 -> -5851.3
A16: 2.3.2.8.1.4 | B16: AGUINALDOS DE C.A.S. | C16: 14016 | D16: 0 | E16: 0 | F16: 0 | G16: 0 | H16: 0 | I16: 0 | J16: =SUM(D16:I16) -> 0 | K16: =C16-J16 -> 14016 | L16: 0 | M16: 7500 | N16: 0 | O16: 0 | P16: 0 | Q16: 0 | R16: 7500 | S16: =SUM(L16:R16) -> 15000 | T16: =+J16+S16 -> 15000 | U16: =+C16-T16 -> -984
A17: 9002 ASIGNACIONES PRESUPUESTARIAS QUE NO RESULTAN EN PRODUCTOS | C17: =SUBTOTAL(9,C18:C20) -> 195256 | D17: =SUBTOTAL(9,D18:D20) -> 16071.2 | E17: =SUBTOTAL(9,E18:E20) -> 16071.2 | F17: =SUBTOTAL(9,F18:F20) -> 16071.2 | G17: =SUBTOTAL(9,G18:G20) -> 14469.4 | H17: =SUBTOTAL(9,H18:H20) -> 16071.2 | I17: =SUBTOTAL(9,I18:I20) -> 0 | J17: =SUM(D17:I17) -> 78754.2 | K17: =C17-J17 -> 116501.8 | L17: =SUBTOTAL(9,L18:L20) -> 16071.2 | M17: =SUBTOTAL(9,M18:M20) -> 17271.2 | N17: =SUBTOTAL(9,N18:N20) -> 16071.2 | O17: =SUBTOTAL(9,O18:O20) -> 16071.2 | P17: =SUBTOTAL(9,P18:P20) -> 16071.2 | Q17: =SUBTOTAL(9,Q18:Q20) -> 16071.2 | R17: =SUBTOTAL(9,R18:R20) -> 17271.2 | S17: =SUM(L17:R17) -> 114898.4 | T17: =+J17+S17 -> 193652.6 | U17: =+C17-T17 -> 1603.4
A18: 2.3.2.8.1.1 | B18: CONTRATO ADMINISTRATIVO DE SERVICIOS | C18: 182400 | D18: 15200 | E18: 15200 | F18: 15200 | G18: 13600 | H18: 15200 | I18: 0 | J18: =SUM(D18:I18) -> 74400 | K18: =C18-J18 -> 108000 | L18: 15200 | M18: 15200 | N18: 15200 | O18: 15200 | P18: 15200 | Q18: 15200 | R18: 15200 | S18: =SUM(L18:R18) -> 106400 | T18: =+J18+S18 -> 180800 | U18: =+C18-T18 -> 1600
A19: 2.3.2.8.1.2 | B19: CONTRIBUCIONES A ESSALUD DE C.A.S. | C19: 10456 | D19: 871.2 | E19: 871.2 | F19: 871.2 | G19: 869.4 | H19: 871.2 | I19: 0 | J19: =SUM(D19:I19) -> 4354.2 | K19: =C19-J19 -> 6101.8 | L19: 871.2 | M19: 871.2 | N19: 871.2 | O19: 871.2 | P19: 871.2 | Q19: 871.2 | R19: 871.2 | S19: =SUM(L19:R19) -> 6098.4 | T19: =+J19+S19 -> 10452.6 | U19: =+C19-T19 -> 3.4
A20: 2.3.2.8.1.4 | B20: AGUINALDOS DE C.A.S. | C20: 2400 | D20: 0 | E20: 0 | F20: 0 | G20: 0 | H20: 0 | I20: 0 | J20: =SUM(D20:I20) -> 0 | K20: =C20-J20 -> 2400 | L20: 0 | M20: 1200 | N20: 0 | O20: 0 | P20: 0 | Q20: 0 | R20: 1200 | S20: =SUM(L20:R20) -> 2400 | T20: =+J20+S20 -> 2400 | U20: =+C20-T20 -> 0
A21: TOTAL G.G. 2.3 CAS | C21: =SUBTOTAL(9,C5:C20) -> 4794909 | D21: =SUBTOTAL(9,D5:D20) -> 401422.81 | E21: =SUBTOTAL(9,E5:E20) -> 391308.69 | F21: =SUBTOTAL(9,F5:F20) -> 393204.3 | G21: =SUBTOTAL(9,G5:G20) -> 385030.74 | H21: =SUBTOTAL(9,H5:H20) -> 367360 | I21: =SUM(I5:I20)/3 -> 0 | J21: =SUM(D21:I21) -> 1938326.5 | K21: =C21-J21 -> 2856582.5 | L21: =SUBTOTAL(9,L5:L20) -> 385901.8 | M21: =SUBTOTAL(9,M5:M20) -> 458562 | N21: =SUBTOTAL(9,N5:N20) -> 416262 | O21: =SUBTOTAL(9,O5:O20) -> 416262 | P21: =SUBTOTAL(9,P5:P20) -> 416262 | Q21: =SUBTOTAL(9,Q5:Q20) -> 416262 | R21: =SUBTOTAL(9,R5:R20) -> 458562 | S21: =SUM(L21:R21) -> 2968073.8 | T21: =+J21+S21 -> 4906400.3 | U21: =+C21-T21 -> -111491.34
A24: RUBRO DE FINANCIAMIENTO: 09 RECURSOS DIRECTAMENTE RECAUDADOS
A26: Cat pptal/ Detalle Específica de Gasto | C26: PIM (1) | D26: Ejecución Devengado UE | K26: Saldo Presupuestal al 08.06.2021 | L26: Proyección del gasto | T26: TOTAL EJECUCION +PROYECCION (2) | U26: Saldo disponible ( 1-2)
D27: Enero | E27: Febrero | F27: Marzo | G27: Abril | H27: Mayo | I27: Junio( 01 al 08) | J27: TOTAL EJECUCION | L27: Junio( 09 al 30) | M27: Julio | N27: Agosto | O27: Setiembre | P27: Octubre | Q27: Noviembre | R27: Diciembre | S27: TOTAL PROYECCIÓN
A28: 1002 PRODUCTOS ESPECIFICOS PARA REDUCCION DE LA VIOLENCIA CONTRA LA MUJER | C28: =SUBTOTAL(9,C29:C31) -> 67139 | D28: =SUBTOTAL(9,D29:D31) -> 0 | E28: =SUBTOTAL(9,E29:E31) -> 0 | F28: =SUBTOTAL(9,F29:F31) -> 0 | G28: =SUBTOTAL(9,G29:G31) -> 0 | H28: =SUBTOTAL(9,H29:H31) -> 27559.43 | I28: =SUBTOTAL(9,I29:I31) -> 0 | J28: =SUM(D28:I28) -> 27559.43 | K28: =C28-J28 -> 39579.57 | L28: =SUBTOTAL(9,L29:L31) -> #REF! | M28: =SUBTOTAL(9,M29:M31) -> 0 | N28: =SUBTOTAL(9,N29:N31) -> 0 | O28: =SUBTOTAL(9,O29:O31) -> 0 | P28: =SUBTOTAL(9,P29:P31) -> 0 | Q28: =SUBTOTAL(9,Q29:Q31) -> 0 | R28: =SUBTOTAL(9,R29:R31) -> 0 | S28: =SUM(L28:R28) -> #REF! | T28: =+J28+S28 -> #REF! | U28: =+C28-T28 -> #REF!
A29: 2.3.2.8.1.1 | B29: CONTRATO ADMINISTRATIVO DE SERVICIOS | C29: 60000 | H29: 25733.33 | I29: 0 | J29: =SUM(D29:I29) -> 25733.33 | K29: =C29-J29 -> 34266.67 | L29: =#REF! -> #REF! | S29: =SUM(L29:R29) -> #REF! | T29: =+J29+S29 -> #REF! | U29: =+C29-T29 -> #REF!
A30: 2.3.2.8.1.2 | B30: CONTRIBUCIONES A ESSALUD DE C.A.S. | C30: 4139 | H30: 1826.1 | I30: 0 | J30: =SUM(D30:I30) -> 1826.1 | K30: =C30-J30 -> 2312.9 | L30: =#REF! -> #REF! | S30: =SUM(L30:R30) -> #REF! | T30: =+J30+S30 -> #REF! | U30: =+C30-T30 -> #REF!
A31: 2.3.2.8.1.4 | B31: AGUINALDOS DE C.A.S. | C31: 3000 | D31: 0 | E31: 0 | F31: 0 | G31: 0 | H31: 0 | I31: 0 | J31: =SUM(D31:I31) -> 0 | K31: =C31-J31 -> 3000 | S31: =SUM(L31:R31) -> 0 | T31: =+J31+S31 -> 0 | U31: =+C31-T31 -> 3000
A32: 9001 ACCIONES CENTRALES | C32: =SUBTOTAL(9,C33:C35) -> 49144 | D32: =SUBTOTAL(9,D33:D35) -> 0 | E32: =SUBTOTAL(9,E33:E35) -> 0 | F32: =SUBTOTAL(9,F33:F35) -> 0 | G32: =SUBTOTAL(9,G33:G35) -> 0 | H32: =SUBTOTAL(9,H33:H35) -> 0 | I32: =SUBTOTAL(9,I33:I35) -> 0 | J32: =SUM(D32:I32) -> 0 | K32: =C32-J32 -> 49144 | L32: =SUBTOTAL(9,L33:L35) -> 0 | M32: =SUBTOTAL(9,M33:M35) -> 0 | N32: =SUBTOTAL(9,N33:N35) -> 0 | O32: =SUBTOTAL(9,O33:O35) -> 0 | P32: =SUBTOTAL(9,P33:P35) -> 0 | Q32: =SUBTOTAL(9,Q33:Q35) -> 0 | R32: =SUBTOTAL(9,R33:R35) -> 0 | S32: =SUM(L32:R32) -> 0 | T32: =+J32+S32 -> 0 | U32: =+C32-T32 -> 49144
A33: 2.3.2.8.1.1 | B33: CONTRATO ADMINISTRATIVO DE SERVICIOS | C33: 49144 | I33: 0 | J33: =SUM(D33:I33) -> 0 | K33: =C33-J33 -> 49144 | S33: =SUM(L33:R33) -> 0 | T33: =+J33+S33 -> 0 | U33: =+C33-T33 -> 49144
A34: 2.3.2.8.1.2 | B34: CONTRIBUCIONES A ESSALUD DE C.A.S. | I34: 0 | J34: =SUM(D34:I34) -> 0 | K34: =C34-J34 -> 0 | S34: =SUM(L34:R34) -> 0 | T34: =+J34+S34 -> 0 | U34: =+C34-T34 -> 0
A35: 2.3.2.8.1.4 | B35: AGUINALDOS DE C.A.S. | I35: 0 | J35: =SUM(D35:I35) -> 0 | K35: =C35-J35 -> 0 | S35: =SUM(L35:R35) -> 0 | T35: =+J35+S35 -> 0 | U35: =+C35-T35 -> 0
A36: TOTAL G.G. 2.3 CAS | C36: =SUBTOTAL(9,C28:C35) -> 116283 | D36: =SUBTOTAL(9,D28:D35) -> 0 | E36: =SUBTOTAL(9,E28:E35) -> 0 | F36: =SUBTOTAL(9,F28:F35) -> 0 | G36: =SUBTOTAL(9,G28:G35) -> 0 | H36: =SUBTOTAL(9,H28:H35) -> 27559.43 | I36: =SUM(I18:I35)/3 -> 0 | J36: =SUM(D36:I36) -> 27559.43 | K36: =C36-J36 -> 88723.57 | L36: =SUBTOTAL(9,L28:L35) -> #REF! | M36: =SUBTOTAL(9,M28:M35) -> 0 | N36: =SUBTOTAL(9,N28:N35) -> 0 | O36: =SUBTOTAL(9,O28:O35) -> 0 | P36: =SUBTOTAL(9,P28:P35) -> 0 | Q36: =SUBTOTAL(9,Q28:Q35) -> 0 | R36: =SUBTOTAL(9,R28:R35) -> 0 | S36: =SUM(L36:R36) -> #REF! | T36: =+J36+S36 -> #REF! | U36: =+C36-T36 -> #REF!
A40: TOTAL UNIDAD EJECUTORA 003: | C40: =C21+C36 -> 4911192 | D40: =D21+D36 -> 401422.81 | E40: =E21+E36 -> 391308.69 | F40: =F21+F36 -> 393204.3 | G40: =G21+G36 -> 385030.74 | H40: =H21+H36 -> 394919.43 | I40: =I21+I36 -> 0 | J40: =J21+J36 -> 1965886 | ... U40: =U21+U36 -> #REF!
A44: Cat pptal/ Detalle Específica de Gasto | C44: PIM (1) | D44: Ejecución Devengado UE | K44: Saldo Presupuestal al 08.06.2021 | L44: Proyección del gasto | T44: TOTAL EJECUCION +PROYECCION (2) | U44: Saldo disponible ( 1-2)
D45: Enero | E45: Febrero | F45: Marzo | G45: Abril | H45: Mayo | I45: Junio( 01 al 08) | J45: TOTAL EJECUCION | L45: Junio( 09 al 30) | M45: Julio | N45: Agosto | O45: Setiembre | P45: Octubre | Q45: Noviembre | R45: Diciembre | S45: TOTAL PROYECCIÓN
A46: 9001 ACCIONES CENTRALES | C46: =SUBTOTAL(9,C47:C47) -> 15000 | D46: =SUBTOTAL(9,D47:D47) -> 0 | E46: =SUBTOTAL(9,E47:E47) -> 0 | F46: =SUBTOTAL(9,F47:F47) -> 0 | G46: =SUBTOTAL(9,G47:G47) -> 0 | H46: =SUBTOTAL(9,H47:H47) -> 0 | I46: =SUBTOTAL(9,I47:I47) -> 0 | J46: =SUM(D46:I46) -> 0 | K46: =C46-J46 -> 15000 | L46: =SUBTOTAL(9,L47:L47) -> 0 | M46: =SUBTOTAL(9,M47:M47) -> 15000 | N46: =SUBTOTAL(9,N47:N47) -> 0 | O46: =SUBTOTAL(9,O47:O47) -> 0 | P46: =SUBTOTAL(9,P47:P47) -> 0 | Q46: =SUBTOTAL(9,Q47:Q47) -> 0 | R46: =SUBTOTAL(9,R47:R47) -> 0 | S46: =SUM(L46:R46) -> 15000 | T46: =+J46+S46 -> 15000 | U46: =+C46-T46 -> 0
A47: 2.2.2.3.4.2 | B47: GASTOS DE SEPELIO Y LUTO DEL PERSONAL ACTIVO | C47: 15000 | D47: 0 | E47: 0 | F47: 0 | G47: 0 | H47: 0 | I47: 0 | J47: =SUM(D47:I47) -> 0 | K47: =C47-J47 -> 15000 | M47: 15000 | S47: =SUM(L47:R47) -> 15000 | T47: =+J47+S47 -> 15000 | U47: =+C47-T47 -> 0
A48: TOTAL G.G. 2.2 PENSIONES Y PRESTACIONES | C48: =SUBTOTAL(9,C46:C47) -> 15000 | D48: =SUBTOTAL(9,D46:D47) -> 0 | E48: =SUBTOTAL(9,E46:E47) -> 0 | F48: =SUBTOTAL(9,F46:F47) -> 0 | G48: =SUBTOTAL(9,G46:G47) -> 0 | H48: =SUBTOTAL(9,H46:H47) -> 0 | I48: =SUM(I46:I47)/3 -> 0 | J48: =SUM(D48:I48) -> 0 | K48: =C48-J48 -> 15000 | L48: =SUBTOTAL(9,L46:L47) -> 0 | M48: =SUBTOTAL(9,M46:M47) -> 15000 | N48: =SUBTOTAL(9,N46:N47) -> 0 | O48: =SUBTOTAL(9,O46:O47) -> 0 | P48: =SUBTOTAL(9,P46:P47) -> 0 | Q48: =SUBTOTAL(9,Q46:Q47) -> 0 | R48: =SUBTOTAL(9,R46:R47) -> 0 | S48: =SUM(L48:R48) -> 15000 | T48: =+J48+S48 -> 15000 | U48: =+C48-T48 -> 0
A51: Cat pptal/ Detalle Específica de Gasto | C51: PIM (1) | D51: Ejecución Devengado UE | K51: Saldo Presupuestal al 08.06.2021 | L51: Proyección del gasto | T51: TOTAL EJECUCION +PROYECCION (2) | U51: Saldo disponible ( 1-2)
D52: Enero | E52: Febrero | F52: Marzo | G52: Abril | H52: Mayo | I52: Junio( 01 al 08) | J52: TOTAL EJECUCION | L52: Junio( 09 al 30) | M52: Julio | N52: Agosto | O52: Setiembre | P52: Octubre | Q52: Noviembre | R52: Diciembre | S52: TOTAL PROYECCIÓN
A53: 0086 MEJORA DE LOS SERVICIOS DEL SISTEMA DE JUSTICIA PENAL | C53: =SUBTOTAL(9,C54:C54) -> 409200 | D53: =SUBTOTAL(9,D54:D54) -> 0 | E53: =SUBTOTAL(9,E54:E54) -> 0 | F53: =SUBTOTAL(9,F54:F54) -> 40920 | G53: =SUBTOTAL(9,G54:G54) -> 40920 | H53: =SUBTOTAL(9,H54:H54) -> 40920 | I53: =SUBTOTAL(9,I54:I54) -> 0 | J53: =SUM(D53:I53) -> 122760 | K53: =C53-J53 -> 286440 | L53: =SUBTOTAL(9,L54:L54) -> 40920 | M53: =SUBTOTAL(9,M54:M54) -> 40920 | N53: =SUBTOTAL(9,N54:N54) -> 40920 | O53: =SUBTOTAL(9,O54:O54) -> 40920 | P53: =SUBTOTAL(9,P54:P54) -> 40920 | Q53: =SUBTOTAL(9,Q54:Q54) -> 40920 | R53: =SUBTOTAL(9,R54:R54) -> 40920 | S53: =SUM(L53:R53) -> 286440 | T53: =+J53+S53 -> 409200 | U53: =+C53-T53 -> 0
A54: 2.3.2.7.5.1 | B54: ESTIPENDIO POR SECIGRA | C54: 409200 | D54: 0 | E54: 0 | F54: 40920 | G54: 40920 | H54: 40920 | I54: 0 | J54: =SUM(D54:I54) -> 122760 | K54: =C54-J54 -> 286440 | L54: 40920 | M54: 40920 | N54: 40920 | O54: 40920 | P54: 40920 | Q54: 40920 | R54: 40920 | S54: =SUM(L54:R54) -> 286440 | T54: =+J54+S54 -> 409200 | U54: =+C54-T54 -> 0
A55: TOTAL G.G. 2.3 SECIGRA | C55: =SUBTOTAL(9,C53:C54) -> 409200 | D55: =SUBTOTAL(9,D53:D54) -> 0 | E55: =SUBTOTAL(9,E53:E54) -> 0 | F55: =SUBTOTAL(9,F53:F54) -> 40920 | G55: =SUBTOTAL(9,G53:G54) -> 40920 | H55: =SUBTOTAL(9,H53:H54) -> 40920 | I55: =SUM(I53:I54)/3 -> 0 | J55: =SUM(D55:I55) -> 122760 | K55: =C55-J55 -> 286440 | L55: =SUBTOTAL(9,L53:L54) -> 40920 | M55: =SUBTOTAL(9,M53:M54) -> 40920 | N55: =SUBTOTAL(9,N53:N54) -> 40920 | O55: =SUBTOTAL(9,O53:O54) -> 40920 | P55: =SUBTOTAL(9,P53:P54) -> 40920 | Q55: =SUBTOTAL(9,Q53:Q54) -> 40920 | R55: =SUBTOTAL(9,R53:R54) -> 40920 | S55: =SUM(L55:R55) -> 286440 | T55: =+J55+S55 -> 409200 | U55: =+C55-T55 -> 0

Sheet 2.1 x categ.pptal
A2: Cat pptal/ Detalle Específica de Gasto | C2: PIM (1) | D2: Ejecución Devengado UE | K2: Saldo Presupuestal al 08.06.2021 | L2: Proyección del gasto | T2: TOTAL EJECUCION +PROYECCION (2) | U2: Saldo disponible ( 1-2)
D3: Enero | E3: Febrero | F3: Marzo | G3: Abril | H3: Mayo | I3: Junio( 01 al 08) | J3: TOTAL EJECUCION | L3: Junio( 09 al 30) | M3: Julio | N3: Agosto | O3: Setiembre | P3: Octubre | Q3: Noviembre | R3: Diciembre | S3: TOTAL PROYECCIÓN
A4: 0086 MEJORA DE LOS SERVICIOS DEL SISTEMA DE JUSTICIA PENAL | C4: =SUBTOTAL(9,C5:C21) -> 35822019 | D4: =SUBTOTAL(9,D5:D21) -> 3022530.2 | E4: =SUBTOTAL(9,E5:E21) -> 2910772.6 | F4: =SUBTOTAL(9,F5:F21) -> 2869476.1 | G4: =SUBTOTAL(9,G5:G21) -> 2886371.5 | H4: =SUBTOTAL(9,H5:H21) -> 3279619 | I4: =SUBTOTAL(9,I5:I21) -> 0 | J4: =SUM(D4:I4) -> 14968769 | K4: =C4-J4 -> 20853250 | L4: =SUBTOTAL(9,L5:L19) -> 2952930.2 | M4: =SUBTOTAL(9,M5:M19) -> 4011159.7 | N4: =SUBTOTAL(9,N5:N19) -> 2952930.2 | O4: =SUBTOTAL(9,O5:O19) -> 2952930.2 | P4: =SUBTOTAL(9,P5:P19) -> 2952930.2 | Q4: =SUBTOTAL(9,Q5:Q19) -> 3397240 | R4: =SUBTOTAL(9,R5:R19) -> 4011159.7 | S4: =SUM(L4:R4) -> 23231280 | T4: =+J4+S4 -> 38200050 | U4: =+C4-T4 -> -2378030.5
A5: 2.1.1.1.1.2 | B5: PERSONAL ADMINISTRATIVO NOMBRADO (REGIMEN PUBLICO) | C5: 130530 | D5: 10877.51 | E5: 10877.51 | F5: 10877.51 | G5: 10877.51 | H5: 10877.51 | I5: 0 | J5: =SUM(D5:I5) -> 54387.55 | K5: =C5-J5 -> 76142.45 | L5: 10877.51 | M5: 10877.51 | N5: 10877.51 | O5: 10877.51 | P5: 10877.51 | Q5: 10877.51 | R5: 10877.51 | S5: =SUM(L5:R5) -> 76142.57 | T5: =+J5+S5 -> 130530.12 | U5: =+C5-T5 -> -0.12
A6: 2.1.1.1.1.4 | B6: PERSONAL CON CONTRATO A PLAZO INDETERMINADO (REGIMEN LABORAL PRIVADO) | C6: 5989239 | D6: 501051.8 | E6: 505766 | F6: 460905.3 | G6: 483718.12 | H6: 496859.8 | I6: 0 | J6: =SUM(D6:I6) -> 2448301 | K6: =C6-J6 -> 3540938 | L6: 502059 | M6: 502059 | N6: 502059 | O6: 502059 | P6: 502059 | Q6: 502059 | R6: 502059 | S6: =SUM(L6:R6) -> 3514413 | T6: =+J6+S6 -> 5962714 | U6: =+C6-T6 -> 26524.98
A7: 2.1.1.1.1.5 | B7: PERSONAL CON CONTRATO A PLAZO FIJO (REGIMEN LABORAL PRIVADO) | C7: 2093811 | D7: 159027.82 | E7: 182484.95 | F7: 186903.57 | G7: 176695 | H7: 172124 | I7: 0 | J7: =SUM(D7:I7) -> 877235.34 | K7: =C7-J7 -> 1216575.7 | L7: 203350 | M7: 203350 | N7: 203350 | O7: 203350 | P7: 203350 | Q7: 203350 | R7: 203350 | S7: =SUM(L7:R7) -> 1423450 | T7: =+J7+S7 -> 2300685.3 | U7: =+C7-T7 -> -206874.34
A8: 2.1.1.1.2.1 | B8: ASIGNACION A FONDOS PARA PERSONAL | C8: 57843 | D8: 4840 | E8: 4800 | F8: 4840 | G8: 7240 | H8: 5440 | I8: 0 | J8: =SUM(D8:I8) -> 27160 | K8: =C8-J8 -> 30683 | L8: 5440 | M8: 5440 | N8: 5440 | O8: 5440 | P8: 5440 | Q8: 5440 | R8: 5440 | S8: =SUM(L8:R8) -> 38080 | T8: =+J8+S8 -> 65240 | U8: =+C8-T8 -> -7397
A9: 2.1.1.3.1.2 | B9: PERSONAL CONTRATADO | C9: 678041 | D9: 51615 | E9: 51615 | F9: 44463.3 | G9: 51460 | H9: 51615 | I9: 0 | J9: =SUM(D9:I9) -> 250768.3 | K9: =C9-J9 -> 427272.7 | L9: 56265 | M9: 56265 | N9: 56265 | O9: 56265 | P9: 56265 | Q9: 56265 | R9: 56265 | S9: =SUM(L9:R9) -> 393855 | T9: =+J9+S9 -> 644623.3 | U9: =+C9-T9 -> 33417.7
A10: 2.1.1.4.1.1 | B10: PERSONAL NOMBRADO | C10: 4266241 | D10: 352637.46 | E10: 356540.19 | F10: 356107.49 | G10: 356705.84 | H10: 351836.55 | I10: 0 | J10: =SUM(D10:I10) -> 1773827.5 | K10: =C10-J10 -> 2492413.5 | L10: 359211.06 | M10: 359211.06 | N10: 359211.06 | O10: 359211.06 | P10: 359211.06 | Q10: 359211.06 | R10: 359211.06 | S10: =SUM(L10:R10) -> 2514477.4 | T10: =+J10+S10 -> 4288304.9 | U10: =+C10-T10 -> -22063.95
A11: 2.1.1.4.2.1 | B11: BONO POR FUNCION JURISDICCIONAL Y FISCAL | C11: 5649388 | D11: 479940 | E11: 488450 | F11: 487400 | G11: 487243.33 | H11: 484486.67 | I11: 0 | J11: =SUM(D11:I11) -> 2427520 | K11: =C11-J11 -> 3221868 | L11: 489900 | M11: 489900 | N11: 489900 | O11: 489900 | P11: 489900 | Q11: 489900 | R11: 489900 | S11: =SUM(L11:R11) -> 3429300 | T11: =+J11+S11 -> 5856820 | U11: =+C11-T11 -> -207432
A12: 2.1.1.4.2.2 | B12: ASIGNACION POR GASTOS OPERATIVOS | C12: 13643407 | D12: 1320749.8 | E12: 1310238.9 | F12: 1317978.9 | G12: 1312431.7 | H12: 1314865.8 | I12: 0 | J12: =SUM(D12:I12) -> 6576265.1 | K12: =C12-J12 -> 7067141.9 | L12: 1325827.6 | M12: 1325827.6 | N12: 1325827.6 | O12: 1325827.6 | P12: 1325827.6 | Q12: 1325827.6 | R12: 1325827.6 | S12: =SUM(L12:R12) -> 9280793.1 | T12: =+J12+S12 -> 15857058 | U12: =+C12-T12 -> -2213651.2
A13: 2.1.1.9.1.1 | B13: GRATIFICACIONES | C13: 1616113 | D13: 0 | E13: 0 | F13: 0 | G13: 0 | H13: 0 | I13: 0 | J13: =SUM(D13:I13) -> 0 | K13: =C13-J13 -> 1616113 | M13: 761674 | R13: 761674 | S13: =SUM(L13:R13) -> 1523348 | T13: =+J13+S13 -> 1523348 | U13: =+C13-T13 -> 92765
A14: 2.1.1.9.1.2 | B14: AGUINALDOS | C14: 610330 | D14: 0 | E14: 0 | F14: 0 | G14: 0 | H14: 0 | I14: 0 | J14: =SUM(D14:I14) -> 0 | K14: =C14-J14 -> 610330 | M14: 269438.58 | R14: 269438.58 | S14: =SUM(L14:R14) -> 538877.16 | T14: =+J14+S14 -> 538877.16 | U14: =+C14-T14 -> 71452.84
A15: 2.1.1.9.1.3 | B15: BONIFICACION POR ESCOLARIDAD | C15: 172004 | D15: 141790.9 | E15: 0 | F15: 0 | G15: 0 | H15: 0 | I15: 0 | J15: =SUM(D15:I15) -> 141790.9 | K15: =C15-J15 -> 30213.1 | S15: =SUM(L15:R15) -> 0 | T15: =+J15+S15 -> 141790.9 | U15: =+C15-T15 -> 30213.1
A16: 2.1.1.9.2.1 | B16: COMPENSACION POR TIEMPO DE SERVICIOS (CTS) | C16: 852798 | D16: 0 | E16: 0 | F16: 0 | G16: 0 | H16: 391513.69 | I16: 0 | J16: =SUM(D16:I16) -> 391513.69 | K16: =C16-J16 -> 461284.31 | Q16: 444309.83 | S16: =SUM(L16:R16) -> 444309.83 | T16: =+J16+S16 -> 835823.52 | U16: =+C16-T16 -> 16974.48
A17: 2.1.1.9.3.3 | B17: COMPENSACION VACACIONAL (VACACIONES TRUNCAS) | C17: 3386 | D17: 0 | E17: 0 | F17: 0 | G17: 0 | H17: 0 | I17: 0 | J17: =SUM(D17:I17) -> 0 | K17: =C17-J17 -> 3386 | S17: =SUM(L17:R17) -> 0 | T17: =+J17+S17 -> 0 | U17: =+C17-T17 -> 3386
A18: 2.1.1.9.3.99 | B18: OTRAS OCASIONALES | C18: 58888 | D18: 0 | E18: 0 | F18: 0 | G18: 0 | H18: 0 | I18: 0 | J18: =SUM(D18:I18) -> 0 | K18: =C18-J18 -> 58888 | M18: 27117.01 | R18: 27117.01 | S18: =SUM(L18:R18) -> 54234.02 | T18: =+J18+S18 -> 54234.02 | U18: =+C18-T18 -> 4653.98
A19: 2.1.3.1.1.1 | B19: APORTES A LOS FONDOS DE SALUD | C19: 28946 | D19: 2247.88 | E19: 2249.75 | F19: 2215.46 | G19: 2217.25 | H19: 2193.41 | I19: 0 | J19: =SUM(D19:I19) -> 11123.75 | K19: =C19-J19 -> 17822.25 | L19: 2205.54 | M19: 2205.54 | N19: 2205.54 | O19: 2205.54 | P19: 2205.54 | Q19: 2205.54 | R19: 2205.54 | S19: =SUM(L19:R19) -> 15438.78 | T19: =+J19+S19 -> 26562.53 | U19: =+C19-T19 -> 2383.47
A20: 2.1.3.1.1.3 | B20: APORTES A LOS FONDOS DE PENSIONES | C20: 12186 | D20: 924.3 | E20: 925.8 | F20: 925.8 | G20: 925.8 | H20: 925.8 | I20: 0 | J20: =SUM(D20:I20) -> 4627.5 | K20: =C20-J20 -> 7558.5 | L20: 925.8 | M20: 925.8 | N20: 925.8 | O20: 925.8 | P20: 925.8 | Q20: 925.8 | R20: 925.8 | S20: =SUM(L20:R20) -> 6480.6 | T20: =+J20+S20 -> 11108.1 | U20: =+C20-T20 -> 1077.9
A21: 2.1.3.1.1.5 | B21: CONTRIBUCIONES A ESSALUD | C21: 695080 | D21: 53980 | E21: 55396.09 | F21: 56020.21 | G21: 54863.25 | H21: 54661 | I21: 0 | J21: =SUM(D21:I21) -> 274920.55 | K21: =C21-J21 -> 420159.45 | L21: 57174.55 | M21: 57174.55 | N21: 57174.55 | O21: 57174.55 | P21: 57174.55 | Q21: 57174.55 | R21: 57174.55 | S21: =SUM(L21:R21) -> 400221.85 | T21: =+J21+S21 -> 675142.4 | U21: =+C21-T21 -> 19937.6
A22: 1002 PRODUCTOS ESPECIFICOS PARA REDUCCION DE LA VIOLENCIA CONTRA LA MUJER | C22: =SUBTOTAL(9,C23:C36) -> 1183400 | D22: =SUBTOTAL(9,D23:D36) -> 201820.54 | E22: =SUBTOTAL(9,E23:E36) -> 191164.85 | F22: =SUBTOTAL(9,F23:F36) -> 188782.55 | G22: =SUBTOTAL(9,G23:G36) -> 188156.81 | H22: =SUBTOTAL(9,H23:H36) -> 213006.35 | I22: =SUBTOTAL(9,I23:I36) -> 0 | J22: =SUM(D22:I22) -> 982931.1 | K22: =C22-J22 -> 200468.9 | L22: =SUBTOTAL(9,L23:L36) -> 191970.54 | M22: =SUBTOTAL(9,M23:M36) -> 249071.89 | N22: =SUBTOTAL(9,N23:N36) -> 191970.54 | O22: =SUBTOTAL(9,O23:O36) -> 191970.54 | P22: =SUBTOTAL(9,P23:P36) -> 191970.54 | Q22: =SUBTOTAL(9,Q23:Q36) -> 214456.87 | R22: =SUBTOTAL(9,R23:R36) -> 249071.89 | S22: =SUM(L22:R22) -> 1480482.8 | T22: =+J22+S22 -> 2463413.9 | U22: =+C22-T22 -> -1280013.9
A23: 2.1.1.1.1.2 | B23: PERSONAL ADMINISTRATIVO NOMBRADO (REGIMEN PUBLICO) | C23: 16315 | D23: 2719.14 | E23: 2719.14 | F23: 2719.14 | G23: 2719.14 | H23: 2719.14 | I23: 0 | J23: =SUM(D23:I23) -> 13595.7 | K23: =C23-J23 -> 2719.3 | L23: 2719.14 | M23: 2719.14 | N23: 2719.14 | O23: 2719.14 | P23: 2719.14 | Q23: 2719.14 | R23: 2719.14 | S23: =SUM(L23:R23) -> 19033.98 | T23: =+J23+S23 -> 32629.68 | U23: =+C23-T23 -> -16314.68
A24: 2.1.1.1.1.4 | B24: PERSONAL CON CONTRATO A PLAZO INDETERMINADO (REGIMEN LABORAL PRIVADO) | C24: 176436 | D24: 29406 | E24: 29406 | F24: 26781 | G24: 26781 | H24: 29406 | I24: 0 | J24: =SUM(D24:I24) -> 141780 | K24: =C24-J24 -> 34656 | L24: 29406 | M24: 29406 | N24: 29406 | O24: 29406 | P24: 29406 | Q24: 29406 | R24: 29406 | S24: =SUM(L24:R24) -> 205842 | T24: =+J24+S24 -> 347622 | U24: =+C24-T24 -> -171186
A25: 2.1.1.1.1.5 | B25: PERSONAL CON CONTRATO A PLAZO FIJO (REGIMEN LABORAL PRIVADO) | C25: 54852 | D25: 9142 | E25: 9142 | F25: 9142 | G25: 9142 | H25: 9142 | I25: 0 | J25: =SUM(D25:I25) -> 45710 | K25: =C25-J25 -> 9142 | L25: 9142 | M25: 9142 | N25: 9142 | O25: 9142 | P25: 9142 | Q25: 9142 | R25: 9142 | S25: =SUM(L25:R25) -> 63994 | T25: =+J25+S25 -> 109704 | U25: =+C25-T25 -> -54852
A26: 2.1.1.1.2.1 | B26: ASIGNACION A FONDOS PARA PERSONAL | C26: 7260 | D26: 1210 | E26: 1210 | F26: 1210 | G26: 1810 | H26: 1360 | I26: 0 | J26: =SUM(D26:I26) -> 6800 | K26: =C26-J26 -> 460 | L26: 1360 | M26: 1360 | N26: 1360 | O26: 1360 | P26: 1360 | Q26: 1360 | R26: 1360 | S26: =SUM(L26:R26) -> 9520 | T26: =+J26+S26 -> 16320 | U26: =+C26-T26 -> -9060
A27: 2.1.1.4.1.1 | B27: PERSONAL NOMBRADO | C27: 151656 | D27: 25275.89 | E27: 24620.2 | F27: 25275.89 | G27: 23637.16 | H27: 23837.67 | I27: 0 | J27: =SUM(D27:I27) -> 122646.81 | K27: =C27-J27 -> 29009.19 | L27: 25275.89 | M27: 25275.89 | N27: 25275.89 | O27: 25275.89 | P27: 25275.89 | Q27: 25275.89 | R27: 25275.89 | S27: =SUM(L27:R27) -> 176931.23 | T27: =+J27+S27 -> 299578.04 | U27: =+C27-T27 -> -147922.04
A28: 2.1.1.4.2.1 | B28: BONO POR FUNCION JURISDICCIONAL Y FISCAL | C28: 214200 | D28: 35700 | E28: 35700 | F28: 35610 | G28: 35700 | H28: 35700 | I28: 0 | J28: =SUM(D28:I28) -> 178410 | K28: =C28-J28 -> 35790 | L28: 35700 | M28: 35700 | N28: 35700 | O28: 35700 | P28: 35700 | Q28: 35700 | R28: 35700 | S28: =SUM(L28:R28) -> 249900 | T28: =+J28+S28 -> 428310 | U28: =+C28-T28 -> -214110
A29: 2.1.1.4.2.2 | B29: ASIGNACION POR GASTOS OPERATIVOS | C29: 530206 | D29: 88367.51 | E29: 88367.51 | F29: 88044.52 | G29: 88367.51 | H29: 88367.51 | I29: 0 | J29: =SUM(D29:I29) -> 441514.56 | K29: =C29-J29 -> 88691.44 | L29: 88367.51 | M29: 88367.51 | N29: 88367.51 | O29: 88367.51 | P29: 88367.51 | Q29: 88367.51 | R29: 88367.51 | S29: =SUM(L29:R29) -> 618572.57 | T29: =+J29+S29 -> 1060087.1 | U29: =+C29-T29 -> -529881.13
A30: 2.1.1.9.1.1 | B30: GRATIFICACIONES | C30: 0 | J30: 0 | K30: 0 | M30: 38548 | R30: 38548 | S30: =SUM(L30:R30) -> 77096 | T30: =+J30+S30 -> 77096 | U30: =+C30-T30 -> -77096
A31: 2.1.1.9.1.2 | B31: AGUINALDOS | C31: 0 | M31: 17145.53 | R31: 17145.53 | S31: =SUM(L31:R31) -> 34291.06 | T31: =+J31+S31 -> 34291.06 | U31: =+C31-T31 -> -34291.06
A32: 2.1.1.9.1.3 | B32: BONIFICACION POR ESCOLARIDAD | C32: 10000 | D32: 10000 | E32: 0 | F32: 0 | G32: 0 | H32: 0 | I32: 0 | J32: =SUM(D32:I32) -> 10000 | K32: =C32-J32 -> 0 | S32: =SUM(L32:R32) -> 0 | T32: =+J32+S32 -> 10000 | U32: =+C32-T32 -> 0
A33: 2.1.1.9.2.1 | B33: COMPENSACION POR TIEMPO DE SERVICIOS (CTS) | C33: 22475 | D33: 0 | E33: 0 | F33: 0 | G33: 0 | H33: 22474.03 | I33: 0 | J33: =SUM(D33:I33) -> 22474.03 | K33: =C33-J33 -> 0.97 | Q33: 22486.33 | S33: =SUM(L33:R33) -> 22486.33 | T33: =+J33+S33 -> 44960.36 | U33: =+C33-T33 -> -22485.36
A34: 2.1.1.9.3.99 | B34: OTRAS OCASIONALES | C34: 0 | M34: 1407.82 | R34: 1407.82 | S34: =SUM(L34:R34) -> 2815.64 | T34: =+J34+S34 -> 2815.64 | U34: =+C34-T34 -> -2815.64
A35: 2.1.3.1.1.1 | B35: APORTES A LOS FONDOS DE SALUD | C35: 1398 | D35: 232.98 | E35: 243.66 | F35: 242.16 | G35: 228.63 | H35: 243.66 | I35: 0 | J35: =SUM(D35:I35) -> 1191.09 | K35: =C35-J35 -> 206.91 | L35: 243.66 | M35: 243.66 | N35: 243.66 | O35: 243.66 | P35: 243.66 | Q35: 243.66 | R35: 243.66 | S35: =SUM(L35:R35) -> 1705.62 | T35: =+J35+S35 -> 2896.71 | U35: =+C35-T35 -> -1498.71
A36: 2.1.3.1.1.5 | B36: CONTRIBUCIONES A ESSALUD | C36: 20766 | D36: 3460.9 | E36: 3492.96 | F36: 3445.7 | G36: 3405.1 | H36: 3478.77 | I36: 0 | J36: =SUM(D36:I36) -> 17283.43 | K36: =C36-J36 -> 3482.57 | L36: 3522.64 | M36: 3522.64 | N36: 3522.64 | O36: 3522.64 | P36: 3522.64 | Q36: 3522.64 | R36: 3522.64 | S36: =SUM(L36:R36) -> 24658.48 | T36: =+J36+S36 -> 41941.91 | U36: =+C36-T36 -> -21175.91
A37: 9001 ACCIONES CENTRALES | C37: =SUBTOTAL(9,C38:C49) -> 3288902 | D37: =SUBTOTAL(9,D38:D49) -> 152421.64 | E37: =SUBTOTAL(9,E38:E49) -> 140331.83 | F37: =SUBTOTAL(9,F38:F49) -> 151506.83 | G37: =SUBTOTAL(9,G38:G49) -> 159340.13 | H37: =SUBTOTAL(9,H38:H49) -> 231478.66 | I37: =SUBTOTAL(9,I38:I49) -> 0 | J37: =SUM(D37:I37) -> 835079.09 | K37: =C37-J37 -> 2453822.9 | L37: =SUBTOTAL(9,L38:L49) -> 182481.83 | M37: =SUBTOTAL(9,M38:M49) -> 367627.66 | N37: =SUBTOTAL(9,N38:N49) -> 182481.83 | O37: =SUBTOTAL(9,O38:O49) -> 182481.83 | P37: =SUBTOTAL(9,P38:P49) -> 182481.83 | Q37: =SUBTOTAL(9,Q38:Q49) -> 286561.91 | R37: =SUBTOTAL(9,R38:R49) -> 367627.66 | S37: =SUM(L37:R37) -> 1751744.5 | T37: =+J37+S37 -> 2586823.6 | U37: =+C37-T37 -> 702078.36
A38: 2.1.1.1.1.2 | B38: PERSONAL ADMINISTRATIVO NOMBRADO (REGIMEN PUBLICO) | C38: 31296 | D38: 2698.83 | E38: 2598.83 | F38: 2598.83 | G38: 2598.83 | H38: 2631.19 | I38: 0 | J38: =SUM(D38:I38) -> 13126.51 | K38: =C38-J38 -> 18169.49 | L38: 2698.83 | M38: 2698.83 | N38: 2698.83 | O38: 2698.83 | P38: 2698.83 | Q38: 2698.83 | R38: 2698.83 | S38: =SUM(L38:R38) -> 18891.81 | T38: =+J38+S38 -> 32018.32 | U38: =+C38-T38 -> -722.32
A39: 2.1.1.1.1.4 | B39: PERSONAL CON CONTRATO A PLAZO INDETERMINADO (REGIMEN LABORAL PRIVADO) | C39: 2253672 | D39: 121223 | E39: 119673 | F39: 130848 | G39: 145186.3 | H39: 146123 | I39: 0 | J39: =SUM(D39:I39) -> 663053.3 | K39: =C39-J39 -> 1590618.7 | L39: 162723 | M39: 162723 | N39: 162723 | O39: 162723 | P39: 162723 | Q39: 162723 | R39: 162723 | S39: =SUM(L39:R39) -> 1139061 | T39: =+J39+S39 -> 1802114.3 | U39: =+C39-T39 -> 451557.7
A40: 2.1.1.1.1.5 | B40: PERSONAL CON CONTRATO A PLAZO FIJO (REGIMEN LABORAL PRIVADO) | C40: 426009 | D40: 16850 | E40: 16850 | F40: 16850 | G40: 9750 | H40: 9750 | I40: 0 | J40: =SUM(D40:I40) -> 70050 | K40: =C40-J40 -> 355959 | L40: 15700 | M40: 15700 | N40: 15700 | O40: 15700 | P40: 15700 | Q40: 15700 | R40: 15700 | S40: =SUM(L40:R40) -> 109900 | T40: =+J40+S40 -> 179950 | U40: =+C40-T40 -> 246059
A41: 2.1.1.1.2.1 | B41: ASIGNACION A FONDOS PARA PERSONAL | C41: 14520 | D41: 1210 | E41: 1210 | F41: 1210 | G41: 1805 | H41: 1360 | I41: 0 | J41: =SUM(D41:I41) -> 6795 | K41: =C41-J41 -> 7725 | L41: 1360 | M41: 1360 | N41: 1360 | O41: 1360 | P41: 1360 | Q41: 1360 | R41: 1360 | S41: =SUM(L41:R41) -> 9520 | T41: =+J41+S41 -> 16315 | U41: =+C41-T41 -> -1795
A42: 2.1.1.9.1.1 | B42: GRATIFICACIONES | C42: 362000 | D42: 0 | E42: 0 | F42: 0 | G42: 0 | H42: 0 | I42: 0 | J42: =SUM(D42:I42) -> 0 | K42: =C42-J42 -> 362000 | M42: 178423 | R42: 178423 | S42: =SUM(L42:R42) -> 356846 | T42: =+J42+S42 -> 356846 | U42: =+C42-T42 -> 5154
A43: 2.1.1.9.1.2 | B43: AGUINALDOS | C43: 600 | D43: 0 | E43: 0 | F43: 0 | G43: 0 | H43: 0 | I43: 0 | J43: =SUM(D43:I43) -> 0 | K43: =C43-J43 -> 600 | M43: 300 | R43: 300 | S43: =SUM(L43:R43) -> 600 | T43: =+J43+S43 -> 600 | U43: =+C43-T43 -> 0
A44: 2.1.1.9.1.3 | B44: BONIFICACION POR ESCOLARIDAD | C44: 11329 | D44: 10439.81 | E44: 0 | F44: 0 | G44: 0 | H44: 0 | I44: 0 | J44: =SUM(D44:I44) -> 10439.81 | K44: =C44-J44 -> 889.19 | S44: =SUM(L44:R44) -> 0 | T44: =+J44+S44 -> 10439.81 | U44: =+C44-T44 -> 889.19
A45: 2.1.1.9.2.1 | B45: COMPENSACION POR TIEMPO DE SERVICIOS (CTS) | C45: 168547 | D45: 0 | E45: 0 | F45: 0 | G45: 0 | H45: 71614.47 | I45: 0 | J45: =SUM(D45:I45) -> 71614.47 | K45: =C45-J45 -> 96932.53 | Q45: 104080.08 | S45: =SUM(L45:R45) -> 104080.08 | T45: =+J45+S45 -> 175694.55 | U45: =+C45-T45 -> -7147.55
A46: 2.1.1.9.3.3 | B46: COMPENSACION VACACIONAL (VACACIONES TRUNCAS) | C46: 7649 | D46: 0 | E46: 0 | F46: 0 | G46: 0 | H46: 0 | I46: 0 | J46: =SUM(D46:I46) -> 0 | K46: =C46-J46 -> 7649 | S46: =SUM(L46:R46) -> 0 | T46: =+J46+S46 -> 0 | U46: =+C46-T46 -> 7649
A47: 2.1.1.9.3.99 | B47: OTRAS OCASIONALES | C47: 13280 | D47: 0 | E47: 0 | F47: 0 | G47: 0 | H47: 0 | I47: 0 | J47: =SUM(D47:I47) -> 0 | K47: =C47-J47 -> 13280 | M47: 6422.83 | R47: 6422.83 | S47: =SUM(L47:R47) -> 12845.66 | T47: =+J47+S47 -> 12845.66 | U47: =+C47-T47 -> 434.34
A48: 2.1.3.1.1.1 | B48: APORTES A LOS FONDOS DE SALUD | C48: 214276 | D48: 55.64 | E48: 55.64 | F48: 55.64 | G48: 55.64 | H48: 55.64 | I48: 0 | J48: =SUM(D48:I48) -> 278.2 | K48: =C48-J48 -> 213997.8 | L48: =55.64+213745.2 -> 213800.84 | M48: 55.64 | N48: 55.64 | O48: 55.64 | P48: 55.64 | Q48: 55.64 | R48: 55.64 | S48: =SUM(L48:R48) -> 214134.68 | T48: =+J48+S48 -> 214412.88 | U48: =+C48-T48 -> -136.88
A49: 2.1.3.1.1.5 | B49: CONTRIBUCIONES A ESSALUD | C49: 75361 | D49: 5034.39 | E49: 4932.01 | F49: 5464.51 | G49: 5610.61 | H49: 5693.31 | I49: 0 | J49: =SUM(D49:I49) -> 26734.83 | K49: =C49-J49 -> 48626.17 | L49: 6506.53 | M49: 6506.53 | N49: 6506.53 | O49: 6506.53 | P49: 6506.53 | Q49: 6506.53 | R49: 6506.53 | S49: =SUM(L49:R49) -> 45545.71 | T49: =+J49+S49 -> 72280.54 | U49: =+C49-T49 -> 3080.46
A50: 9002 ASIGNACIONES PRESUPUESTARIAS QUE NO RESULTAN EN PRODUCTOS | C50: =SUBTOTAL(9,C51:C65) -> 7143901 | D50: =SUBTOTAL(9,D51:D65) -> 426853.41 | E50: =SUBTOTAL(9,E51:E65) -> 414592.74 | F50: =SUBTOTAL(9,F51:F65) -> 414726.41 | G50: =SUBTOTAL(9,G51:G65) -> 412421.31 | H50: =SUBTOTAL(9,H51:H65) -> 450092.47 | I50: =SUBTOTAL(9,I51:I65) -> 0 | J50: =SUM(D50:I50) -> 2118686.3 | K50: =C50-J50 -> 5025214.7 | L50: =SUBTOTAL(9,L51:L65) -> 514527.17 | M50: =SUBTOTAL(9,M51:M65) -> 709362.45 | N50: =SUBTOTAL(9,N51:N65) -> 514527.17 | O50: =SUBTOTAL(9,O51:O65) -> 514527.17 | P50: =SUBTOTAL(9,P51:P65) -> 514527.17 | Q50: =SUBTOTAL(9,Q51:Q65) -> 599796.67 | R50: =SUBTOTAL(9,R51:R65) -> 709362.45 | S50: =SUM(L50:R50) -> 4076630.2 | T50: =+J50+S50 -> 6195316.6 | U50: =+C50-T50 -> 948584.41
A51: 2.1.1.1.1.2 | B51: PERSONAL ADMINISTRATIVO NOMBRADO (REGIMEN PUBLICO) | C51: 65202 | D51: 2714.33 | E51: 2714.33 | F51: 2714.33 | G51: 2714.33 | H51: 2714.33 | I51: 0 | J51: =SUM(D51:I51) -> 13571.65 | K51: =C51-J51 -> 51630.35 | L51: 2714.33 | M51: 2714.33 | N51: 2714.33 | O51: 2714.33 | P51: 2714.33 | Q51: 2714.33 | R51: 2714.33 | S51: =SUM(L51:R51) -> 19000.31 | T51: =+J51+S51 -> 32571.96 | U51: =+C51-T51 -> 32630.04
A52: 2.1.1.1.1.4 | B52: PERSONAL CON CONTRATO A PLAZO INDETERMINADO (REGIMEN LABORAL PRIVADO) | C52: 936329 | D52: 69254 | E52: 69254 | F52: 69254 | G52: 69161 | H52: 69161 | I52: 0 | J52: =SUM(D52:I52) -> 346084 | K52: =C52-J52 -> 590245 | L52: 69161 | M52: 69161 | N52: 69161 | O52: 69161 | P52: 69161 | Q52: 69161 | R52: 69161 | S52: =SUM(L52:R52) -> 484127 | T52: =+J52+S52 -> 830211 | U52: =+C52-T52 -> 106118
A53: 2.1.1.1.1.5 | B53: PERSONAL CON CONTRATO A PLAZO FIJO (REGIMEN LABORAL PRIVADO) | C53: 333788 | D53: 15186.97 | E53: 21434 | F53: 21434 | G53: 21434 | H53: 21434 | I53: 0 | J53: =SUM(D53:I53) -> 100922.97 | K53: =C53-J53 -> 232865.03 | L53: 77002 | M53: 77002 | N53: 77002 | O53: 77002 | P53: 77002 | Q53: 77002 | R53: 77002 | S53: =SUM(L53:R53) -> 539014 | T53: =+J53+S53 -> 639936.97 | U53: =+C53-T53 -> -306148.97
A54: 2.1.1.1.2.1 | B54: ASIGNACION A FONDOS PARA PERSONAL | C54: 29040 | D54: 1210 | E54: 1210 | F54: 1210 | G54: 1810 | H54: 1360 | I54: 0 | J54: =SUM(D54:I54) -> 6800 | K54: =C54-J54 -> 22240 | L54: 1360 | M54: 1360 | N54: 1360 | O54: 1360 | P54: 1360 | Q54: 1360 | R54: 1360 | S54: =SUM(L54:R54) -> 9520 | T54: =+J54+S54 -> 16320 | U54: =+C54-T54 -> 12720
A55: 2.1.1.4.1.1 | B55: PERSONAL NOMBRADO | C55: 946401 | D55: 50149.28 | E55: 50015.61 | F55: 50149.28 | G55: 49815.1 | H55: 48077.37 | I55: 0 | J55: =SUM(D55:I55) -> 248206.64 | K55: =C55-J55 -> 698194.36 | L55: 59984.63 | M55: 59984.63 | N55: 59984.63 | O55: 59984.63 | P55: 59984.63 | Q55: 59984.63 | R55: 59984.63 | S55: =SUM(L55:R55) -> 419892.41 | T55: =+J55+S55 -> 668099.05 | U55: =+C55-T55 -> 278301.95
A56: 2.1.1.4.2.1 | B56: BONO POR FUNCION JURISDICCIONAL Y FISCAL | C56: 1325690 | D56: 66420 | E56: 66600 | F56: 66600 | G56: 66060 | H56: 63900 | I56: 0 | J56: =SUM(D56:I56) -> 329580 | K56: =C56-J56 -> 996110 | L56: 81300 | M56: 81300 | N56: 81300 | O56: 81300 | P56: 81300 | Q56: 81300 | R56: 81300 | S56: =SUM(L56:R56) -> 569100 | T56: =+J56+S56 -> 898680 | U56: =+C56-T56 -> 427010
A57: 2.1.1.4.2.2 | B57: ASIGNACION POR GASTOS OPERATIVOS | C57: 3006653 | D57: 202718.83 | E57: 203364.8 | F57: 203364.8 | G57: 201426.88 | H57: 193675.21 | I57: 0 | J57: =SUM(D57:I57) -> 1004550.5 | K57: =C57-J57 -> 2002102.5 | L57: 223005.21 | M57: 223005.21 | N57: 223005.21 | O57: 223005.21 | P57: 223005.21 | Q57: 223005.21 | R57: 223005.21 | S57: =SUM(L57:R57) -> 1561036.5 | T57: =+J57+S57 -> 2565587 | U57: =+C57-T57 -> 441066.01
A58: 2.1.1.9.1.1 | B58: GRATIFICACIONES | C58: 259030 | D58: 0 | E58: 0 | F58: 0 | G58: 0 | H58: 0 | I58: 0 | J58: =SUM(D58:I58) -> 0 | K58: =C58-J58 -> 259030 | M58: 146163 | R58: 146163 | S58: =SUM(L58:R58) -> 292326 | T58: =+J58+S58 -> 292326 | U58: =+C58-T58 -> -33296
A59: 2.1.1.9.1.2 | B59: AGUINALDOS | C59: 59221 | D59: 0 | E59: 0 | F59: 0 | G59: 0 | H59: 0 | I59: 0 | J59: =SUM(D59:I59) -> 0 | K59: =C59-J59 -> 59221 | M59: 43416.39 | R59: 43416.39 | S59: =SUM(L59:R59) -> 86832.78 | T59: =+J59+S59 -> 86832.78 | U59: =+C59-T59 -> -27611.78
A60: 2.1.1.9.1.3 | B60: BONIFICACION POR ESCOLARIDAD | C60: 32249 | D60: 19200 | E60: 0 | F60: 0 | G60: 0 | H60: 0 | I60: 0 | J60: =SUM(D60:I60) -> 19200 | K60: =C60-J60 -> 13049 | S60: =SUM(L60:R60) -> 0 | T60: =+J60+S60 -> 19200 | U60: =+C60-T60 -> 13049
A61: 2.1.1.9.2.1 | B61: COMPENSACION POR TIEMPO DE SERVICIOS (CTS) | C61: 140973 | D61: 0 | E61: 0 | F61: 0 | G61: 0 | H61: 49770.56 | I61: 0 | J61: =SUM(D61:I61) -> 49770.56 | K61: =C61-J61 -> 91202.44 | Q61: 85269.5 | S61: =SUM(L61:R61) -> 85269.5 | T61: =+J61+S61 -> 135040.06 | U61: =+C61-T61 -> 5932.94
A62: 2.1.1.9.3.99 | B62: OTRAS OCASIONALES | C62: 9325 | D62: 0 | E62: 0 | F62: 0 | G62: 0 | H62: 0 | I62: 0 | J62: =SUM(D62:I62) -> 0 | K62: =C62-J62 -> 9325 | M62: 5255.89 | R62: 5255.89 | S62: =SUM(L62:R62) -> 10511.78 | T62: =+J62+S62 -> 10511.78 | U62: =+C62-T62 -> -1186.78
A63: 2.1.3.1.1.1 | B63: APORTES A LOS FONDOS DE SALUD | C63: 4545 | D63: 131.36 | E63: 131.36 | F63: 131.36 | G63: 131.36 | H63: 131.36 | I63: 0 | J63: =SUM(D63:I63) -> 656.8 | K63: =C63-J63 -> 3888.2 | L63: 131.36 | M63: 131.36 | N63: 131.36 | O63: 131.36 | P63: 131.36 | Q63: 131.36 | R63: 131.36 | S63: =SUM(L63:R63) -> 919.52 | T63: =+J63+S63 -> 1576.32 | U63: =+C63-T63 -> 2968.68
A64: 2.1.3.1.1.3 | B64: APORTES A LOS FONDOS DE PENSIONES | C64: 1444 | D64: 120.3 | E64: 120.3 | F64: 120.3 | G64: 120.3 | H64: 120.3 | I64: 0 | J64: =SUM(D64:I64) -> 601.5 | K64: =C64-J64 -> 842.5 | L64: 120.3 | M64: 120.3 | N64: 120.3 | O64: 120.3 | P64: 120.3 | Q64: 120.3 | R64: 120.3 | S64: =SUM(L64:R64) -> 842.1 | T64: =+J64+S64 -> 1443.6 | U64: =+C64-T64 -> 0.4
A65: 2.1.3.1.1.5 | B65: CONTRIBUCIONES A ESSALUD | C65: 111188 | D65: 7319.95 | E65: 7446.67 | F65: 7500.05 | G65: 7455.41 | H65: 7213.53 | I65: 0 | J65: =SUM(D65:I65) -> 36935.61 | K65: =C65-J65 -> 74252.39 | L65: 10377.23 | M65: 10377.23 | N65: 10377.23 | O65: 10377.23 | P65: 10377.23 | Q65: 10377.23 | R65: 10377.23 | S65: =SUM(L65:R65) -> 72640.61 | T65: =+J65+S65 -> 109576.22 | U65: =+C65-T65 -> 1611.78
A66: TOTAL G.G. 2.1 PERSONAL Y OB. SOCIALES | C66: =SUBTOTAL(9,C4:C65) -> 47438222 | D66: =SUBTOTAL(9,D4:D65) -> 3803625.8 | E66: =SUBTOTAL(9,E4:E65) -> 3656862 | F66: =SUBTOTAL(9,F4:F65) -> 3624491.9 | G66: =SUBTOTAL(9,G4:G65) -> 3646289.8 | H66: =SUBTOTAL(9,H4:H65) -> 4174196.5 | I66: =SUM(I4:I65)/3 -> 0 | J66: =SUM(D66:I66) -> 18905466 | K66: =C66-J66 -> 28532756 | L66: =SUBTOTAL(9,L4:L65) -> 3841909.7 | M66: =SUBTOTAL(9,M4:M65) -> 5337221.8 | N66: =SUBTOTAL(9,N4:N65) -> 3841909.7 | O66: =SUBTOTAL(9,O4:O65) -> 3841909.7 | P66: =SUBTOTAL(9,P4:P65) -> 3841909.7 | Q66: =SUBTOTAL(9,Q4:Q65) -> 4498055.4 | R66: =SUBTOTAL(9,R4:R65) -> 5337221.8 | S66: =SUM(L66:R66) -> 30540138 | T66: =+J66+S66 -> 49445604 | U66: =+C66-T66 -> -2007381.7
